Workbook
Name Input_Date: '[1]9.91 OPERA (84)'!$BV$4:$BV$22
Name Input_Date_2: '[1]9.92 OPERA (85)'!$BV$4:$BV$21
Name Input_Date_3: '[1]9.94 OPERA (87)'!$CT$4:$CT$22
Name YEAR: '[1]9.40 Malaysia (Trent XWB)'!$BV$22:$BV$41

Sheet SoA Summary
B2: Current Debt Position
B3: Type | C3: Amount overdue
B4: TotalCare | C4: ='SoA 26.1.26'!F19 -> 0
B5: CRC | C5: ='SoA 26.1.26'!F65 -> 19419421
B6: Spare Parts | C6: ='SoA 26.1.26'!F109 -> 581179
B7: LPI | C7: ='SoA 26.1.26'!F125 -> 1087289.2
B8: Total Overdue | C8: =SUM(C4:C7) -> 21087889
B10: Available Credit
B11: Type | C11: Value
B12: CRC ULW | C12: ='SoA 26.1.26'!F66 -> -40166155
B13: Other | C13: ='SoA 26.1.26'!F10 -> -28217715
B14: Total Credit | C14: =SUM(C12:C13) -> -68383870
B16: LPI
B17: Type | C17: Value
B18: Invoiced | C18: =SUMIF('SoA 26.1.26'!H69:H119,"Late Payment Invoice",'SoA 26.1.26'!F69:F119) -> 1050679.4
B19: Not yet invoiced (cum.) | C19: =SUM('SoA 26.1.26'!O:O) -> 465124.51
B20: Total | C20: =SUM(C18:C19) -> 1515803.9

Sheet SoA 26.1.26
A1: Ethiopian Statement of Account with Rolls-Royce
A2: Customer Name: | C2: Ethiopian Airlines / EA Enterprise | K2: LPI rate > | L2: 0.00035
A3: Customer Nº: | C3: 1009374 / 1014433
A4: Contact email: | C4: Eyerusalemta@ethiopianairlines.com | K4: Today > | L4: =TODAY() -> 46069
K5: AVERAGE DAYS LATE = | L5: =AVERAGE(L12:L68) -> 113.93103
A7: Company Code | B7: Account | C7: Reference | D7: Document Date | E7: Net due date | F7: Amount in doc. curr. | G7: Curr | H7: Text | I7: Assignment | J7: R-R Comments | K7: Action Owner / Awaiting Approval | L7: DAYS LATE | M7: ETH Comments | N7: ETH PO Reference | O7: LPI Cumulated
A8: Credits usable | Q8: INVOICE
C9: 1620061217 | D9: 45806 | F9: -28217715 | G9: USD | H9: TRENT 1000 NON-EXCUSABLE DELAY CREDIT. | J9: 1 Apr - 31 Dec 24, 1 Jan - 30 Apr 25 | M9: Used in part for CRC offset June 25. | Q9: 1620061893
E10: Total | F10: =SUM(F9:F9) -> -28217715 | Q10: 99600294
Q11: 99630101
A12: TotalCare Charges | Q12: 1620062267
A13: 1200 | B13: 1009374 | C13: 99648079 | D13: 46003 | E13: 46054 | F13: 1701900.7 | G13: USD | H13: TotalCare - Trent 1000-D | I13: DEG 9054 | K13: ET to process | L13: =IF(('SoA 26.1.26'!$L$4-E13)<0,"",'SoA 26.1.26'!$L$4-E13) -> 15 | M13: Not released from Tech Support | O13: =(IF(AND(F13>0,('SoA 26.1.26'!$L$4-E13)>0),((F13*((1+('SoA 26.1.26'!$L$2*30))^(ROUNDDOWN((('SoA 26.1.26'!$L$4-E13)/30),0)))-F13))+(F13+(ROUNDDOWN((('SoA 26.1.26'!$L$4-E13)/30),0)))*'SoA 26.1.26'!$L$2*(30*((('SoA 26.1.26'!$L$4-E13)/30)-(ROUNDDOWN((('SoA 26.1.26'!$L$4-E13)/30),0)))),0)) -> 8934.9785 | Q13: 99540446
A14: 1200 | B14: 1009374 | C14: 99648074 | D14: 46003 | E14: 46054 | F14: 1859754.7 | G14: USD | H14: TotalCare - Trent 1000-K | I14: DEG 9054 | K14: ET to process | L14: =IF(('SoA 26.1.26'!$L$4-E14)<0,"",'SoA 26.1.26'!$L$4-E14) -> 15 | M14: Not released from Tech Support | O14: =(IF(AND(F14>0,('SoA 26.1.26'!$L$4-E14)>0),((F14*((1+('SoA 26.1.26'!$L$2*30))^(ROUNDDOWN((('SoA 26.1.26'!$L$4-E14)/30),0)))-F14))+(F14+(ROUNDDOWN((('SoA 26.1.26'!$L$4-E14)/30),0)))*'SoA 26.1.26'!$L$2*(30*((('SoA 26.1.26'!$L$4-E14)/30)-(ROUNDDOWN((('SoA 26.1.26'!$L$4-E14)/30),0)))),0)) -> 9763.7121 | Q14: 99540450
A15: 1200 | B15: 1009374 | C15: 99648089 | D15: 46003 | E15: 46054 | F15: 2183708.8 | G15: USD | H15: TotalCare - Trent XWB-97 | I15: DEG 10215 | K15: ET to process | M15: Not released from Tech Support | Q15: 99645940
A16: 1200 | B16: 1009374 | C16: 99648084 | D16: 46003 | E16: 46054 | F16: 7491732.3 | G16: USD | H16: TotalCare - Trent XWB-84 | I16: DEG 10215 | K16: ET to process | M16: Not released from Tech Support | Q16: 99645934
Q17: 99645930
E18: Total | F18: =SUM(F13:F14:F15:F16) -> 13237096 | Q18: 99542667
E19: Overdue | F19: =SUMIF(L15:L16, ">0", F15:F16) -> 0 | Q19: 99615649
Q20: 99615641
A21: Customer Responsible Charges | Q21: 99615640
A22: 1200 | B22: 1009374 | C22: 1820146074 | D22: 45218 | E22: 45249 | F22: 318419 | G22: USD | H22: CRC - Line Maintenance | I22: CRC for ESN 10499 | J22: Disputed ET engine air leak | K22: R-R | L22: =IF(($L$4-E22)<0,"",$L$4-E22) -> 820 | M22: Waiting ET Line Maintenance Review | O22: =(IF(AND(F22>0,($L$4-E22)>0),((F22*((1+($L$2*30))^(ROUNDDOWN((($L$4-E22)/30),0)))-F22))+(F22+(ROUNDDOWN((($L$4-E22)/30),0)))*$L$2*(30*((($L$4-E22)/30)-(ROUNDDOWN((($L$4-E22)/30),0)))),0)) -> 104857.97 | Q22: 99615643
A23: 1200 | B23: 1009374 | C23: 1620059837 | D23: 45562 | F23: -1042434.1 | G23: USD | H23: Credit note for 21104 LPT | I23: Credit for 21104 | K23: RR to issue invoice | M23: To correct error with LPT | O23: =(IF(AND(F23>0,($L$4-E23)>0),((F23*((1+($L$2*30))^(ROUNDDOWN((($L$4-E23)/30),0)))-F23))+(F23+(ROUNDDOWN((($L$4-E23)/30),0)))*$L$2*(30*((($L$4-E23)/30)-(ROUNDDOWN((($L$4-E23)/30),0)))),0)) -> 0 | Q23: 99615645
A24: 1200 | B24: 1009374 | C24: 2000638764 | D24: 45884 | F24: -168000 | G24: USD | H24: Credit for 11138 | I24: Credit 11138 | M24: Credit to reflect SUM not new | O24: =(IF(AND(F24>0,($L$4-E24)>0),((F24*((1+($L$2*30))^(ROUNDDOWN((($L$4-E24)/30),0)))-F24))+(F24+(ROUNDDOWN((($L$4-E24)/30),0)))*$L$2*(30*((($L$4-E24)/30)-(ROUNDDOWN((($L$4-E24)/30),0)))),0)) -> 0 | Q24: 99615647
A25: 1200 | B25: 1009374 | C25: 2000638769 | D25: 45884 | F25: -123153 | G25: USD | H25: Credit for 10590 | I25: Credit 10590 | M25: Credit to reflect SUM not new | O25: =(IF(AND(F25>0,($L$4-E25)>0),((F25*((1+($L$2*30))^(ROUNDDOWN((($L$4-E25)/30),0)))-F25))+(F25+(ROUNDDOWN((($L$4-E25)/30),0)))*$L$2*(30*((($L$4-E25)/30)-(ROUNDDOWN((($L$4-E25)/30),0)))),0)) -> 0 | Q25: 99615646
A26: 1200 | B26: 1009374 | C26: 99057194 | D26: 45642 | E26: 45672 | F26: 555734.33 | G26: USD | H26: CRC for 21105 | I26: CRC for 21105 | J26: Balance Invoice Disputed. Insurer rejected claim | K26: Alemnah to review | L26: =IF(($L$4-E26)<0,"",$L$4-E26) -> 397 | M26: Balance from bird strike CRC fan blades and acoustic panels. | O26: =(IF(AND(F26>0,($L$4-E26)>0),((F26*((1+($L$2*30))^(ROUNDDOWN((($L$4-E26)/30),0)))-F26))+(F26+(ROUNDDOWN((($L$4-E26)/30),0)))*$L$2*(30*((($L$4-E26)/30)-(ROUNDDOWN((($L$4-E26)/30),0)))),0)) -> 82187.27 | Q26: 99615644
A27: 1200 | B27: 1009374 | C27: 1820158804 | D27: 45849 | E27: 45879 | F27: 47900 | G27: USD | H27: OWS 10509 EGB replacement charges | J27: Disputed | L27: =IF(($L$4-E27)<0,"",$L$4-E27) -> 190 | N27: 4590160364 | Q27: 99615642
A28: 1200 | B28: 1009374 | C28: 1620061893 | D28: 45922 | F28: -341535.28 | G28: USD | H28: Credit note 21299 | I28: Credit 21299 | J28: Ready For Payment | Q28: 99615648
A29: 1200 | B29: 1009374 | C29: 99600294 | D29: 45974 | E29: 46004 | F29: 516997.85 | G29: USD | H29: CRC LLP for 21299 | I29: CRC 21299 | J29: Ready For Payment | L29: =IF(($L$4-E29)<0,"",$L$4-E29) -> 65 | M29: Paid this week, final stage. | Q29: 99661192
A30: 1200 | B30: 1009374 | C30: 1620061894 | D30: 45922 | F30: -5304093.4 | G30: USD | H30: Credit note for 21814 | I30: Credit 21814 | J30: DACS Summary provided. NET OFF CREDIT | Q30: 99666161
A31: 1200 | B31: 1009374 | C31: 99661057 | D31: 46378 | E31: 46043 | F31: 7254617.1 | G31: USD | H31: CRC LLP 21814 | I31: CRC 21814 | J31: Under approval | L31: =IF(($L$4-E31)<0,"",$L$4-E31) -> 26 | M31: Under approval | Q31: 99666160
A32: 1200 | B32: 1009374 | C32: 1620062188 | D32: 45967 | F32: -5424372 | G32: USD | H32: Credit note for 21428 | I32: Credit 21428 | J32: DACS Summary provided | Q32: 99666159
A33: 1200 | B33: 1009374 | C33: 1620062187 | D33: 45967 | F33: -5562918.8 | G33: USD | H33: Credit note 21950 | I33: Credit 21950 | J33: DACS Summary provided | Q33: 99674528
A34: 1200 | B34: 1009374 | C34: 99630101 | D34: 45993 | E34: 46023 | F34: 2227793.9 | G34: USD | H34: CRC LLP 11109 | I34: CRC 11109 | J34: Ready For Payment | L34: =IF(($L$4-E34)<0,"",$L$4-E34) -> 46 | M34: Approved Tech Support pay next week | Q34: 99674529
A35: 1200 | B35: 1009374 | C35: 1620062267 | D35: 45980 | F35: -1759792.7 | G35: USD | H35: Credit note 11109 | I35: Credit 11109 | J35: Ready For Payment | Q35: 99674530
A36: 1200 | B36: 1009374 | C36: 3000121886 | D36: 45909 | F36: -2389260.7 | G36: USD | H36: Credit note 21185 | I36: Credit 21185 | J36: DACS Summary provided | Q36: 99674531
A37: 1200 | B37: 1009374 | C37: 1620062566 | D37: 46015 | F37: -5470072.1 | G37: USD | H37: Credit note 21608 | I37: Credit 21608 | J37: DACS Summary provided | Q37: 99700686
A38: 1200 | B38: 1009374 | C38: 1620062565 | D38: 46015 | F38: -7085775.8 | G38: USD | H38: Credit note 21376 | I38: Credit 21376 | J38: DACS Summary provided | Q38: 99683381
A39: 1200 | B39: 1009374 | C39: 1620062625 | D39: 46036 | F39: -5479868.7 | G39: USD | H39: Credit note 21171 | I39: Credit 21171 | J39: DACS Summary provided | Q39: 99683378
A40: 1200 | B40: 1009374 | C40: 99540446 | D40: 45938 | E40: 45968 | F40: 105107.09 | G40: USD | H40: CRC 21273 | I40: CRC 21273 | J40: Ready For Payment | L40: =IF(($L$4-E40)<0,"",$L$4-E40) -> 101 | M40: Under approval - paid before year end | N40: P0483839 | Q40: 99683379
A41: 1200 | B41: 1009374 | C41: 99540444 | D41: 45938 | E41: 45968 | F41: 145559.38 | G41: USD | H41: CRC 21229 | I41: CRC 21229 | J41: Under review | L41: =IF(($L$4-E41)<0,"",$L$4-E41) -> 101 | M41: Under review | Q41: 99683382
A42: 1200 | B42: 1009374 | C42: 99540442 | D42: 45938 | E42: 45968 | F42: 985508.72 | G42: USD | H42: CRC 10410 | I42: CRC 10410 | J42: Under approval | L42: =IF(($L$4-E42)<0,"",$L$4-E42) -> 101 | M42: Under approval | Q42: 99683383
A43: 1200 | B43: 1009374 | C43: 99540447 | D43: 45938 | E43: 45968 | F43: 885351.01 | G43: USD | H43: CRC 10517 | I43: CRC 10517 | J43: Under review | L43: =IF(($L$4-E43)<0,"",$L$4-E43) -> 101 | M43: Under review | Q43: 99683384
A44: 1200 | B44: 1009374 | C44: 99540448 | D44: 45938 | E44: 45968 | F44: 365292.59 | G44: USD | H44: CRC 10509 | I44: CRC 10509 | J44: Under approval | L44: =IF(($L$4-E44)<0,"",$L$4-E44) -> 101 | M44: Under approval | Q44: 99700685
A45: 1200 | B45: 1009374 | C45: 99540450 | D45: 45938 | E45: 45968 | F45: 267054.86 | G45: USD | H45: CRC 21185 | I45: CRC 21185 | J45: READY FOR PAYMENT | L45: =IF(($L$4-E45)<0,"",$L$4-E45) -> 101 | M45: Under approval | N45: P0480308
A46: 1200 | B46: 1009374 | C46: 99540449 | D46: 45938 | E46: 45968 | F46: 373041.61 | G46: USD | H46: CRC 21294 | I46: CRC 21294 | J46: Ready For Payment | L46: =IF(($L$4-E46)<0,"",$L$4-E46) -> 101 | M46: Under approval | N46: P0489689
A47: 1200 | B47: 1009374 | C47: 99540445 | D47: 45938 | E47: 45968 | F47: 125356.33 | G47: USD | H47: CRC 21186 | I47: CRC 21186 | J47: LRU NDE (Jan 25) | L47: =IF(($L$4-E47)<0,"",$L$4-E47) -> 101 | M47: Duplicate repair & new charge ?
C48: 2000647559 | D48: 46013 | F48: -14878.43 | G48: USD | H48: Credit note 21186 | I48: Credit 21186 | J48: Error repair and new charge
A49: 1200 | B49: 1009374 | C49: 99542646 | D49: 45939 | E49: 45969 | F49: 38452.28 | G49: USD | H49: CRC 21405 | I49: CRC 21405 | J49: Ready For Payment | L49: =IF(($L$4-E49)<0,"",$L$4-E49) -> 100 | M49: Under approval | N49: P0478098
A50: 1200 | B50: 1009374 | C50: 99542625 | D50: 45939 | E50: 45969 | F50: 586645.78 | G50: USD | H50: CRC 21942 | I50: CRC 21942 | J50: LLP Grp B Oct 24, Indicated amount not correct with invoice RR should be amend | L50: =IF(($L$4-E50)<0,"",$L$4-E50) -> 100 | M50: Under approval | N50: P0479443
A51: 1200 | B51: 1009374 | C51: 99542667 | D51: 45939 | E51: 45969 | F51: 2384.13 | G51: USD | H51: CRC 11109 | I51: CRC 11109 | J51: Ready For Payment | L51: =IF(($L$4-E51)<0,"",$L$4-E51) -> 100 | M51: premature removal
A52: 1200 | B52: 1009374 | C52: 99542665 | D52: 45939 | E52: 45969 | F52: 717919.91 | G52: USD | H52: CRC 10599 | I52: CRC 10599 | J52: Under review | L52: =IF(($L$4-E52)<0,"",$L$4-E52) -> 100 | M52: premature removal
A53: 1200 | B53: 1009374 | C53: 99542662 | D53: 45939 | E53: 45969 | F53: 765603.71 | G53: USD | H53: CRC 10456 | I53: CRC 10456 | J53: Under approval | L53: =IF(($L$4-E53)<0,"",$L$4-E53) -> 100 | M53: Under approval
A54: 1200 | B54: 1009374 | C54: 99542661 | D54: 45939 | E54: 45969 | F54: 880035.72 | G54: USD | H54: CRC 10418 | I54: CRC 10418 | J54: Under review | L54: =IF(($L$4-E54)<0,"",$L$4-E54) -> 100 | M54: Under review
A55: 1200 | B55: 1009374 | C55: 99542659 | D55: 45939 | E55: 45969 | F55: 1063163.2 | G55: USD | H55: CRC 10590 | I55: CRC 10590 | J55: Under review | L55: =IF(($L$4-E55)<0,"",$L$4-E55) -> 100 | M55: Under review
A56: 1200 | B56: 1009374 | C56: 99645961 | D56: 46002 | E56: 46032 | F56: 2425.1 | G56: USD | H56: CRC 21599 | I56: CRC 21599 | J56: Transport | L56: =IF(($L$4-E56)<0,"",$L$4-E56) -> 37 | M56: released for approval
A57: 1200 | B57: 1009374 | C57: 99645940 | D57: 46002 | E57: 46032 | F57: 50336.34 | G57: USD | H57: CRC 21273 | I57: CRC 21273 | J57: Ready For Payment | L57: =IF(($L$4-E57)<0,"",$L$4-E57) -> 37 | M57: released for approval
A58: 1200 | B58: 1009374 | C58: 99645934 | D58: 46002 | E58: 46032 | F58: 154410.93 | G58: USD | H58: CRC 21274 | I58: CRC 21274 | J58: Ready For Payment | L58: =IF(($L$4-E58)<0,"",$L$4-E58) -> 37 | M58: released for approval
A59: 1200 | B59: 1009374 | C59: 99645943 | D59: 46002 | E59: 46032 | F59: 45036.04 | G59: USD | H59: CRC 21376 | I59: CRC 21376 | J59: LRU | L59: =IF(($L$4-E59)<0,"",$L$4-E59) -> 37 | M59: ]#'
A60: 1200 | B60: 1009374 | C60: 99645931 | D60: 46002 | E60: 46032 | F60: 287462.67 | G60: USD | H60: CRC 21602 | I60: CRC 21602 | J60: Under approval | L60: =IF(($L$4-E60)<0,"",$L$4-E60) -> 37 | M60: Under approval
A61: 1200 | B61: 1009374 | C61: 99645930 | D61: 46002 | E61: 46032 | F61: 651811.51 | G61: USD | H61: CRC 21230 | I61: CRC 21230 | J61: Ready For Payment | L61: =IF(($L$4-E61)<0,"",$L$4-E61) -> 37 | M61: released for approval
O63: =(IF(AND(F63>0,($L$4-E63)>0),((F63*((1+($L$2*30))^(ROUNDDOWN((($L$4-E63)/30),0)))-F63))+(F63+(ROUNDDOWN((($L$4-E63)/30),0)))*$L$2*(30*((($L$4-E63)/30)-(ROUNDDOWN((($L$4-E63)/30),0)))),0)) -> 0
E64: Total | F64: =SUMIF(F22:F63,">"&0,F22:F63) -> 19419421
E65: Overdue | F65: =SUMIF(L22:L63, ">0", F22:F63) -> 19419421
E66: Available Credit | F66: =SUMIF(F22:F63,"<"&0,F22:F63) -> -40166155
A68: Spare Parts Charges
A69: 1200 | B69: 1009374 | C69: 1820151587 | D69: 45499 | E69: 45529 | F69: 1700 | G69: USD | H69: For the charges of tool loan on TL2024_0305 | I69: 7G-P0461526 | J69: ET to process | K69: RR | L69: =IF(($L$4-E69)<0,"",$L$4-E69) -> 540 | M69: TOOL/Part not received. Rob Invoice copy required. | O69: =(IF(AND(F69>0,($L$4-E69)>0),((F69*((1+($L$2*30))^(ROUNDDOWN((($L$4-E69)/30),0)))-F69))+(F69+(ROUNDDOWN((($L$4-E69)/30),0)))*$L$2*(30*((($L$4-E69)/30)-(ROUNDDOWN((($L$4-E69)/30),0)))),0)) -> 351.64702
A70: 1200 | B70: 1009374 | C70: 99219798 | D70: 45744 | E70: 45774 | F70: 28320 | G70: USD | H70: Spare Parts | I70: 4E-P0499770 | J70: ET to process | K70: RR Jade | L70: =IF(($L$4-E70)<0,"",$L$4-E70) -> 295 | M70: THE ORDER CALLS ICON AEROSPACE RATHER THAN RR | O70: =(IF(AND(F70>0,($L$4-E70)>0),((F70*((1+($L$2*30))^(ROUNDDOWN((($L$4-E70)/30),0)))-F70))+(F70+(ROUNDDOWN((($L$4-E70)/30),0)))*$L$2*(30*((($L$4-E70)/30)-(ROUNDDOWN((($L$4-E70)/30),0)))),0)) -> 3039.3185
A71: 1200 | B71: 1009374 | C71: 99334366 | D71: 45810 | E71: 45840 | F71: 1590 | G71: USD | H71: Spare Parts | I71: P0515913 | J71: ET to process | K71: Chalie Engda | L71: =IF(($L$4-E71)<0,"",$L$4-E71) -> 229 | M71: Disputed – price increased after the order acknowledgment by RR | O71: =(IF(AND(F71>0,($L$4-E71)>0),((F71*((1+($L$2*30))^(ROUNDDOWN((($L$4-E71)/30),0)))-F71))+(F71+(ROUNDDOWN((($L$4-E71)/30),0)))*$L$2*(30*((($L$4-E71)/30)-(ROUNDDOWN((($L$4-E71)/30),0)))),0)) -> 131.2314
A72: 1200 | B72: 1009374 | C72: 99334365 | D72: 45810 | E72: 45840 | F72: 1638 | G72: USD | H72: Spare Parts | I72: P0515913 | J72: ET to process | K72: Chalie Engda | L72: =IF(($L$4-E72)<0,"",$L$4-E72) -> 229 | M72: Disputed – price increased after the order acknowledgment by RR | O72: =(IF(AND(F72>0,($L$4-E72)>0),((F72*((1+($L$2*30))^(ROUNDDOWN((($L$4-E72)/30),0)))-F72))+(F72+(ROUNDDOWN((($L$4-E72)/30),0)))*$L$2*(30*((($L$4-E72)/30)-(ROUNDDOWN((($L$4-E72)/30),0)))),0)) -> 135.1917
A73: 1200 | B73: 1009374 | C73: 99335798 | D73: 45811 | E73: 45841 | F73: 24050 | G73: USD | H73: Spare Parts | I73: 4E-P0515702 | J73: Part returned | K73: Chalie Engda | L73: =IF(($L$4-E73)<0,"",$L$4-E73) -> 228 | M73: Disputed – price increased after the order acknowledgment by RR | O73: =(IF(AND(F73>0,($L$4-E73)>0),((F73*((1+($L$2*30))^(ROUNDDOWN((($L$4-E73)/30),0)))-F73))+(F73+(ROUNDDOWN((($L$4-E73)/30),0)))*$L$2*(30*((($L$4-E73)/30)-(ROUNDDOWN((($L$4-E73)/30),0)))),0)) -> 1975.9006
A74: 1200 | B74: 1009374 | C74: 99354865 | D74: 45824 | E74: 45854 | F74: 72810 | G74: USD | H74: Spare Parts | I74: 4E-P0515712 | J74: ET to process | K74: Chalie Engda | L74: =IF(($L$4-E74)<0,"",$L$4-E74) -> 215 | M74: Disputed – price increased after the order acknowledgment by RR | O74: =(IF(AND(F74>0,($L$4-E74)>0),((F74*((1+($L$2*30))^(ROUNDDOWN((($L$4-E74)/30),0)))-F74))+(F74+(ROUNDDOWN((($L$4-E74)/30),0)))*$L$2*(30*((($L$4-E74)/30)-(ROUNDDOWN((($L$4-E74)/30),0)))),0)) -> 5650.5193
A75: 1200 | B75: 1009374 | C75: 99425814 | D75: 45868 | E75: 45898 | F75: 247.5 | G75: USD | H75: Spare Parts | I75: 4E-P0521900-07 | J75: ET to process | K75: Chalie Engda | L75: =IF(($L$4-E75)<0,"",$L$4-E75) -> 171 | M75: READY FOR PAYMENT | O75: =(IF(AND(F75>0,($L$4-E75)>0),((F75*((1+($L$2*30))^(ROUNDDOWN((($L$4-E75)/30),0)))-F75))+(F75+(ROUNDDOWN((($L$4-E75)/30),0)))*$L$2*(30*((($L$4-E75)/30)-(ROUNDDOWN((($L$4-E75)/30),0)))),0)) -> 15.125374
A76: 1200 | B76: 1009374 | C76: 99615649 | D76: 45983 | E76: 46013 | F76: 296.5 | G76: USD | H76: Spare Parts | I76: 4E-P0533432-03 | J76: ET to process | K76: Chalie Engda | L76: =IF(($L$4-E76)<0,"",$L$4-E76) -> 56 | M76: READY FOR PAYMENT
A77: 1200 | B77: 1009374 | C77: 99615641 | D77: 45983 | E77: 46013 | F77: 882 | G77: USD | H77: Spare Parts | I77: 4E-P0533432-04 | J77: ET to process | K77: Chalie Engda | L77: =IF(($L$4-E77)<0,"",$L$4-E77) -> 56 | M77: READY FOR PAYMENT
A78: 1200 | B78: 1009374 | C78: 99615640 | D78: 45983 | E78: 46013 | F78: 3476 | G78: USD | H78: Spare Parts | I78: 4E-P0533432-02 | J78: ET to process | K78: Chalie Engda | L78: =IF(($L$4-E78)<0,"",$L$4-E78) -> 56 | M78: READY FOR PAYMENT
A79: 1200 | B79: 1009374 | C79: 99615643 | D79: 45983 | E79: 46013 | F79: 12226 | G79: USD | H79: Spare Parts | I79: 4E-P0533342-01 | J79: ET to process | K79: Chalie Engda | L79: =IF(($L$4-E79)<0,"",$L$4-E79) -> 56 | M79: part not received
A80: 1200 | B80: 1009374 | C80: 99615645 | D80: 45983 | E80: 46013 | F80: 12382 | G80: USD | H80: Spare Parts | I80: 4E-P0533342-05 | J80: ET to process | K80: Chalie Engda | L80: =IF(($L$4-E80)<0,"",$L$4-E80) -> 56 | M80: part not received
A81: 1200 | B81: 1009374 | C81: 99615647 | D81: 45983 | E81: 46013 | F81: 13918 | G81: USD | H81: Spare Parts | I81: 4E-P0533342-07 | J81: ET to process | K81: Chalie Engda | L81: =IF(($L$4-E81)<0,"",$L$4-E81) -> 56 | M81: part not received
A82: 1200 | B82: 1009374 | C82: 99615646 | D82: 45983 | E82: 46013 | F82: 14686 | G82: USD | H82: Spare Parts | I82: 4E-P0533342-06 | J82: ET to process | K82: Chalie Engda | L82: =IF(($L$4-E82)<0,"",$L$4-E82) -> 56 | M82: part not received
A83: 1200 | B83: 1009374 | C83: 99615644 | D83: 45983 | E83: 46013 | F83: 17476 | G83: USD | H83: Spare Parts | I83: 4E-P0533342-02 | J83: ET to process | K83: Chalie Engda | L83: =IF(($L$4-E83)<0,"",$L$4-E83) -> 56 | M83: part not received
A84: 1200 | B84: 1009374 | C84: 99615642 | D84: 45983 | E84: 46013 | F84: 18288 | G84: USD | H84: Spare Parts | I84: 4E-P0533318-01 | J84: ET to process | K84: Chalie Engda | L84: =IF(($L$4-E84)<0,"",$L$4-E84) -> 56 | M84: part not received
A85: 1200 | B85: 1009374 | C85: 99615648 | D85: 45983 | E85: 46013 | F85: 69445 | G85: USD | H85: Spare Parts | I85: 4E-P0533318-10 | J85: ET to process | K85: Chalie Engda | L85: =IF(($L$4-E85)<0,"",$L$4-E85) -> 56 | M85: part not received
A86: 1200 | B86: 1009374 | C86: 99661192 | D86: 46013 | E86: 46043 | F86: 8736 | G86: USD | H86: Spare Parts | I86: 5N-P0540975 | J86: ET to process | K86: Chalie Engda | L86: =IF(($L$4-E86)<0,"",$L$4-E86) -> 26 | M86: READY FOR PAYMENT
A87: 1200 | B87: 1009374 | C87: 99666161 | D87: 46013 | E87: 46043 | F87: 992 | G87: USD | H87: Spare Parts | I87: 5L-P0541993 | J87: ET to process | K87: Chalie Engda | L87: =IF(($L$4-E87)<0,"",$L$4-E87) -> 26 | M87: READY FOR PAYMENT
... A92: 1200 | B92: 1009374 | C92: 99674530 | D92: 46025 | E92: 46055 | F92: 22896 | G92: USD | H92: Spare Parts | I92: P0541472-02 | J92: ET to process | K92: Chalie Engda | L92: =IF(($L$4-E92)<0,"",$L$4-E92) -> 14 | M92: READY FOR PAYMENT
A93: 1200 | B93: 1009374 | C93: 99674531 | D93: 46025 | E93: 46055 | F93: 119616 | G93: USD | H93: Spare Parts | I93: 4E-P0541374-02 | J93: ET to process | K93: Chalie Engda | L93: =IF(($L$4-E93)<0,"",$L$4-E93) -> 14
A94: 1200 | B94: 1009374 | C94: 99700686 | D94: 18/01/2026 | E94: 17/02/2026 | F94: 252 | G94: USD | H94: Spare Parts | I94: 5N-P0543706-01 | J94: ET to process | K94: Chalie Engda | L94: =IF(($L$4-E94)<0,"",$L$4-E94)
A95: 1200 | B95: 1009374 | C95: 99692880 | D95: 14/01/2026 | E95: 13/02/2026 | F95: 27891 | G95: USD | H95: Spare Parts | I95: 4E-P0512609-01 | J95: ET to process | K95: Chalie Engda | L95: =IF(($L$4-E95)<0,"",$L$4-E95) -> 3
A96: 1200 | B96: 1009374 | C96: 99692879 | D96: 14/01/2026 | E96: 13/02/2026 | F96: 46206 | G96: USD | H96: Spare Parts | I96: P0541472-01 | J96: ET to process | K96: Chalie Engda | L96: =IF(($L$4-E96)<0,"",$L$4-E96) -> 3
A97: 1200 | B97: 1009374 | C97: 99683381 | D97: 46235 | E97: 46205 | F97: 23500 | G97: USD | H97: Spare Parts | I97: 4E-P0533318-04 | J97: ET to process | K97: Chalie Engda | L97: =IF(($L$4-E97)<0,"",$L$4-E97)
A98: 1200 | B98: 1009374 | C98: 99683378 | D98: 46235 | E98: 46205 | F98: 98736 | G98: USD | H98: Spare Parts | I98: 4E-P0542037 | J98: ET to process | K98: Chalie Engda | L98: =IF(($L$4-E98)<0,"",$L$4-E98)
A99: 1200 | B99: 1009374 | C99: 99683380 | D99: 46235 | E99: 46205 | F99: 105042 | G99: USD | H99: Spare Parts | I99: 4E-P0542488 | J99: ET to process | K99: Chalie Engda | L99: =IF(($L$4-E99)<0,"",$L$4-E99)
A100: 1200 | B100: 1009374 | C100: 99683379 | D100: 46235 | E100: 46205 | F100: 10340 | G100: USD | H100: Spare Parts | I100: 4E-P0542592 | J100: ET to process | K100: Chalie Engda | L100: =IF(($L$4-E100)<0,"",$L$4-E100)
A101: 1200 | B101: 1009374 | C101: 99683382 | D101: 46235 | E101: 46205 | F101: 20896 | G101: USD | H101: Spare Parts | I101: P0541369 | J101: ET to process | K101: Chalie Engda | L101: =IF(($L$4-E101)<0,"",$L$4-E101)
A102: 1200 | B102: 1009374 | C102: 99683383 | D102: 46235 | E102: 46205 | F102: 20896 | G102: USD | H102: Spare Parts | I102: P0541372 | J102: ET to process | K102: Chalie Engda | L102: =IF(($L$4-E102)<0,"",$L$4-E102)
A103: 1200 | B103: 1009374 | C103: 99683384 | D103: 46235 | E103: 46205 | F103: 20896 | G103: USD | H103: Spare Parts | I103: P0541373 | J103: ET to process | K103: Chalie Engda | L103: =IF(($L$4-E103)<0,"",$L$4-E103)
A104: 1200 | B104: 1009374 | C104: 99692878 | D104: 14/01/2026 | E104: 13/02/2026 | F104: 75173 | G104: USD | H104: Spare Parts | I104: 4E-P0541374-01 | J104: ET to process | K104: Chalie Engda | L104: =IF(($L$4-E104)<0,"",$L$4-E104) -> 3
A105: 1200 | B105: 1009374 | C105: 99678291 | D105: 46174 | E105: 46144 | F105: 245 | G105: USD | H105: Spare Parts | I105: 4E-P0533310 | J105: ET to process | K105: Chalie Engda | L105: =IF(($L$4-E105)<0,"",$L$4-E105)
A106: 1200 | B106: 1009374 | C106: 99700685 | D106: 18/01/2026 | E106: 17/02/2026 | F106: 6676 | G106: USD | H106: Spare Parts | I106: 5N-P0543706-02 | J106: ET to process | K106: Chalie Engda | L106: =IF(($L$4-E106)<0,"",$L$4-E106)
A107: 1200 | B107: 1009374 | C107: 99713816 | D107: 46048 | E107: 46078 | F107: 13700 | G107: USD | H107: Spare Parts | I107: 4T-P0544676 | J107: ET to process | K107: Chalie Engda | L107: =IF(($L$4-E107)<0,"",$L$4-E107)
...

Sheet Offset
A2: Offset 28 May 25
A4: 1009374 | B4: 99036727 | C4: 45629 | D4: 45659 | E4: 70308.84 | G4: CRC for 21814
A5: 1009374 | B5: 99036726 | C5: 45629 | D5: 45659 | E5: 187920.02 | G5: CRC for 21602
A6: 1009374 | B6: 99036725 | C6: 45629 | D6: 45659 | E6: 176153.13 | G6: CRC for 21591
A7: 1009374 | B7: 99036724 | C7: 45629 | D7: 45659 | E7: 147596.69 | G7: CRC for 21564
A8: 1009374 | B8: 99036723 | C8: 45629 | D8: 45659 | E8: 209221.99 | G8: CRC for 21528
A9: 1009374 | B9: 99036704 | C9: 45629 | D9: 45659 | E9: 113386.82 | G9: CRC for 21299
A10: 1009374 | B10: 99036705 | C10: 45629 | D10: 45659 | E10: 1276395.1 | G10: CRC for 21299
A11: 1009374 | B11: 99036707 | C11: 45629 | D11: 45659 | E11: 40060.71 | G11: CRC for 21400
A12: 1009374 | B12: 99036709 | C12: 45629 | D12: 45659 | E12: 118120.98 | G12: CRC for 21405
A13: 1009374 | B13: 99036706 | C13: 45629 | D13: 45659 | E13: 16178.63 | G13: CRC for 21400
A14: 1009374 | B14: 99059380 | C14: 45643 | D14: 45673 | E14: 145575.75 | G14: CRC for 21185
A15: 1009374 | B15: 99059382 | C15: 45643 | D15: 45673 | E15: 54002.95 | G15: CRC for 21230
... A17: 1009374 | B17: 99059385 | C17: 45643 | D17: 45673 | E17: 183061.85 | G17: CRC for 21608
E19: =SUM(E4:E17) -> 2792006
A20: Offset 25 June 25
B22: 99179557 | C22: 45720 | D22: 45750 | E22: 28567.49 | G22: CRC for 21599
B23: 99179555 | C23: 45720 | D23: 45750 | E23: 392610.66 | G23: CRC for 21771
B24: 99179553 | C24: 45720 | D24: 45750 | E24: 256884.92 | G24: CRC for 21525
B25: 99179552 | C25: 45720 | D25: 45750 | E25: 268527.82 | G25: CRC for 21406
B26: 99179562 | C26: 45720 | D26: 45750 | E26: 397114.57 | G26: CRC for 21599
B27: 99179576 | C27: 45720 | D27: 45750 | E27: 34552.55 | G27: CRC for 21525
B28: 99179578 | C28: 45720 | D28: 45750 | E28: 470710.66 | G28: CRC for 21104
B29: 99179579 | C29: 45720 | D29: 45750 | E29: 177109.23 | G29: CRC for 21405
B30: 99179582 | C30: 45720 | D30: 45750 | E30: 237185.97 | G30: CRC for 21528
B31: 99179588 | C31: 45720 | D31: 45750 | E31: 296833.18 | G31: CRC for 21140
B32: 99179598 | C32: 45720 | D32: 45750 | E32: 168458.12 | G32: CRC for 21229
B33: 99179600 | C33: 45720 | D33: 45750 | E33: 197661.55 | G33: CRC for 21230
... B64: 99184249 | C64: 45722 | D64: 45752 | E64: 34873.16 | G64: CRC for 21528
E66: 12306643

Sheet Paymen
A1: 46049
A5: 1200 | B5: 1009374 | C5: 99627769 | D5: 45992 | E5: 46023 | F5: 7491732.3 | G5: USD | H5: TotalCare - Trent XWB-84 | I5: DEG 10215 | K5: ET to process | L5: =IF(('SoA 26.1.26'!$L$4-E5)<0,"",'SoA 26.1.26'!$L$4-E5) -> 46 | M5: Under approval payment ? | N5: 4590160127 | O5: =(IF(AND(F5>0,('SoA 26.1.26'!$L$4-E5)>0),((F5*((1+('SoA 26.1.26'!$L$2*30))^(ROUNDDOWN((('SoA 26.1.26'!$L$4-E5)/30),0)))-F5))+(F5+(ROUNDDOWN((('SoA 26.1.26'!$L$4-E5)/30),0)))*'SoA 26.1.26'!$L$2*(30*((('SoA 26.1.26'!$L$4-E5)/30)-(ROUNDDOWN((('SoA 26.1.26'!$L$4-E5)/30),0)))),0)) -> 120616.9
A6: 1200 | B6: 1009374 | C6: 99627772 | D6: 45992 | E6: 46023 | F6: 2183708.8 | G6: USD | H6: TotalCare - Trent XWB-97 | I6: DEG 10215 | K6: ET to process | L6: =IF(('SoA 26.1.26'!$L$4-E6)<0,"",'SoA 26.1.26'!$L$4-E6) -> 46 | M6: Under approval payment ? | N6: 4590160125 | O6: =(IF(AND(F6>0,('SoA 26.1.26'!$L$4-E6)>0),((F6*((1+('SoA 26.1.26'!$L$2*30))^(ROUNDDOWN((('SoA 26.1.26'!$L$4-E6)/30),0)))-F6))+(F6+(ROUNDDOWN((('SoA 26.1.26'!$L$4-E6)/30),0)))*'SoA 26.1.26'!$L$2*(30*((('SoA 26.1.26'!$L$4-E6)/30)-(ROUNDDOWN((('SoA 26.1.26'!$L$4-E6)/30),0)))),0)) -> 35157.717
B7: Rolls-Royce plc
B8: INVOICE | C8: AMOUNT(USD)
B9: 1620061893 | C9: -341535.28
B10: 99600294 | C10: 516997.85
B11: 99630101 | C11: 2227793.9
B12: 1620062267 | C12: -1759792.7
B13: 99540446 | C13: 105107.09
B14: 99540450 | C14: 267054.86
B15: 99645940 | C15: 50336.34
B16: 99645934 | C16: 154410.93
B17: 99645930 | C17: 651811.51
B18: 99542667 | C18: 2384.13
B19: 99615649 | C19: 296.5
B20: 99615641 | C20: 882
... B44: 99700685 | C44: 6676
B45: TOTAL | C45: 2527584.1

Sheet 2022 Cash payments
A1: Ethiopian Statement of Account with Rolls-Royce
A2: Customer Name: | C2: Ethiopian Airlines / EA Enterprise
A3: Customer Nº: | C3: 1009374 / 1014433
A4: Contact email: | C4: Eyerusalemta@ethiopianairlines.com | K4: Today > | L4: =TODAY() -> 46069
K5: AVERAGE DAYS LATE = | L5: =AVERAGE(L9:L62) -> #DIV/0!
A7: Company Code | B7: Account | C7: Reference | D7: Document Date | E7: Net due date | F7: Amount in doc. curr. | G7: Curr | H7: Text | I7: Assignment | J7: Comments | K7: Comments | L7: DAYS LATE | M7: Current status
H8: W/C 07/02/22
A9: 1200 | B9: 1009374 | C9: 97466491 | D9: 44496 | E9: 44531 | F9: 4535354.9 | G9: USD | H9: TotalCare - Trent XWB-84 | I9: DEG 10215 December 2021 | J9: PAID | K9: 44601
A10: 2500 | B10: 1014433 | C10: 97490154 | D10: 44516 | E10: 44561 | F10: 46998 | G10: USD | H10: Lease Engine LLP Charges - Trent 1000 TEN | I10: ESN 11307 JANUARY 2021 | J10: PAID | K10: 44601
A11: 2500 | B11: 1014433 | C11: 97490167 | D11: 44516 | E11: 44561 | F11: 67140 | G11: USD | H11: Lease Engine LLP Charges - Trent 1000 Pack B/C | I11: ESN 10588 June 2021 | J11: PAID | K11: 44601
A12: 2500 | B12: 1014433 | C12: 97540553 | D12: 44561 | E12: 44606 | F12: 59680 | G12: USD | H12: Lease Engine LLP Charges - Trent 1000 Pack B/C | I12: ESN 10588 November 2021 | J12: PAID | K12: 44601
A13: 2500 | B13: 1014433 | C13: 97540559 | D13: 44561 | E13: 44606 | F13: 43600 | G13: USD | H13: Lease Engine LLP Charges - Trent 1000 Pack B/C | I13: ESN 10353 November 2021 | J13: PAID | K13: 44601
F14: =SUM(F9:F13) -> 4752772.9
H15: W/C 14/02/22
A16: 2500 | B16: 1014433 | C16: 97500018 | D16: 44525 | E16: 44570 | F16: 70870 | G16: USD | H16: Lease Engine LLP Charges - Trent 1000 Pack B/C | I16: ESN 10588 September 2021 | J16: PAID | K16: 44607
A17: 2500 | B17: 1014433 | C17: 97490171 | D17: 44516 | E17: 44561 | F17: 58934 | G17: USD | H17: Lease Engine LLP Charges - Trent 1000 Pack B/C | I17: ESN 10588 August 2021 | J17: PAID | K17: 44607
A18: 2500 | B18: 1014433 | C18: 97490162 | D18: 44516 | E18: 44561 | F18: 47744 | G18: USD | H18: Lease Engine LLP Charges - Trent 1000 Pack B/C | I18: ESN 10588 APRIL 2021 | J18: PAID | K18: 44607
A19: 2500 | B19: 1014433 | C19: 97490163 | D19: 44516 | E19: 44561 | F19: 64156 | G19: USD | H19: Lease Engine LLP Charges - Trent 1000 Pack B/C | I19: ESN 10559 APRIL 2021 | J19: PAID | K19: 44608
F20: =SUM(F16:F19) -> 241704
H21: W/C 21/02/22
A22: 1200 | B22: 1009374 | C22: 97417341 | D22: 44452 | E22: 44482 | F22: 806 | G22: USD | H22: Spare Parts | I22: 3A1-P0366840-1 | J22: PAID | K22: 44615
A23: 1200 | B23: 1009374 | C23: 97417342 | D23: 44452 | E23: 44482 | F23: 3680 | G23: USD | H23: Spare Parts | I23: P0366840-2 | J23: PAID | K23: 44615
A24: 1200 | B24: 1009374 | C24: 97417343 | D24: 44452 | E24: 44482 | F24: 2624 | G24: USD | H24: Spare Parts | I24: P0366840-3 | J24: PAID | K24: 44615
A25: 1200 | B25: 1009374 | C25: 97417344 | D25: 44452 | E25: 44482 | F25: 2807 | G25: USD | H25: Spare Parts | I25: P0366840-3 | J25: PAID | K25: 44615
A26: 1200 | B26: 1009374 | C26: 97438098 | D26: 44470 | E26: 44500 | F26: 162 | G26: USD | H26: Spare Parts | I26: 4F-P0357975 | J26: PAID | K26: 44615
A27: 1200 | B27: 1009374 | C27: 97438099 | D27: 44470 | E27: 44500 | F27: 16750 | G27: USD | H27: Spare Parts | I27: 4E-P0366970 | J27: PAID | K27: 44615
A28: 1200 | B28: 1009374 | C28: 97440885 | D28: 44472 | E28: 44502 | F28: 7100 | G28: USD | H28: Spare Parts | I28: 4E-P0366858 | J28: PAID | K28: 44615
A29: 1200 | B29: 1009374 | C29: 97442845 | D29: 44474 | E29: 44504 | F29: 38542 | G29: USD | H29: Spare Parts | I29: 4F-P0366042 | J29: PAID | K29: 44615
A30: 1200 | B30: 1009374 | C30: 97449172 | D30: 44481 | E30: 44511 | F30: 3582 | G30: USD | H30: Spare Parts | I30: 4F-P0368757 | J30: PAID | K30: 44615
A31: 1200 | B31: 1009374 | C31: 97451398 | D31: 44482 | E31: 44512 | F31: 75165 | G31: USD | H31: Spare Parts | I31: 4F-P0364791 | J31: PAID | K31: 44615
A32: 1200 | B32: 1009374 | C32: 97453801 | D32: 44484 | E32: 44514 | F32: 3154.5 | G32: USD | H32: Spare Parts | I32: 5X-P0369712 | J32: PAID | K32: 44615
A33: 1200 | B33: 1009374 | C33: 97455370 | D33: 44487 | E33: 44517 | F33: 453 | G33: USD | H33: Spare Parts | I33: 5X-P0369712 | J33: PAID | K33: 44615
... A54: 1200 | B54: 1009374 | C54: 97543780 | D54: 44565 | E54: 44595 | F54: 6744 | G54: USD | H54: Spare Parts | I54: 4A-P0376419 | J54: PAID | K54: 44615
A55: 1200 | B55: 1009374 | C55: 97452559 | D55: 44483 | E55: 44531 | F55: 1577970 | G55: USD | H55: TotalCare - Trent 1000-D | I55: DEG 9054 December 2021 | J55: PAID | K55: 44617
A56: 1200 | B56: 1009374 | C56: 97452560 | D56: 44483 | E56: 44531 | F56: 1239030 | G56: USD | H56: TotalCare - Trent 1000-K | I56: DEG 9054 December 2021 | J56: PAID | K56: 44617
A57: 2500 | B57: 1014433 | C57: 97490082 | D57: 44516 | E57: 44561 | F57: 49236 | G57: USD | H57: Lease Engine LLP Charges - Trent 1000 Pack B/C | I57: ESN 10588 JANUARY 2021 | J57: PAID | K57: 44617
A58: 2500 | B58: 1014433 | C58: 97490157 | D58: 44516 | E58: 44561 | F58: 12682 | G58: USD | H58: Lease Engine LLP Charges - Trent 1000 Pack B/C | I58: ESN 10559 FEBRUARY 2021 | J58: PAID | K58: 44617
A59: 2500 | B59: 1014433 | C59: 97490168 | D59: 44516 | E59: 44561 | F59: 57442 | G59: USD | H59: Lease Engine LLP Charges - Trent 1000 Pack B/C | I59: ESN 10559 June 2021 | J59: PAID | K59: 44617
A60: 2500 | B60: 1014433 | C60: 97312243 | D60: 44343 | E60: 44388 | F60: 39057 | G60: USD | H60: Lease Engine LLP Charges - Trent 1000 TEN | I60: ESN 11382 APRIL 2021 | J60: PAID | K60: 44617
A61: 2500 | B61: 1014433 | C61: 97490158 | D61: 44516 | E61: 44561 | F61: n | G61: USD | H61: Lease Engine LLP Charges - Trent 1000 Pack B/C | I61: ESN 10353 FEBRUARY 2021 | J61: PAID | K61: 44617
F62: =SUM(F22:F61) -> 3381381.5
H63: W/C 28/02/22
A64: NO PAYMENT
F65: 0
H66: W/C 07/03/22
A67: 1200 | B67: 1009374 | C67: 97496008 | D67: 44522 | E67: 44562 | F67: 1629720 | G67: USD | H67: TotalCare - Trent 1000-D | I67: DEG 9054 January 2022 | J67: PAID | K67: 44628
A68: 1200 | B68: 1009374 | C68: 97496007 | D68: 44522 | E68: 44562 | F68: 1279680 | G68: USD | H68: TotalCare - Trent 1000-K | I68: DEG 9054 January 2022 | J68: PAID | K68: 44628
A69: 1200 | B69: 1009374 | C69: 97504467 | D69: 44530 | E69: 44562 | F69: 5111568 | G69: USD | H69: TotalCare - Trent XWB-84 | I69: DEG 10215 January 2022 | J69: PAID | K69: 44628
F70: =SUM(F67:F69) -> 8020968
H71: W/C 14/03/22
A72: 1200 | B72: 1009374 | C72: 97524861 | D72: 44545 | E72: 44593 | F72: 1279680 | G72: USD | H72: TotalCare - Trent 1000-K | I72: DEG 9054 February 2022 | J72: PAID | K72: 44271
A73: 1200 | B73: 1009374 | C73: 97524863 | D73: 44545 | E73: 44593 | F73: 1629720 | G73: USD | H73: TotalCare - Trent 1000-D | I73: DEG 9054 February 2022 | J73: PAID | K73: 44271
A74: 1200 | B74: 1009374 | C74: 97545196 | D74: 44566 | E74: 44593 | F74: 5111568 | G74: USD | H74: TotalCare - Trent XWB-84 | I74: DEG 10215 February 2022 | J74: PAID | K74: 44271
A75: 2500 | B75: 1014433 | C75: 97569895 | D75: 44589 | E75: 44634 | F75: 64902 | G75: USD | H75: Lease Engine LLP Charges - Trent 1000 Pack B/C | I75: ESN 10588 DECEMBER 2021 | J75: PAID | K75: 44271
A76: 2500 | B76: 1014433 | C76: 97569899 | D76: 44589 | E76: 44634 | F76: 48490 | G76: USD | H76: Lease Engine LLP Charges - Trent 1000 Pack B/C | I76: ESN 10559 DECEMBER 2021 | J76: PAID | K76: 44271
A77: 2500 | B77: 1014433 | C77: 97569902 | D77: 44589 | E77: 44634 | F77: 47960 | G77: USD | H77: Lease Engine LLP Charges - Trent 1000 Pack B/C | I77: ESN 10353 December 2021 | J77: PAID | K77: 44271
F78: =SUM(F72:F77) -> 8182320
H79: W/C 21/03/22
A80: 1200 | B80: 1009374 | C80: 97559262 | D80: 44579 | E80: 44621 | F80: 1279680 | G80: USD | H80: TotalCare - Trent 1000-K | I80: DEG 9054 March 2022 | J80: PAID | K80: 44280
A81: 1200 | B81: 1009374 | C81: 97559251 | D81: 44579 | E81: 44621 | F81: 1629720 | G81: USD | H81: TotalCare - Trent 1000-D | I81: DEG 9054 March 2022 | J81: PAID | K81: 44280
A82: 1200 | B82: 1009374 | C82: 97568668 | D82: 44588 | E82: 44622 | F82: 5111568 | G82: USD | H82: TotalCare - Trent XWB-84 | I82: DEG 10215 March 2022 | J82: PAID | K82: 44280
F83: =SUM(F80:F82) -> 8020968
H84: W/C 28/03/22
A85: NO PAYMENT
F86: 0
H87: W/C 04/04/22
A88: 2500 | B88: 1014433 | C88: 97500022 | D88: 44525 | E88: 44570 | F88: 69378 | G88: USD | H88: Lease Engine LLP Charges - Trent 1000 Pack B/C | I88: ESN 10559 October 2021 | J88: PAID | K88: 44290
A89: 2500 | B89: 1014433 | C89: 97540555 | D89: 44561 | E89: 44606 | F89: 61918 | G89: USD | H89: Lease Engine LLP Charges - Trent XWB-84 | I89: ESN 10559 November 2021 | J89: PAID | K89: 44290
A90: 2500 | B90: 1014433 | C90: 97540556 | D90: 44561 | E90: 44606 | F90: 9232 | G90: USD | H90: Lease Engine LLP Charges - Trent XWB-84 | I90: ESN 21191 October 2021 | J90: PAID | K90: 44290
A91: 2500 | B91: 1014433 | C91: 97540557 | D91: 44561 | E91: 44606 | F91: 39236 | G91: USD | H91: Lease Engine LLP Charges - Trent XWB-84 | I91: ESN 21191 November 2021 | J91: PAID | K91: 44290
A92: 2500 | B92: 1014433 | C92: 97569900 | D92: 44589 | E92: 44634 | F92: 35197 | G92: USD | H92: Lease Engine LLP Charges - Trent XWB-84 | I92: ESN 21191 December 2021 | J92: PAID | K92: 44290
F93: =SUM(F88:F92) -> 214961
H94: W/C 11/04/22
A95: 2500 | B95: 1014433 | C95: 97228774 | D95: 44251 | E95: 44296 | F95: 19618 | G95: USD | H95: Lease Engine LLP Charges - Trent XWB-84 | I95: ESN 21111 JANUARY 2021 | J95: PAID | K95: 44299
A96: 2500 | B96: 1014433 | C96: 97243371 | D96: 44266 | E96: 44311 | F96: 31158 | G96: USD | H96: Lease Engine LLP Charges - Trent XWB-84 | I96: ESN 21111 FEBRUARY 2021 | J96: PAID | K96: 44299
A97: 2500 | B97: 1014433 | C97: 97312237 | D97: 44343 | E97: 44388 | F97: 30004 | G97: USD | H97: Lease Engine LLP Charges - Trent XWB-84 | I97: ESN 21111 MARCH 2021 | J97: PAID | K97: 44299
A98: 2500 | B98: 1014433 | C98: 97312244 | D98: 44343 | E98: 44388 | F98: 32889 | G98: USD | H98: Lease Engine LLP Charges - Trent XWB-84 | I98: ESN 21111 APRIL 2021 | J98: PAID | K98: 44299
A99: 2500 | B99: 1014433 | C99: 97337630 | D99: 44370 | E99: 44415 | F99: 36351 | G99: USD | H99: Lease Engine LLP Charges - Trent XWB-84 | I99: ESN 21111 May 2021 | J99: PAID | K99: 44299
A100: 2500 | B100: 1014433 | C100: 97371459 | D100: 44404 | E100: 44449 | F100: 25388 | G100: USD | H100: Lease Engine LLP Charges - Trent XWB-84 | I100: ESN 21111 June 2021 | J100: PAID | K100: 44299
A101: 2500 | B101: 1014433 | C101: 97500011 | D101: 44525 | E101: 44570 | F101: 43275 | G101: USD | H101: Lease Engine LLP Charges - Trent XWB-84 | I101: ESN 21111 July 2021 | J101: PAID | K101: 44299
A102: 2500 | B102: 1014433 | C102: 97500012 | D102: 44525 | E102: 44570 | F102: 30581 | G102: USD | H102: Lease Engine LLP Charges - Trent XWB-84 | I102: ESN 21111 August 2021 | J102: PAID | K102: 44299
A103: 2500 | B103: 1014433 | C103: 97500013 | D103: 44525 | E103: 44570 | F103: 38659 | G103: USD | H103: Lease Engine LLP Charges - Trent XWB-84 | I103: ESN 21111 September 2021 | J103: PAID | K103: 44299
A104: 2500 | B104: 1014433 | C104: 97500014 | D104: 44525 | E104: 44570 | F104: 36351 | G104: USD | H104: Lease Engine LLP Charges - Trent XWB-84 | I104: ESN 21111 October 2021 | J104: PAID | K104: 44299
A105: 2500 | B105: 1014433 | C105: 97569898 | D105: 44589 | E105: 44634 | F105: 43275 | G105: USD | H105: Lease Engine LLP Charges - Trent 1000 Pack B/C | I105: ESN 21111 December 2021 | J105: PAID | K105: 44299
A106: 2500 | B106: 1014433 | C106: 97222484 | D106: 44243 | E106: 44288 | F106: 30581 | G106: USD | H106: Lease Engine LLP Charges - Trent XWB-84 | I106: ESN 21191 JANUARY 2021 | J106: PAID | K106: 44299
... A110: 2500 | B110: 1014433 | C110: 97632475 | D110: 44642 | E110: 44642 | F110: 872 | G110: USD | H110: Lease Engine LLP Charges - Trent 1000 | I110: ESN 11124 May 2021 | J110: PAID | K110: 44299
F111: =SUM(F95:F110) -> 492454
H112: W/C 18/04/22
A113: 2500 | B113: 1014433 | C113: 97632476 | D113: 44642 | E113: 44642 | F113: 69760 | G113: USD | H113: Lease Engine LLP Charges - Trent 1000 | I113: ESN 11124 June 2021 | J113: PAID | K113: 44307
A114: 2500 | B114: 1014433 | C114: 97632478 | D114: 44642 | E114: 44642 | F114: 70632 | G114: USD | H114: Lease Engine LLP Charges - Trent 1000 | I114: ESN 11124 July 2021 | J114: PAID | K114: 44307
A115: 2500 | B115: 1014433 | C115: 97632480 | D115: 44642 | E115: 44642 | F115: 58424 | G115: USD | H115: Lease Engine LLP Charges - Trent 1000 | I115: ESN 11124 September 2021 | J115: PAID | K115: 44307
A116: 2500 | B116: 1014433 | C116: 97632481 | D116: 44642 | E116: 44642 | F116: 80224 | G116: USD | H116: Lease Engine LLP Charges - Trent 1000 | I116: ESN 11124 October2021 | J116: PAID | K116: 44307
A117: 2500 | B117: 1014433 | C117: 97632483 | D117: 44642 | E117: 44642 | F117: 72376 | G117: USD | H117: Lease Engine LLP Charges - Trent 1000 | I117: ESN 11124 November 2021 | J117: PAID | K117: 44307
A118: 2500 | B118: 1014433 | C118: 97632484 | D118: 44642 | E118: 44642 | F118: 78480 | G118: USD | H118: Lease Engine LLP Charges - Trent 1000 | I118: ESN 11124 December 2021 | J118: PAID | K118: 44307
A119: 2500 | B119: 1014433 | C119: 97632485 | D119: 44642 | E119: 44642 | F119: 76028 | G119: USD | H119: Lease Engine LLP Charges - Trent 1000 | I119: ESN 11124 January 2022 | J119: PAID | K119: 44307
A120: 1200 | B120: 1009374 | C120: 97354421 | D120: 44386 | E120: 44416 | F120: 453 | G120: USD | H120: Spare Parts - Pack B/C Spares | I120: 5X-P0369712 | J120: PAID | K120: 44307
A121: 1200 | B121: 1009374 | C121: 97558179 | D121: 44578 | E121: 44608 | F121: 6940 | G121: USD | H121: Trent XWB-84k Spares | I121: 4A-P0376672 | J121: PAID | K121: 44307
A122: 1200 | B122: 1009374 | C122: 97560549 | D122: 44580 | E122: 44610 | F122: 9495 | G122: USD | H122: Trent XWB-84k Spares | I122: 4A-P0376752 | J122: PAID | K122: 44307
A123: 1200 | B123: 1009374 | C123: 97269608 | D123: 44298 | E123: 44328 | F123: 11764 | G123: USD | H123: Trent XWB-84k Spares | I123: 4F-P0352564 | J123: PAID | K123: 44307
A124: 1200 | B124: 1009374 | C124: 97593123 | D124: 44608 | E124: 44638 | F124: 30920 | G124: USD | H124: Trent 1000 Pack B/C Spares | I124: 4C-P0378156 | J124: PAID | K124: 44307
...

Sheet 2022 Credit Usage
A1: Customer Name: | C1: Ethiopian Airlines / EA Enterprise
A2: Customer Nº: | C2: 1009374 / 1014433
A3: Contact email: | C3: Eyerusalemta@ethiopianairlines.com
A6: Company Code | B6: Account | C6: Reference | D6: Document Date | E6: Net due date | F6: Amount in doc. curr. | G6: Curr | H6: Text | I6: Assignment | J6: Comments | K6: Comments
A7: 1200 | B7: 1014433 | C7: 1620053556 | D7: 44386 | E7: 44386 | F7: -693.46 | G7: USD | H7: Credit note balance | I7: ESN10509 Credit - settlement agreement | J7: Usable credit | K7: < Available to use
A8: 1200 | B8: 1014433 | C8: 1620053707 | D8: 44873 | E8: 44873 | F8: -7051465.8 | G8: USD | H8: Credit note balance | I8: 2021 Trent 1000 Reconciliation | J8: Usable credit | K8: < Available to use
E9: Available Credits | F9: =SUM(F7:F7) -> -693.46
A12: Company Code | B12: Account | C12: Reference | D12: Document Date | E12: Net due date | F12: Amount in doc. curr. | G12: Curr | H12: Text | I12: Assignment | J12: Comments | K12: Comments
A13: 1200 | B13: 1014433 | C13: 1620053927 | D13: 44483 | E13: 44483 | F13: -3350377.4 | G13: USD | H13: Credit note balance | I13: Warranty Credit - ULW - CRC ESN 21117 | J13: USED | K13: 97458467
A14: 1200 | B14: 1014433 | C14: 1620053917 | D14: 44482 | E14: 44482 | F14: -3276026.5 | G14: USD | H14: Credit note balance | I14: Warranty Credit - ULW - CRC ESN 21185 | J14: USED | K14: 97458474
A15: 1200 | B15: 1014433 | C15: 1620053925 | D15: 44483 | E15: 44483 | F15: -3279287.5 | G15: USD | H15: Credit note balance | I15: Warranty Credit - ULW - CRC ESN 21230 | J15: USED | K15: 97456818
A16: 1200 | B16: 1014433 | C16: 1620053926 | D16: 44483 | E16: 44483 | F16: -3287443.2 | G16: USD | H16: Credit note balance | I16: Warranty Credit - ULW - CRC ESN 21229 | J16: USED | K16: 97452578
A17: 1200 | B17: 1009374 | C17: 1620054520 | D17: 44610 | E17: 44610 | F17: -285188 | G17: USD | H17: Credit note balance | I17: DEG9054/CN13307 | J17: USED | K17: Numerous on 10/06/22
A18: 1200 | B18: 1014433 | C18: 1620052627 | D18: 44210 | E18: 44210 | F18: -105732.34 | G18: USD | H18: Credit note balance | I18: Q1 2020 Deferred Interim settlement | J18: USED | K18: 97625156
A19: 1200 | B19: 1014433 | C19: 1620053707 | D19: 44431 | E19: 44431 | F19: -11919 | G19: USD | H19: Credit note balance | I19: Failure on ESN 21942 on 24th Jul 2021 | J19: USED | K19: 97625156
A20: 1200 | B20: 1009374 | C20: 1620054739 | D20: 44659 | E20: 44659 | F20: -11711 | G20: USD | H20: WAG4990/CA6811 | I20: DEG6272/WAG4990 | J20: USED | K20: 97625156
A21: 1200 | B21: 1014433 | C21: 1620054140 | D21: 44526 | E21: 44526 | F21: -4499795.7 | G21: USD | H21: Credit note balance | I21: Warranty Credit - ULW - CRC ESN 10410 | J21: USED | K21: 97508399
A22: 1200 | B22: 1009374 | C22: 1620054753 | D22: 44662 | E22: 44692 | F22: -1426282 | G22: USD | H22: Credit note balance | I22: Warranty Credit - ULW - CRC ESN 11139 | J22: USED | K22: 97603008
A23: 1200 | B23: 1009374 | C23: 1620054330 | D23: 44571 | E23: 44571 | F23: -1423146.2 | G23: USD | H23: Credit note balance | I23: Warranty Credit - ULW - CRC ESN 11108 | J23: USED | K23: 97653372
A24: 1200 | B24: 1009374 | C24: 2000557281 | D24: 44729 | E24: 44792 | F24: =#REF! -> #REF! | G24: USD | H24: Credit note balance | I24: Trent XWB Reconciliation Credit | J24: USED | K24: 97730879, 97730878 & 97744202
A25: 1200 | B25: 1009374 | C25: 1620054991 | D25: 44729 | E25: 44759 | F25: -3526043.5 | G25: USD | H25: Credit note balance | I25: Warranty Credit - ULW - CRC ESN 21428 | J25: USED | K25: < Available to use
A26: 1200 | B26: 1009374 | C26: 1620054992 | D26: 44729 | E26: 44759 | F26: -3501286.2 | G26: USD | H26: Credit note balance | I26: Warranty Credit - ULW - CRC ESN 21294 | J26: USED | K26: < Available to use
A27: 1200 | B27: 1009374 | C27: 1620054818 | D27: 44662 | E27: 44692 | F27: -3502526.8 | G27: USD | H27: Credit note balance | I27: Warranty Credit - ULW - CRC ESN 21273 | J27: USED | K27: < Available to use
A28: 1200 | B28: 1009374 | C28: 1620054958 | D28: 44725 | E28: 44755 | F28: -1426282 | G28: USD | H28: Credit note balance | I28: Warranty Credit - ULW - CRC ESN 11138 | J28: USED | K28: < Available to use
A29: 1200 | B29: 1009374 | C29: 1620054993 | D29: 44729 | E29: 44759 | F29: -3315388.1 | G29: USD | H29: Credit note balance | I29: Warranty Credit - ULW - CRC ESN 21186 | J29: USED | K29: 97508400
A30: 1200 | B30: 1014433 | C30: 1620053970 | D30: 44491 | E30: 44491 | F30: -4119030.9 | G30: USD | H30: Credit note balance | I30: Warranty Credit - ULW - CRC ESN 10409 | J30: USED | K30: 97459613
A31: 1200 | B31: 1014433 | C31: 1620053969 | D31: 44491 | E31: 44491 | F31: -4419321.7 | G31: USD | H31: Credit note balance | I31: Warranty Credit - ULW - CRC ESN 10434 | J31: USED | K31: 97460864
E32: Used Credits | F32: =SUM(F13:F31) -> #REF!
