Workbook
Name Slicer_Customer: #N/A
Name Slicer_Engine_Value_Stream: #N/A
Name Slicer_Engine_Value_Stream1: #N/A
Name Slicer_Expected_year_of_signature: #N/A
Name Slicer_Expected_year_of_signature1: #N/A
Name Slicer_Onerous_Non_Onerous: #N/A
Name Slicer_Onerous_Non_Onerous1: #N/A
Name Slicer_Region: #N/A
Name Slicer_Region1: #N/A
Name Slicer_Restructure_Type: #N/A
Name Slicer_Restructure_Type1: #N/A
Name Slicer_Top_Level_EVS: #N/A
Name Slicer_Top_Level_EVS1: #N/A

Sheet COVER
C3: COMMERCIAL OPTIMISATION OPPORTUNITY REPORT
D10: Link to Guidance Document | H10: Guidance | N10: Restructure Type - Definitions
H13: 1. All plans defined as 'Full Contract Restructures' and over £10m CRP term benefit require a project plan. 2. All initiatives defined as 'Simple/Limited Restructures', 'Increase Spare Engine Holding' or under £10m CRP term benefit do not require a project plan and will be monitored using the hopper. 3. All initiatives should be grouped by engine programme (Trent 1000, Trent 900, Trent XWB 84 etc). Each engine programme will require its own project plan. | N13: 1. 'Full Contract Restructure' - When a restructure means changing the contract term, plus any other changes such as price (rate/escalation), or credit restructure. Requires Service Business to re-model the CRP 2. 'Simple/Limited Restructure' - For one or two small changes which do not impact the CRP Term, such as Credit back restructure (standalone), TotalCare Escalation or rate increases/trade, Credit or Guarantee restructure. Requires Customer Finance team to model using a simple spreadsheet. 3. 'Increase Spare Engine Holidng' - When selling incremental Spare Engines to calculates NDSES cost savings. Requires Fleet Business Managers to model using the Poisson tool.
D28: Link to Project Document

Sheet GLOBAL LOG
C3: Global Commercial Optimisation Hopper
C5: Region | D5: Customer | E5: Engine Value Stream | F5: Top Level EVS | G5: VP/Account Manager Owner | H5: Restructure Type | I5: Opportunity Maturity | J5: Onerous/Non Onerous | K5: Initative | L5: Project Plan Requirements | M5: Status | N5: Expected year of signature | O5: Signature AP | P5: CRP Term Benefit £m | Q5: Profit 2026 £m | R5: Profit 2027 £m | S5: Profit 2028 £m | T5: Profit 2029 £m | U5: Profit 2030 £m
C6: Americas | D6: FedEx Corporation | E6: RB211-535 | F6: =IFERROR(VLOOKUP(E6,'Data Validations'!$A$2:$B$13,2,0),"") -> TFAME | G6: Meagan Austgen | H6: Full Contract Restructure | I6: Mature | J6: Not Onerous | K6: FedEx - agreement/amendment to unadministrable TotalCare clauses and incentivisation of SV inductions - RB211-535 | L6: =IF(C6="","",IF(AND(OR(H6="Full Contract Restructure"),P6>9.9),"Required","Not Required")) -> Required | M6: Negotations Started | N6: 2026 | O6: AP6 | P6: 21.15 | Q6: 6.43 | R6: 6.96 | S6: 7.77
C7: Americas | D7: American Airlines | E7: Trent 800 | F7: =IFERROR(VLOOKUP(E7,'Data Validations'!$A$2:$B$13,2,0),"") -> TFAME | G7: David Gonzalez-Gomez | H7: Full Contract Restructure | I7: Mature | J7: Not Onerous | K7: American Airlines requested input on longer extension to 2035 | L7: =IF(C7="","",IF(AND(OR(H7="Full Contract Restructure"),P7>9.9),"Required","Not Required")) -> Required | M7: Financial Modelling Complete | N7: 2026 | O7: AP12 | P7: 318 | Q7: 0
C8: APAC | D8: Thai Airways International Ltd | E8: Trent XWB-84 | F8: =IFERROR(VLOOKUP(E8,'Data Validations'!$A$2:$B$13,2,0),"") -> Trent XWB | G8: Nick Chadwick / Ben Gan | H8: Full Contract Restructure | I8: Mature | J8: Not Onerous | K8: Min term extension involving reinstating some discount, EOCL removal and escalation improvement. Jun-2025 Level 3 approval secured in .Jul 2025 - Proposal presented to THAI with minor trades, Sep 2025 formal proposal requested in, Feb 2026 proposal issued and expect to contract pending THA acceptance Apr 2026 - Senior engagement at AIX, awaiting feedback before next steps, possible adjustment pending ICT confirmation. | L8: =IF(C8="","",IF(AND(OR(H8="Full Contract Restructure"),P8>9.9),"Required","Not Required")) -> Required | M8: Negotations Started | N8: 2026 | O8: AP12 | P8: 294.1 | Q8: tbc | R8: Confirm with Harry | S8: Confirm with Harry | T8: Confirm with Harry | U8: Confirm with Harry
C9: MEA | D9: Emirates | E9: Trent XWB-84 | F9: =IFERROR(VLOOKUP(E9,'Data Validations'!$A$2:$B$13,2,0),"") -> Trent XWB | G9: Matt Whatley / Darren O'neill | H9: Full Contract Restructure | I9: Mature | J9: Not Onerous | K9: Finiq 2 - 3 year-extension + LRU Management + 23 a/c. Term benefit includes a % of DI7 | L9: =IF(C9="","",IF(AND(OR(H9="Full Contract Restructure"),P9>9.9),"Required","Not Required")) -> Required | M9: Contracting Concluded | N9: 2025 | P9: 193 | Q9: 0
C10: APAC | D10: Singapore Airlines | E10: Trent XWB-84 | F10: =IFERROR(VLOOKUP(E10,'Data Validations'!$A$2:$B$13,2,0),"") -> Trent XWB | G10: Paul Hallam | H10: Full Contract Restructure | I10: Mature | J10: Onerous Contract | K10: Project Aegis contractual negotiations continue - final key points (Charging Period, R-R Mitigation, Build Life Guarantee) being worked ahead of final closing meeting between JK and HP Lau Note expected approval to close in March 2026 is £5m and so these figures have not been amended | L10: =IF(C10="","",IF(AND(OR(H10="Full Contract Restructure"),P10>9.9),"Required","Not Required")) -> Required | M10: Contracting Started | N10: 2026 | O10: AP3 | P10: =236-5 -> 231 | Q10: 24 | R10: Confirm with Harry | S10: Confirm with Harry | T10: Confirm with Harry | U10: Confirm with Harry
C11: APAC | D11: Vietnam Airlines | E11: Trent XWB-84 | F11: =IFERROR(VLOOKUP(E11,'Data Validations'!$A$2:$B$13,2,0),"") -> Trent XWB | G11: Paul Hallam | H11: Full Contract Restructure | I11: Mature | J11: Not Onerous | K11: Life min term extension from 2027 to 2031 to align with lease term extension and 2x XWB SPE sales in Q4 2026. Linked with Claim and reconcliation account issues. Initial engagement with customer structurally ok. Construstive Level 2 workshop took place on 8 July and follow up Level 2 strategy to be planned for end of July - considering if we can find a solution that could be used Trent XWB engines, rather than new in 2026. Already commited in XWB 5YP | L11: =IF(C11="","",IF(AND(OR(H11="Full Contract Restructure"),P11>9.9),"Required","Not Required")) -> Required | M11: Negotations Started | N11: 2026 | O11: AP6 | P11: 186 | Q11: 10 | R11: 6 | S11: 7 | T11: 20 | U11: 9
C12: APAC | D12: Singapore Airlines | E12: Trent 1000 | F12: =IFERROR(VLOOKUP(E12,'Data Validations'!$A$2:$B$13,2,0),"") -> TFAME | G12: Paul Hallam | H12: Full Contract Restructure | I12: Immature | J12: Onerous Contract | K12: Strategy being developed 1) lessons learnt from Trent XWB Project Aegis in terms of complexity, time to conclude and not doing the Final Restoration Shop Visit Guarantee. 2) Proposed strategy to split into Phase 1 (Period of Cover(and Phase 2 (post term extension) abd Phase 2 post POC extension including escalated and value trades. 3) Phase 1 customer engagement planned ahead of the CEO meeting (8 April 2026) | L12: =IF(C12="","",IF(AND(OR(H12="Full Contract Restructure"),P12>9.9),"Required","Not Required")) -> Required | M12: ICT formed | N12: 2026 | O12: AP12 | P12: 80 | Q12: 80 | R12: Confirm with Bobby | S12: Confirm with Bobby | T12: Confirm with Bobby | U12: Confirm with Bobby
C13: MEA | D13: Emirates | E13: Trent 900 | F13: Trent 900 | G13: Matt Whatley / Darren O'neill | H13: Full Contract Restructure | I13: Mature | J13: Not Onerous | K13: Pantheon - Trent 900 Full MRO for improved CRP | L13: =IF(C13="","",IF(AND(OR(H13="Full Contract Restructure"),P13>9.9),"Required","Not Required")) -> Required | M13: Financial Modelling Started | N13: 2026 | O13: AP9 | P13: 73 | Q13: 0
C14: Europe | D14: British Airways | E14: Trent XWB-97 | F14: =IFERROR(VLOOKUP(E14,'Data Validations'!$A$2:$B$13,2,0),"") -> Trent XWB | G14: Matt O'Connor | H14: Full Contract Restructure | I14: Mature | J14: Not Onerous | K14: Life Min Term extension to 24 years for owned a/c and 12 years for leased a/c, plus removal of EoCL for a $/efh discount on both Engine & LLPs. | L14: =IF(C14="","",IF(AND(OR(H14="Full Contract Restructure"),P14>9.9),"Required","Not Required")) -> Required | M14: Negotations Started | N14: 2026 | O14: AP6 | P14: 330
C15: APAC | D15: Srilankan Airlines | E15: Trent 700 | F15: =IFERROR(VLOOKUP(E15,'Data Validations'!$A$2:$B$13,2,0),"") -> TFAME | G15: Kendrick Lim | H15: Full Contract Restructure | I15: Mature | J15: Not Onerous | K15: Min term extension of existing contract (Life) of 6 years. This will need to be revised as per FBM direction post Avalon requirements to extend to the next SV as the min term which will in turn amend the financials that was already prepared. Previous IY profit impact was £(7)m negative due to being lower % margin than existing 75% but > 57% fleet average. However, this has not been to L2 approval yet. Work on next SV duration will require urgent resource | L15: =IF(C15="","",IF(AND(OR(H15="Full Contract Restructure"),P15>9.9),"Required","Not Required")) -> Required | M15: Negotations Started | N15: 2026 | O15: AP6 | P15: =150/1.44 -> 104.16667 | Q15: 20 | R15: 2 | S15: 1 | T15: 8 | U15: 15
C16: Europe | D16: World2Fly | E16: Trent XWB-84 | F16: =IFERROR(VLOOKUP(E16,'Data Validations'!$A$2:$B$13,2,0),"") -> Trent XWB | G16: Neeraj Sunger | H16: Increase Spare Engine Holding | I16: Mature | J16: Not Onerous | K16: Min term extension (life) - 1 a/c exit from 2026. 5yr term but 12yr lease term. Contract extension in 2025 Plus sell used SPE to reduce NDSES costs in CRP (Minimal but supports the OE sale) | L16: =IF(C16="","",IF(AND(OR(H16="Full Contract Restructure"),P16>9.9),"Required","Not Required")) -> Not Required | M16: ICT formed | N16: 2026
C17: Europe | D17: British Airways | E17: Trent 1000 | F17: =IFERROR(VLOOKUP(E17,'Data Validations'!$A$2:$B$13,2,0),"") -> TFAME | G17: Matt O'Connor | H17: Full Contract Restructure | I17: Mature | J17: Onerous Contract | K17: Life Min Term extension to 25 years for owned a/c and 12 years for leased a/c, plus removal of EoCL for a $/efh discount on both Engine & LLPs. | L17: =IF(C17="","",IF(AND(OR(H17="Full Contract Restructure"),P17>9.9),"Required","Not Required")) -> Required | M17: Negotations Started | N17: 2026 | O17: AP6 | P17: 303 | Q17: 35
C18: Americas | D18: Hawaiian Airlines | E18: Trent 700 | F18: =IFERROR(VLOOKUP(E18,'Data Validations'!$A$2:$B$13,2,0),"") -> TFAME | G18: Harrison Green | H18: Full Contract Restructure | I18: Mature | J18: Not Onerous | K18: EFH discount in return for addition 20x SV commitment. Negotiations ongoing. | L18: =IF(C18="","",IF(AND(OR(H18="Full Contract Restructure"),P18>9.9),"Required","Not Required")) -> Required | M18: Contracting Concluded | N18: 2025 | O18: AP11 | P18: 53.2 | Q18: 7.6 | R18: 7.6 | S18: 7.6 | T18: 7.6 | U18: 7.6
C19: MEA | D19: Qatar | E19: Trent XWB-84 | F19: =IFERROR(VLOOKUP(E19,'Data Validations'!$A$2:$B$13,2,0),"") -> Trent XWB | G19: Matt Whatley / Issy Walton | H19: Full Contract Restructure | I19: Mature | J19: Not Onerous | K19: Exit for convenience removal -84 | L19: =IF(C19="","",IF(AND(OR(H19="Full Contract Restructure"),P19>9.9),"Required","Not Required")) -> Not Required | M19: Contracting Started | N19: 2026 | O19: AP5 | Q19: 15 | R19: 39 | S19: 16 | T19: 16 | U19: 11
C20: MEA | D20: Etihad | E20: Trent XWB-97 | F20: =IFERROR(VLOOKUP(E20,'Data Validations'!$A$2:$B$13,2,0),"") -> Trent XWB | G20: Gordon Deas | H20: Simple/Limited Restructure | I20: Mature | J20: Not Onerous | K20: TCA Reconciliation (CRP Improvement) | L20: =IF(C20="","",IF(AND(OR(H20="Full Contract Restructure"),P20>9.9),"Required","Not Required")) -> Not Required | M20: Contracting Concluded | N20: 2025 | P20: =3.2/1.38 -> 2.3188406 | Q20: 2.32
C21: MEA | D21: Emirates | E21: Trent XWB-84 | F21: =IFERROR(VLOOKUP(E21,'Data Validations'!$A$2:$B$13,2,0),"") -> Trent XWB | G21: Matt Whatley / Darren O'neill | H21: Simple/Limited Restructure | I21: Immature | J21: Not Onerous | K21: Trent XWB Full MRO for improved CRP | L21: =IF(C21="","",IF(AND(OR(H21="Full Contract Restructure"),P21>9.9),"Required","Not Required")) -> Not Required | M21: Initial idea | N21: 2027 | P21: 33 | Q21: 0
C22: MEA | D22: Qatar | E22: Trent XWB-97 | F22: =IFERROR(VLOOKUP(E22,'Data Validations'!$A$2:$B$13,2,0),"") -> Trent XWB | G22: Matt Whatley / Issy Walton | H22: Full Contract Restructure | I22: Immature | J22: Not Onerous | K22: Exit for convenience removal -97 | L22: =IF(C22="","",IF(AND(OR(H22="Full Contract Restructure"),P22>9.9),"Required","Not Required")) -> Not Required | M22: Initial idea | N22: 2027
C23: MEA | D23: Ethiopian Airlines | E23: Trent XWB-84 | F23: =IFERROR(VLOOKUP(E23,'Data Validations'!$A$2:$B$13,2,0),"") -> Trent XWB | G23: Gordon Deas | H23: Simple/Limited Restructure | I23: Mature | J23: Not Onerous | K23: Restructure exisiting contract -Credit Back Removal As part of A350-900 campaign | L23: =IF(C23="","",IF(AND(OR(H23="Full Contract Restructure"),P23>9.9),"Required","Not Required")) -> Not Required | M23: ICT formed | N23: 2026 | Q23: 0
C24: Europe | D24: Iberia | E24: Trent XWB-84 | F24: =IFERROR(VLOOKUP(E24,'Data Validations'!$A$2:$B$13,2,0),"") -> Trent XWB | G24: Neeraj Sunger | H24: Simple/Limited Restructure | I24: Mature | J24: Not Onerous | K24: Min term extension (life) - 2x leased a/c meet minimum term in 2026. Contract extension to 2030 inline with revised lease terms. Contracted in 2025, linked to matrix extension resolution. | L24: =IF(C24="","",IF(AND(OR(H24="Full Contract Restructure"),P24>9.9),"Required","Not Required")) -> Not Required | M24: Contracting Concluded | N24: 2025
C25: Americas | D25: Air Canada | E25: Trent 700 | F25: =IFERROR(VLOOKUP(E25,'Data Validations'!$A$2:$B$13,2,0),"") -> TFAME | G25: David Gonzalez-Gomez | I25: Immature | J25: Not Onerous | K25: Flex contract extension. Current contract expiring end of 2027. | L25: =IF(C25="","",IF(AND(OR(H25="Full Contract Restructure"),P25>9.9),"Required","Not Required")) -> Not Required | P25: 15 | Q25: =0.001 -> 0.001 | R25: =0.001 -> 0.001 | S25: 5 | T25: 5 | U25: 5
C26: Europe | D26: Lufthansa | E26: Trent XWB-84 | F26: =IFERROR(VLOOKUP(E26,'Data Validations'!$A$2:$B$13,2,0),"") -> Trent XWB | G26: Keith Coull | H26: Simple/Limited Restructure | I26: Mature | J26: Not Onerous | K26: Pull forward of spare engines, working capital improvements (payment terms), reverse lease of engines, EP upsell | L26: =IF(C26="","",IF(AND(OR(H26="Full Contract Restructure"),P26>9.9),"Required","Not Required")) -> Not Required | M26: Negotations Concluded | N26: 2026 | O26: AP3 | P26: 14
C27: APAC | D27: Royal Brunei Airlines | E27: Trent 1000 | F27: =IFERROR(VLOOKUP(E27,'Data Validations'!$A$2:$B$13,2,0),"") -> TFAME | G27: Kendrick Lim | I27: Mature | J27: Onerous Contract | K27: 4th Mar 26 (KL): Awaiting campaign final decision. Either way a requirement to account to aircraft swap dates on existing min term is needed to lock in more TCA vs CRP which only goes out for 12-18mths. RBA has asked for the contract for the new aircraft which will require this to be signed in parallel, so the urgency has gone up. This specific Commercial Optimisation Initiative type should be considered a Term Extension as opposed to New Aircraft. | L27: =IF(C27="","",IF(AND(OR(H27="Full Contract Restructure"),P27>9.9),"Required","Not Required")) -> Not Required | M27: ICT formed | P27: 13 | Q27: 4 | R27: Confirm with Bobby | S27: Confirm with Bobby | T27: Confirm with Bobby | U27: Confirm with Bobby
C28: MEA | D28: Saudia | E28: Trent 700 | F28: =IFERROR(VLOOKUP(E28,'Data Validations'!$A$2:$B$13,2,0),"") -> TFAME | G28: Georges Abou-Nasr | H28: Full Contract Restructure | I28: Immature | J28: Not Onerous | K28: Extend Classic | L28: =IF(C28="","",IF(AND(OR(H28="Full Contract Restructure"),P28>9.9),"Required","Not Required")) -> Not Required | M28: Initial idea | N28: 2027 | Q28: 0 | R28: 0
C29: Europe | D29: LOT Polish Airlines | E29: Trent 1000 | F29: =IFERROR(VLOOKUP(E29,'Data Validations'!$A$2:$B$13,2,0),"") -> TFAME | G29: Sean Burke | H29: Increase Spare Engine Holding | I29: Immature | J29: Not Onerous | K29: 1 new SPE in Q1 linked to 2 Dr Peters transition a/c. Life Min Term extension on purchased existing fleet as part of the 9 a/c campaign. | L29: =IF(C29="","",IF(AND(OR(H29="Full Contract Restructure"),P29>9.9),"Required","Not Required")) -> Not Required | M29: Negotations Started | N29: 2026 | O29: AP6 | P29: 10
C30: Europe | D30: Condor Flugdienst Gmbh | E30: Trent 7000 | F30: =IFERROR(VLOOKUP(E30,'Data Validations'!$A$2:$B$13,2,0),"") -> TFAME | G30: Aaron Taylor | H30: Increase Spare Engine Holding | I30: Mature | J30: Not Onerous | K30: NDSES improvement through SPE sales associated to new deal + FCRG and NED Remedy Improvement | L30: =IF(C30="","",IF(AND(OR(H30="Full Contract Restructure"),P30>9.9),"Required","Not Required")) -> Not Required | M30: Contracting Started | N30: 2026 | P30: =12.9/1.38 -> 9.3478261
C31: Europe | D31: TAP Air Portugal | E31: Trent 7000 | F31: =IFERROR(VLOOKUP(E31,'Data Validations'!$A$2:$B$13,2,0),"") -> TFAME | G31: Richard Docherty | H31: Increase Spare Engine Holding | I31: Mature | J31: Not Onerous | K31: Two aircraft delays to Original Delivery Schedule. Plan to progress 2026 Used SPE, credit pull-forward for CRP improvement and Optional AOG+1 NDSES Service. | L31: =IF(C31="","",IF(AND(OR(H31="Full Contract Restructure"),P31>9.9),"Required","Not Required")) -> Not Required | M31: Negotations Concluded | N31: 2026 | P31: 6
C32: MEA | D32: Gulf | E32: Trent 1000 | F32: =IFERROR(VLOOKUP(E32,'Data Validations'!$A$2:$B$13,2,0),"") -> TFAME | G32: Georgia Chapman | H32: Full Contract Restructure | I32: Mature | J32: Not Onerous | K32: Commerical Offer - 3 Year Extension/ SPE Sales (NDSES Improvement) | L32: =IF(C32="","",IF(AND(OR(H32="Full Contract Restructure"),P32>9.9),"Required","Not Required")) -> Required | M32: Negotations Started | N32: 2026 | O32: AP6 | P32: 32.3 | Q32: -7.4 | R32: 2.5 | S32: 3.4 | T32: 4.6 | U32: 4.1
C33: MEA | D33: Rwanda | E33: Trent 700 | F33: =IFERROR(VLOOKUP(E33,'Data Validations'!$A$2:$B$13,2,0),"") -> TFAME | G33: Gordon Deas | H33: Full Contract Restructure | I33: Immature | J33: Not Onerous | K33: TCA Life Min Term Extension | L33: =IF(C33="","",IF(AND(OR(H33="Full Contract Restructure"),P33>9.9),"Required","Not Required")) -> Not Required | M33: Initial idea | N33: 2026 | P33: 8.88 | Q33: 0 | R33: 0
C34: MEA | D34: Ethiopian Airlines | E34: Trent XWB-84 | F34: =IFERROR(VLOOKUP(E34,'Data Validations'!$A$2:$B$13,2,0),"") -> Trent XWB | G34: Gordon Deas | H34: Full Contract Restructure | I34: Mature | J34: Not Onerous | K34: Restructure exisiting contract - Min Term Extension As part of A350-900 campaign | L34: =IF(C34="","",IF(AND(OR(H34="Full Contract Restructure"),P34>9.9),"Required","Not Required")) -> Not Required | M34: ICT formed | N34: 2026 | Q34: 0
C35: MEA | D35: Egypt | E35: Trent XWB-84 | F35: =IFERROR(VLOOKUP(E35,'Data Validations'!$A$2:$B$13,2,0),"") -> Trent XWB | G35: Georges Abou-Nasr | H35: Full Contract Restructure | I35: Immature | J35: Not Onerous | K35: EP Upsell (2028+ deliveries) | L35: =IF(C35="","",IF(AND(OR(H35="Full Contract Restructure"),P35>9.9),"Required","Not Required")) -> Not Required | M35: Initial idea | N35: 2027
C36: Greater China | D36: China Southern | E36: Trent 700 | F36: =IFERROR(VLOOKUP(E36,'Data Validations'!$A$2:$B$13,2,0),"") -> TFAME | G36: Daniel Hector | H36: Simple/Limited Restructure | I36: Mature | J36: Not Onerous | K36: Updated 27/02/2026: Add ex-Block 1 Spare Engine to Block 2 TCA with Buy-in SV at SelectCare Pricing (less exit credits) delivering dilution benefits. Pricing and use of exit credit appoved at L2 in 2025. SV slot currently identified in Q2 2026 and can be secured if deal can rapidly be done. The method of contracting internally agreed to be added to Block 2 Buy-in fee. Feb 2026: customer going through final internal approvals. 25/07/2025: Add ex-Block 1 Spare Engine to Block 2 TCA with Buy-In SV at SelectCare Pricing (less exit credits) delivering dilution benefits. Pricing and use of exit credit approved at L2 in May-25. First round of discussion with customer in early June. Customer has since been evaluating internally and not yet provided formal feedback. SV slot identified in Q3 2025 and can be secured if deal can rapidly be done. Contracting method confirmed by value stream to be Add to Block 2 with Buy-in Fee. | L36: =IF(C36="","",IF(AND(OR(H36="Full Contract Restructure"),P36>9.9),"Required","Not Required")) -> Not Required | M36: Negotations Started | N36: 2026 | P36: 5 | Q36: 5
C37: Americas | D37: Keylime | E37: AE3007 | F37: =IFERROR(VLOOKUP(E37,'Data Validations'!$A$2:$B$13,2,0),"") -> TFAME | G37: Cory Noel | H37: Simple/Limited Restructure | I37: Mature | J37: Not Onerous | K37: Keylime Air _ AE3007 _ Add 2 in possession aircraft to TotalCare & extend all to 2030 | L37: =IF(C37="","",IF(AND(OR(H37="Full Contract Restructure"),P37>9.9),"Required","Not Required")) -> Not Required | M37: Contracting Concluded | N37: 2025 | P37: 5 | Q37: 0
C38: APAC | D38: All Nippon Airways | E38: Trent 1000 | F38: =IFERROR(VLOOKUP(E38,'Data Validations'!$A$2:$B$13,2,0),"") -> TFAME | G38: Nick Chadwick / Chong Sien Lim | H38: Increase Spare Engine Holding | I38: Immature | K38: Acceleration of backlog assets from Boeing to backstop Trent 1000 fleet health. Financial opportunity relates to direct sale of engines to ANA (Q4 25) and mitigation of NDSES costs/remedies. We have positioned optimising economics to ANA, offsetting a $33m non-contractual claim for Trent 1000 disruption in 2024. L2 approved trading $7.3m of NDSES savings for 2025, to be ‘offset’ against their claim. Proposal communicated to ANA 31/7, contract amendment being drafted for submission by 9/8. (Note: potential for further 2026 NDSES remedy avoidance of ~US30m). | L38: =IF(C38="","",IF(AND(OR(H38="Full Contract Restructure"),P38>9.9),"Required","Not Required")) -> Not Required | M38: Contracting Concluded | N38: 2025 | P38: 4.9 | Q38: =4.9*0.42 -> 2.058
C39: Americas | D39: Sterling | E39: AE2100 | F39: =IFERROR(VLOOKUP(E39,'Data Validations'!$A$2:$B$13,2,0),"") -> TFAME | G39: Cory Noel | H39: Full Contract Restructure | I39: Mature | J39: Not Onerous | K39: Sterling _ AE2100 _ restructure & add spare engines | L39: =IF(C39="","",IF(AND(OR(H39="Full Contract Restructure"),P39>9.9),"Required","Not Required")) -> Not Required | M39: Financial Modelling Complete | N39: 2026 | P39: 3.87 | Q39: 0
C40: MEA | D40: Austral | E40: Trent 1000 | F40: =IFERROR(VLOOKUP(E40,'Data Validations'!$A$2:$B$13,2,0),"") -> TFAME | G40: Georgia Chapman | H40: Full Contract Restructure | I40: Immature | J40: Not Onerous | K40: TCA Extension (Life)/Exit credit trade | L40: =IF(C40="","",IF(AND(OR(H40="Full Contract Restructure"),P40>9.9),"Required","Not Required")) -> Not Required | M40: Initial idea | P40: 3.552 | Q40: 0
C41: MEA | D41: Ethiopian Airlines | E41: Trent 1000 | F41: =IFERROR(VLOOKUP(E41,'Data Validations'!$A$2:$B$13,2,0),"") -> TFAME | G41: Gordon Deas | H41: Full Contract Restructure | I41: Mature | J41: Onerous Contract | K41: TCA Life Min Term Extension (life) As part of 787-9 campaign | L41: =IF(C41="","",IF(AND(OR(H41="Full Contract Restructure"),P41>9.9),"Required","Not Required")) -> Not Required | M41: ICT formed | N41: 2026 | Q41: 23
C42: MEA | D42: Tanzania | E42: Trent 1000 | F42: =IFERROR(VLOOKUP(E42,'Data Validations'!$A$2:$B$13,2,0),"") -> TFAME | G42: Gordon Deas | H42: Increase Spare Engine Holding | I42: Mature | J42: Not Onerous | K42: Sale of incremental spare engine. NDSES CRP | L42: =IF(C42="","",IF(AND(OR(H42="Full Contract Restructure"),P42>9.9),"Required","Not Required")) -> Not Required | M42: Contracting Concluded | N42: 2026 | O42: AP4 | P42: 2.62848 | Q42: 0.525696 | R42: 0.525696
C43: Europe | D43: Virgin Atlantic | E43: Trent 1000 | F43: =IFERROR(VLOOKUP(E43,'Data Validations'!$A$2:$B$13,2,0),"") -> TFAME | G43: Keith Coull | H43: Increase Spare Engine Holding | I43: Mature | J43: Onerous Contract | K43: Sale of incremental Trent 1000 used SPE to meet inventory targets with RRPF S&LB. Review of NDSES cost savings and CRP improvements. | L43: =IF(C43="","",IF(AND(OR(H43="Full Contract Restructure"),P43>9.9),"Required","Not Required")) -> Not Required | M43: Negotations Started | N43: 2026 | O43: AP6 | P43: 2 | Q43: 2
C44: Europe | D44: British Airways | E44: Trent 900 | F44: =IFERROR(VLOOKUP(E44,'Data Validations'!$A$2:$B$13,2,0),"") -> TFAME | G44: Matt O'Connor | H44: Full Contract Restructure | I44: Mature | J44: Not Onerous | K44: Descoping of nacelle services (thrust reverser) | L44: =IF(C44="","",IF(AND(OR(H44="Full Contract Restructure"),P44>9.9),"Required","Not Required")) -> Not Required | M44: ICT formed | N44: 2026 | P44: 1.1 | Q44: 0.5 | R44: 0
C45: Americas | D45: Keylime | E45: AE3007 | F45: =IFERROR(VLOOKUP(E45,'Data Validations'!$A$2:$B$13,2,0),"") -> TFAME | G45: Cory Noel | H45: Simple/Limited Restructure | I45: Mature | J45: Not Onerous | K45: Keylime Air _ AE3007 _ Add 2 aircraft to TotalCare, purchase of AC under eval | L45: =IF(C45="","",IF(AND(OR(H45="Full Contract Restructure"),P45>9.9),"Required","Not Required")) -> Not Required | M45: Contracting Started | N45: 2026 | P45: 1 | Q45: 0
C46: Americas | D46: Satena | E46: AE3007 | F46: =IFERROR(VLOOKUP(E46,'Data Validations'!$A$2:$B$13,2,0),"") -> TFAME | G46: Cory Noel | H46: Simple/Limited Restructure | I46: Immature | J46: Not Onerous | K46: Satena _ AE3007 _ Contract extension for 2 AC | L46: =IF(C46="","",IF(AND(OR(H46="Full Contract Restructure"),P46>9.9),"Required","Not Required")) -> Not Required | P46: 1 | Q46: 0
C47: MEA | D47: Ethiopian Airlines | E47: Trent XWB-84 | F47: =IFERROR(VLOOKUP(E47,'Data Validations'!$A$2:$B$13,2,0),"") -> Trent XWB | G47: Gordon Deas | H47: Simple/Limited Restructure | I47: Immature | J47: Not Onerous | K47: Restructure exisiting contract -Increase escalation As part of A350-900 sales campaign | L47: =IF(C47="","",IF(AND(OR(H47="Full Contract Restructure"),P47>9.9),"Required","Not Required")) -> Not Required | M47: ICT formed | N47: 2027 | P47: 0 | Q47: 0
C48: Americas | D48: United | E48: RB211-535 | F48: =IFERROR(VLOOKUP(E48,'Data Validations'!$A$2:$B$13,2,0),"") -> TFAME | G48: Meagan Austgen | I48: Immature | J48: Not Onerous | K48: UNITED TotalCare restructure to SelectCare and term extension - 535E$ | L48: =IF(C48="","",IF(AND(OR(H48="Full Contract Restructure"),P48>9.9),"Required","Not Required")) -> Not Required | P48: 0 | Q48: 0 | R48: 0 | S48: 0 | T48: 0 | U48: 0
C49: APAC | D49: Air New Zealand | E49: Trent 1000 | F49: =IFERROR(VLOOKUP(E49,'Data Validations'!$A$2:$B$13,2,0),"") -> TFAME | G49: Kendrick Lim | H49: Simple/Limited Restructure | I49: Immature | J49: Onerous Contract | K49: Min Term extension of existing contract 4 to 6 years post L1 last week. Fixed SV's to propose to be ascertained with support from Service business planner run post min term. Customer on board ("Pulling") and is waiting for RR proposal. Whilst we have a phase 1 and Phase 2 approach (Phase 1 not requiring additional support from outside of AM) we would seek to lock in resource in Q2 2025. Phase 1 amendment has now been shared with ANZ (10 July 2025) with initial feedback received from ANZ (24 July 2025). Action is on R-R to respond. | L49: =IF(C49="","",IF(AND(OR(H49="Full Contract Restructure"),P49>9.9),"Required","Not Required")) -> Not Required | M49: Negotations Started | N49: 2026 | O49: AP6 | P49: 14 | Q49: 14 | R49: Confirm with Bobby | S49: Confirm with Bobby | T49: Confirm with Bobby | U49: Confirm with Bobby
C50: APAC | D50: All Nippon Airways | E50: Trent 1000 | F50: =IFERROR(VLOOKUP(E50,'Data Validations'!$A$2:$B$13,2,0),"") -> TFAME | G50: Nick Chadwick / Chong Sien Lim | I50: Immature | K50: Restructure of ANA spare engine solution, utilising off-ramp of our Trent 1000 lease pool assets. Current spare engine holding is 15%, we are targeting uplifting closer to 20%, an opportunity for up to 8 used assets. Our lease pool engines are capitalised at cost, upside opportunity to transact at a premium to our balance sheet value. Any discount to market price will be offset against ANA's $33m non-contractual claim for Trent 1000 disruption in 2024. L2 rejected our simple approach of offering credits towards future spare engine purchases. Further due diligence required on both sides to align on the end solution, representing phase 2 of value co-creation with ANA. | L50: =IF(C50="","",IF(AND(OR(H50="Full Contract Restructure"),P50>9.9),"Required","Not Required")) -> Not Required | N50: 2026 | Q50: 0
C51: APAC | D51: Singapore Airlines | E51: Trent 900 | F51: =IFERROR(VLOOKUP(E51,'Data Validations'!$A$2:$B$13,2,0),"") -> TFAME | G51: Paul Hallam | I51: Mature | K51: To be assessed in 2025 - possible opportunity to harmoinise SelectCare & TCA contracts. A few open Trent 900 commercial items will be closed as part of Aegis closing position - with further optimisation opportunities to be assessed later in 2025, with scope for improvements to be included as part of the Trent 1000 optimisation project. Start expeceted in 2026 given Aegis contracting delay and Trent 1000 restructure priority | L51: =IF(C51="","",IF(AND(OR(H51="Full Contract Restructure"),P51>9.9),"Required","Not Required")) -> Not Required | Q51: 0
C52: Europe | D52: Finnair | E52: Trent XWB-84 | F52: =IFERROR(VLOOKUP(E52,'Data Validations'!$A$2:$B$13,2,0),"") -> Trent XWB | G52: Matt Haddon | H52: Full Contract Restructure | I52: Immature | J52: Not Onerous | K52: Min Term Extension for both Life & Term mix of structures - discussions to commence following their fleet expansion analysis in Q2. | L52: =IF(C52="","",IF(AND(OR(H52="Full Contract Restructure"),P52>9.9),"Required","Not Required")) -> Not Required | M52: Initial idea | N52: 2027
C53: Europe | D53: Virgin Atlantic | E53: Trent 7000 | F53: =IFERROR(VLOOKUP(E53,'Data Validations'!$A$2:$B$13,2,0),"") -> TFAME | G53: Keith Coull | H53: Full Contract Restructure | I53: Immature | J53: Not Onerous | K53: Descoping of unprofitable services in conjunction with new a/c opportunity. Test with new a/c (decision expected Q2 2026) before descoping existing fleet. | L53: =IF(C53="","",IF(AND(OR(H53="Full Contract Restructure"),P53>9.9),"Required","Not Required")) -> Not Required | M53: Negotations Started
C54: Europe | D54: Air France | E54: Trent XWB-84 | F54: =IFERROR(VLOOKUP(E54,'Data Validations'!$A$2:$B$13,2,0),"") -> Trent XWB | G54: Richard Docherty | H54: Full Contract Restructure | I54: Mature | J54: Not Onerous | K54: Min term extension (life) - 3 a/c exit from 2029. Maybe add in 2026 RFP | L54: =IF(C54="","",IF(AND(OR(H54="Full Contract Restructure"),P54>9.9),"Required","Not Required")) -> Not Required | M54: Initial idea | N54: 2027
C55: APAC | D55: Thai Airasia X | E55: Trent 700 | F55: =IFERROR(VLOOKUP(E55,'Data Validations'!$A$2:$B$13,2,0),"") -> TFAME | G55: Nick Chadwick | I55: Mature | K55: Carried $25m debt with TAAX at interim, of which majority relates to Supplementary Service Fee (pre-pandemic Min U & LPI). Once TAAX has made payments in early Q3 to support withdrawal of Notices of Default, we will engage on a restrucutre of the Supplementary Service Fee to make the deal more financially sustainable to TAAX, whilst preserving healthy margins. Alternative scenario could be termination, which we are doing internal due diligence on. | L55: =IF(C55="","",IF(AND(OR(H55="Full Contract Restructure"),P55>9.9),"Required","Not Required")) -> Not Required | Q55: 0 | R55: Rebecca to confirm | S55: Rebecca to confirm | T55: Rebecca to confirm | U55: Rebecca to confirm
C56: Europe | D56: Lufthansa | E56: Trent XWB-84 | F56: =IFERROR(VLOOKUP(E56,'Data Validations'!$A$2:$B$13,2,0),"") -> Trent XWB | G56: Keith Coull | H56: Full Contract Restructure | I56: Mature | J56: Not Onerous | K56: Min term extension (life) - 4 a/c exit from 2028 | L56: =IF(C56="","",IF(AND(OR(H56="Full Contract Restructure"),P56>9.9),"Required","Not Required")) -> Not Required | M56: Initial idea | N56: 2027
C57: Europe | D57: Air Caraibes | E57: Trent XWB-84 | F57: =IFERROR(VLOOKUP(E57,'Data Validations'!$A$2:$B$13,2,0),"") -> Trent XWB | G57: Richard Docherty | H57: Full Contract Restructure | I57: Mature | J57: Not Onerous | K57: Min term extension (life) - 3 a/c exit from 2029 | L57: =IF(C57="","",IF(AND(OR(H57="Full Contract Restructure"),P57>9.9),"Required","Not Required")) -> Not Required | M57: Initial idea | N57: 2027
C58: Greater China | D58: China Airlines | E58: Trent XWB-84 | F58: =IFERROR(VLOOKUP(E58,'Data Validations'!$A$2:$B$13,2,0),"") -> Trent XWB | G58: Daniel Hector | H58: Simple/Limited Restructure | I58: Mature | J58: Not Onerous | K58: 26 Feb 2026: The customer welcomes the proposed term extension approach on existing fleet. S&C will begin drafting the documents shortly. The contract is expected to be ready by March. Expected closure by Q2 2026. Assess other issues (Life to term conversation but that is early stages and capture in as a line item seperately) 7 Aug 2025: L2 strategy approved to persue launching detailed evaluation work and engagement with customer has commenced. Contract optimation is reliant on achieving contract amendment of the term extension rather than expected new contract. Confirmed new DEG approach can trigger start-stop commercial optimisation. Customer meeting (SVP) iniated the activity. VP visit in mid-Aug to follow up. | L58: =IF(C58="","",IF(AND(OR(H58="Full Contract Restructure"),P58>9.9),"Required","Not Required")) -> Not Required | M58: Contracting Started | N58: 2026 | O58: AP12 | P58: =SUM(Q58:U58) -> 23 | Q58: 9 | R58: 4 | S58: 3 | T58: 4 | U58: 3
C59: APAC | D59: Asiana Airlines | E59: Trent XWB-84 | F59: =IFERROR(VLOOKUP(E59,'Data Validations'!$A$2:$B$13,2,0),"") -> Trent XWB | G59: Nick Chadwick / Chong Sien Lim | H59: Full Contract Restructure | I59: Immature | J59: Not Onerous | K59: Restructure/re-price backlog to compensate for erorsion of value relating backlog deferral. R-R position presented to Asiana during Customer visit to Seletar in May. Initial Customer feedback that they expect this activity to be rolled into conslidation of agreements with Korean Air, post the 2 year merger transition period. | L59: =IF(C59="","",IF(AND(OR(H59="Full Contract Restructure"),P59>9.9),"Required","Not Required")) -> Required | M59: Initial idea | P59: TBD | Q59: 0
C60: Greater China | D60: Cathay Pacific Airways | E60: Trent XWB-84 | F60: =IFERROR(VLOOKUP(E60,'Data Validations'!$A$2:$B$13,2,0),"") -> Trent XWB | G60: Daniel Hector | H60: Simple/Limited Restructure | I60: Mature | J60: Not Onerous | K60: 4 March 2026: Previous LLP cost of ownership initiative is parked. However following the lost longhaul campaign in 2025, various trades are being proposed to be repackaged: Law 1/2 (win-win), deletion of Benefit Sharing Mechanism (take), securing Climb Derate Algorithim (take), closure of Fire Claim without non-contractual give (mitigation), concession of Lease Engine Cyclic Charges rate (give), other minor settlements of CPA incremental costs incurred (give). L2 scheduled for 6 March to approve strategy. | L60: =IF(C60="","",IF(AND(OR(H60="Full Contract Restructure"),P60>9.9),"Required","Not Required")) -> Not Required | M60: ICT formed | N60: 2026 | O60: AP9 | P60: 30 | Q60: 12
C61: Greater China | D61: Air China | E61: Trent 1000 | F61: =IFERROR(VLOOKUP(E61,'Data Validations'!$A$2:$B$13,2,0),"") -> TFAME | G61: Xiaowei Liu | H61: Full Contract Restructure | I61: Immature | J61: Onerous Contract | L61: =IF(C61="","",IF(AND(OR(H61="Full Contract Restructure"),P61>9.9),"Required","Not Required")) -> Required | M61: Financials Approved | N61: 2027 | P61: 30 | R61: 30
C62: APAC | D62: Cebu Pacific | E62: Trent 7000 | F62: =IFERROR(VLOOKUP(E62,'Data Validations'!$A$2:$B$13,2,0),"") -> TFAME | G62: Kendrick Lim | I62: Immature | J62: Not Onerous | K62: Low margin contract and asked by value stream to brainstorm ideas to improve CRP | L62: =IF(C62="","",IF(AND(OR(H62="Full Contract Restructure"),P62>9.9),"Required","Not Required")) -> Not Required | M62: Initial idea | Q62: 0
C63: APAC | D63: Lion Air | E63: Trent 7000 | F63: =IFERROR(VLOOKUP(E63,'Data Validations'!$A$2:$B$13,2,0),"") -> TFAME | G63: Paul Hallam | H63: Full Contract Restructure | I63: Mature | J63: Not Onerous | K63: 2 Aircraft Cancellation settlement agreed in 2025Q4, expected to be contracted by 2026Q2. Min U uplift, 2y extension and escalation increased. Resultant is Utilisation uplifted to 2175, 2y extension for 6 ac and escalation set to 5.15%. | L63: =IF(C63="","",IF(AND(OR(H63="Full Contract Restructure"),P63>9.9),"Required","Not Required")) -> Required | M63: Contracting Concluded | N63: 2026 | O63: AP3 | P63: 30 | Q63: 8.5 | R63: Confirm with Laura | S63: Confirm with Laura | T63: Confirm with Laura | U63: Confirm with Laura
C64: APAC | D64: Garuda | E64: Trent 7000 | F64: =IFERROR(VLOOKUP(E64,'Data Validations'!$A$2:$B$13,2,0),"") -> TFAME | G64: Paul Hallam | I64: Immature | K64: Note: Notice of Breach Served on Garuda: Contract restructure, including possible PAYG->PASV flip, in the event of continuing payment disputes and as avenue to avoid termination of profitable CRPs - opportunity to sell new/used additional SPE's | L64: =IF(C64="","",IF(AND(OR(H64="Full Contract Restructure"),P64>9.9),"Required","Not Required")) -> Not Required | Q64: 0
C65: Americas | D65: Delta Air Lines | E65: Trent 7000 | F65: =IFERROR(VLOOKUP(E65,'Data Validations'!$A$2:$B$13,2,0),"") -> TFAME | G65: Meagan Austgen | H65: Increase Spare Engine Holding | I65: Immature | J65: Onerous Contract | K65: To be assessed in 2026 - Incremental SPE sale to further reduce NDSES costs | L65: =IF(C65="","",IF(AND(OR(H65="Full Contract Restructure"),P65>9.9),"Required","Not Required")) -> Not Required | M65: Initial idea | N65: 2026 | Q65: 0
C66: Europe | D66: Virgin Atlantic | E66: Trent 1000 | F66: =IFERROR(VLOOKUP(E66,'Data Validations'!$A$2:$B$13,2,0),"") -> TFAME | G66: Keith Coull | H66: Simple/Limited Restructure | I66: Immature | J66: Onerous Contract | K66: Restructure/buy-out of environmental partnership guarentee | L66: =IF(C66="","",IF(AND(OR(H66="Full Contract Restructure"),P66>9.9),"Required","Not Required")) -> Not Required | M66: Initial idea
C67: Americas | D67: Latam | E67: Trent 1000 | F67: =IFERROR(VLOOKUP(E67,'Data Validations'!$A$2:$B$13,2,0),"") -> TFAME | G67: David Gonzalez-Gomez | H67: Full Contract Restructure | I67: Immature | J67: Onerous Contract | K67: Focus on fleet health at present, ICT generating ideas to improve onerous position (potential sale of used spare engine and term extension). | L67: =IF(C67="","",IF(AND(OR(H67="Full Contract Restructure"),P67>9.9),"Required","Not Required")) -> Required | M67: Contracting Started | N67: 2026 | O67: AP12 | P67: 50 | Q67: 50
C68: Americas | D68: Air Transat | E68: Trent 700 | F68: =IFERROR(VLOOKUP(E68,'Data Validations'!$A$2:$B$13,2,0),"") -> TFAME | G68: Christian Bencid | I68: Immature | J68: Not Onerous | K68: Consolidation of TotalCare structures | L68: =IF(C68="","",IF(AND(OR(H68="Full Contract Restructure"),P68>9.9),"Required","Not Required")) -> Not Required | Q68: 0
C69: Americas | D69: Mas Air | E69: Trent 700 | F69: =IFERROR(VLOOKUP(E69,'Data Validations'!$A$2:$B$13,2,0),"") -> TFAME | G69: Cory Noel | H69: Simple/Limited Restructure | I69: Immature | J69: Not Onerous | K69: Adding aircraft to the TotalCare - either FSA currently or newly acquired AC | L69: =IF(C69="","",IF(AND(OR(H69="Full Contract Restructure"),P69>9.9),"Required","Not Required")) -> Not Required | M69: Initial idea | Q69: 0
C70: Americas | D70: Western Air | E70: AE3007 | F70: =IFERROR(VLOOKUP(E70,'Data Validations'!$A$2:$B$13,2,0),"") -> TFAME | G70: Cory Noel | H70: Simple/Limited Restructure | I70: Mature | J70: Not Onerous | K70: Western Air Limited _ AE3007 _ Extension / Amendment for 2 AC | L70: =IF(C70="","",IF(AND(OR(H70="Full Contract Restructure"),P70>9.9),"Required","Not Required")) -> Not Required | M70: Negotations Concluded | N70: 2026 | Q70: 0
C71: Americas | D71: Western Air | E71: AE3007 | F71: =IFERROR(VLOOKUP(E71,'Data Validations'!$A$2:$B$13,2,0),"") -> TFAME | G71: Cory Noel | H71: Simple/Limited Restructure | I71: Immature | J71: Not Onerous | K71: Western Air Limited _ AE3007 _ Extension for full fleet of 9 | L71: =IF(C71="","",IF(AND(OR(H71="Full Contract Restructure"),P71>9.9),"Required","Not Required")) -> Not Required | M71: Initial idea | Q71: 0
C72: Americas | D72: IBC Airways | E72: AE3007 | F72: =IFERROR(VLOOKUP(E72,'Data Validations'!$A$2:$B$13,2,0),"") -> TFAME | G72: Cory Noel | H72: Simple/Limited Restructure | I72: Mature | J72: Not Onerous | K72: IBC Airways _ AE3007 _ Extension for 1 AC | L72: =IF(C72="","",IF(AND(OR(H72="Full Contract Restructure"),P72>9.9),"Required","Not Required")) -> Not Required | M72: Contracting Concluded | N72: 2025 | Q72: 0
C73: Greater China | D73: Air China | E73: Trent XWB-84 | F73: =IFERROR(VLOOKUP(E73,'Data Validations'!$A$2:$B$13,2,0),"") -> Trent XWB | G73: Xiaowei Liu | H73: Increase Spare Engine Holding | I73: Immature | J73: Not Onerous | K73: Opportunity to increase SPE level on Trent XWB x 2 SPE's at 40% | L73: =IF(C73="","",IF(AND(OR(H73="Full Contract Restructure"),P73>9.9),"Required","Not Required")) -> Not Required | M73: Financials Approved | N73: 2026 | O73: AP6 | P73: 19.3 | Q73: 5.3 | R73: 3.6 | S73: 2 | T73: 1.3 | U73: 1.3
C74: Europe | D74: Air France | E74: Trent XWB-84 | F74: =IFERROR(VLOOKUP(E74,'Data Validations'!$A$2:$B$13,2,0),"") -> Trent XWB | G74: Richard Docherty | H74: Full Contract Restructure | I74: Mature | J74: Not Onerous | K74: Opporunity to add a 1. XWB-84 Used SPE (Q1 2027) 2. Firm Up six (6) aircraft from existing Options. 3. PAS for A350F based on the volume change (4 to 3 FIRM) of A350F. | L74: =IF(C74="","",IF(AND(OR(H74="Full Contract Restructure"),P74>9.9),"Required","Not Required")) -> Not Required | M74: Contracting Started | N74: 2026
C75: Europe | D75: Air France | E75: Trent XWB-84 | F75: =IFERROR(VLOOKUP(E75,'Data Validations'!$A$2:$B$13,2,0),"") -> Trent XWB | G75: Richard Docherty | H75: Full Contract Restructure | I75: Mature | J75: Not Onerous | K75: Opportunity to sell combined PAS to both KLM and Martinair for XWB-84 and XWB-97 due to A350F volume change | L75: =IF(C75="","",IF(AND(OR(H75="Full Contract Restructure"),P75>9.9),"Required","Not Required")) -> Not Required | M75: Contracting Started | N75: 2026
C76: Europe | D76: British Airways | E76: Trent XWB-97 | F76: =IFERROR(VLOOKUP(E76,'Data Validations'!$A$2:$B$13,2,0),"") -> Trent XWB | G76: Matt O'Connor | H76: Simple/Limited Restructure | I76: Mature | J76: Not Onerous | K76: Change escalation period to Jul instead of Jun to simplify recon | L76: =IF(C76="","",IF(AND(OR(H76="Full Contract Restructure"),P76>9.9),"Required","Not Required")) -> Not Required | M76: Initial idea
C77: Europe | D77: British Airways | E77: Trent 800 | F77: =IFERROR(VLOOKUP(E77,'Data Validations'!$A$2:$B$13,2,0),"") -> TFAME | G77: Matt O'Connor | H77: Simple/Limited Restructure | I77: Immature | J77: Not Onerous | K77: Change escalation period to Jul instead of Jun to simplify recon | L77: =IF(C77="","",IF(AND(OR(H77="Full Contract Restructure"),P77>9.9),"Required","Not Required")) -> Not Required | M77: Initial idea
C78: Europe | D78: Sunclass Airlines | E78: Trent 7000 | F78: =IFERROR(VLOOKUP(E78,'Data Validations'!$A$2:$B$13,2,0),"") -> TFAME | G78: Matt Haddon | H78: Increase Spare Engine Holding | I78: Mature | J78: Not Onerous | K78: Sale of a first used Spare Engine which would reduce NDSES cost in the CRP | L78: =IF(C78="","",IF(AND(OR(H78="Full Contract Restructure"),P78>9.9),"Required","Not Required")) -> Not Required | M78: Initial idea | N78: 2026
C79: Europe | D79: ITA | E79: Trent 7000 | F79: =IFERROR(VLOOKUP(E79,'Data Validations'!$A$2:$B$13,2,0),"") -> TFAME | G79: Aaron Taylor | H79: Increase Spare Engine Holding | I79: Mature | J79: Not Onerous | K79: 2 incremental a/c under LoI - opportunity to sell incremental used Spare Engine early to help CRP NDSES cost/fleet health | L79: =IF(C79="","",IF(AND(OR(H79="Full Contract Restructure"),P79>9.9),"Required","Not Required")) -> Not Required | M79: ICT formed
C80: Europe | D80: Turkish Airlines | E80: Trent 700 | F80: =IFERROR(VLOOKUP(E80,'Data Validations'!$A$2:$B$13,2,0),"") -> TFAME | G80: Matt O'Connor | H80: Full Contract Restructure | I80: Mature | J80: Not Onerous | K80: Extend minimum term of remaining fleet | L80: =IF(C80="","",IF(AND(OR(H80="Full Contract Restructure"),P80>9.9),"Required","Not Required")) -> Not Required | M80: Initial idea
C81: Europe | D81: DHL | E81: Trent 700 | F81: =IFERROR(VLOOKUP(E81,'Data Validations'!$A$2:$B$13,2,0),"") -> TFAME | G81: Aaron Taylor | H81: Simple/Limited Restructure | I81: Immature | J81: Not Onerous | K81: LRU upsell | L81: =IF(C81="","",IF(AND(OR(H81="Full Contract Restructure"),P81>9.9),"Required","Not Required")) -> Not Required | M81: Initial idea
C82: Europe | D82: British Airways | E82: Trent XWB-97 | F82: =IFERROR(VLOOKUP(E82,'Data Validations'!$A$2:$B$13,2,0),"") -> Trent XWB | G82: Matt O'Connor | H82: Full Contract Restructure | I82: Immature | J82: Not Onerous | K82: Below the pylon - potential descope | L82: =IF(C82="","",IF(AND(OR(H82="Full Contract Restructure"),P82>9.9),"Required","Not Required")) -> Not Required | M82: ICT formed
C83: Europe | D83: British Airways | E83: Trent 1000 | F83: =IFERROR(VLOOKUP(E83,'Data Validations'!$A$2:$B$13,2,0),"") -> TFAME | G83: Matt O'Connor | H83: Full Contract Restructure | I83: Immature | J83: Onerous Contract | K83: Below the pylon - potential descope | L83: =IF(C83="","",IF(AND(OR(H83="Full Contract Restructure"),P83>9.9),"Required","Not Required")) -> Not Required | M83: ICT formed
C84: Europe | D84: British Airways | E84: Trent 900 | F84: =IFERROR(VLOOKUP(E84,'Data Validations'!$A$2:$B$13,2,0),"") -> TFAME | G84: Matt O'Connor | H84: Full Contract Restructure | I84: Immature | J84: Not Onerous | K84: Below the pylon - potential descope (Trent 900) | L84: =IF(C84="","",IF(AND(OR(H84="Full Contract Restructure"),P84>9.9),"Required","Not Required")) -> Not Required | M84: ICT formed
C85: Europe | D85: Virgin Atlantic | E85: Trent XWB-97 | F85: =IFERROR(VLOOKUP(E85,'Data Validations'!$A$2:$B$13,2,0),"") -> Trent XWB | G85: Keith Coull | H85: Full Contract Restructure | I85: Immature | J85: Onerous Contract | K85: Onerous -Transistion AC if possilbe, Extend contract or EOCL buy out | L85: =IF(C85="","",IF(AND(OR(H85="Full Contract Restructure"),P85>9.9),"Required","Not Required")) -> Not Required | M85: Initial idea
C86: Europe | D86: Air Caraibes | E86: Trent XWB-84 | F86: =IFERROR(VLOOKUP(E86,'Data Validations'!$A$2:$B$13,2,0),"") -> Trent XWB | G86: Alejandra Barrionuevo | H86: Full Contract Restructure | I86: Immature | J86: Not Onerous | K86: Life Min Term extension for owned a/c, plus removal of EoCL for a $/efh discount | L86: =IF(C86="","",IF(AND(OR(H86="Full Contract Restructure"),P86>9.9),"Required","Not Required")) -> Not Required | M86: Initial idea | N86: 2027
C87: Europe | D87: ITA | E87: Trent 7000 | F87: =IFERROR(VLOOKUP(E87,'Data Validations'!$A$2:$B$13,2,0),"") -> TFAME | G87: Aaron Taylor | H87: Increase Spare Engine Holding | I87: Mature | J87: Not Onerous | K87: SPE#4 Pull-forward | L87: =IF(C87="","",IF(AND(OR(H87="Full Contract Restructure"),P87>9.9),"Required","Not Required")) -> Not Required | M87: Contracting Started | N87: 2026 | P87: 1.9
C88: Europe | D88: ITA | E88: Trent XWB-84 | F88: =IFERROR(VLOOKUP(E88,'Data Validations'!$A$2:$B$13,2,0),"") -> Trent XWB | G88: Aaron Taylor | H88: Simple/Limited Restructure | I88: Immature | J88: Not Onerous | K88: ITA integration into GEM (+ additional aircraft) | L88: =IF(C88="","",IF(AND(OR(H88="Full Contract Restructure"),P88>9.9),"Required","Not Required")) -> Not Required | M88: Initial idea
C89: Europe | D89: British Airways | E89: Trent 900 | F89: =IFERROR(VLOOKUP(E89,'Data Validations'!$A$2:$B$13,2,0),"") -> TFAME | G89: Sachin Fernandes | H89: Simple/Limited Restructure | I89: Mature | J89: Not Onerous | K89: Restructure nacelle factor calculations to simplify covered services rate calculations and resulting recons | L89: =IF(C89="","",IF(AND(OR(H89="Full Contract Restructure"),P89>9.9),"Required","Not Required")) -> Not Required | M89: Initial idea
C90: Europe | D90: Virgin Atlantic Airways | E90: Trent 7000 | F90: =IFERROR(VLOOKUP(E90,'Data Validations'!$A$2:$B$13,2,0),"") -> TFAME | G90: Keith Coull | H90: Increase Spare Engine Holding | I90: Immature | J90: Not Onerous | K90: Sell of an incremental used Spare engine to mitigate Contractual risk associated with Additional Dedicated Lease Engine clause | L90: =IF(C90="","",IF(AND(OR(H90="Full Contract Restructure"),P90>9.9),"Required","Not Required")) -> Not Required | M90: Initial idea | N90: 2026 | P90: 2.5
C91: Americas | D91: Delta Air Lines | E91: Trent XWB-84 | F91: =IFERROR(VLOOKUP(E91,'Data Validations'!$A$2:$B$13,2,0),"") -> Trent XWB | G91: Meagan Austgen | H91: Increase Spare Engine Holding | I91: Immature | J91: Not Onerous | K91: additional SPE sales to increase SPE holding | L91: =IF(C91="","",IF(AND(OR(H91="Full Contract Restructure"),P91>9.9),"Required","Not Required")) -> Not Required | M91: Initial idea
C92: Americas | D92: Delta Air Lines | E92: Trent XWB-84 | F92: =IFERROR(VLOOKUP(E92,'Data Validations'!$A$2:$B$13,2,0),"") -> Trent XWB | G92: Meagan Austgen | H92: Simple/Limited Restructure | I92: Immature | J92: Not Onerous | K92: extending to next SV after 20 years, rather then 15 years (in aligment with other engine types) | L92: =IF(C92="","",IF(AND(OR(H92="Full Contract Restructure"),P92>9.9),"Required","Not Required")) -> Not Required
C93: APAC | D93: Philippine Airlines | E93: Trent XWB-84 | F93: =IFERROR(VLOOKUP(E93,'Data Validations'!$A$2:$B$13,2,0),"") -> Trent XWB | G93: Kendrick Lim | H93: Full Contract Restructure | I93: Immature | J93: Not Onerous | K93: Contract amendment if new AC campaign | L93: =IF(C93="","",IF(AND(OR(H93="Full Contract Restructure"),P93>9.9),"Required","Not Required")) -> Not Required
C94: APAC | D94: Philippine Airlines | E94: Trent XWB-97 | F94: =IFERROR(VLOOKUP(E94,'Data Validations'!$A$2:$B$13,2,0),"") -> Trent XWB | G94: Kendrick Lim | H94: Full Contract Restructure | I94: Immature | J94: Not Onerous | K94: Contract amendment if new AC campaign | L94: =IF(C94="","",IF(AND(OR(H94="Full Contract Restructure"),P94>9.9),"Required","Not Required")) -> Not Required
C95: APAC | D95: Singapore Airlines | E95: Trent XWB-84 | F95: =IFERROR(VLOOKUP(E95,'Data Validations'!$A$2:$B$13,2,0),"") -> Trent XWB | G95: Paul Hallam | H95: Full Contract Restructure | I95: Immature | J95: Not Onerous | K95: Batch 2 restrucuture could be in scope - after T1000 onerous negotiaion | L95: =IF(C95="","",IF(AND(OR(H95="Full Contract Restructure"),P95>9.9),"Required","Not Required")) -> Not Required | M95: Initial idea
C96: APAC | D96: Vietnam Airlines | E96: Trent XWB-84 | F96: =IFERROR(VLOOKUP(E96,'Data Validations'!$A$2:$B$13,2,0),"") -> Trent XWB | G96: Paul Hallam | H96: Full Contract Restructure | I96: Mature | J96: Not Onerous | K96: Part 2: Min Term Extension | L96: =IF(C96="","",IF(AND(OR(H96="Full Contract Restructure"),P96>9.9),"Required","Not Required")) -> Not Required | M96: Strategy Approved | N96: 2026
C97: APAC | D97: Japan Airlines | E97: Trent XWB-97 | F97: =IFERROR(VLOOKUP(E97,'Data Validations'!$A$2:$B$13,2,0),"") -> Trent XWB | G97: Nicholas Chadwick | H97: Increase Spare Engine Holding | I97: Mature | J97: Not Onerous | K97: SPE #1 - benefit to CRP | L97: =IF(C97="","",IF(AND(OR(H97="Full Contract Restructure"),P97>9.9),"Required","Not Required")) -> Not Required | M97: Strategy Approved | N97: 2026 | O97: AP6 | P97: 7
C98: APAC | D98: Japan Airlines | E98: Trent XWB-97 | F98: =IFERROR(VLOOKUP(E98,'Data Validations'!$A$2:$B$13,2,0),"") -> Trent XWB | G98: Nicholas Chadwick | H98: Increase Spare Engine Holding | I98: Immature | J98: Not Onerous | K98: SPE #2 - would be in trade for SL2 and net neutral benefit | L98: =IF(C98="","",IF(AND(OR(H98="Full Contract Restructure"),P98>9.9),"Required","Not Required")) -> Not Required | M98: Strategy Approved
C99: APAC | D99: Japan Airlines | E99: Trent XWB-84 | F99: =IFERROR(VLOOKUP(E99,'Data Validations'!$A$2:$B$13,2,0),"") -> Trent XWB | G99: Nicholas Chadwick | H99: Simple/Limited Restructure | I99: Mature | J99: Not Onerous | K99: 7 yr extension of existing contract (included as option in contract) - Looks like double count vs above row 59 | L99: =IF(C99="","",IF(AND(OR(H99="Full Contract Restructure"),P99>9.9),"Required","Not Required")) -> Not Required | M99: Initial idea | N99: 2026 | P99: 442 | Q99: 3.2 | R99: Harry to confirm | S99: Harry to confirm | T99: Harry to confirm | U99: Harry to confirm
C100: APAC | D100: Air India | E100: Trent XWB-84 | F100: =IFERROR(VLOOKUP(E100,'Data Validations'!$A$2:$B$13,2,0),"") -> Trent XWB | G100: Nick Chadwick / Ben Gan | H100: Simple/Limited Restructure | I100: Immature | J100: Not Onerous | K100: Flexibility rights - value trade being considered as part of 2025 Campaign for 30+70 | L100: =IF(C100="","",IF(AND(OR(H100="Full Contract Restructure"),P100>9.9),"Required","Not Required")) -> Not Required | M100: Initial idea
C101: APAC | D101: Air India | E101: Trent XWB-84 | F101: =IFERROR(VLOOKUP(E101,'Data Validations'!$A$2:$B$13,2,0),"") -> Trent XWB | G101: Nick Chadwick / Ben Gan | H101: Simple/Limited Restructure | I101: Immature | J101: Not Onerous | K101: £500m credit back held on CRP and is not "real" due to credit back clause. a min term extension or end at next SV would resolve this. | L101: =IF(C101="","",IF(AND(OR(H101="Full Contract Restructure"),P101>9.9),"Required","Not Required")) -> Not Required | M101: Initial idea
C102: Europe | D102: SAS Group | E102: Trent XWB-84 | F102: =IFERROR(VLOOKUP(E102,'Data Validations'!$A$2:$B$13,2,0),"") -> Trent XWB | G102: Matt Haddon | H102: Full Contract Restructure | I102: Immature | J102: Not Onerous | K102: Potential Low probability opportunity to upsell LRU service as there has been some discussion with SAS on this. Lufthansa Technic incumbent LRU service supplier | L102: =IF(C102="","",IF(AND(OR(H102="Full Contract Restructure"),P102>9.9),"Required","Not Required")) -> Not Required | M102: Initial idea | N102: 2027
C103: Greater China | D103: China Airlines | E103: Trent XWB-84 | F103: =IFERROR(VLOOKUP(E103,'Data Validations'!$A$2:$B$13,2,0),"") -> Trent XWB | G103: Daniel Hector | H103: Simple/Limited Restructure | I103: Mature | J103: Not Onerous | K103: 4 March 2026: Transition of 3 AerCap leased aircraft from Sichuan to China Airlines with aircraft being purchased from AerCap. Contract amendments signed at end Jan-26 to move from Sichuan Life TCA to existing China Airlines Life TCA with profit upside due to better margins on China Airlines CRP. | L103: =IF(C103="","",IF(AND(OR(H103="Full Contract Restructure"),P103>9.9),"Required","Not Required")) -> Not Required | M103: Contracting Concluded | N103: 2026
...

Sheet COUNT
C2: COUNT
C8: PROJECTS
G9: PROGRAM | N9: PROBABILITY | Q9: COMPLEXITY | T9: STATUS | Y9: YEARS
C10: PROJECT | D10: COUNT OF ASKS | E10: OF WHICH SPE RELATED | F10: NO.OF SPE | G10: Trent XWB-84 | H10: Trent XWB-97 | I10: Trent 1000 | J10: Trent 500 | K10: Trent 700 | L10: RB211-524 | M10: Trent 7000 | N10: COUNT OF HIGH PROB | O10: COUNT OF MED PROB | P10: COUNT OF LOW PROB | Q10: COUNT OF HIGH COMP | R10: COUNT OF MED COMP | S10: COUNT OF LOW COMP | T10: COUNT OF COMPLETED | U10: COUNT OF CONTRACTING | V10: COUNT OF NEGOTIATIONS | W10: COUNT OF ICT | X10: COUNT OF HOPPER | Y10: 2026 | Z10: 2027 | AA10: SUM OF 26/27 | AB10: SUM OF TERM BENEFIT | AD10: SORTED CUSTOMER | AE10: SORTED TERM IMPACT A | AG10: SORTED CUSTOMER | AH10: SORTED 2026 | AJ10: SORTED CUSTOMER | AK10: SORTED 2027 | AM10: SORTED CUSTOMER | AN10: SORTED 2026/2027
C11: {=_xlfn._xlws.FILTER('Data Validations'!C2:C153,TRUE)} -> Aer Lingus | D11: =COUNTIFS('GLOBAL LOG'!$D$6:$D$128,C11,'GLOBAL LOG'!$K$6:$K$128,"<>") -> 0 | E11: =COUNTIFS('GLOBAL LOG'!$D$6:$D$128,C11,'GLOBAL LOG'!#REF!,"Yes") -> #REF! | F11: =SUMIF('GLOBAL LOG'!$D$6:$D$128,COUNT!C11,'GLOBAL LOG'!#REF!) -> #REF! | G11: =COUNTIFS('GLOBAL LOG'!$E$6:$E$128,G$10,'GLOBAL LOG'!$D$6:$D$128,$C11) -> 0 | H11: =COUNTIFS('GLOBAL LOG'!$E$6:$E$128,H$10,'GLOBAL LOG'!$D$6:$D$128,$C11) -> 0 | I11: =COUNTIFS('GLOBAL LOG'!$E$6:$E$128,I$10,'GLOBAL LOG'!$D$6:$D$128,$C11) -> 0 | J11: =COUNTIFS('GLOBAL LOG'!$E$6:$E$128,J$10,'GLOBAL LOG'!$D$6:$D$128,$C11) -> 0 | K11: =COUNTIFS('GLOBAL LOG'!$E$6:$E$128,K$10,'GLOBAL LOG'!$D$6:$D$128,$C11) -> 0 | L11: =COUNTIFS('GLOBAL LOG'!$E$6:$E$128,L$10,'GLOBAL LOG'!$D$6:$D$128,$C11) -> 0 | M11: =COUNTIFS('GLOBAL LOG'!$E$6:$E$128,M$10,'GLOBAL LOG'!$D$6:$D$128,$C11) -> 0 | N11: =COUNTIFS('GLOBAL LOG'!$D$6:$D$128,$C11,'GLOBAL LOG'!#REF!,"High") -> #REF! | O11: =COUNTIFS('GLOBAL LOG'!$D$6:$D$128,$C11,'GLOBAL LOG'!#REF!,"Med") -> #REF! | P11: =COUNTIFS('GLOBAL LOG'!$D$6:$D$128,$C11,'GLOBAL LOG'!#REF!,"Low") -> #REF! | Q11: =COUNTIFS('GLOBAL LOG'!$D$6:$D$128,$C11,'GLOBAL LOG'!#REF!,"High") -> #REF! | R11: =COUNTIFS('GLOBAL LOG'!$D$6:$D$128,$C11,'GLOBAL LOG'!#REF!,"Med") -> #REF! | S11: =COUNTIFS('GLOBAL LOG'!$D$6:$D$128,$C11,'GLOBAL LOG'!#REF!,"Low") -> #REF! | T11: =COUNTIFS('GLOBAL LOG'!$D$6:$D$128,$C11,'GLOBAL LOG'!#REF!,"Completed") -> #REF! | U11: =COUNTIFS('GLOBAL LOG'!$D$6:$D$128,$C11,'GLOBAL LOG'!#REF!,"Contracting") -> #REF! | V11: =COUNTIFS('GLOBAL LOG'!$D$6:$D$128,$C11,'GLOBAL LOG'!#REF!,"Negotiations") -> #REF! | W11: =COUNTIFS('GLOBAL LOG'!$D$6:$D$128,$C11,'GLOBAL LOG'!#REF!,"ICT") -> #REF! | X11: =COUNTIFS('GLOBAL LOG'!$D$6:$D$128,$C11,'GLOBAL LOG'!#REF!,"Hopper") -> #REF! | Y11: =SUMIF('GLOBAL LOG'!$D$6:$D$128,$C11,'GLOBAL LOG'!$Q$6:$Q$128) -> 0 | Z11: =SUMIF('GLOBAL LOG'!$D$6:$D$128,$C11,'GLOBAL LOG'!$R$6:$R$128) -> 0 | AA11: =Y11+Z11 -> 0 | AB11: =SUMIF('GLOBAL LOG'!$D$6:$D$128,C11,'GLOBAL LOG'!#REF!) -> #REF! | AD11: {=_xlfn.SORTBY(C11:C164,AB11:AB164,-1)} -> Aer Lingus | AE11: {=_xlfn.SORTBY(AB11:AB164,AB11:AB164,-1)} -> #REF! | AG11: {=_xlfn.SORTBY(C11:C164,Y11:Y164,-1)} -> Singapore Airlines | AH11: {=_xlfn.SORTBY(Y11:Y164,Y11:Y164,-1)} -> 104 | AJ11: {=_xlfn.SORTBY(C11:C164,Z11:Z164,-1)} -> Air China | AK11: {=_xlfn.SORTBY(Z11:Z164,Z11:Z164,-1)} -> 33.6 | AM11: {=_xlfn.SORTBY(C11:C164,AA11:AA164,-1)} -> Singapore Airlines | AN11: {=_xlfn.SORTBY(AA11:AA164,AA11:AA164,-1)} -> 104
C12: AerCap | D12: =COUNTIFS('GLOBAL LOG'!$D$6:$D$128,C12,'GLOBAL LOG'!$K$6:$K$128,"<>") -> 0 | E12: =COUNTIFS('GLOBAL LOG'!$D$6:$D$128,C12,'GLOBAL LOG'!#REF!,"Yes") -> #REF! | F12: =SUMIF('GLOBAL LOG'!$D$6:$D$128,COUNT!C12,'GLOBAL LOG'!#REF!) -> #REF! | G12: =COUNTIFS('GLOBAL LOG'!$E$6:$E$128,G$10,'GLOBAL LOG'!$D$6:$D$128,$C12) -> 0 | H12: =COUNTIFS('GLOBAL LOG'!$E$6:$E$128,H$10,'GLOBAL LOG'!$D$6:$D$128,$C12) -> 0 | I12: =COUNTIFS('GLOBAL LOG'!$E$6:$E$128,I$10,'GLOBAL LOG'!$D$6:$D$128,$C12) -> 0 | J12: =COUNTIFS('GLOBAL LOG'!$E$6:$E$128,J$10,'GLOBAL LOG'!$D$6:$D$128,$C12) -> 0 | K12: =COUNTIFS('GLOBAL LOG'!$E$6:$E$128,K$10,'GLOBAL LOG'!$D$6:$D$128,$C12) -> 0 | L12: =COUNTIFS('GLOBAL LOG'!$E$6:$E$128,L$10,'GLOBAL LOG'!$D$6:$D$128,$C12) -> 0 | M12: =COUNTIFS('GLOBAL LOG'!$E$6:$E$128,M$10,'GLOBAL LOG'!$D$6:$D$128,$C12) -> 0 | N12: =COUNTIFS('GLOBAL LOG'!$D$6:$D$128,$C12,'GLOBAL LOG'!#REF!,"High") -> #REF! | O12: =COUNTIFS('GLOBAL LOG'!$D$6:$D$128,$C12,'GLOBAL LOG'!#REF!,"Med") -> #REF! | P12: =COUNTIFS('GLOBAL LOG'!$D$6:$D$128,$C12,'GLOBAL LOG'!#REF!,"Low") -> #REF! | Q12: =COUNTIFS('GLOBAL LOG'!$D$6:$D$128,$C12,'GLOBAL LOG'!#REF!,"High") -> #REF! | R12: =COUNTIFS('GLOBAL LOG'!$D$6:$D$128,$C12,'GLOBAL LOG'!#REF!,"Med") -> #REF! | S12: =COUNTIFS('GLOBAL LOG'!$D$6:$D$128,$C12,'GLOBAL LOG'!#REF!,"Low") -> #REF! | T12: =COUNTIFS('GLOBAL LOG'!$D$6:$D$128,$C12,'GLOBAL LOG'!#REF!,"Completed") -> #REF! | U12: =COUNTIFS('GLOBAL LOG'!$D$6:$D$128,$C12,'GLOBAL LOG'!#REF!,"Contracting") -> #REF! | V12: =COUNTIFS('GLOBAL LOG'!$D$6:$D$128,$C12,'GLOBAL LOG'!#REF!,"Negotiations") -> #REF! | W12: =COUNTIFS('GLOBAL LOG'!$D$6:$D$128,$C12,'GLOBAL LOG'!#REF!,"ICT") -> #REF! | X12: =COUNTIFS('GLOBAL LOG'!$D$6:$D$128,$C12,'GLOBAL LOG'!#REF!,"Hopper") -> #REF! | Y12: =SUMIF('GLOBAL LOG'!$D$6:$D$128,$C12,'GLOBAL LOG'!$Q$6:$Q$128) -> 0 | Z12: =SUMIF('GLOBAL LOG'!$D$6:$D$128,$C12,'GLOBAL LOG'!$R$6:$R$128) -> 0 | AA12: =Y12+Z12 -> 0 | AB12: =SUMIF('GLOBAL LOG'!$D$6:$D$128,C12,'GLOBAL LOG'!#REF!) -> #REF! | AD12: AerCap | AE12: #REF! | AG12: Delta Air Lines | AH12: 59 | AJ12: FedEx Corporation | AK12: 6.96 | AM12: Delta Air Lines | AN12: 59
C13: Aeroflot Russian Airlines | D13: =COUNTIFS('GLOBAL LOG'!$D$6:$D$128,C13,'GLOBAL LOG'!$K$6:$K$128,"<>") -> 0 | E13: =COUNTIFS('GLOBAL LOG'!$D$6:$D$128,C13,'GLOBAL LOG'!#REF!,"Yes") -> #REF! | F13: =SUMIF('GLOBAL LOG'!$D$6:$D$128,COUNT!C13,'GLOBAL LOG'!#REF!) -> #REF! | G13: =COUNTIFS('GLOBAL LOG'!$E$6:$E$128,G$10,'GLOBAL LOG'!$D$6:$D$128,$C13) -> 0 | H13: =COUNTIFS('GLOBAL LOG'!$E$6:$E$128,H$10,'GLOBAL LOG'!$D$6:$D$128,$C13) -> 0 | I13: =COUNTIFS('GLOBAL LOG'!$E$6:$E$128,I$10,'GLOBAL LOG'!$D$6:$D$128,$C13) -> 0 | J13: =COUNTIFS('GLOBAL LOG'!$E$6:$E$128,J$10,'GLOBAL LOG'!$D$6:$D$128,$C13) -> 0 | K13: =COUNTIFS('GLOBAL LOG'!$E$6:$E$128,K$10,'GLOBAL LOG'!$D$6:$D$128,$C13) -> 0 | L13: =COUNTIFS('GLOBAL LOG'!$E$6:$E$128,L$10,'GLOBAL LOG'!$D$6:$D$128,$C13) -> 0 | M13: =COUNTIFS('GLOBAL LOG'!$E$6:$E$128,M$10,'GLOBAL LOG'!$D$6:$D$128,$C13) -> 0 | N13: =COUNTIFS('GLOBAL LOG'!$D$6:$D$128,$C13,'GLOBAL LOG'!#REF!,"High") -> #REF! | O13: =COUNTIFS('GLOBAL LOG'!$D$6:$D$128,$C13,'GLOBAL LOG'!#REF!,"Med") -> #REF! | P13: =COUNTIFS('GLOBAL LOG'!$D$6:$D$128,$C13,'GLOBAL LOG'!#REF!,"Low") -> #REF! | Q13: =COUNTIFS('GLOBAL LOG'!$D$6:$D$128,$C13,'GLOBAL LOG'!#REF!,"High") -> #REF! | R13: =COUNTIFS('GLOBAL LOG'!$D$6:$D$128,$C13,'GLOBAL LOG'!#REF!,"Med") -> #REF! | S13: =COUNTIFS('GLOBAL LOG'!$D$6:$D$128,$C13,'GLOBAL LOG'!#REF!,"Low") -> #REF! | T13: =COUNTIFS('GLOBAL LOG'!$D$6:$D$128,$C13,'GLOBAL LOG'!#REF!,"Completed") -> #REF! | U13: =COUNTIFS('GLOBAL LOG'!$D$6:$D$128,$C13,'GLOBAL LOG'!#REF!,"Contracting") -> #REF! | V13: =COUNTIFS('GLOBAL LOG'!$D$6:$D$128,$C13,'GLOBAL LOG'!#REF!,"Negotiations") -> #REF! | W13: =COUNTIFS('GLOBAL LOG'!$D$6:$D$128,$C13,'GLOBAL LOG'!#REF!,"ICT") -> #REF! | X13: =COUNTIFS('GLOBAL LOG'!$D$6:$D$128,$C13,'GLOBAL LOG'!#REF!,"Hopper") -> #REF! | Y13: =SUMIF('GLOBAL LOG'!$D$6:$D$128,$C13,'GLOBAL LOG'!$Q$6:$Q$128) -> 0 | Z13: =SUMIF('GLOBAL LOG'!$D$6:$D$128,$C13,'GLOBAL LOG'!$R$6:$R$128) -> 0 | AA13: =Y13+Z13 -> 0 | AB13: =SUMIF('GLOBAL LOG'!$D$6:$D$128,C13,'GLOBAL LOG'!#REF!) -> #REF! | AD13: Aeroflot Russian Airlines | AE13: #REF! | AG13: Ethiopian Airlines | AH13: 23 | AJ13: Aer Lingus | AK13: 0 | AM13: Air China | AN13: 38.9
C14: Aerolineas | D14: =COUNTIFS('GLOBAL LOG'!$D$6:$D$128,C14,'GLOBAL LOG'!$K$6:$K$128,"<>") -> 0 | E14: =COUNTIFS('GLOBAL LOG'!$D$6:$D$128,C14,'GLOBAL LOG'!#REF!,"Yes") -> #REF! | F14: =SUMIF('GLOBAL LOG'!$D$6:$D$128,COUNT!C14,'GLOBAL LOG'!#REF!) -> #REF! | G14: =COUNTIFS('GLOBAL LOG'!$E$6:$E$128,G$10,'GLOBAL LOG'!$D$6:$D$128,$C14) -> 0 | H14: =COUNTIFS('GLOBAL LOG'!$E$6:$E$128,H$10,'GLOBAL LOG'!$D$6:$D$128,$C14) -> 0 | I14: =COUNTIFS('GLOBAL LOG'!$E$6:$E$128,I$10,'GLOBAL LOG'!$D$6:$D$128,$C14) -> 0 | J14: =COUNTIFS('GLOBAL LOG'!$E$6:$E$128,J$10,'GLOBAL LOG'!$D$6:$D$128,$C14) -> 0 | K14: =COUNTIFS('GLOBAL LOG'!$E$6:$E$128,K$10,'GLOBAL LOG'!$D$6:$D$128,$C14) -> 0 | L14: =COUNTIFS('GLOBAL LOG'!$E$6:$E$128,L$10,'GLOBAL LOG'!$D$6:$D$128,$C14) -> 0 | M14: =COUNTIFS('GLOBAL LOG'!$E$6:$E$128,M$10,'GLOBAL LOG'!$D$6:$D$128,$C14) -> 0 | N14: =COUNTIFS('GLOBAL LOG'!$D$6:$D$128,$C14,'GLOBAL LOG'!#REF!,"High") -> #REF! | O14: =COUNTIFS('GLOBAL LOG'!$D$6:$D$128,$C14,'GLOBAL LOG'!#REF!,"Med") -> #REF! | P14: =COUNTIFS('GLOBAL LOG'!$D$6:$D$128,$C14,'GLOBAL LOG'!#REF!,"Low") -> #REF! | Q14: =COUNTIFS('GLOBAL LOG'!$D$6:$D$128,$C14,'GLOBAL LOG'!#REF!,"High") -> #REF! | R14: =COUNTIFS('GLOBAL LOG'!$D$6:$D$128,$C14,'GLOBAL LOG'!#REF!,"Med") -> #REF! | S14: =COUNTIFS('GLOBAL LOG'!$D$6:$D$128,$C14,'GLOBAL LOG'!#REF!,"Low") -> #REF! | T14: =COUNTIFS('GLOBAL LOG'!$D$6:$D$128,$C14,'GLOBAL LOG'!#REF!,"Completed") -> #REF! | U14: =COUNTIFS('GLOBAL LOG'!$D$6:$D$128,$C14,'GLOBAL LOG'!#REF!,"Contracting") -> #REF! | V14: =COUNTIFS('GLOBAL LOG'!$D$6:$D$128,$C14,'GLOBAL LOG'!#REF!,"Negotiations") -> #REF! | W14: =COUNTIFS('GLOBAL LOG'!$D$6:$D$128,$C14,'GLOBAL LOG'!#REF!,"ICT") -> #REF! | X14: =COUNTIFS('GLOBAL LOG'!$D$6:$D$128,$C14,'GLOBAL LOG'!#REF!,"Hopper") -> #REF! | Y14: =SUMIF('GLOBAL LOG'!$D$6:$D$128,$C14,'GLOBAL LOG'!$Q$6:$Q$128) -> 0 | Z14: =SUMIF('GLOBAL LOG'!$D$6:$D$128,$C14,'GLOBAL LOG'!$R$6:$R$128) -> 0 | AA14: =Y14+Z14 -> 0 | AB14: =SUMIF('GLOBAL LOG'!$D$6:$D$128,C14,'GLOBAL LOG'!#REF!) -> #REF! | AD14: Aerolineas | AE14: #REF! | AG14: FedEx Corporation | AH14: 6.43 | AJ14: AerCap | AK14: 0 | AM14: Ethiopian Airlines | AN14: 23
C15: Air Algerie | D15: =COUNTIFS('GLOBAL LOG'!$D$6:$D$128,C15,'GLOBAL LOG'!$K$6:$K$128,"<>") -> 0 | E15: =COUNTIFS('GLOBAL LOG'!$D$6:$D$128,C15,'GLOBAL LOG'!#REF!,"Yes") -> #REF! | F15: =SUMIF('GLOBAL LOG'!$D$6:$D$128,COUNT!C15,'GLOBAL LOG'!#REF!) -> #REF! | G15: =COUNTIFS('GLOBAL LOG'!$E$6:$E$128,G$10,'GLOBAL LOG'!$D$6:$D$128,$C15) -> 0 | H15: =COUNTIFS('GLOBAL LOG'!$E$6:$E$128,H$10,'GLOBAL LOG'!$D$6:$D$128,$C15) -> 0 | I15: =COUNTIFS('GLOBAL LOG'!$E$6:$E$128,I$10,'GLOBAL LOG'!$D$6:$D$128,$C15) -> 0 | J15: =COUNTIFS('GLOBAL LOG'!$E$6:$E$128,J$10,'GLOBAL LOG'!$D$6:$D$128,$C15) -> 0 | K15: =COUNTIFS('GLOBAL LOG'!$E$6:$E$128,K$10,'GLOBAL LOG'!$D$6:$D$128,$C15) -> 0 | L15: =COUNTIFS('GLOBAL LOG'!$E$6:$E$128,L$10,'GLOBAL LOG'!$D$6:$D$128,$C15) -> 0 | M15: =COUNTIFS('GLOBAL LOG'!$E$6:$E$128,M$10,'GLOBAL LOG'!$D$6:$D$128,$C15) -> 0 | N15: =COUNTIFS('GLOBAL LOG'!$D$6:$D$128,$C15,'GLOBAL LOG'!#REF!,"High") -> #REF! | O15: =COUNTIFS('GLOBAL LOG'!$D$6:$D$128,$C15,'GLOBAL LOG'!#REF!,"Med") -> #REF! | P15: =COUNTIFS('GLOBAL LOG'!$D$6:$D$128,$C15,'GLOBAL LOG'!#REF!,"Low") -> #REF! | Q15: =COUNTIFS('GLOBAL LOG'!$D$6:$D$128,$C15,'GLOBAL LOG'!#REF!,"High") -> #REF! | R15: =COUNTIFS('GLOBAL LOG'!$D$6:$D$128,$C15,'GLOBAL LOG'!#REF!,"Med") -> #REF! | S15: =COUNTIFS('GLOBAL LOG'!$D$6:$D$128,$C15,'GLOBAL LOG'!#REF!,"Low") -> #REF! | T15: =COUNTIFS('GLOBAL LOG'!$D$6:$D$128,$C15,'GLOBAL LOG'!#REF!,"Completed") -> #REF! | U15: =COUNTIFS('GLOBAL LOG'!$D$6:$D$128,$C15,'GLOBAL LOG'!#REF!,"Contracting") -> #REF! | V15: =COUNTIFS('GLOBAL LOG'!$D$6:$D$128,$C15,'GLOBAL LOG'!#REF!,"Negotiations") -> #REF! | W15: =COUNTIFS('GLOBAL LOG'!$D$6:$D$128,$C15,'GLOBAL LOG'!#REF!,"ICT") -> #REF! | X15: =COUNTIFS('GLOBAL LOG'!$D$6:$D$128,$C15,'GLOBAL LOG'!#REF!,"Hopper") -> #REF! | Y15: =SUMIF('GLOBAL LOG'!$D$6:$D$128,$C15,'GLOBAL LOG'!$Q$6:$Q$128) -> 0 | Z15: =SUMIF('GLOBAL LOG'!$D$6:$D$128,$C15,'GLOBAL LOG'!$R$6:$R$128) -> 0 | AA15: =Y15+Z15 -> 0 | AB15: =SUMIF('GLOBAL LOG'!$D$6:$D$128,C15,'GLOBAL LOG'!#REF!) -> #REF! | AD15: Air Algerie | AE15: #REF! | AG15: Air China | AH15: 5.3 | AJ15: Aeroflot Russian Airlines | AK15: 0 | AM15: FedEx Corporation | AN15: 13.39
C16: Air Austral | D16: =COUNTIFS('GLOBAL LOG'!$D$6:$D$128,C16,'GLOBAL LOG'!$K$6:$K$128,"<>") -> 0 | E16: =COUNTIFS('GLOBAL LOG'!$D$6:$D$128,C16,'GLOBAL LOG'!#REF!,"Yes") -> #REF! | F16: =SUMIF('GLOBAL LOG'!$D$6:$D$128,COUNT!C16,'GLOBAL LOG'!#REF!) -> #REF! | G16: =COUNTIFS('GLOBAL LOG'!$E$6:$E$128,G$10,'GLOBAL LOG'!$D$6:$D$128,$C16) -> 0 | H16: =COUNTIFS('GLOBAL LOG'!$E$6:$E$128,H$10,'GLOBAL LOG'!$D$6:$D$128,$C16) -> 0 | I16: =COUNTIFS('GLOBAL LOG'!$E$6:$E$128,I$10,'GLOBAL LOG'!$D$6:$D$128,$C16) -> 0 | J16: =COUNTIFS('GLOBAL LOG'!$E$6:$E$128,J$10,'GLOBAL LOG'!$D$6:$D$128,$C16) -> 0 | K16: =COUNTIFS('GLOBAL LOG'!$E$6:$E$128,K$10,'GLOBAL LOG'!$D$6:$D$128,$C16) -> 0 | L16: =COUNTIFS('GLOBAL LOG'!$E$6:$E$128,L$10,'GLOBAL LOG'!$D$6:$D$128,$C16) -> 0 | M16: =COUNTIFS('GLOBAL LOG'!$E$6:$E$128,M$10,'GLOBAL LOG'!$D$6:$D$128,$C16) -> 0 | N16: =COUNTIFS('GLOBAL LOG'!$D$6:$D$128,$C16,'GLOBAL LOG'!#REF!,"High") -> #REF! | O16: =COUNTIFS('GLOBAL LOG'!$D$6:$D$128,$C16,'GLOBAL LOG'!#REF!,"Med") -> #REF! | P16: =COUNTIFS('GLOBAL LOG'!$D$6:$D$128,$C16,'GLOBAL LOG'!#REF!,"Low") -> #REF! | Q16: =COUNTIFS('GLOBAL LOG'!$D$6:$D$128,$C16,'GLOBAL LOG'!#REF!,"High") -> #REF! | R16: =COUNTIFS('GLOBAL LOG'!$D$6:$D$128,$C16,'GLOBAL LOG'!#REF!,"Med") -> #REF! | S16: =COUNTIFS('GLOBAL LOG'!$D$6:$D$128,$C16,'GLOBAL LOG'!#REF!,"Low") -> #REF! | T16: =COUNTIFS('GLOBAL LOG'!$D$6:$D$128,$C16,'GLOBAL LOG'!#REF!,"Completed") -> #REF! | U16: =COUNTIFS('GLOBAL LOG'!$D$6:$D$128,$C16,'GLOBAL LOG'!#REF!,"Contracting") -> #REF! | V16: =COUNTIFS('GLOBAL LOG'!$D$6:$D$128,$C16,'GLOBAL LOG'!#REF!,"Negotiations") -> #REF! | W16: =COUNTIFS('GLOBAL LOG'!$D$6:$D$128,$C16,'GLOBAL LOG'!#REF!,"ICT") -> #REF! | X16: =COUNTIFS('GLOBAL LOG'!$D$6:$D$128,$C16,'GLOBAL LOG'!#REF!,"Hopper") -> #REF! | Y16: =SUMIF('GLOBAL LOG'!$D$6:$D$128,$C16,'GLOBAL LOG'!$Q$6:$Q$128) -> 0 | Z16: =SUMIF('GLOBAL LOG'!$D$6:$D$128,$C16,'GLOBAL LOG'!$R$6:$R$128) -> 0 | AA16: =Y16+Z16 -> 0 | AB16: =SUMIF('GLOBAL LOG'!$D$6:$D$128,C16,'GLOBAL LOG'!#REF!) -> #REF! | AD16: Air Austral | AE16: #REF! | AG16: China Southern | AH16: 5 | AJ16: Aerolineas | AK16: 0 | AM16: China Southern | AN16: 5
C17: Air Belgium | D17: =COUNTIFS('GLOBAL LOG'!$D$6:$D$128,C17,'GLOBAL LOG'!$K$6:$K$128,"<>") -> 0 | E17: =COUNTIFS('GLOBAL LOG'!$D$6:$D$128,C17,'GLOBAL LOG'!#REF!,"Yes") -> #REF! | F17: =SUMIF('GLOBAL LOG'!$D$6:$D$128,COUNT!C17,'GLOBAL LOG'!#REF!) -> #REF! | G17: =COUNTIFS('GLOBAL LOG'!$E$6:$E$128,G$10,'GLOBAL LOG'!$D$6:$D$128,$C17) -> 0 | H17: =COUNTIFS('GLOBAL LOG'!$E$6:$E$128,H$10,'GLOBAL LOG'!$D$6:$D$128,$C17) -> 0 | I17: =COUNTIFS('GLOBAL LOG'!$E$6:$E$128,I$10,'GLOBAL LOG'!$D$6:$D$128,$C17) -> 0 | J17: =COUNTIFS('GLOBAL LOG'!$E$6:$E$128,J$10,'GLOBAL LOG'!$D$6:$D$128,$C17) -> 0 | K17: =COUNTIFS('GLOBAL LOG'!$E$6:$E$128,K$10,'GLOBAL LOG'!$D$6:$D$128,$C17) -> 0 | L17: =COUNTIFS('GLOBAL LOG'!$E$6:$E$128,L$10,'GLOBAL LOG'!$D$6:$D$128,$C17) -> 0 | M17: =COUNTIFS('GLOBAL LOG'!$E$6:$E$128,M$10,'GLOBAL LOG'!$D$6:$D$128,$C17) -> 0 | N17: =COUNTIFS('GLOBAL LOG'!$D$6:$D$128,$C17,'GLOBAL LOG'!#REF!,"High") -> #REF! | O17: =COUNTIFS('GLOBAL LOG'!$D$6:$D$128,$C17,'GLOBAL LOG'!#REF!,"Med") -> #REF! | P17: =COUNTIFS('GLOBAL LOG'!$D$6:$D$128,$C17,'GLOBAL LOG'!#REF!,"Low") -> #REF! | Q17: =COUNTIFS('GLOBAL LOG'!$D$6:$D$128,$C17,'GLOBAL LOG'!#REF!,"High") -> #REF! | R17: =COUNTIFS('GLOBAL LOG'!$D$6:$D$128,$C17,'GLOBAL LOG'!#REF!,"Med") -> #REF! | S17: =COUNTIFS('GLOBAL LOG'!$D$6:$D$128,$C17,'GLOBAL LOG'!#REF!,"Low") -> #REF! | T17: =COUNTIFS('GLOBAL LOG'!$D$6:$D$128,$C17,'GLOBAL LOG'!#REF!,"Completed") -> #REF! | U17: =COUNTIFS('GLOBAL LOG'!$D$6:$D$128,$C17,'GLOBAL LOG'!#REF!,"Contracting") -> #REF! | V17: =COUNTIFS('GLOBAL LOG'!$D$6:$D$128,$C17,'GLOBAL LOG'!#REF!,"Negotiations") -> #REF! | W17: =COUNTIFS('GLOBAL LOG'!$D$6:$D$128,$C17,'GLOBAL LOG'!#REF!,"ICT") -> #REF! | X17: =COUNTIFS('GLOBAL LOG'!$D$6:$D$128,$C17,'GLOBAL LOG'!#REF!,"Hopper") -> #REF! | Y17: =SUMIF('GLOBAL LOG'!$D$6:$D$128,$C17,'GLOBAL LOG'!$Q$6:$Q$128) -> 0 | Z17: =SUMIF('GLOBAL LOG'!$D$6:$D$128,$C17,'GLOBAL LOG'!$R$6:$R$128) -> 0 | AA17: =Y17+Z17 -> 0 | AB17: =SUMIF('GLOBAL LOG'!$D$6:$D$128,C17,'GLOBAL LOG'!#REF!) -> #REF! | AD17: Air Belgium | AE17: #REF! | AG17: Japan Airlines | AH17: 3.2 | AJ17: Air Algerie | AK17: 0 | AM17: Japan Airlines | AN17: 3.2
C18: Air Canada | D18: =COUNTIFS('GLOBAL LOG'!$D$6:$D$128,C18,'GLOBAL LOG'!$K$6:$K$128,"<>") -> 0 | E18: =COUNTIFS('GLOBAL LOG'!$D$6:$D$128,C18,'GLOBAL LOG'!#REF!,"Yes") -> #REF! | F18: =SUMIF('GLOBAL LOG'!$D$6:$D$128,COUNT!C18,'GLOBAL LOG'!#REF!) -> #REF! | G18: =COUNTIFS('GLOBAL LOG'!$E$6:$E$128,G$10,'GLOBAL LOG'!$D$6:$D$128,$C18) -> 0 | H18: =COUNTIFS('GLOBAL LOG'!$E$6:$E$128,H$10,'GLOBAL LOG'!$D$6:$D$128,$C18) -> 0 | I18: =COUNTIFS('GLOBAL LOG'!$E$6:$E$128,I$10,'GLOBAL LOG'!$D$6:$D$128,$C18) -> 0 | J18: =COUNTIFS('GLOBAL LOG'!$E$6:$E$128,J$10,'GLOBAL LOG'!$D$6:$D$128,$C18) -> 0 | K18: =COUNTIFS('GLOBAL LOG'!$E$6:$E$128,K$10,'GLOBAL LOG'!$D$6:$D$128,$C18) -> 0 | L18: =COUNTIFS('GLOBAL LOG'!$E$6:$E$128,L$10,'GLOBAL LOG'!$D$6:$D$128,$C18) -> 0 | M18: =COUNTIFS('GLOBAL LOG'!$E$6:$E$128,M$10,'GLOBAL LOG'!$D$6:$D$128,$C18) -> 0 | N18: =COUNTIFS('GLOBAL LOG'!$D$6:$D$128,$C18,'GLOBAL LOG'!#REF!,"High") -> #REF! | O18: =COUNTIFS('GLOBAL LOG'!$D$6:$D$128,$C18,'GLOBAL LOG'!#REF!,"Med") -> #REF! | P18: =COUNTIFS('GLOBAL LOG'!$D$6:$D$128,$C18,'GLOBAL LOG'!#REF!,"Low") -> #REF! | Q18: =COUNTIFS('GLOBAL LOG'!$D$6:$D$128,$C18,'GLOBAL LOG'!#REF!,"High") -> #REF! | R18: =COUNTIFS('GLOBAL LOG'!$D$6:$D$128,$C18,'GLOBAL LOG'!#REF!,"Med") -> #REF! | S18: =COUNTIFS('GLOBAL LOG'!$D$6:$D$128,$C18,'GLOBAL LOG'!#REF!,"Low") -> #REF! | T18: =COUNTIFS('GLOBAL LOG'!$D$6:$D$128,$C18,'GLOBAL LOG'!#REF!,"Completed") -> #REF! | U18: =COUNTIFS('GLOBAL LOG'!$D$6:$D$128,$C18,'GLOBAL LOG'!#REF!,"Contracting") -> #REF! | V18: =COUNTIFS('GLOBAL LOG'!$D$6:$D$128,$C18,'GLOBAL LOG'!#REF!,"Negotiations") -> #REF! | W18: =COUNTIFS('GLOBAL LOG'!$D$6:$D$128,$C18,'GLOBAL LOG'!#REF!,"ICT") -> #REF! | X18: =COUNTIFS('GLOBAL LOG'!$D$6:$D$128,$C18,'GLOBAL LOG'!#REF!,"Hopper") -> #REF! | Y18: =SUMIF('GLOBAL LOG'!$D$6:$D$128,$C18,'GLOBAL LOG'!$Q$6:$Q$128) -> 0 | Z18: =SUMIF('GLOBAL LOG'!$D$6:$D$128,$C18,'GLOBAL LOG'!$R$6:$R$128) -> 0 | AA18: =Y18+Z18 -> 0 | AB18: =SUMIF('GLOBAL LOG'!$D$6:$D$128,C18,'GLOBAL LOG'!#REF!) -> #REF! | AD18: Air Canada | AE18: #REF! | AG18: Aer Lingus | AH18: 0 | AJ18: Air Austral | AK18: 0 | AM18: Aer Lingus | AN18: 0
C19: Air Caraibes Atlantique | D19: =COUNTIFS('GLOBAL LOG'!$D$6:$D$128,C19,'GLOBAL LOG'!$K$6:$K$128,"<>") -> 0 | E19: =COUNTIFS('GLOBAL LOG'!$D$6:$D$128,C19,'GLOBAL LOG'!#REF!,"Yes") -> #REF! | F19: =SUMIF('GLOBAL LOG'!$D$6:$D$128,COUNT!C19,'GLOBAL LOG'!#REF!) -> #REF! | G19: =COUNTIFS('GLOBAL LOG'!$E$6:$E$128,G$10,'GLOBAL LOG'!$D$6:$D$128,$C19) -> 0 | H19: =COUNTIFS('GLOBAL LOG'!$E$6:$E$128,H$10,'GLOBAL LOG'!$D$6:$D$128,$C19) -> 0 | I19: =COUNTIFS('GLOBAL LOG'!$E$6:$E$128,I$10,'GLOBAL LOG'!$D$6:$D$128,$C19) -> 0 | J19: =COUNTIFS('GLOBAL LOG'!$E$6:$E$128,J$10,'GLOBAL LOG'!$D$6:$D$128,$C19) -> 0 | K19: =COUNTIFS('GLOBAL LOG'!$E$6:$E$128,K$10,'GLOBAL LOG'!$D$6:$D$128,$C19) -> 0 | L19: =COUNTIFS('GLOBAL LOG'!$E$6:$E$128,L$10,'GLOBAL LOG'!$D$6:$D$128,$C19) -> 0 | M19: =COUNTIFS('GLOBAL LOG'!$E$6:$E$128,M$10,'GLOBAL LOG'!$D$6:$D$128,$C19) -> 0 | N19: =COUNTIFS('GLOBAL LOG'!$D$6:$D$128,$C19,'GLOBAL LOG'!#REF!,"High") -> #REF! | O19: =COUNTIFS('GLOBAL LOG'!$D$6:$D$128,$C19,'GLOBAL LOG'!#REF!,"Med") -> #REF! | P19: =COUNTIFS('GLOBAL LOG'!$D$6:$D$128,$C19,'GLOBAL LOG'!#REF!,"Low") -> #REF! | Q19: =COUNTIFS('GLOBAL LOG'!$D$6:$D$128,$C19,'GLOBAL LOG'!#REF!,"High") -> #REF! | R19: =COUNTIFS('GLOBAL LOG'!$D$6:$D$128,$C19,'GLOBAL LOG'!#REF!,"Med") -> #REF! | S19: =COUNTIFS('GLOBAL LOG'!$D$6:$D$128,$C19,'GLOBAL LOG'!#REF!,"Low") -> #REF! | T19: =COUNTIFS('GLOBAL LOG'!$D$6:$D$128,$C19,'GLOBAL LOG'!#REF!,"Completed") -> #REF! | U19: =COUNTIFS('GLOBAL LOG'!$D$6:$D$128,$C19,'GLOBAL LOG'!#REF!,"Contracting") -> #REF! | V19: =COUNTIFS('GLOBAL LOG'!$D$6:$D$128,$C19,'GLOBAL LOG'!#REF!,"Negotiations") -> #REF! | W19: =COUNTIFS('GLOBAL LOG'!$D$6:$D$128,$C19,'GLOBAL LOG'!#REF!,"ICT") -> #REF! | X19: =COUNTIFS('GLOBAL LOG'!$D$6:$D$128,$C19,'GLOBAL LOG'!#REF!,"Hopper") -> #REF! | Y19: =SUMIF('GLOBAL LOG'!$D$6:$D$128,$C19,'GLOBAL LOG'!$Q$6:$Q$128) -> 0 | Z19: =SUMIF('GLOBAL LOG'!$D$6:$D$128,$C19,'GLOBAL LOG'!$R$6:$R$128) -> 0 | AA19: =Y19+Z19 -> 0 | AB19: =SUMIF('GLOBAL LOG'!$D$6:$D$128,C19,'GLOBAL LOG'!#REF!) -> #REF! | AD19: Air Caraibes Atlantique | AE19: #REF! | AG19: AerCap | AH19: 0 | AJ19: Air Belgium | AK19: 0 | AM19: AerCap | AN19: 0
C20: Air China | D20: =COUNTIFS('GLOBAL LOG'!$D$6:$D$128,C20,'GLOBAL LOG'!$K$6:$K$128,"<>") -> 1 | E20: =COUNTIFS('GLOBAL LOG'!$D$6:$D$128,C20,'GLOBAL LOG'!#REF!,"Yes") -> #REF! | F20: =SUMIF('GLOBAL LOG'!$D$6:$D$128,COUNT!C20,'GLOBAL LOG'!#REF!) -> #REF! | G20: =COUNTIFS('GLOBAL LOG'!$E$6:$E$128,G$10,'GLOBAL LOG'!$D$6:$D$128,$C20) -> 2 | H20: =COUNTIFS('GLOBAL LOG'!$E$6:$E$128,H$10,'GLOBAL LOG'!$D$6:$D$128,$C20) -> 0 | I20: =COUNTIFS('GLOBAL LOG'!$E$6:$E$128,I$10,'GLOBAL LOG'!$D$6:$D$128,$C20) -> 1 | J20: =COUNTIFS('GLOBAL LOG'!$E$6:$E$128,J$10,'GLOBAL LOG'!$D$6:$D$128,$C20) -> 0 | K20: =COUNTIFS('GLOBAL LOG'!$E$6:$E$128,K$10,'GLOBAL LOG'!$D$6:$D$128,$C20) -> 0 | L20: =COUNTIFS('GLOBAL LOG'!$E$6:$E$128,L$10,'GLOBAL LOG'!$D$6:$D$128,$C20) -> 0 | M20: =COUNTIFS('GLOBAL LOG'!$E$6:$E$128,M$10,'GLOBAL LOG'!$D$6:$D$128,$C20) -> 0 | N20: =COUNTIFS('GLOBAL LOG'!$D$6:$D$128,$C20,'GLOBAL LOG'!#REF!,"High") -> #REF! | O20: =COUNTIFS('GLOBAL LOG'!$D$6:$D$128,$C20,'GLOBAL LOG'!#REF!,"Med") -> #REF! | P20: =COUNTIFS('GLOBAL LOG'!$D$6:$D$128,$C20,'GLOBAL LOG'!#REF!,"Low") -> #REF! | Q20: =COUNTIFS('GLOBAL LOG'!$D$6:$D$128,$C20,'GLOBAL LOG'!#REF!,"High") -> #REF! | R20: =COUNTIFS('GLOBAL LOG'!$D$6:$D$128,$C20,'GLOBAL LOG'!#REF!,"Med") -> #REF! | S20: =COUNTIFS('GLOBAL LOG'!$D$6:$D$128,$C20,'GLOBAL LOG'!#REF!,"Low") -> #REF! | T20: =COUNTIFS('GLOBAL LOG'!$D$6:$D$128,$C20,'GLOBAL LOG'!#REF!,"Completed") -> #REF! | U20: =COUNTIFS('GLOBAL LOG'!$D$6:$D$128,$C20,'GLOBAL LOG'!#REF!,"Contracting") -> #REF! | V20: =COUNTIFS('GLOBAL LOG'!$D$6:$D$128,$C20,'GLOBAL LOG'!#REF!,"Negotiations") -> #REF! | W20: =COUNTIFS('GLOBAL LOG'!$D$6:$D$128,$C20,'GLOBAL LOG'!#REF!,"ICT") -> #REF! | X20: =COUNTIFS('GLOBAL LOG'!$D$6:$D$128,$C20,'GLOBAL LOG'!#REF!,"Hopper") -> #REF! | Y20: =SUMIF('GLOBAL LOG'!$D$6:$D$128,$C20,'GLOBAL LOG'!$Q$6:$Q$128) -> 5.3 | Z20: =SUMIF('GLOBAL LOG'!$D$6:$D$128,$C20,'GLOBAL LOG'!$R$6:$R$128) -> 33.6 | AA20: =Y20+Z20 -> 38.9 | AB20: =SUMIF('GLOBAL LOG'!$D$6:$D$128,C20,'GLOBAL LOG'!#REF!) -> #REF! | AD20: Air China | AE20: #REF! | AG20: Aeroflot Russian Airlines | AH20: 0 | AJ20: Air Canada | AK20: 0 | AM20: Aeroflot Russian Airlines | AN20: 0
C21: Air Europa Lineas Aereas S.A.U. | D21: =COUNTIFS('GLOBAL LOG'!$D$6:$D$128,C21,'GLOBAL LOG'!$K$6:$K$128,"<>") -> 0 | E21: =COUNTIFS('GLOBAL LOG'!$D$6:$D$128,C21,'GLOBAL LOG'!#REF!,"Yes") -> #REF! | F21: =SUMIF('GLOBAL LOG'!$D$6:$D$128,COUNT!C21,'GLOBAL LOG'!#REF!) -> #REF! | G21: =COUNTIFS('GLOBAL LOG'!$E$6:$E$128,G$10,'GLOBAL LOG'!$D$6:$D$128,$C21) -> 0 | H21: =COUNTIFS('GLOBAL LOG'!$E$6:$E$128,H$10,'GLOBAL LOG'!$D$6:$D$128,$C21) -> 0 | I21: =COUNTIFS('GLOBAL LOG'!$E$6:$E$128,I$10,'GLOBAL LOG'!$D$6:$D$128,$C21) -> 0 | J21: =COUNTIFS('GLOBAL LOG'!$E$6:$E$128,J$10,'GLOBAL LOG'!$D$6:$D$128,$C21) -> 0 | K21: =COUNTIFS('GLOBAL LOG'!$E$6:$E$128,K$10,'GLOBAL LOG'!$D$6:$D$128,$C21) -> 0 | L21: =COUNTIFS('GLOBAL LOG'!$E$6:$E$128,L$10,'GLOBAL LOG'!$D$6:$D$128,$C21) -> 0 | M21: =COUNTIFS('GLOBAL LOG'!$E$6:$E$128,M$10,'GLOBAL LOG'!$D$6:$D$128,$C21) -> 0 | N21: =COUNTIFS('GLOBAL LOG'!$D$6:$D$128,$C21,'GLOBAL LOG'!#REF!,"High") -> #REF! | O21: =COUNTIFS('GLOBAL LOG'!$D$6:$D$128,$C21,'GLOBAL LOG'!#REF!,"Med") -> #REF! | P21: =COUNTIFS('GLOBAL LOG'!$D$6:$D$128,$C21,'GLOBAL LOG'!#REF!,"Low") -> #REF! | Q21: =COUNTIFS('GLOBAL LOG'!$D$6:$D$128,$C21,'GLOBAL LOG'!#REF!,"High") -> #REF! | R21: =COUNTIFS('GLOBAL LOG'!$D$6:$D$128,$C21,'GLOBAL LOG'!#REF!,"Med") -> #REF! | S21: =COUNTIFS('GLOBAL LOG'!$D$6:$D$128,$C21,'GLOBAL LOG'!#REF!,"Low") -> #REF! | T21: =COUNTIFS('GLOBAL LOG'!$D$6:$D$128,$C21,'GLOBAL LOG'!#REF!,"Completed") -> #REF! | U21: =COUNTIFS('GLOBAL LOG'!$D$6:$D$128,$C21,'GLOBAL LOG'!#REF!,"Contracting") -> #REF! | V21: =COUNTIFS('GLOBAL LOG'!$D$6:$D$128,$C21,'GLOBAL LOG'!#REF!,"Negotiations") -> #REF! | W21: =COUNTIFS('GLOBAL LOG'!$D$6:$D$128,$C21,'GLOBAL LOG'!#REF!,"ICT") -> #REF! | X21: =COUNTIFS('GLOBAL LOG'!$D$6:$D$128,$C21,'GLOBAL LOG'!#REF!,"Hopper") -> #REF! | Y21: =SUMIF('GLOBAL LOG'!$D$6:$D$128,$C21,'GLOBAL LOG'!$Q$6:$Q$128) -> 0 | Z21: =SUMIF('GLOBAL LOG'!$D$6:$D$128,$C21,'GLOBAL LOG'!$R$6:$R$128) -> 0 | AA21: =Y21+Z21 -> 0 | AB21: =SUMIF('GLOBAL LOG'!$D$6:$D$128,C21,'GLOBAL LOG'!#REF!) -> #REF! | AD21: Air Europa Lineas Aereas S.A.U. | AE21: #REF! | AG21: Aerolineas | AH21: 0 | AJ21: Air Caraibes Atlantique | AK21: 0 | AM21: Aerolineas | AN21: 0
C22: Air France | D22: =COUNTIFS('GLOBAL LOG'!$D$6:$D$128,C22,'GLOBAL LOG'!$K$6:$K$128,"<>") -> 0 | E22: =COUNTIFS('GLOBAL LOG'!$D$6:$D$128,C22,'GLOBAL LOG'!#REF!,"Yes") -> #REF! | F22: =SUMIF('GLOBAL LOG'!$D$6:$D$128,COUNT!C22,'GLOBAL LOG'!#REF!) -> #REF! | G22: =COUNTIFS('GLOBAL LOG'!$E$6:$E$128,G$10,'GLOBAL LOG'!$D$6:$D$128,$C22) -> 0 | H22: =COUNTIFS('GLOBAL LOG'!$E$6:$E$128,H$10,'GLOBAL LOG'!$D$6:$D$128,$C22) -> 0 | I22: =COUNTIFS('GLOBAL LOG'!$E$6:$E$128,I$10,'GLOBAL LOG'!$D$6:$D$128,$C22) -> 0 | J22: =COUNTIFS('GLOBAL LOG'!$E$6:$E$128,J$10,'GLOBAL LOG'!$D$6:$D$128,$C22) -> 0 | K22: =COUNTIFS('GLOBAL LOG'!$E$6:$E$128,K$10,'GLOBAL LOG'!$D$6:$D$128,$C22) -> 0 | L22: =COUNTIFS('GLOBAL LOG'!$E$6:$E$128,L$10,'GLOBAL LOG'!$D$6:$D$128,$C22) -> 0 | M22: =COUNTIFS('GLOBAL LOG'!$E$6:$E$128,M$10,'GLOBAL LOG'!$D$6:$D$128,$C22) -> 0 | N22: =COUNTIFS('GLOBAL LOG'!$D$6:$D$128,$C22,'GLOBAL LOG'!#REF!,"High") -> #REF! | O22: =COUNTIFS('GLOBAL LOG'!$D$6:$D$128,$C22,'GLOBAL LOG'!#REF!,"Med") -> #REF! | P22: =COUNTIFS('GLOBAL LOG'!$D$6:$D$128,$C22,'GLOBAL LOG'!#REF!,"Low") -> #REF! | Q22: =COUNTIFS('GLOBAL LOG'!$D$6:$D$128,$C22,'GLOBAL LOG'!#REF!,"High") -> #REF! | R22: =COUNTIFS('GLOBAL LOG'!$D$6:$D$128,$C22,'GLOBAL LOG'!#REF!,"Med") -> #REF! | S22: =COUNTIFS('GLOBAL LOG'!$D$6:$D$128,$C22,'GLOBAL LOG'!#REF!,"Low") -> #REF! | T22: =COUNTIFS('GLOBAL LOG'!$D$6:$D$128,$C22,'GLOBAL LOG'!#REF!,"Completed") -> #REF! | U22: =COUNTIFS('GLOBAL LOG'!$D$6:$D$128,$C22,'GLOBAL LOG'!#REF!,"Contracting") -> #REF! | V22: =COUNTIFS('GLOBAL LOG'!$D$6:$D$128,$C22,'GLOBAL LOG'!#REF!,"Negotiations") -> #REF! | W22: =COUNTIFS('GLOBAL LOG'!$D$6:$D$128,$C22,'GLOBAL LOG'!#REF!,"ICT") -> #REF! | X22: =COUNTIFS('GLOBAL LOG'!$D$6:$D$128,$C22,'GLOBAL LOG'!#REF!,"Hopper") -> #REF! | Y22: =SUMIF('GLOBAL LOG'!$D$6:$D$128,$C22,'GLOBAL LOG'!$Q$6:$Q$128) -> 0 | Z22: =SUMIF('GLOBAL LOG'!$D$6:$D$128,$C22,'GLOBAL LOG'!$R$6:$R$128) -> 0 | AA22: =Y22+Z22 -> 0 | AB22: =SUMIF('GLOBAL LOG'!$D$6:$D$128,C22,'GLOBAL LOG'!#REF!) -> #REF! | AD22: Air France | AE22: #REF! | AG22: Air Algerie | AH22: 0 | AJ22: Air Europa Lineas Aereas S.A.U. | AK22: 0 | AM22: Air Algerie | AN22: 0
C23: Air Greenland | D23: =COUNTIFS('GLOBAL LOG'!$D$6:$D$128,C23,'GLOBAL LOG'!$K$6:$K$128,"<>") -> 0 | E23: =COUNTIFS('GLOBAL LOG'!$D$6:$D$128,C23,'GLOBAL LOG'!#REF!,"Yes") -> #REF! | F23: =SUMIF('GLOBAL LOG'!$D$6:$D$128,COUNT!C23,'GLOBAL LOG'!#REF!) -> #REF! | G23: =COUNTIFS('GLOBAL LOG'!$E$6:$E$128,G$10,'GLOBAL LOG'!$D$6:$D$128,$C23) -> 0 | H23: =COUNTIFS('GLOBAL LOG'!$E$6:$E$128,H$10,'GLOBAL LOG'!$D$6:$D$128,$C23) -> 0 | I23: =COUNTIFS('GLOBAL LOG'!$E$6:$E$128,I$10,'GLOBAL LOG'!$D$6:$D$128,$C23) -> 0 | J23: =COUNTIFS('GLOBAL LOG'!$E$6:$E$128,J$10,'GLOBAL LOG'!$D$6:$D$128,$C23) -> 0 | K23: =COUNTIFS('GLOBAL LOG'!$E$6:$E$128,K$10,'GLOBAL LOG'!$D$6:$D$128,$C23) -> 0 | L23: =COUNTIFS('GLOBAL LOG'!$E$6:$E$128,L$10,'GLOBAL LOG'!$D$6:$D$128,$C23) -> 0 | M23: =COUNTIFS('GLOBAL LOG'!$E$6:$E$128,M$10,'GLOBAL LOG'!$D$6:$D$128,$C23) -> 0 | N23: =COUNTIFS('GLOBAL LOG'!$D$6:$D$128,$C23,'GLOBAL LOG'!#REF!,"High") -> #REF! | O23: =COUNTIFS('GLOBAL LOG'!$D$6:$D$128,$C23,'GLOBAL LOG'!#REF!,"Med") -> #REF! | P23: =COUNTIFS('GLOBAL LOG'!$D$6:$D$128,$C23,'GLOBAL LOG'!#REF!,"Low") -> #REF! | Q23: =COUNTIFS('GLOBAL LOG'!$D$6:$D$128,$C23,'GLOBAL LOG'!#REF!,"High") -> #REF! | R23: =COUNTIFS('GLOBAL LOG'!$D$6:$D$128,$C23,'GLOBAL LOG'!#REF!,"Med") -> #REF! | S23: =COUNTIFS('GLOBAL LOG'!$D$6:$D$128,$C23,'GLOBAL LOG'!#REF!,"Low") -> #REF! | T23: =COUNTIFS('GLOBAL LOG'!$D$6:$D$128,$C23,'GLOBAL LOG'!#REF!,"Completed") -> #REF! | U23: =COUNTIFS('GLOBAL LOG'!$D$6:$D$128,$C23,'GLOBAL LOG'!#REF!,"Contracting") -> #REF! | V23: =COUNTIFS('GLOBAL LOG'!$D$6:$D$128,$C23,'GLOBAL LOG'!#REF!,"Negotiations") -> #REF! | W23: =COUNTIFS('GLOBAL LOG'!$D$6:$D$128,$C23,'GLOBAL LOG'!#REF!,"ICT") -> #REF! | X23: =COUNTIFS('GLOBAL LOG'!$D$6:$D$128,$C23,'GLOBAL LOG'!#REF!,"Hopper") -> #REF! | Y23: =SUMIF('GLOBAL LOG'!$D$6:$D$128,$C23,'GLOBAL LOG'!$Q$6:$Q$128) -> 0 | Z23: =SUMIF('GLOBAL LOG'!$D$6:$D$128,$C23,'GLOBAL LOG'!$R$6:$R$128) -> 0 | AA23: =Y23+Z23 -> 0 | AB23: =SUMIF('GLOBAL LOG'!$D$6:$D$128,C23,'GLOBAL LOG'!#REF!) -> #REF! | AD23: Air Greenland | AE23: #REF! | AG23: Air Austral | AH23: 0 | AJ23: Air France | AK23: 0 | AM23: Air Austral | AN23: 0
... C162: VallJet | D162: =COUNTIFS('GLOBAL LOG'!$D$6:$D$128,C162,'GLOBAL LOG'!$K$6:$K$128,"<>") -> 0 | E162: =COUNTIFS('GLOBAL LOG'!$D$6:$D$128,C162,'GLOBAL LOG'!#REF!,"Yes") -> #REF! | F162: =SUMIF('GLOBAL LOG'!$D$6:$D$128,COUNT!C162,'GLOBAL LOG'!#REF!) -> #REF! | G162: =COUNTIFS('GLOBAL LOG'!$E$6:$E$128,G$10,'GLOBAL LOG'!$D$6:$D$128,$C162) -> 0 | H162: =COUNTIFS('GLOBAL LOG'!$E$6:$E$128,H$10,'GLOBAL LOG'!$D$6:$D$128,$C162) -> 0 | I162: =COUNTIFS('GLOBAL LOG'!$E$6:$E$128,I$10,'GLOBAL LOG'!$D$6:$D$128,$C162) -> 0 | J162: =COUNTIFS('GLOBAL LOG'!$E$6:$E$128,J$10,'GLOBAL LOG'!$D$6:$D$128,$C162) -> 0 | K162: =COUNTIFS('GLOBAL LOG'!$E$6:$E$128,K$10,'GLOBAL LOG'!$D$6:$D$128,$C162) -> 0 | L162: =COUNTIFS('GLOBAL LOG'!$E$6:$E$128,L$10,'GLOBAL LOG'!$D$6:$D$128,$C162) -> 0 | M162: =COUNTIFS('GLOBAL LOG'!$E$6:$E$128,M$10,'GLOBAL LOG'!$D$6:$D$128,$C162) -> 0 | N162: =COUNTIFS('GLOBAL LOG'!$D$6:$D$128,$C162,'GLOBAL LOG'!#REF!,"High") -> #REF! | O162: =COUNTIFS('GLOBAL LOG'!$D$6:$D$128,$C162,'GLOBAL LOG'!#REF!,"Med") -> #REF! | P162: =COUNTIFS('GLOBAL LOG'!$D$6:$D$128,$C162,'GLOBAL LOG'!#REF!,"Low") -> #REF! | Q162: =COUNTIFS('GLOBAL LOG'!$D$6:$D$128,$C162,'GLOBAL LOG'!#REF!,"High") -> #REF! | R162: =COUNTIFS('GLOBAL LOG'!$D$6:$D$128,$C162,'GLOBAL LOG'!#REF!,"Med") -> #REF! | S162: =COUNTIFS('GLOBAL LOG'!$D$6:$D$128,$C162,'GLOBAL LOG'!#REF!,"Low") -> #REF! | T162: =COUNTIFS('GLOBAL LOG'!$D$6:$D$128,$C162,'GLOBAL LOG'!#REF!,"Completed") -> #REF! | U162: =COUNTIFS('GLOBAL LOG'!$D$6:$D$128,$C162,'GLOBAL LOG'!#REF!,"Contracting") -> #REF! | V162: =COUNTIFS('GLOBAL LOG'!$D$6:$D$128,$C162,'GLOBAL LOG'!#REF!,"Negotiations") -> #REF! | W162: =COUNTIFS('GLOBAL LOG'!$D$6:$D$128,$C162,'GLOBAL LOG'!#REF!,"ICT") -> #REF! | X162: =COUNTIFS('GLOBAL LOG'!$D$6:$D$128,$C162,'GLOBAL LOG'!#REF!,"Hopper") -> #REF! | Y162: =SUMIF('GLOBAL LOG'!$D$6:$D$128,$C162,'GLOBAL LOG'!$Q$6:$Q$128) -> 0 | Z162: =SUMIF('GLOBAL LOG'!$D$6:$D$128,$C162,'GLOBAL LOG'!$R$6:$R$128) -> 0 | AA162: =Y162+Z162 -> 0 | AB162: =SUMIF('GLOBAL LOG'!$D$6:$D$128,C162,'GLOBAL LOG'!#REF!) -> #REF! | AD162: VallJet | AE162: #REF! | AG162: VallJet | AH162: 0 | AJ162: VallJet | AK162: 0 | AM162: VallJet | AN162: 0
D163: =COUNTIFS('GLOBAL LOG'!$D$6:$D$128,C163,'GLOBAL LOG'!$K$6:$K$128,"<>") -> 0 | E163: =COUNTIFS('GLOBAL LOG'!$D$6:$D$128,C163,'GLOBAL LOG'!#REF!,"Yes") -> #REF! | F163: =SUMIF('GLOBAL LOG'!$D$6:$D$128,COUNT!C163,'GLOBAL LOG'!#REF!) -> #REF! | G163: =COUNTIFS('GLOBAL LOG'!$E$6:$E$128,G$10,'GLOBAL LOG'!$D$6:$D$128,$C163) -> 0 | H163: =COUNTIFS('GLOBAL LOG'!$E$6:$E$128,H$10,'GLOBAL LOG'!$D$6:$D$128,$C163) -> 0 | I163: =COUNTIFS('GLOBAL LOG'!$E$6:$E$128,I$10,'GLOBAL LOG'!$D$6:$D$128,$C163) -> 0 | J163: =COUNTIFS('GLOBAL LOG'!$E$6:$E$128,J$10,'GLOBAL LOG'!$D$6:$D$128,$C163) -> 0 | K163: =COUNTIFS('GLOBAL LOG'!$E$6:$E$128,K$10,'GLOBAL LOG'!$D$6:$D$128,$C163) -> 0 | L163: =COUNTIFS('GLOBAL LOG'!$E$6:$E$128,L$10,'GLOBAL LOG'!$D$6:$D$128,$C163) -> 0 | M163: =COUNTIFS('GLOBAL LOG'!$E$6:$E$128,M$10,'GLOBAL LOG'!$D$6:$D$128,$C163) -> 0 | N163: =COUNTIFS('GLOBAL LOG'!$D$6:$D$128,$C163,'GLOBAL LOG'!#REF!,"High") -> #REF! | O163: =COUNTIFS('GLOBAL LOG'!$D$6:$D$128,$C163,'GLOBAL LOG'!#REF!,"Med") -> #REF! | P163: =COUNTIFS('GLOBAL LOG'!$D$6:$D$128,$C163,'GLOBAL LOG'!#REF!,"Low") -> #REF! | Q163: =COUNTIFS('GLOBAL LOG'!$D$6:$D$128,$C163,'GLOBAL LOG'!#REF!,"High") -> #REF! | R163: =COUNTIFS('GLOBAL LOG'!$D$6:$D$128,$C163,'GLOBAL LOG'!#REF!,"Med") -> #REF! | S163: =COUNTIFS('GLOBAL LOG'!$D$6:$D$128,$C163,'GLOBAL LOG'!#REF!,"Low") -> #REF! | T163: =COUNTIFS('GLOBAL LOG'!$D$6:$D$128,$C163,'GLOBAL LOG'!#REF!,"Completed") -> #REF! | U163: =COUNTIFS('GLOBAL LOG'!$D$6:$D$128,$C163,'GLOBAL LOG'!#REF!,"Contracting") -> #REF! | V163: =COUNTIFS('GLOBAL LOG'!$D$6:$D$128,$C163,'GLOBAL LOG'!#REF!,"Negotiations") -> #REF! | W163: =COUNTIFS('GLOBAL LOG'!$D$6:$D$128,$C163,'GLOBAL LOG'!#REF!,"ICT") -> #REF! | X163: =COUNTIFS('GLOBAL LOG'!$D$6:$D$128,$C163,'GLOBAL LOG'!#REF!,"Hopper") -> #REF! | Y163: =SUMIF('GLOBAL LOG'!$D$6:$D$128,$C163,'GLOBAL LOG'!$Q$6:$Q$128) -> 0 | Z163: =SUMIF('GLOBAL LOG'!$D$6:$D$128,$C163,'GLOBAL LOG'!$R$6:$R$128) -> 0 | AA163: =Y163+Z163 -> 0 | AB163: =SUMIF('GLOBAL LOG'!$D$6:$D$128,C163,'GLOBAL LOG'!#REF!) -> #REF! | AD163: 0 | AE163: #REF! | AG163: 0 | AH163: 0 | AJ163: 0 | AK163: 0 | AM163: 0 | AN163: 0
D164: =COUNTIFS('GLOBAL LOG'!$D$6:$D$128,C164,'GLOBAL LOG'!$K$6:$K$128,"<>") -> 0 | E164: =COUNTIFS('GLOBAL LOG'!$D$6:$D$128,C164,'GLOBAL LOG'!#REF!,"Yes") -> #REF! | F164: =SUMIF('GLOBAL LOG'!$D$6:$D$128,COUNT!C164,'GLOBAL LOG'!#REF!) -> #REF! | G164: =COUNTIFS('GLOBAL LOG'!$E$6:$E$128,G$10,'GLOBAL LOG'!$D$6:$D$128,$C164) -> 0 | H164: =COUNTIFS('GLOBAL LOG'!$E$6:$E$128,H$10,'GLOBAL LOG'!$D$6:$D$128,$C164) -> 0 | I164: =COUNTIFS('GLOBAL LOG'!$E$6:$E$128,I$10,'GLOBAL LOG'!$D$6:$D$128,$C164) -> 0 | J164: =COUNTIFS('GLOBAL LOG'!$E$6:$E$128,J$10,'GLOBAL LOG'!$D$6:$D$128,$C164) -> 0 | K164: =COUNTIFS('GLOBAL LOG'!$E$6:$E$128,K$10,'GLOBAL LOG'!$D$6:$D$128,$C164) -> 0 | L164: =COUNTIFS('GLOBAL LOG'!$E$6:$E$128,L$10,'GLOBAL LOG'!$D$6:$D$128,$C164) -> 0 | M164: =COUNTIFS('GLOBAL LOG'!$E$6:$E$128,M$10,'GLOBAL LOG'!$D$6:$D$128,$C164) -> 0 | N164: =COUNTIFS('GLOBAL LOG'!$D$6:$D$128,$C164,'GLOBAL LOG'!#REF!,"High") -> #REF! | O164: =COUNTIFS('GLOBAL LOG'!$D$6:$D$128,$C164,'GLOBAL LOG'!#REF!,"Med") -> #REF! | P164: =COUNTIFS('GLOBAL LOG'!$D$6:$D$128,$C164,'GLOBAL LOG'!#REF!,"Low") -> #REF! | Q164: =COUNTIFS('GLOBAL LOG'!$D$6:$D$128,$C164,'GLOBAL LOG'!#REF!,"High") -> #REF! | R164: =COUNTIFS('GLOBAL LOG'!$D$6:$D$128,$C164,'GLOBAL LOG'!#REF!,"Med") -> #REF! | S164: =COUNTIFS('GLOBAL LOG'!$D$6:$D$128,$C164,'GLOBAL LOG'!#REF!,"Low") -> #REF! | T164: =COUNTIFS('GLOBAL LOG'!$D$6:$D$128,$C164,'GLOBAL LOG'!#REF!,"Completed") -> #REF! | U164: =COUNTIFS('GLOBAL LOG'!$D$6:$D$128,$C164,'GLOBAL LOG'!#REF!,"Contracting") -> #REF! | V164: =COUNTIFS('GLOBAL LOG'!$D$6:$D$128,$C164,'GLOBAL LOG'!#REF!,"Negotiations") -> #REF! | W164: =COUNTIFS('GLOBAL LOG'!$D$6:$D$128,$C164,'GLOBAL LOG'!#REF!,"ICT") -> #REF! | X164: =COUNTIFS('GLOBAL LOG'!$D$6:$D$128,$C164,'GLOBAL LOG'!#REF!,"Hopper") -> #REF! | Y164: =SUMIF('GLOBAL LOG'!$D$6:$D$128,$C164,'GLOBAL LOG'!$Q$6:$Q$128) -> 0 | Z164: =SUMIF('GLOBAL LOG'!$D$6:$D$128,$C164,'GLOBAL LOG'!$R$6:$R$128) -> 0 | AA164: =Y164+Z164 -> 0 | AB164: =SUMIF('GLOBAL LOG'!$D$6:$D$128,C164,'GLOBAL LOG'!#REF!) -> #REF! | AD164: 0 | AE164: #REF! | AG164: 0 | AH164: 0 | AJ164: 0 | AK164: 0 | AM164: 0 | AN164: 0
C166: MATRIX
C168: OPP | D168: TERM IMPACT | E168: 2026 | F168: 2027 | G168: 26/27 | H168: P | I168: PF | J168: PF x W | K168: C | L168: CF | M168: CF x W | N168: TERM IMPACT A | O168: 2026A | P168: 2027A | Q168: 26/27 a | S168: SORTED OPP | T168: SORTED TERM IMPACT A | V168: SORTED OPP | W168: SORTED 2026 | Y168: SORTED OPP | Z168: SORTED 2027 | AB168: SORTED OPP | AC168: SORTED 2026/2027
C169: {=IF(_xlfn._xlws.FILTER('GLOBAL LOG'!D6:D128,TRUE)=0,"",'GLOBAL LOG'!D6:D128)&" "&IF(_xlfn._xlws.FILTER('GLOBAL LOG'!K6:K128,TRUE)=0,"",'GLOBAL LOG'!K6:K128)} -> FedEx Corporation FedEx - agreement/amendment to unadministrable TotalCare clauses and incentivisation of SV inductions - RB211-535 | D169: {=_xlfn._xlws.FILTER('GLOBAL LOG'!#REF!,TRUE,"-")} -> #REF! | E169: {=_xlfn._xlws.FILTER('GLOBAL LOG'!Q6:Q128,TRUE,"-")} -> 6.43 | F169: {=_xlfn._xlws.FILTER('GLOBAL LOG'!R6:R128,TRUE,"-")} -> 6.96 | G169: =E169+F169 -> 13.39 | H169: {=INDEX('GLOBAL LOG'!#REF!,ROW()-169+15)} -> #REF! | I169: =_xlfn.XLOOKUP(H169,#REF!,#REF!,"",0,1) -> #REF! | J169: =IFERROR(I169*#REF!,"") | K169: {=INDEX('GLOBAL LOG'!#REF!,ROW()-169+15)} -> #REF! | L169: =_xlfn.XLOOKUP(K169,#REF!,#REF!,"",0,1) -> #REF! | M169: =IFERROR(L169*#REF!,"") | N169: =IFERROR(D169*J169*M169,-1) -> -1 | O169: =IFERROR(E169*J169*M169,-1) -> -1 | P169: =IFERROR(F169*J169*M169,-1) -> -1 | Q169: =IFERROR(G169*J169*M169,-1) -> -1 | S169: {=_xlfn.SORTBY(C169:C1189,N169:N1189,-1)} -> FedEx Corporation FedEx - agreement/amendment to unadministrable TotalCare clauses and incentivisation of SV inductions - RB211-535 | T169: {=_xlfn.SORTBY(N169:N1189,N169:N1189,-1)} -> -1 | V169: {=_xlfn.SORTBY(C169:C1189,O169:O1189,-1)} -> FedEx Corporation FedEx - agreement/amendment to unadministrable TotalCare clauses and incentivisation of SV inductions - RB211-535 | W169: {=_xlfn.SORTBY(O169:O1189,O169:O1189,-1)} -> -1 | Y169: {=_xlfn.SORTBY(C169:C1189,P169:P1189,-1)} -> FedEx Corporation FedEx - agreement/amendment to unadministrable TotalCare clauses and incentivisation of SV inductions - RB211-535 | Z169: {=_xlfn.SORTBY(P169:P1189,P169:P1189,-1)} -> -1 | AB169: {=_xlfn.SORTBY(C169:C1189,Q169:Q1189,-1)} -> FedEx Corporation FedEx - agreement/amendment to unadministrable TotalCare clauses and incentivisation of SV inductions - RB211-535 | AC169: {=_xlfn.SORTBY(Q169:Q1189,Q169:Q1189,-1)} -> -1
C170: American Airlines American Airlines requested input on longer extension to 2035 | E170: 0 | F170: 0 | G170: =E170+F170 -> 0 | H170: {=INDEX('GLOBAL LOG'!#REF!,ROW()-169+15)} -> #REF! | I170: =_xlfn.XLOOKUP(H170,#REF!,#REF!,"",0,1) -> #REF! | J170: =IFERROR(I170*#REF!,"") | K170: {=INDEX('GLOBAL LOG'!#REF!,ROW()-169+15)} -> #REF! | L170: =_xlfn.XLOOKUP(K170,#REF!,#REF!,"",0,1) -> #REF! | M170: =IFERROR(L170*#REF!,"") | N170: =IFERROR(D170*J170*M170,-1) -> -1 | O170: =IFERROR(E170*J170*M170,-1) -> -1 | P170: =IFERROR(F170*J170*M170,-1) -> -1 | Q170: =IFERROR(G170*J170*M170,-1) -> -1 | S170: American Airlines American Airlines requested input on longer extension to 2035 | T170: -1 | V170: American Airlines American Airlines requested input on longer extension to 2035 | W170: -1 | Y170: American Airlines American Airlines requested input on longer extension to 2035 | Z170: -1 | AB170: American Airlines American Airlines requested input on longer extension to 2035 | AC170: -1
C171: Thai Airways International Ltd Min term extension involving reinstating some discount, EOCL removal and escalation improvement. Jun-2025 Level 3 approval secured in .Jul 2025 - Proposal presented to THAI with minor trades, Sep 2025 formal proposal requested in, Feb 2026 proposal issued and expect to contract pending THA acceptance Apr 2026 - Senior engagement at AIX, awaiting feedback before next steps, possible adjustment pending ICT confirmation. | E171: tbc | F171: Confirm with Harry | G171: =E171+F171 -> #VALUE! | H171: {=INDEX('GLOBAL LOG'!#REF!,ROW()-169+15)} -> #REF! | I171: =_xlfn.XLOOKUP(H171,#REF!,#REF!,"",0,1) -> #REF! | J171: =IFERROR(I171*#REF!,"") | K171: {=INDEX('GLOBAL LOG'!#REF!,ROW()-169+15)} -> #REF! | L171: =_xlfn.XLOOKUP(K171,#REF!,#REF!,"",0,1) -> #REF! | M171: =IFERROR(L171*#REF!,"") | N171: =IFERROR(D171*J171*M171,-1) -> -1 | O171: =IFERROR(E171*J171*M171,-1) -> -1 | P171: =IFERROR(F171*J171*M171,-1) -> -1 | Q171: =IFERROR(G171*J171*M171,-1) -> -1 | S171: Thai Airways International Ltd Min term extension involving reinstating some discount, EOCL removal and escalation improvement. Jun-2025 Level 3 approval secured in .Jul 2025 - Proposal presented to THAI with minor trades, Sep 2025 formal proposal requested in, Feb 2026 proposal issued and expect to contract pending THA acceptance Apr 2026 - Senior engagement at AIX, awaiting feedback before next steps, possible adjustment pending ICT confirmation. | T171: -1 | V171: Thai Airways International Ltd Min term extension involving reinstating some discount, EOCL removal and escalation improvement. Jun-2025 Level 3 approval secured in .Jul 2025 - Proposal presented to THAI with minor trades, Sep 2025 formal proposal requested in, Feb 2026 proposal issued and expect to contract pending THA acceptance Apr 2026 - Senior engagement at AIX, awaiting feedback before next steps, possible adjustment pending ICT confirmation. | W171: -1 | Y171: Thai Airways International Ltd Min term extension involving reinstating some discount, EOCL removal and escalation improvement. Jun-2025 Level 3 approval secured in .Jul 2025 - Proposal presented to THAI with minor trades, Sep 2025 formal proposal requested in, Feb 2026 proposal issued and expect to contract pending THA acceptance Apr 2026 - Senior engagement at AIX, awaiting feedback before next steps, possible adjustment pending ICT confirmation. | Z171: -1 | AB171: Thai Airways International Ltd Min term extension involving reinstating some discount, EOCL removal and escalation improvement. Jun-2025 Level 3 approval secured in .Jul 2025 - Proposal presented to THAI with minor trades, Sep 2025 formal proposal requested in, Feb 2026 proposal issued and expect to contract pending THA acceptance Apr 2026 - Senior engagement at AIX, awaiting feedback before next steps, possible adjustment pending ICT confirmation. | AC171: -1
C172: Emirates Finiq 2 - 3 year-extension + LRU Management + 23 a/c. Term benefit includes a % of DI7 | E172: 0 | G172: =E172+F172 -> #VALUE! | H172: {=INDEX('GLOBAL LOG'!#REF!,ROW()-169+15)} -> #REF! | I172: =_xlfn.XLOOKUP(H172,#REF!,#REF!,"",0,1) -> #REF! | J172: =IFERROR(I172*#REF!,"") | K172: {=INDEX('GLOBAL LOG'!#REF!,ROW()-169+15)} -> #REF! | L172: =_xlfn.XLOOKUP(K172,#REF!,#REF!,"",0,1) -> #REF! | M172: =IFERROR(L172*#REF!,"") | N172: =IFERROR(D172*J172*M172,-1) -> -1 | O172: =IFERROR(E172*J172*M172,-1) -> -1 | P172: =IFERROR(F172*J172*M172,-1) -> -1 | Q172: =IFERROR(G172*J172*M172,-1) -> -1 | S172: Emirates Finiq 2 - 3 year-extension + LRU Management + 23 a/c. Term benefit includes a % of DI7 | T172: -1 | V172: Emirates Finiq 2 - 3 year-extension + LRU Management + 23 a/c. Term benefit includes a % of DI7 | W172: -1 | Y172: Emirates Finiq 2 - 3 year-extension + LRU Management + 23 a/c. Term benefit includes a % of DI7 | Z172: -1 | AB172: Emirates Finiq 2 - 3 year-extension + LRU Management + 23 a/c. Term benefit includes a % of DI7 | AC172: -1
C173: Singapore Airlines Project Aegis contractual negotiations continue - final key points (Charging Period, R-R Mitigation, Build Life Guarantee) being worked ahead of final closing meeting between JK and HP Lau Note expected approval to close in March 2026 is £5m and so these figures have not been amended | E173: 24 | F173: Confirm with Harry | G173: =E173+F173 -> #VALUE! | H173: {=INDEX('GLOBAL LOG'!#REF!,ROW()-169+15)} -> #REF! | I173: =_xlfn.XLOOKUP(H173,#REF!,#REF!,"",0,1) -> #REF! | J173: =IFERROR(I173*#REF!,"") | K173: {=INDEX('GLOBAL LOG'!#REF!,ROW()-169+15)} -> #REF! | L173: =_xlfn.XLOOKUP(K173,#REF!,#REF!,"",0,1) -> #REF! | M173: =IFERROR(L173*#REF!,"") | N173: =IFERROR(D173*J173*M173,-1) -> -1 | O173: =IFERROR(E173*J173*M173,-1) -> -1 | P173: =IFERROR(F173*J173*M173,-1) -> -1 | Q173: =IFERROR(G173*J173*M173,-1) -> -1 | S173: Singapore Airlines Project Aegis contractual negotiations continue - final key points (Charging Period, R-R Mitigation, Build Life Guarantee) being worked ahead of final closing meeting between JK and HP Lau Note expected approval to close in March 2026 is £5m and so these figures have not been amended | T173: -1 | V173: Singapore Airlines Project Aegis contractual negotiations continue - final key points (Charging Period, R-R Mitigation, Build Life Guarantee) being worked ahead of final closing meeting between JK and HP Lau Note expected approval to close in March 2026 is £5m and so these figures have not been amended | W173: -1 | Y173: Singapore Airlines Project Aegis contractual negotiations continue - final key points (Charging Period, R-R Mitigation, Build Life Guarantee) being worked ahead of final closing meeting between JK and HP Lau Note expected approval to close in March 2026 is £5m and so these figures have not been amended | Z173: -1 | AB173: Singapore Airlines Project Aegis contractual negotiations continue - final key points (Charging Period, R-R Mitigation, Build Life Guarantee) being worked ahead of final closing meeting between JK and HP Lau Note expected approval to close in March 2026 is £5m and so these figures have not been amended | AC173: -1
C174: Vietnam Airlines Life min term extension from 2027 to 2031 to align with lease term extension and 2x XWB SPE sales in Q4 2026. Linked with Claim and reconcliation account issues. Initial engagement with customer structurally ok. Construstive Level 2 workshop took place on 8 July and follow up Level 2 strategy to be planned for end of July - considering if we can find a solution that could be used Trent XWB engines, rather than new in 2026. Already commited in XWB 5YP | E174: 10 | F174: 6 | G174: =E174+F174 -> 16 | H174: {=INDEX('GLOBAL LOG'!#REF!,ROW()-169+15)} -> #REF! | I174: =_xlfn.XLOOKUP(H174,#REF!,#REF!,"",0,1) -> #REF! | J174: =IFERROR(I174*#REF!,"") | K174: {=INDEX('GLOBAL LOG'!#REF!,ROW()-169+15)} -> #REF! | L174: =_xlfn.XLOOKUP(K174,#REF!,#REF!,"",0,1) -> #REF! | M174: =IFERROR(L174*#REF!,"") | N174: =IFERROR(D174*J174*M174,-1) -> -1 | O174: =IFERROR(E174*J174*M174,-1) -> -1 | P174: =IFERROR(F174*J174*M174,-1) -> -1 | Q174: =IFERROR(G174*J174*M174,-1) -> -1 | S174: Vietnam Airlines Life min term extension from 2027 to 2031 to align with lease term extension and 2x XWB SPE sales in Q4 2026. Linked with Claim and reconcliation account issues. Initial engagement with customer structurally ok. Construstive Level 2 workshop took place on 8 July and follow up Level 2 strategy to be planned for end of July - considering if we can find a solution that could be used Trent XWB engines, rather than new in 2026. Already commited in XWB 5YP | T174: -1 | V174: Vietnam Airlines Life min term extension from 2027 to 2031 to align with lease term extension and 2x XWB SPE sales in Q4 2026. Linked with Claim and reconcliation account issues. Initial engagement with customer structurally ok. Construstive Level 2 workshop took place on 8 July and follow up Level 2 strategy to be planned for end of July - considering if we can find a solution that could be used Trent XWB engines, rather than new in 2026. Already commited in XWB 5YP | W174: -1 | Y174: Vietnam Airlines Life min term extension from 2027 to 2031 to align with lease term extension and 2x XWB SPE sales in Q4 2026. Linked with Claim and reconcliation account issues. Initial engagement with customer structurally ok. Construstive Level 2 workshop took place on 8 July and follow up Level 2 strategy to be planned for end of July - considering if we can find a solution that could be used Trent XWB engines, rather than new in 2026. Already commited in XWB 5YP | Z174: -1 | AB174: Vietnam Airlines Life min term extension from 2027 to 2031 to align with lease term extension and 2x XWB SPE sales in Q4 2026. Linked with Claim and reconcliation account issues. Initial engagement with customer structurally ok. Construstive Level 2 workshop took place on 8 July and follow up Level 2 strategy to be planned for end of July - considering if we can find a solution that could be used Trent XWB engines, rather than new in 2026. Already commited in XWB 5YP | AC174: -1
C175: Singapore Airlines Strategy being developed 1) lessons learnt from Trent XWB Project Aegis in terms of complexity, time to conclude and not doing the Final Restoration Shop Visit Guarantee. 2) Proposed strategy to split into Phase 1 (Period of Cover(and Phase 2 (post term extension) abd Phase 2 post POC extension including escalated and value trades. 3) Phase 1 customer engagement planned ahead of the CEO meeting (8 April 2026) | E175: 80 | F175: Confirm with Bobby | G175: =E175+F175 -> #VALUE! | H175: {=INDEX('GLOBAL LOG'!#REF!,ROW()-169+15)} -> #REF! | I175: =_xlfn.XLOOKUP(H175,#REF!,#REF!,"",0,1) -> #REF! | J175: =IFERROR(I175*#REF!,"") | K175: {=INDEX('GLOBAL LOG'!#REF!,ROW()-169+15)} -> #REF! | L175: =_xlfn.XLOOKUP(K175,#REF!,#REF!,"",0,1) -> #REF! | M175: =IFERROR(L175*#REF!,"") | N175: =IFERROR(D175*J175*M175,-1) -> -1 | O175: =IFERROR(E175*J175*M175,-1) -> -1 | P175: =IFERROR(F175*J175*M175,-1) -> -1 | Q175: =IFERROR(G175*J175*M175,-1) -> -1 | S175: Singapore Airlines Strategy being developed 1) lessons learnt from Trent XWB Project Aegis in terms of complexity, time to conclude and not doing the Final Restoration Shop Visit Guarantee. 2) Proposed strategy to split into Phase 1 (Period of Cover(and Phase 2 (post term extension) abd Phase 2 post POC extension including escalated and value trades. 3) Phase 1 customer engagement planned ahead of the CEO meeting (8 April 2026) | T175: -1 | V175: Singapore Airlines Strategy being developed 1) lessons learnt from Trent XWB Project Aegis in terms of complexity, time to conclude and not doing the Final Restoration Shop Visit Guarantee. 2) Proposed strategy to split into Phase 1 (Period of Cover(and Phase 2 (post term extension) abd Phase 2 post POC extension including escalated and value trades. 3) Phase 1 customer engagement planned ahead of the CEO meeting (8 April 2026) | W175: -1 | Y175: Singapore Airlines Strategy being developed 1) lessons learnt from Trent XWB Project Aegis in terms of complexity, time to conclude and not doing the Final Restoration Shop Visit Guarantee. 2) Proposed strategy to split into Phase 1 (Period of Cover(and Phase 2 (post term extension) abd Phase 2 post POC extension including escalated and value trades. 3) Phase 1 customer engagement planned ahead of the CEO meeting (8 April 2026) | Z175: -1 | AB175: Singapore Airlines Strategy being developed 1) lessons learnt from Trent XWB Project Aegis in terms of complexity, time to conclude and not doing the Final Restoration Shop Visit Guarantee. 2) Proposed strategy to split into Phase 1 (Period of Cover(and Phase 2 (post term extension) abd Phase 2 post POC extension including escalated and value trades. 3) Phase 1 customer engagement planned ahead of the CEO meeting (8 April 2026) | AC175: -1
C176: Emirates Pantheon - Trent 900 Full MRO for improved CRP | E176: 0 | G176: =E176+F176 -> #VALUE! | H176: {=INDEX('GLOBAL LOG'!#REF!,ROW()-169+15)} -> #REF! | I176: =_xlfn.XLOOKUP(H176,#REF!,#REF!,"",0,1) -> #REF! | J176: =IFERROR(I176*#REF!,"") | K176: {=INDEX('GLOBAL LOG'!#REF!,ROW()-169+15)} -> #REF! | L176: =_xlfn.XLOOKUP(K176,#REF!,#REF!,"",0,1) -> #REF! | M176: =IFERROR(L176*#REF!,"") | N176: =IFERROR(D176*J176*M176,-1) -> -1 | O176: =IFERROR(E176*J176*M176,-1) -> -1 | P176: =IFERROR(F176*J176*M176,-1) -> -1 | Q176: =IFERROR(G176*J176*M176,-1) -> -1 | S176: Emirates Pantheon - Trent 900 Full MRO for improved CRP | T176: -1 | V176: Emirates Pantheon - Trent 900 Full MRO for improved CRP | W176: -1 | Y176: Emirates Pantheon - Trent 900 Full MRO for improved CRP | Z176: -1 | AB176: Emirates Pantheon - Trent 900 Full MRO for improved CRP | AC176: -1
C177: British Airways Life Min Term extension to 24 years for owned a/c and 12 years for leased a/c, plus removal of EoCL for a $/efh discount on both Engine & LLPs. | E177: 0 | F177: 0 | G177: =E177+F177 -> 0 | H177: {=INDEX('GLOBAL LOG'!#REF!,ROW()-169+15)} -> #REF! | I177: =_xlfn.XLOOKUP(H177,#REF!,#REF!,"",0,1) -> #REF! | J177: =IFERROR(I177*#REF!,"") | K177: {=INDEX('GLOBAL LOG'!#REF!,ROW()-169+15)} -> #REF! | L177: =_xlfn.XLOOKUP(K177,#REF!,#REF!,"",0,1) -> #REF! | M177: =IFERROR(L177*#REF!,"") | N177: =IFERROR(D177*J177*M177,-1) -> -1 | O177: =IFERROR(E177*J177*M177,-1) -> -1 | P177: =IFERROR(F177*J177*M177,-1) -> -1 | Q177: =IFERROR(G177*J177*M177,-1) -> -1 | S177: British Airways Life Min Term extension to 24 years for owned a/c and 12 years for leased a/c, plus removal of EoCL for a $/efh discount on both Engine & LLPs. | T177: -1 | V177: British Airways Life Min Term extension to 24 years for owned a/c and 12 years for leased a/c, plus removal of EoCL for a $/efh discount on both Engine & LLPs. | W177: -1 | Y177: British Airways Life Min Term extension to 24 years for owned a/c and 12 years for leased a/c, plus removal of EoCL for a $/efh discount on both Engine & LLPs. | Z177: -1 | AB177: British Airways Life Min Term extension to 24 years for owned a/c and 12 years for leased a/c, plus removal of EoCL for a $/efh discount on both Engine & LLPs. | AC177: -1
C178: Srilankan Airlines Min term extension of existing contract (Life) of 6 years. This will need to be revised as per FBM direction post Avalon requirements to extend to the next SV as the min term which will in turn amend the financials that was already prepared. Previous IY profit impact was £(7)m negative due to being lower % margin than existing 75% but > 57% fleet average. However, this has not been to L2 approval yet. Work on next SV duration will require urgent resource | E178: 20 | F178: 2 | G178: =E178+F178 -> 22 | H178: {=INDEX('GLOBAL LOG'!#REF!,ROW()-169+15)} -> #REF! | I178: =_xlfn.XLOOKUP(H178,#REF!,#REF!,"",0,1) -> #REF! | J178: =IFERROR(I178*#REF!,"") | K178: {=INDEX('GLOBAL LOG'!#REF!,ROW()-169+15)} -> #REF! | L178: =_xlfn.XLOOKUP(K178,#REF!,#REF!,"",0,1) -> #REF! | M178: =IFERROR(L178*#REF!,"") | N178: =IFERROR(D178*J178*M178,-1) -> -1 | O178: =IFERROR(E178*J178*M178,-1) -> -1 | P178: =IFERROR(F178*J178*M178,-1) -> -1 | Q178: =IFERROR(G178*J178*M178,-1) -> -1 | S178: Srilankan Airlines Min term extension of existing contract (Life) of 6 years. This will need to be revised as per FBM direction post Avalon requirements to extend to the next SV as the min term which will in turn amend the financials that was already prepared. Previous IY profit impact was £(7)m negative due to being lower % margin than existing 75% but > 57% fleet average. However, this has not been to L2 approval yet. Work on next SV duration will require urgent resource | T178: -1 | V178: Srilankan Airlines Min term extension of existing contract (Life) of 6 years. This will need to be revised as per FBM direction post Avalon requirements to extend to the next SV as the min term which will in turn amend the financials that was already prepared. Previous IY profit impact was £(7)m negative due to being lower % margin than existing 75% but > 57% fleet average. However, this has not been to L2 approval yet. Work on next SV duration will require urgent resource | W178: -1 | Y178: Srilankan Airlines Min term extension of existing contract (Life) of 6 years. This will need to be revised as per FBM direction post Avalon requirements to extend to the next SV as the min term which will in turn amend the financials that was already prepared. Previous IY profit impact was £(7)m negative due to being lower % margin than existing 75% but > 57% fleet average. However, this has not been to L2 approval yet. Work on next SV duration will require urgent resource | Z178: -1 | AB178: Srilankan Airlines Min term extension of existing contract (Life) of 6 years. This will need to be revised as per FBM direction post Avalon requirements to extend to the next SV as the min term which will in turn amend the financials that was already prepared. Previous IY profit impact was £(7)m negative due to being lower % margin than existing 75% but > 57% fleet average. However, this has not been to L2 approval yet. Work on next SV duration will require urgent resource | AC178: -1
C179: World2Fly Min term extension (life) - 1 a/c exit from 2026. 5yr term but 12yr lease term. Contract extension in 2025 Plus sell used SPE to reduce NDSES costs in CRP (Minimal but supports the OE sale) | E179: 0 | F179: 0 | G179: =E179+F179 -> 0 | H179: {=INDEX('GLOBAL LOG'!#REF!,ROW()-169+15)} -> #REF! | I179: =_xlfn.XLOOKUP(H179,#REF!,#REF!,"",0,1) -> #REF! | J179: =IFERROR(I179*#REF!,"") | K179: {=INDEX('GLOBAL LOG'!#REF!,ROW()-169+15)} -> #REF! | L179: =_xlfn.XLOOKUP(K179,#REF!,#REF!,"",0,1) -> #REF! | M179: =IFERROR(L179*#REF!,"") | N179: =IFERROR(D179*J179*M179,-1) -> -1 | O179: =IFERROR(E179*J179*M179,-1) -> -1 | P179: =IFERROR(F179*J179*M179,-1) -> -1 | Q179: =IFERROR(G179*J179*M179,-1) -> -1 | S179: World2Fly Min term extension (life) - 1 a/c exit from 2026. 5yr term but 12yr lease term. Contract extension in 2025 Plus sell used SPE to reduce NDSES costs in CRP (Minimal but supports the OE sale) | T179: -1 | V179: World2Fly Min term extension (life) - 1 a/c exit from 2026. 5yr term but 12yr lease term. Contract extension in 2025 Plus sell used SPE to reduce NDSES costs in CRP (Minimal but supports the OE sale) | W179: -1 | Y179: World2Fly Min term extension (life) - 1 a/c exit from 2026. 5yr term but 12yr lease term. Contract extension in 2025 Plus sell used SPE to reduce NDSES costs in CRP (Minimal but supports the OE sale) | Z179: -1 | AB179: World2Fly Min term extension (life) - 1 a/c exit from 2026. 5yr term but 12yr lease term. Contract extension in 2025 Plus sell used SPE to reduce NDSES costs in CRP (Minimal but supports the OE sale) | AC179: -1
C180: British Airways Life Min Term extension to 25 years for owned a/c and 12 years for leased a/c, plus removal of EoCL for a $/efh discount on both Engine & LLPs. | E180: 35 | F180: 0 | G180: =E180+F180 -> 35 | H180: {=INDEX('GLOBAL LOG'!#REF!,ROW()-169+15)} -> #REF! | I180: =_xlfn.XLOOKUP(H180,#REF!,#REF!,"",0,1) -> #REF! | J180: =IFERROR(I180*#REF!,"") | K180: {=INDEX('GLOBAL LOG'!#REF!,ROW()-169+15)} -> #REF! | L180: =_xlfn.XLOOKUP(K180,#REF!,#REF!,"",0,1) -> #REF! | M180: =IFERROR(L180*#REF!,"") | N180: =IFERROR(D180*J180*M180,-1) -> -1 | O180: =IFERROR(E180*J180*M180,-1) -> -1 | P180: =IFERROR(F180*J180*M180,-1) -> -1 | Q180: =IFERROR(G180*J180*M180,-1) -> -1 | S180: British Airways Life Min Term extension to 25 years for owned a/c and 12 years for leased a/c, plus removal of EoCL for a $/efh discount on both Engine & LLPs. | T180: -1 | V180: British Airways Life Min Term extension to 25 years for owned a/c and 12 years for leased a/c, plus removal of EoCL for a $/efh discount on both Engine & LLPs. | W180: -1 | Y180: British Airways Life Min Term extension to 25 years for owned a/c and 12 years for leased a/c, plus removal of EoCL for a $/efh discount on both Engine & LLPs. | Z180: -1 | AB180: British Airways Life Min Term extension to 25 years for owned a/c and 12 years for leased a/c, plus removal of EoCL for a $/efh discount on both Engine & LLPs. | AC180: -1
C181: Hawaiian Airlines EFH discount in return for addition 20x SV commitment. Negotiations ongoing. | E181: 7.6 | F181: 7.6 | G181: =E181+F181 -> 15.2 | H181: {=INDEX('GLOBAL LOG'!#REF!,ROW()-169+15)} -> #REF! | I181: =_xlfn.XLOOKUP(H181,#REF!,#REF!,"",0,1) -> #REF! | J181: =IFERROR(I181*#REF!,"") | K181: {=INDEX('GLOBAL LOG'!#REF!,ROW()-169+15)} -> #REF! | L181: =_xlfn.XLOOKUP(K181,#REF!,#REF!,"",0,1) -> #REF! | M181: =IFERROR(L181*#REF!,"") | N181: =IFERROR(D181*J181*M181,-1) -> -1 | O181: =IFERROR(E181*J181*M181,-1) -> -1 | P181: =IFERROR(F181*J181*M181,-1) -> -1 | Q181: =IFERROR(G181*J181*M181,-1) -> -1 | S181: Hawaiian Airlines EFH discount in return for addition 20x SV commitment. Negotiations ongoing. | T181: -1 | V181: Hawaiian Airlines EFH discount in return for addition 20x SV commitment. Negotiations ongoing. | W181: -1 | Y181: Hawaiian Airlines EFH discount in return for addition 20x SV commitment. Negotiations ongoing. | Z181: -1 | AB181: Hawaiian Airlines EFH discount in return for addition 20x SV commitment. Negotiations ongoing. | AC181: -1
C182: Qatar Exit for convenience removal -84 | E182: 15 | F182: 39 | G182: =E182+F182 -> 54 | H182: {=INDEX('GLOBAL LOG'!#REF!,ROW()-169+15)} -> #REF! | I182: =_xlfn.XLOOKUP(H182,#REF!,#REF!,"",0,1) -> #REF! | J182: =IFERROR(I182*#REF!,"") | K182: {=INDEX('GLOBAL LOG'!#REF!,ROW()-169+15)} -> #REF! | L182: =_xlfn.XLOOKUP(K182,#REF!,#REF!,"",0,1) -> #REF! | M182: =IFERROR(L182*#REF!,"") | N182: =IFERROR(D182*J182*M182,-1) -> -1 | O182: =IFERROR(E182*J182*M182,-1) -> -1 | P182: =IFERROR(F182*J182*M182,-1) -> -1 | Q182: =IFERROR(G182*J182*M182,-1) -> -1 | S182: Qatar Exit for convenience removal -84 | T182: -1 | V182: Qatar Exit for convenience removal -84 | W182: -1 | Y182: Qatar Exit for convenience removal -84 | Z182: -1 | AB182: Qatar Exit for convenience removal -84 | AC182: -1
C183: Etihad TCA Reconciliation (CRP Improvement) | E183: 2.32 | F183: 0 | G183: =E183+F183 -> 2.32 | H183: {=INDEX('GLOBAL LOG'!#REF!,ROW()-169+15)} -> #REF! | I183: =_xlfn.XLOOKUP(H183,#REF!,#REF!,"",0,1) -> #REF! | J183: =IFERROR(I183*#REF!,"") | K183: {=INDEX('GLOBAL LOG'!#REF!,ROW()-169+15)} -> #REF! | L183: =_xlfn.XLOOKUP(K183,#REF!,#REF!,"",0,1) -> #REF! | M183: =IFERROR(L183*#REF!,"") | N183: =IFERROR(D183*J183*M183,-1) -> -1 | O183: =IFERROR(E183*J183*M183,-1) -> -1 | P183: =IFERROR(F183*J183*M183,-1) -> -1 | Q183: =IFERROR(G183*J183*M183,-1) -> -1 | S183: Etihad TCA Reconciliation (CRP Improvement) | T183: -1 | V183: Etihad TCA Reconciliation (CRP Improvement) | W183: -1 | Y183: Etihad TCA Reconciliation (CRP Improvement) | Z183: -1 | AB183: Etihad TCA Reconciliation (CRP Improvement) | AC183: -1
C184: Emirates Trent XWB Full MRO for improved CRP | E184: 0 | G184: =E184+F184 -> #VALUE! | H184: {=INDEX('GLOBAL LOG'!#REF!,ROW()-169+15)} -> #REF! | I184: =_xlfn.XLOOKUP(H184,#REF!,#REF!,"",0,1) -> #REF! | J184: =IFERROR(I184*#REF!,"") | K184: {=INDEX('GLOBAL LOG'!#REF!,ROW()-169+15)} -> #REF! | L184: =_xlfn.XLOOKUP(K184,#REF!,#REF!,"",0,1) -> #REF! | M184: =IFERROR(L184*#REF!,"") | N184: =IFERROR(D184*J184*M184,-1) -> -1 | O184: =IFERROR(E184*J184*M184,-1) -> -1 | P184: =IFERROR(F184*J184*M184,-1) -> -1 | Q184: =IFERROR(G184*J184*M184,-1) -> -1 | S184: Emirates Trent XWB Full MRO for improved CRP | T184: -1 | V184: Emirates Trent XWB Full MRO for improved CRP | W184: -1 | Y184: Emirates Trent XWB Full MRO for improved CRP | Z184: -1 | AB184: Emirates Trent XWB Full MRO for improved CRP | AC184: -1
C185: Qatar Exit for convenience removal -97 | E185: 0 | F185: 0 | G185: =E185+F185 -> 0 | H185: {=INDEX('GLOBAL LOG'!#REF!,ROW()-169+15)} -> #REF! | I185: =_xlfn.XLOOKUP(H185,#REF!,#REF!,"",0,1) -> #REF! | J185: =IFERROR(I185*#REF!,"") | K185: {=INDEX('GLOBAL LOG'!#REF!,ROW()-169+15)} -> #REF! | L185: =_xlfn.XLOOKUP(K185,#REF!,#REF!,"",0,1) -> #REF! | M185: =IFERROR(L185*#REF!,"") | N185: =IFERROR(D185*J185*M185,-1) -> -1 | O185: =IFERROR(E185*J185*M185,-1) -> -1 | P185: =IFERROR(F185*J185*M185,-1) -> -1 | Q185: =IFERROR(G185*J185*M185,-1) -> -1 | S185: Qatar Exit for convenience removal -97 | T185: -1 | V185: Qatar Exit for convenience removal -97 | W185: -1 | Y185: Qatar Exit for convenience removal -97 | Z185: -1 | AB185: Qatar Exit for convenience removal -97 | AC185: -1
C186: Ethiopian Airlines Restructure exisiting contract -Credit Back Removal As part of A350-900 campaign | E186: 0 | F186: 0 | G186: =E186+F186 -> 0 | H186: {=INDEX('GLOBAL LOG'!#REF!,ROW()-169+15)} -> #REF! | I186: =_xlfn.XLOOKUP(H186,#REF!,#REF!,"",0,1) -> #REF! | J186: =IFERROR(I186*#REF!,"") | K186: {=INDEX('GLOBAL LOG'!#REF!,ROW()-169+15)} -> #REF! | L186: =_xlfn.XLOOKUP(K186,#REF!,#REF!,"",0,1) -> #REF! | M186: =IFERROR(L186*#REF!,"") | N186: =IFERROR(D186*J186*M186,-1) -> -1 | O186: =IFERROR(E186*J186*M186,-1) -> -1 | P186: =IFERROR(F186*J186*M186,-1) -> -1 | Q186: =IFERROR(G186*J186*M186,-1) -> -1 | S186: Ethiopian Airlines Restructure exisiting contract -Credit Back Removal As part of A350-900 campaign | T186: -1 | V186: Ethiopian Airlines Restructure exisiting contract -Credit Back Removal As part of A350-900 campaign | W186: -1 | Y186: Ethiopian Airlines Restructure exisiting contract -Credit Back Removal As part of A350-900 campaign | Z186: -1 | AB186: Ethiopian Airlines Restructure exisiting contract -Credit Back Removal As part of A350-900 campaign | AC186: -1
C187: Iberia Min term extension (life) - 2x leased a/c meet minimum term in 2026. Contract extension to 2030 inline with revised lease terms. Contracted in 2025, linked to matrix extension resolution. | E187: 0 | F187: 0 | G187: =E187+F187 -> 0 | H187: {=INDEX('GLOBAL LOG'!#REF!,ROW()-169+15)} -> #REF! | I187: =_xlfn.XLOOKUP(H187,#REF!,#REF!,"",0,1) -> #REF! | J187: =IFERROR(I187*#REF!,"") | K187: {=INDEX('GLOBAL LOG'!#REF!,ROW()-169+15)} -> #REF! | L187: =_xlfn.XLOOKUP(K187,#REF!,#REF!,"",0,1) -> #REF! | M187: =IFERROR(L187*#REF!,"") | N187: =IFERROR(D187*J187*M187,-1) -> -1 | O187: =IFERROR(E187*J187*M187,-1) -> -1 | P187: =IFERROR(F187*J187*M187,-1) -> -1 | Q187: =IFERROR(G187*J187*M187,-1) -> -1 | S187: Iberia Min term extension (life) - 2x leased a/c meet minimum term in 2026. Contract extension to 2030 inline with revised lease terms. Contracted in 2025, linked to matrix extension resolution. | T187: -1 | V187: Iberia Min term extension (life) - 2x leased a/c meet minimum term in 2026. Contract extension to 2030 inline with revised lease terms. Contracted in 2025, linked to matrix extension resolution. | W187: -1 | Y187: Iberia Min term extension (life) - 2x leased a/c meet minimum term in 2026. Contract extension to 2030 inline with revised lease terms. Contracted in 2025, linked to matrix extension resolution. | Z187: -1 | AB187: Iberia Min term extension (life) - 2x leased a/c meet minimum term in 2026. Contract extension to 2030 inline with revised lease terms. Contracted in 2025, linked to matrix extension resolution. | AC187: -1
C188: Air Canada Flex contract extension. Current contract expiring end of 2027. | E188: 0.001 | F188: 0.001 | G188: =E188+F188 -> 0.002 | H188: {=INDEX('GLOBAL LOG'!#REF!,ROW()-169+15)} -> #REF! | I188: =_xlfn.XLOOKUP(H188,#REF!,#REF!,"",0,1) -> #REF! | J188: =IFERROR(I188*#REF!,"") | K188: {=INDEX('GLOBAL LOG'!#REF!,ROW()-169+15)} -> #REF! | L188: =_xlfn.XLOOKUP(K188,#REF!,#REF!,"",0,1) -> #REF! | M188: =IFERROR(L188*#REF!,"") | N188: =IFERROR(D188*J188*M188,-1) -> -1 | O188: =IFERROR(E188*J188*M188,-1) -> -1 | P188: =IFERROR(F188*J188*M188,-1) -> -1 | Q188: =IFERROR(G188*J188*M188,-1) -> -1 | S188: Air Canada Flex contract extension. Current contract expiring end of 2027. | T188: -1 | V188: Air Canada Flex contract extension. Current contract expiring end of 2027. | W188: -1 | Y188: Air Canada Flex contract extension. Current contract expiring end of 2027. | Z188: -1 | AB188: Air Canada Flex contract extension. Current contract expiring end of 2027. | AC188: -1
C189: Lufthansa Pull forward of spare engines, working capital improvements (payment terms), reverse lease of engines, EP upsell | E189: 0 | F189: 0 | G189: =E189+F189 -> 0 | H189: {=INDEX('GLOBAL LOG'!#REF!,ROW()-169+15)} -> #REF! | I189: =_xlfn.XLOOKUP(H189,#REF!,#REF!,"",0,1) -> #REF! | J189: =IFERROR(I189*#REF!,"") | K189: {=INDEX('GLOBAL LOG'!#REF!,ROW()-169+15)} -> #REF! | L189: =_xlfn.XLOOKUP(K189,#REF!,#REF!,"",0,1) -> #REF! | M189: =IFERROR(L189*#REF!,"") | N189: =IFERROR(D189*J189*M189,-1) -> -1 | O189: =IFERROR(E189*J189*M189,-1) -> -1 | P189: =IFERROR(F189*J189*M189,-1) -> -1 | Q189: =IFERROR(G189*J189*M189,-1) -> -1 | S189: Lufthansa Pull forward of spare engines, working capital improvements (payment terms), reverse lease of engines, EP upsell | T189: -1 | V189: Lufthansa Pull forward of spare engines, working capital improvements (payment terms), reverse lease of engines, EP upsell | W189: -1 | Y189: Lufthansa Pull forward of spare engines, working capital improvements (payment terms), reverse lease of engines, EP upsell | Z189: -1 | AB189: Lufthansa Pull forward of spare engines, working capital improvements (payment terms), reverse lease of engines, EP upsell | AC189: -1
C190: Royal Brunei Airlines 4th Mar 26 (KL): Awaiting campaign final decision. Either way a requirement to account to aircraft swap dates on existing min term is needed to lock in more TCA vs CRP which only goes out for 12-18mths. RBA has asked for the contract for the new aircraft which will require this to be signed in parallel, so the urgency has gone up. This specific Commercial Optimisation Initiative type should be considered a Term Extension as opposed to New Aircraft. | E190: 4 | F190: Confirm with Bobby | G190: =E190+F190 -> #VALUE! | H190: {=INDEX('GLOBAL LOG'!#REF!,ROW()-169+15)} -> #REF! | I190: =_xlfn.XLOOKUP(H190,#REF!,#REF!,"",0,1) -> #REF! | J190: =IFERROR(I190*#REF!,"") | K190: {=INDEX('GLOBAL LOG'!#REF!,ROW()-169+15)} -> #REF! | L190: =_xlfn.XLOOKUP(K190,#REF!,#REF!,"",0,1) -> #REF! | M190: =IFERROR(L190*#REF!,"") | N190: =IFERROR(D190*J190*M190,-1) -> -1 | O190: =IFERROR(E190*J190*M190,-1) -> -1 | P190: =IFERROR(F190*J190*M190,-1) -> -1 | Q190: =IFERROR(G190*J190*M190,-1) -> -1 | S190: Royal Brunei Airlines 4th Mar 26 (KL): Awaiting campaign final decision. Either way a requirement to account to aircraft swap dates on existing min term is needed to lock in more TCA vs CRP which only goes out for 12-18mths. RBA has asked for the contract for the new aircraft which will require this to be signed in parallel, so the urgency has gone up. This specific Commercial Optimisation Initiative type should be considered a Term Extension as opposed to New Aircraft. | T190: -1 | V190: Royal Brunei Airlines 4th Mar 26 (KL): Awaiting campaign final decision. Either way a requirement to account to aircraft swap dates on existing min term is needed to lock in more TCA vs CRP which only goes out for 12-18mths. RBA has asked for the contract for the new aircraft which will require this to be signed in parallel, so the urgency has gone up. This specific Commercial Optimisation Initiative type should be considered a Term Extension as opposed to New Aircraft. | W190: -1 | Y190: Royal Brunei Airlines 4th Mar 26 (KL): Awaiting campaign final decision. Either way a requirement to account to aircraft swap dates on existing min term is needed to lock in more TCA vs CRP which only goes out for 12-18mths. RBA has asked for the contract for the new aircraft which will require this to be signed in parallel, so the urgency has gone up. This specific Commercial Optimisation Initiative type should be considered a Term Extension as opposed to New Aircraft. | Z190: -1 | AB190: Royal Brunei Airlines 4th Mar 26 (KL): Awaiting campaign final decision. Either way a requirement to account to aircraft swap dates on existing min term is needed to lock in more TCA vs CRP which only goes out for 12-18mths. RBA has asked for the contract for the new aircraft which will require this to be signed in parallel, so the urgency has gone up. This specific Commercial Optimisation Initiative type should be considered a Term Extension as opposed to New Aircraft. | AC190: -1
C191: Saudia Extend Classic | E191: 0 | F191: 0 | G191: =E191+F191 -> 0 | H191: {=INDEX('GLOBAL LOG'!#REF!,ROW()-169+15)} -> #REF! | I191: =_xlfn.XLOOKUP(H191,#REF!,#REF!,"",0,1) -> #REF! | J191: =IFERROR(I191*#REF!,"") | K191: {=INDEX('GLOBAL LOG'!#REF!,ROW()-169+15)} -> #REF! | L191: =_xlfn.XLOOKUP(K191,#REF!,#REF!,"",0,1) -> #REF! | M191: =IFERROR(L191*#REF!,"") | N191: =IFERROR(D191*J191*M191,-1) -> -1 | O191: =IFERROR(E191*J191*M191,-1) -> -1 | P191: =IFERROR(F191*J191*M191,-1) -> -1 | Q191: =IFERROR(G191*J191*M191,-1) -> -1 | S191: Saudia Extend Classic | T191: -1 | V191: Saudia Extend Classic | W191: -1 | Y191: Saudia Extend Classic | Z191: -1 | AB191: Saudia Extend Classic | AC191: -1
C192: LOT Polish Airlines 1 new SPE in Q1 linked to 2 Dr Peters transition a/c. Life Min Term extension on purchased existing fleet as part of the 9 a/c campaign. | E192: 0 | F192: 0 | G192: =E192+F192 -> 0 | H192: {=INDEX('GLOBAL LOG'!#REF!,ROW()-169+15)} -> #REF! | I192: =_xlfn.XLOOKUP(H192,#REF!,#REF!,"",0,1) -> #REF! | J192: =IFERROR(I192*#REF!,"") | K192: {=INDEX('GLOBAL LOG'!#REF!,ROW()-169+15)} -> #REF! | L192: =_xlfn.XLOOKUP(K192,#REF!,#REF!,"",0,1) -> #REF! | M192: =IFERROR(L192*#REF!,"") | N192: =IFERROR(D192*J192*M192,-1) -> -1 | O192: =IFERROR(E192*J192*M192,-1) -> -1 | P192: =IFERROR(F192*J192*M192,-1) -> -1 | Q192: =IFERROR(G192*J192*M192,-1) -> -1 | S192: LOT Polish Airlines 1 new SPE in Q1 linked to 2 Dr Peters transition a/c. Life Min Term extension on purchased existing fleet as part of the 9 a/c campaign. | T192: -1 | V192: LOT Polish Airlines 1 new SPE in Q1 linked to 2 Dr Peters transition a/c. Life Min Term extension on purchased existing fleet as part of the 9 a/c campaign. | W192: -1 | Y192: LOT Polish Airlines 1 new SPE in Q1 linked to 2 Dr Peters transition a/c. Life Min Term extension on purchased existing fleet as part of the 9 a/c campaign. | Z192: -1 | AB192: LOT Polish Airlines 1 new SPE in Q1 linked to 2 Dr Peters transition a/c. Life Min Term extension on purchased existing fleet as part of the 9 a/c campaign. | AC192: -1
C193: Condor Flugdienst Gmbh NDSES improvement through SPE sales associated to new deal + FCRG and NED Remedy Improvement | E193: 0 | F193: 0 | G193: =E193+F193 -> 0 | H193: {=INDEX('GLOBAL LOG'!#REF!,ROW()-169+15)} -> #REF! | I193: =_xlfn.XLOOKUP(H193,#REF!,#REF!,"",0,1) -> #REF! | J193: =IFERROR(I193*#REF!,"") | K193: {=INDEX('GLOBAL LOG'!#REF!,ROW()-169+15)} -> #REF! | L193: =_xlfn.XLOOKUP(K193,#REF!,#REF!,"",0,1) -> #REF! | M193: =IFERROR(L193*#REF!,"") | N193: =IFERROR(D193*J193*M193,-1) -> -1 | O193: =IFERROR(E193*J193*M193,-1) -> -1 | P193: =IFERROR(F193*J193*M193,-1) -> -1 | Q193: =IFERROR(G193*J193*M193,-1) -> -1 | S193: Condor Flugdienst Gmbh NDSES improvement through SPE sales associated to new deal + FCRG and NED Remedy Improvement | T193: -1 | V193: Condor Flugdienst Gmbh NDSES improvement through SPE sales associated to new deal + FCRG and NED Remedy Improvement | W193: -1 | Y193: Condor Flugdienst Gmbh NDSES improvement through SPE sales associated to new deal + FCRG and NED Remedy Improvement | Z193: -1 | AB193: Condor Flugdienst Gmbh NDSES improvement through SPE sales associated to new deal + FCRG and NED Remedy Improvement | AC193: -1
C194: TAP Air Portugal Two aircraft delays to Original Delivery Schedule. Plan to progress 2026 Used SPE, credit pull-forward for CRP improvement and Optional AOG+1 NDSES Service. | E194: 0 | F194: 0 | G194: =E194+F194 -> 0 | H194: {=INDEX('GLOBAL LOG'!#REF!,ROW()-169+15)} -> #REF! | I194: =_xlfn.XLOOKUP(H194,#REF!,#REF!,"",0,1) -> #REF! | J194: =IFERROR(I194*#REF!,"") | K194: {=INDEX('GLOBAL LOG'!#REF!,ROW()-169+15)} -> #REF! | L194: =_xlfn.XLOOKUP(K194,#REF!,#REF!,"",0,1) -> #REF! | M194: =IFERROR(L194*#REF!,"") | N194: =IFERROR(D194*J194*M194,-1) -> -1 | O194: =IFERROR(E194*J194*M194,-1) -> -1 | P194: =IFERROR(F194*J194*M194,-1) -> -1 | Q194: =IFERROR(G194*J194*M194,-1) -> -1 | S194: TAP Air Portugal Two aircraft delays to Original Delivery Schedule. Plan to progress 2026 Used SPE, credit pull-forward for CRP improvement and Optional AOG+1 NDSES Service. | T194: -1 | V194: TAP Air Portugal Two aircraft delays to Original Delivery Schedule. Plan to progress 2026 Used SPE, credit pull-forward for CRP improvement and Optional AOG+1 NDSES Service. | W194: -1 | Y194: TAP Air Portugal Two aircraft delays to Original Delivery Schedule. Plan to progress 2026 Used SPE, credit pull-forward for CRP improvement and Optional AOG+1 NDSES Service. | Z194: -1 | AB194: TAP Air Portugal Two aircraft delays to Original Delivery Schedule. Plan to progress 2026 Used SPE, credit pull-forward for CRP improvement and Optional AOG+1 NDSES Service. | AC194: -1
C195: Gulf Commerical Offer - 3 Year Extension/ SPE Sales (NDSES Improvement) | E195: -7.4 | F195: 2.5 | G195: =E195+F195 -> -4.9 | H195: {=INDEX('GLOBAL LOG'!#REF!,ROW()-169+15)} -> #REF! | I195: =_xlfn.XLOOKUP(H195,#REF!,#REF!,"",0,1) -> #REF! | J195: =IFERROR(I195*#REF!,"") | K195: {=INDEX('GLOBAL LOG'!#REF!,ROW()-169+15)} -> #REF! | L195: =_xlfn.XLOOKUP(K195,#REF!,#REF!,"",0,1) -> #REF! | M195: =IFERROR(L195*#REF!,"") | N195: =IFERROR(D195*J195*M195,-1) -> -1 | O195: =IFERROR(E195*J195*M195,-1) -> -1 | P195: =IFERROR(F195*J195*M195,-1) -> -1 | Q195: =IFERROR(G195*J195*M195,-1) -> -1 | S195: Gulf Commerical Offer - 3 Year Extension/ SPE Sales (NDSES Improvement) | T195: -1 | V195: Gulf Commerical Offer - 3 Year Extension/ SPE Sales (NDSES Improvement) | W195: -1 | Y195: Gulf Commerical Offer - 3 Year Extension/ SPE Sales (NDSES Improvement) | Z195: -1 | AB195: Gulf Commerical Offer - 3 Year Extension/ SPE Sales (NDSES Improvement) | AC195: -1
C196: Rwanda TCA Life Min Term Extension | E196: 0 | F196: 0 | G196: =E196+F196 -> 0 | H196: {=INDEX('GLOBAL LOG'!#REF!,ROW()-169+15)} -> #REF! | I196: =_xlfn.XLOOKUP(H196,#REF!,#REF!,"",0,1) -> #REF! | J196: =IFERROR(I196*#REF!,"") | K196: {=INDEX('GLOBAL LOG'!#REF!,ROW()-169+15)} -> #REF! | L196: =_xlfn.XLOOKUP(K196,#REF!,#REF!,"",0,1) -> #REF! | M196: =IFERROR(L196*#REF!,"") | N196: =IFERROR(D196*J196*M196,-1) -> -1 | O196: =IFERROR(E196*J196*M196,-1) -> -1 | P196: =IFERROR(F196*J196*M196,-1) -> -1 | Q196: =IFERROR(G196*J196*M196,-1) -> -1 | S196: Rwanda TCA Life Min Term Extension | T196: -1 | V196: Rwanda TCA Life Min Term Extension | W196: -1 | Y196: Rwanda TCA Life Min Term Extension | Z196: -1 | AB196: Rwanda TCA Life Min Term Extension | AC196: -1
C197: Ethiopian Airlines Restructure exisiting contract - Min Term Extension As part of A350-900 campaign | E197: 0 | F197: 0 | G197: =E197+F197 -> 0 | H197: {=INDEX('GLOBAL LOG'!#REF!,ROW()-169+15)} -> #REF! | I197: =_xlfn.XLOOKUP(H197,#REF!,#REF!,"",0,1) -> #REF! | J197: =IFERROR(I197*#REF!,"") | K197: {=INDEX('GLOBAL LOG'!#REF!,ROW()-169+15)} -> #REF! | L197: =_xlfn.XLOOKUP(K197,#REF!,#REF!,"",0,1) -> #REF! | M197: =IFERROR(L197*#REF!,"") | N197: =IFERROR(D197*J197*M197,-1) -> -1 | O197: =IFERROR(E197*J197*M197,-1) -> -1 | P197: =IFERROR(F197*J197*M197,-1) -> -1 | Q197: =IFERROR(G197*J197*M197,-1) -> -1 | S197: Ethiopian Airlines Restructure exisiting contract - Min Term Extension As part of A350-900 campaign | T197: -1 | V197: Ethiopian Airlines Restructure exisiting contract - Min Term Extension As part of A350-900 campaign | W197: -1 | Y197: Ethiopian Airlines Restructure exisiting contract - Min Term Extension As part of A350-900 campaign | Z197: -1 | AB197: Ethiopian Airlines Restructure exisiting contract - Min Term Extension As part of A350-900 campaign | AC197: -1
C198: Egypt EP Upsell (2028+ deliveries) | E198: 0 | F198: 0 | G198: =E198+F198 -> 0 | H198: {=INDEX('GLOBAL LOG'!#REF!,ROW()-169+15)} -> #REF! | I198: =_xlfn.XLOOKUP(H198,#REF!,#REF!,"",0,1) -> #REF! | J198: =IFERROR(I198*#REF!,"") | K198: {=INDEX('GLOBAL LOG'!#REF!,ROW()-169+15)} -> #REF! | L198: =_xlfn.XLOOKUP(K198,#REF!,#REF!,"",0,1) -> #REF! | M198: =IFERROR(L198*#REF!,"") | N198: =IFERROR(D198*J198*M198,-1) -> -1 | O198: =IFERROR(E198*J198*M198,-1) -> -1 | P198: =IFERROR(F198*J198*M198,-1) -> -1 | Q198: =IFERROR(G198*J198*M198,-1) -> -1 | S198: Egypt EP Upsell (2028+ deliveries) | T198: -1 | V198: Egypt EP Upsell (2028+ deliveries) | W198: -1 | Y198: Egypt EP Upsell (2028+ deliveries) | Z198: -1 | AB198: Egypt EP Upsell (2028+ deliveries) | AC198: -1
C199: China Southern Updated 27/02/2026: Add ex-Block 1 Spare Engine to Block 2 TCA with Buy-in SV at SelectCare Pricing (less exit credits) delivering dilution benefits. Pricing and use of exit credit appoved at L2 in 2025. SV slot currently identified in Q2 2026 and can be secured if deal can rapidly be done. The method of contracting internally agreed to be added to Block 2 Buy-in fee. Feb 2026: customer going through final internal approvals. 25/07/2025: Add ex-Block 1 Spare Engine to Block 2 TCA with Buy-In SV at SelectCare Pricing (less exit credits) delivering dilution benefits. Pricing and use of exit credit approved at L2 in May-25. First round of discussion with customer in early June. Customer has since been evaluating internally and not yet provided formal feedback. SV slot identified in Q3 2025 and can be secured if deal can rapidly be done. Contracting method confirmed by value stream to be Add to Block 2 with Buy-in Fee. | E199: 5 | F199: 0 | G199: =E199+F199 -> 5 | H199: {=INDEX('GLOBAL LOG'!#REF!,ROW()-169+15)} -> #REF! | I199: =_xlfn.XLOOKUP(H199,#REF!,#REF!,"",0,1) -> #REF! | J199: =IFERROR(I199*#REF!,"") | K199: {=INDEX('GLOBAL LOG'!#REF!,ROW()-169+15)} -> #REF! | L199: =_xlfn.XLOOKUP(K199,#REF!,#REF!,"",0,1) -> #REF! | M199: =IFERROR(L199*#REF!,"") | N199: =IFERROR(D199*J199*M199,-1) -> -1 | O199: =IFERROR(E199*J199*M199,-1) -> -1 | P199: =IFERROR(F199*J199*M199,-1) -> -1 | Q199: =IFERROR(G199*J199*M199,-1) -> -1 | S199: China Southern Updated 27/02/2026: Add ex-Block 1 Spare Engine to Block 2 TCA with Buy-in SV at SelectCare Pricing (less exit credits) delivering dilution benefits. Pricing and use of exit credit appoved at L2 in 2025. SV slot currently identified in Q2 2026 and can be secured if deal can rapidly be done. The method of contracting internally agreed to be added to Block 2 Buy-in fee. Feb 2026: customer going through final internal approvals. 25/07/2025: Add ex-Block 1 Spare Engine to Block 2 TCA with Buy-In SV at SelectCare Pricing (less exit credits) delivering dilution benefits. Pricing and use of exit credit approved at L2 in May-25. First round of discussion with customer in early June. Customer has since been evaluating internally and not yet provided formal feedback. SV slot identified in Q3 2025 and can be secured if deal can rapidly be done. Contracting method confirmed by value stream to be Add to Block 2 with Buy-in Fee. | T199: -1 | V199: China Southern Updated 27/02/2026: Add ex-Block 1 Spare Engine to Block 2 TCA with Buy-in SV at SelectCare Pricing (less exit credits) delivering dilution benefits. Pricing and use of exit credit appoved at L2 in 2025. SV slot currently identified in Q2 2026 and can be secured if deal can rapidly be done. The method of contracting internally agreed to be added to Block 2 Buy-in fee. Feb 2026: customer going through final internal approvals. 25/07/2025: Add ex-Block 1 Spare Engine to Block 2 TCA with Buy-In SV at SelectCare Pricing (less exit credits) delivering dilution benefits. Pricing and use of exit credit approved at L2 in May-25. First round of discussion with customer in early June. Customer has since been evaluating internally and not yet provided formal feedback. SV slot identified in Q3 2025 and can be secured if deal can rapidly be done. Contracting method confirmed by value stream to be Add to Block 2 with Buy-in Fee. | W199: -1 | Y199: China Southern Updated 27/02/2026: Add ex-Block 1 Spare Engine to Block 2 TCA with Buy-in SV at SelectCare Pricing (less exit credits) delivering dilution benefits. Pricing and use of exit credit appoved at L2 in 2025. SV slot currently identified in Q2 2026 and can be secured if deal can rapidly be done. The method of contracting internally agreed to be added to Block 2 Buy-in fee. Feb 2026: customer going through final internal approvals. 25/07/2025: Add ex-Block 1 Spare Engine to Block 2 TCA with Buy-In SV at SelectCare Pricing (less exit credits) delivering dilution benefits. Pricing and use of exit credit approved at L2 in May-25. First round of discussion with customer in early June. Customer has since been evaluating internally and not yet provided formal feedback. SV slot identified in Q3 2025 and can be secured if deal can rapidly be done. Contracting method confirmed by value stream to be Add to Block 2 with Buy-in Fee. | Z199: -1 | AB199: China Southern Updated 27/02/2026: Add ex-Block 1 Spare Engine to Block 2 TCA with Buy-in SV at SelectCare Pricing (less exit credits) delivering dilution benefits. Pricing and use of exit credit appoved at L2 in 2025. SV slot currently identified in Q2 2026 and can be secured if deal can rapidly be done. The method of contracting internally agreed to be added to Block 2 Buy-in fee. Feb 2026: customer going through final internal approvals. 25/07/2025: Add ex-Block 1 Spare Engine to Block 2 TCA with Buy-In SV at SelectCare Pricing (less exit credits) delivering dilution benefits. Pricing and use of exit credit approved at L2 in May-25. First round of discussion with customer in early June. Customer has since been evaluating internally and not yet provided formal feedback. SV slot identified in Q3 2025 and can be secured if deal can rapidly be done. Contracting method confirmed by value stream to be Add to Block 2 with Buy-in Fee. | AC199: -1
C200: Keylime Keylime Air _ AE3007 _ Add 2 in possession aircraft to TotalCare & extend all to 2030 | E200: 0 | F200: 0 | G200: =E200+F200 -> 0 | H200: {=INDEX('GLOBAL LOG'!#REF!,ROW()-169+15)} -> #REF! | I200: =_xlfn.XLOOKUP(H200,#REF!,#REF!,"",0,1) -> #REF! | J200: =IFERROR(I200*#REF!,"") | K200: {=INDEX('GLOBAL LOG'!#REF!,ROW()-169+15)} -> #REF! | L200: =_xlfn.XLOOKUP(K200,#REF!,#REF!,"",0,1) -> #REF! | M200: =IFERROR(L200*#REF!,"") | N200: =IFERROR(D200*J200*M200,-1) -> -1 | O200: =IFERROR(E200*J200*M200,-1) -> -1 | P200: =IFERROR(F200*J200*M200,-1) -> -1 | Q200: =IFERROR(G200*J200*M200,-1) -> -1 | S200: Keylime Keylime Air _ AE3007 _ Add 2 in possession aircraft to TotalCare & extend all to 2030 | T200: -1 | V200: Keylime Keylime Air _ AE3007 _ Add 2 in possession aircraft to TotalCare & extend all to 2030 | W200: -1 | Y200: Keylime Keylime Air _ AE3007 _ Add 2 in possession aircraft to TotalCare & extend all to 2030 | Z200: -1 | AB200: Keylime Keylime Air _ AE3007 _ Add 2 in possession aircraft to TotalCare & extend all to 2030 | AC200: -1
C201: All Nippon Airways Acceleration of backlog assets from Boeing to backstop Trent 1000 fleet health. Financial opportunity relates to direct sale of engines to ANA (Q4 25) and mitigation of NDSES costs/remedies. We have positioned optimising economics to ANA, offsetting a $33m non-contractual claim for Trent 1000 disruption in 2024. L2 approved trading $7.3m of NDSES savings for 2025, to be ‘offset’ against their claim. Proposal communicated to ANA 31/7, contract amendment being drafted for submission by 9/8. (Note: potential for further 2026 NDSES remedy avoidance of ~US30m). | E201: 2.058 | F201: 0 | G201: =E201+F201 -> 2.058 | H201: {=INDEX('GLOBAL LOG'!#REF!,ROW()-169+15)} -> #REF! | I201: =_xlfn.XLOOKUP(H201,#REF!,#REF!,"",0,1) -> #REF! | J201: =IFERROR(I201*#REF!,"") | K201: {=INDEX('GLOBAL LOG'!#REF!,ROW()-169+15)} -> #REF! | L201: =_xlfn.XLOOKUP(K201,#REF!,#REF!,"",0,1) -> #REF! | M201: =IFERROR(L201*#REF!,"") | N201: =IFERROR(D201*J201*M201,-1) -> -1 | O201: =IFERROR(E201*J201*M201,-1) -> -1 | P201: =IFERROR(F201*J201*M201,-1) -> -1 | Q201: =IFERROR(G201*J201*M201,-1) -> -1 | S201: All Nippon Airways Acceleration of backlog assets from Boeing to backstop Trent 1000 fleet health. Financial opportunity relates to direct sale of engines to ANA (Q4 25) and mitigation of NDSES costs/remedies. We have positioned optimising economics to ANA, offsetting a $33m non-contractual claim for Trent 1000 disruption in 2024. L2 approved trading $7.3m of NDSES savings for 2025, to be ‘offset’ against their claim. Proposal communicated to ANA 31/7, contract amendment being drafted for submission by 9/8. (Note: potential for further 2026 NDSES remedy avoidance of ~US30m). | T201: -1 | V201: All Nippon Airways Acceleration of backlog assets from Boeing to backstop Trent 1000 fleet health. Financial opportunity relates to direct sale of engines to ANA (Q4 25) and mitigation of NDSES costs/remedies. We have positioned optimising economics to ANA, offsetting a $33m non-contractual claim for Trent 1000 disruption in 2024. L2 approved trading $7.3m of NDSES savings for 2025, to be ‘offset’ against their claim. Proposal communicated to ANA 31/7, contract amendment being drafted for submission by 9/8. (Note: potential for further 2026 NDSES remedy avoidance of ~US30m). | W201: -1 | Y201: All Nippon Airways Acceleration of backlog assets from Boeing to backstop Trent 1000 fleet health. Financial opportunity relates to direct sale of engines to ANA (Q4 25) and mitigation of NDSES costs/remedies. We have positioned optimising economics to ANA, offsetting a $33m non-contractual claim for Trent 1000 disruption in 2024. L2 approved trading $7.3m of NDSES savings for 2025, to be ‘offset’ against their claim. Proposal communicated to ANA 31/7, contract amendment being drafted for submission by 9/8. (Note: potential for further 2026 NDSES remedy avoidance of ~US30m). | Z201: -1 | AB201: All Nippon Airways Acceleration of backlog assets from Boeing to backstop Trent 1000 fleet health. Financial opportunity relates to direct sale of engines to ANA (Q4 25) and mitigation of NDSES costs/remedies. We have positioned optimising economics to ANA, offsetting a $33m non-contractual claim for Trent 1000 disruption in 2024. L2 approved trading $7.3m of NDSES savings for 2025, to be ‘offset’ against their claim. Proposal communicated to ANA 31/7, contract amendment being drafted for submission by 9/8. (Note: potential for further 2026 NDSES remedy avoidance of ~US30m). | AC201: -1
C202: Sterling Sterling _ AE2100 _ restructure & add spare engines | E202: 0 | F202: 0 | G202: =E202+F202 -> 0 | H202: {=INDEX('GLOBAL LOG'!#REF!,ROW()-169+15)} -> #REF! | I202: =_xlfn.XLOOKUP(H202,#REF!,#REF!,"",0,1) -> #REF! | J202: =IFERROR(I202*#REF!,"") | K202: {=INDEX('GLOBAL LOG'!#REF!,ROW()-169+15)} -> #REF! | L202: =_xlfn.XLOOKUP(K202,#REF!,#REF!,"",0,1) -> #REF! | M202: =IFERROR(L202*#REF!,"") | N202: =IFERROR(D202*J202*M202,-1) -> -1 | O202: =IFERROR(E202*J202*M202,-1) -> -1 | P202: =IFERROR(F202*J202*M202,-1) -> -1 | Q202: =IFERROR(G202*J202*M202,-1) -> -1 | S202: Sterling Sterling _ AE2100 _ restructure & add spare engines | T202: -1 | V202: Sterling Sterling _ AE2100 _ restructure & add spare engines | W202: -1 | Y202: Sterling Sterling _ AE2100 _ restructure & add spare engines | Z202: -1 | AB202: Sterling Sterling _ AE2100 _ restructure & add spare engines | AC202: -1
... C211: United UNITED TotalCare restructure to SelectCare and term extension - 535E$ | E211: 0 | F211: 0 | G211: =E211+F211 -> 0 | H211: {=INDEX('GLOBAL LOG'!#REF!,ROW()-169+15)} -> #REF! | I211: =_xlfn.XLOOKUP(H211,#REF!,#REF!,"",0,1) -> #REF! | J211: =IFERROR(I211*#REF!,"") | K211: {=INDEX('GLOBAL LOG'!#REF!,ROW()-169+15)} -> #REF! | L211: =_xlfn.XLOOKUP(K211,#REF!,#REF!,"",0,1) -> #REF! | M211: =IFERROR(L211*#REF!,"") | N211: =IFERROR(D211*J211*M211,-1) -> -1 | O211: =IFERROR(E211*J211*M211,-1) -> -1 | P211: =IFERROR(F211*J211*M211,-1) -> -1 | Q211: =IFERROR(G211*J211*M211,-1) -> -1 | S211: United UNITED TotalCare restructure to SelectCare and term extension - 535E$ | T211: -1 | V211: United UNITED TotalCare restructure to SelectCare and term extension - 535E$ | W211: -1 | Y211: United UNITED TotalCare restructure to SelectCare and term extension - 535E$ | Z211: -1 | AB211: United UNITED TotalCare restructure to SelectCare and term extension - 535E$ | AC211: -1
C212: Air New Zealand Min Term extension of existing contract 4 to 6 years post L1 last week. Fixed SV's to propose to be ascertained with support from Service business planner run post min term. Customer on board ("Pulling") and is waiting for RR proposal. Whilst we have a phase 1 and Phase 2 approach (Phase 1 not requiring additional support from outside of AM) we would seek to lock in resource in Q2 2025. Phase 1 amendment has now been shared with ANZ (10 July 2025) with initial feedback received from ANZ (24 July 2025). Action is on R-R to respond. | E212: 14 | F212: Confirm with Bobby | G212: =E212+F212 -> #VALUE! | H212: {=INDEX('GLOBAL LOG'!#REF!,ROW()-169+15)} -> #REF! | I212: =_xlfn.XLOOKUP(H212,#REF!,#REF!,"",0,1) -> #REF! | J212: =IFERROR(I212*#REF!,"") | K212: {=INDEX('GLOBAL LOG'!#REF!,ROW()-169+15)} -> #REF! | L212: =_xlfn.XLOOKUP(K212,#REF!,#REF!,"",0,1) -> #REF! | M212: =IFERROR(L212*#REF!,"") | N212: =IFERROR(D212*J212*M212,-1) -> -1 | O212: =IFERROR(E212*J212*M212,-1) -> -1 | P212: =IFERROR(F212*J212*M212,-1) -> -1 | Q212: =IFERROR(G212*J212*M212,-1) -> -1 | S212: Air New Zealand Min Term extension of existing contract 4 to 6 years post L1 last week. Fixed SV's to propose to be ascertained with support from Service business planner run post min term. Customer on board ("Pulling") and is waiting for RR proposal. Whilst we have a phase 1 and Phase 2 approach (Phase 1 not requiring additional support from outside of AM) we would seek to lock in resource in Q2 2025. Phase 1 amendment has now been shared with ANZ (10 July 2025) with initial feedback received from ANZ (24 July 2025). Action is on R-R to respond. | T212: -1 | V212: Air New Zealand Min Term extension of existing contract 4 to 6 years post L1 last week. Fixed SV's to propose to be ascertained with support from Service business planner run post min term. Customer on board ("Pulling") and is waiting for RR proposal. Whilst we have a phase 1 and Phase 2 approach (Phase 1 not requiring additional support from outside of AM) we would seek to lock in resource in Q2 2025. Phase 1 amendment has now been shared with ANZ (10 July 2025) with initial feedback received from ANZ (24 July 2025). Action is on R-R to respond. | W212: -1 | Y212: Air New Zealand Min Term extension of existing contract 4 to 6 years post L1 last week. Fixed SV's to propose to be ascertained with support from Service business planner run post min term. Customer on board ("Pulling") and is waiting for RR proposal. Whilst we have a phase 1 and Phase 2 approach (Phase 1 not requiring additional support from outside of AM) we would seek to lock in resource in Q2 2025. Phase 1 amendment has now been shared with ANZ (10 July 2025) with initial feedback received from ANZ (24 July 2025). Action is on R-R to respond. | Z212: -1 | AB212: Air New Zealand Min Term extension of existing contract 4 to 6 years post L1 last week. Fixed SV's to propose to be ascertained with support from Service business planner run post min term. Customer on board ("Pulling") and is waiting for RR proposal. Whilst we have a phase 1 and Phase 2 approach (Phase 1 not requiring additional support from outside of AM) we would seek to lock in resource in Q2 2025. Phase 1 amendment has now been shared with ANZ (10 July 2025) with initial feedback received from ANZ (24 July 2025). Action is on R-R to respond. | AC212: -1
C213: All Nippon Airways Restructure of ANA spare engine solution, utilising off-ramp of our Trent 1000 lease pool assets. Current spare engine holding is 15%, we are targeting uplifting closer to 20%, an opportunity for up to 8 used assets. Our lease pool engines are capitalised at cost, upside opportunity to transact at a premium to our balance sheet value. Any discount to market price will be offset against ANA's $33m non-contractual claim for Trent 1000 disruption in 2024. L2 rejected our simple approach of offering credits towards future spare engine purchases. Further due diligence required on both sides to align on the end solution, representing phase 2 of value co-creation with ANA. | E213: 0 | F213: 0 | G213: =E213+F213 -> 0 | H213: {=INDEX('GLOBAL LOG'!#REF!,ROW()-169+15)} -> #REF! | I213: =_xlfn.XLOOKUP(H213,#REF!,#REF!,"",0,1) -> #REF! | J213: =IFERROR(I213*#REF!,"") | K213: {=INDEX('GLOBAL LOG'!#REF!,ROW()-169+15)} -> #REF! | L213: =_xlfn.XLOOKUP(K213,#REF!,#REF!,"",0,1) -> #REF! | M213: =IFERROR(L213*#REF!,"") | N213: =IFERROR(D213*J213*M213,-1) -> -1 | O213: =IFERROR(E213*J213*M213,-1) -> -1 | P213: =IFERROR(F213*J213*M213,-1) -> -1 | Q213: =IFERROR(G213*J213*M213,-1) -> -1 | S213: All Nippon Airways Restructure of ANA spare engine solution, utilising off-ramp of our Trent 1000 lease pool assets. Current spare engine holding is 15%, we are targeting uplifting closer to 20%, an opportunity for up to 8 used assets. Our lease pool engines are capitalised at cost, upside opportunity to transact at a premium to our balance sheet value. Any discount to market price will be offset against ANA's $33m non-contractual claim for Trent 1000 disruption in 2024. L2 rejected our simple approach of offering credits towards future spare engine purchases. Further due diligence required on both sides to align on the end solution, representing phase 2 of value co-creation with ANA. | T213: -1 | V213: All Nippon Airways Restructure of ANA spare engine solution, utilising off-ramp of our Trent 1000 lease pool assets. Current spare engine holding is 15%, we are targeting uplifting closer to 20%, an opportunity for up to 8 used assets. Our lease pool engines are capitalised at cost, upside opportunity to transact at a premium to our balance sheet value. Any discount to market price will be offset against ANA's $33m non-contractual claim for Trent 1000 disruption in 2024. L2 rejected our simple approach of offering credits towards future spare engine purchases. Further due diligence required on both sides to align on the end solution, representing phase 2 of value co-creation with ANA. | W213: -1 | Y213: All Nippon Airways Restructure of ANA spare engine solution, utilising off-ramp of our Trent 1000 lease pool assets. Current spare engine holding is 15%, we are targeting uplifting closer to 20%, an opportunity for up to 8 used assets. Our lease pool engines are capitalised at cost, upside opportunity to transact at a premium to our balance sheet value. Any discount to market price will be offset against ANA's $33m non-contractual claim for Trent 1000 disruption in 2024. L2 rejected our simple approach of offering credits towards future spare engine purchases. Further due diligence required on both sides to align on the end solution, representing phase 2 of value co-creation with ANA. | Z213: -1 | AB213: All Nippon Airways Restructure of ANA spare engine solution, utilising off-ramp of our Trent 1000 lease pool assets. Current spare engine holding is 15%, we are targeting uplifting closer to 20%, an opportunity for up to 8 used assets. Our lease pool engines are capitalised at cost, upside opportunity to transact at a premium to our balance sheet value. Any discount to market price will be offset against ANA's $33m non-contractual claim for Trent 1000 disruption in 2024. L2 rejected our simple approach of offering credits towards future spare engine purchases. Further due diligence required on both sides to align on the end solution, representing phase 2 of value co-creation with ANA. | AC213: -1
C214: Singapore Airlines To be assessed in 2025 - possible opportunity to harmoinise SelectCare & TCA contracts. A few open Trent 900 commercial items will be closed as part of Aegis closing position - with further optimisation opportunities to be assessed later in 2025, with scope for improvements to be included as part of the Trent 1000 optimisation project. Start expeceted in 2026 given Aegis contracting delay and Trent 1000 restructure priority | E214: 0 | F214: 0 | G214: =E214+F214 -> 0 | H214: {=INDEX('GLOBAL LOG'!#REF!,ROW()-169+15)} -> #REF! | I214: =_xlfn.XLOOKUP(H214,#REF!,#REF!,"",0,1) -> #REF! | J214: =IFERROR(I214*#REF!,"") | K214: {=INDEX('GLOBAL LOG'!#REF!,ROW()-169+15)} -> #REF! | L214: =_xlfn.XLOOKUP(K214,#REF!,#REF!,"",0,1) -> #REF! | M214: =IFERROR(L214*#REF!,"") | N214: =IFERROR(D214*J214*M214,-1) -> -1 | O214: =IFERROR(E214*J214*M214,-1) -> -1 | P214: =IFERROR(F214*J214*M214,-1) -> -1 | Q214: =IFERROR(G214*J214*M214,-1) -> -1 | S214: Singapore Airlines To be assessed in 2025 - possible opportunity to harmoinise SelectCare & TCA contracts. A few open Trent 900 commercial items will be closed as part of Aegis closing position - with further optimisation opportunities to be assessed later in 2025, with scope for improvements to be included as part of the Trent 1000 optimisation project. Start expeceted in 2026 given Aegis contracting delay and Trent 1000 restructure priority | T214: -1 | V214: Singapore Airlines To be assessed in 2025 - possible opportunity to harmoinise SelectCare & TCA contracts. A few open Trent 900 commercial items will be closed as part of Aegis closing position - with further optimisation opportunities to be assessed later in 2025, with scope for improvements to be included as part of the Trent 1000 optimisation project. Start expeceted in 2026 given Aegis contracting delay and Trent 1000 restructure priority | W214: -1 | Y214: Singapore Airlines To be assessed in 2025 - possible opportunity to harmoinise SelectCare & TCA contracts. A few open Trent 900 commercial items will be closed as part of Aegis closing position - with further optimisation opportunities to be assessed later in 2025, with scope for improvements to be included as part of the Trent 1000 optimisation project. Start expeceted in 2026 given Aegis contracting delay and Trent 1000 restructure priority | Z214: -1 | AB214: Singapore Airlines To be assessed in 2025 - possible opportunity to harmoinise SelectCare & TCA contracts. A few open Trent 900 commercial items will be closed as part of Aegis closing position - with further optimisation opportunities to be assessed later in 2025, with scope for improvements to be included as part of the Trent 1000 optimisation project. Start expeceted in 2026 given Aegis contracting delay and Trent 1000 restructure priority | AC214: -1
C215: Finnair Min Term Extension for both Life & Term mix of structures - discussions to commence following their fleet expansion analysis in Q2. | E215: 0 | F215: 0 | G215: =E215+F215 -> 0 | H215: {=INDEX('GLOBAL LOG'!#REF!,ROW()-169+15)} -> #REF! | I215: =_xlfn.XLOOKUP(H215,#REF!,#REF!,"",0,1) -> #REF! | J215: =IFERROR(I215*#REF!,"") | K215: {=INDEX('GLOBAL LOG'!#REF!,ROW()-169+15)} -> #REF! | L215: =_xlfn.XLOOKUP(K215,#REF!,#REF!,"",0,1) -> #REF! | M215: =IFERROR(L215*#REF!,"") | N215: =IFERROR(D215*J215*M215,-1) -> -1 | O215: =IFERROR(E215*J215*M215,-1) -> -1 | P215: =IFERROR(F215*J215*M215,-1) -> -1 | Q215: =IFERROR(G215*J215*M215,-1) -> -1 | S215: Finnair Min Term Extension for both Life & Term mix of structures - discussions to commence following their fleet expansion analysis in Q2. | T215: -1 | V215: Finnair Min Term Extension for both Life & Term mix of structures - discussions to commence following their fleet expansion analysis in Q2. | W215: -1 | Y215: Finnair Min Term Extension for both Life & Term mix of structures - discussions to commence following their fleet expansion analysis in Q2. | Z215: -1 | AB215: Finnair Min Term Extension for both Life & Term mix of structures - discussions to commence following their fleet expansion analysis in Q2. | AC215: -1
C216: Virgin Atlantic Descoping of unprofitable services in conjunction with new a/c opportunity. Test with new a/c (decision expected Q2 2026) before descoping existing fleet. | E216: 0 | F216: 0 | G216: =E216+F216 -> 0 | H216: {=INDEX('GLOBAL LOG'!#REF!,ROW()-169+15)} -> #REF! | I216: =_xlfn.XLOOKUP(H216,#REF!,#REF!,"",0,1) -> #REF! | J216: =IFERROR(I216*#REF!,"") | K216: {=INDEX('GLOBAL LOG'!#REF!,ROW()-169+15)} -> #REF! | L216: =_xlfn.XLOOKUP(K216,#REF!,#REF!,"",0,1) -> #REF! | M216: =IFERROR(L216*#REF!,"") | N216: =IFERROR(D216*J216*M216,-1) -> -1 | O216: =IFERROR(E216*J216*M216,-1) -> -1 | P216: =IFERROR(F216*J216*M216,-1) -> -1 | Q216: =IFERROR(G216*J216*M216,-1) -> -1 | S216: Virgin Atlantic Descoping of unprofitable services in conjunction with new a/c opportunity. Test with new a/c (decision expected Q2 2026) before descoping existing fleet. | T216: -1 | V216: Virgin Atlantic Descoping of unprofitable services in conjunction with new a/c opportunity. Test with new a/c (decision expected Q2 2026) before descoping existing fleet. | W216: -1 | Y216: Virgin Atlantic Descoping of unprofitable services in conjunction with new a/c opportunity. Test with new a/c (decision expected Q2 2026) before descoping existing fleet. | Z216: -1 | AB216: Virgin Atlantic Descoping of unprofitable services in conjunction with new a/c opportunity. Test with new a/c (decision expected Q2 2026) before descoping existing fleet. | AC216: -1
C217: Air France Min term extension (life) - 3 a/c exit from 2029. Maybe add in 2026 RFP | E217: 0 | F217: 0 | G217: =E217+F217 -> 0 | H217: {=INDEX('GLOBAL LOG'!#REF!,ROW()-169+15)} -> #REF! | I217: =_xlfn.XLOOKUP(H217,#REF!,#REF!,"",0,1) -> #REF! | J217: =IFERROR(I217*#REF!,"") | K217: {=INDEX('GLOBAL LOG'!#REF!,ROW()-169+15)} -> #REF! | L217: =_xlfn.XLOOKUP(K217,#REF!,#REF!,"",0,1) -> #REF! | M217: =IFERROR(L217*#REF!,"") | N217: =IFERROR(D217*J217*M217,-1) -> -1 | O217: =IFERROR(E217*J217*M217,-1) -> -1 | P217: =IFERROR(F217*J217*M217,-1) -> -1 | Q217: =IFERROR(G217*J217*M217,-1) -> -1 | S217: Air France Min term extension (life) - 3 a/c exit from 2029. Maybe add in 2026 RFP | T217: -1 | V217: Air France Min term extension (life) - 3 a/c exit from 2029. Maybe add in 2026 RFP | W217: -1 | Y217: Air France Min term extension (life) - 3 a/c exit from 2029. Maybe add in 2026 RFP | Z217: -1 | AB217: Air France Min term extension (life) - 3 a/c exit from 2029. Maybe add in 2026 RFP | AC217: -1
C218: Thai Airasia X Carried $25m debt with TAAX at interim, of which majority relates to Supplementary Service Fee (pre-pandemic Min U & LPI). Once TAAX has made payments in early Q3 to support withdrawal of Notices of Default, we will engage on a restrucutre of the Supplementary Service Fee to make the deal more financially sustainable to TAAX, whilst preserving healthy margins. Alternative scenario could be termination, which we are doing internal due diligence on. | E218: 0 | F218: Rebecca to confirm | G218: =E218+F218 -> #VALUE! | H218: {=INDEX('GLOBAL LOG'!#REF!,ROW()-169+15)} -> #REF! | I218: =_xlfn.XLOOKUP(H218,#REF!,#REF!,"",0,1) -> #REF! | J218: =IFERROR(I218*#REF!,"") | K218: {=INDEX('GLOBAL LOG'!#REF!,ROW()-169+15)} -> #REF! | L218: =_xlfn.XLOOKUP(K218,#REF!,#REF!,"",0,1) -> #REF! | M218: =IFERROR(L218*#REF!,"") | N218: =IFERROR(D218*J218*M218,-1) -> -1 | O218: =IFERROR(E218*J218*M218,-1) -> -1 | P218: =IFERROR(F218*J218*M218,-1) -> -1 | Q218: =IFERROR(G218*J218*M218,-1) -> -1 | S218: Thai Airasia X Carried $25m debt with TAAX at interim, of which majority relates to Supplementary Service Fee (pre-pandemic Min U & LPI). Once TAAX has made payments in early Q3 to support withdrawal of Notices of Default, we will engage on a restrucutre of the Supplementary Service Fee to make the deal more financially sustainable to TAAX, whilst preserving healthy margins. Alternative scenario could be termination, which we are doing internal due diligence on. | T218: -1 | V218: Thai Airasia X Carried $25m debt with TAAX at interim, of which majority relates to Supplementary Service Fee (pre-pandemic Min U & LPI). Once TAAX has made payments in early Q3 to support withdrawal of Notices of Default, we will engage on a restrucutre of the Supplementary Service Fee to make the deal more financially sustainable to TAAX, whilst preserving healthy margins. Alternative scenario could be termination, which we are doing internal due diligence on. | W218: -1 | Y218: Thai Airasia X Carried $25m debt with TAAX at interim, of which majority relates to Supplementary Service Fee (pre-pandemic Min U & LPI). Once TAAX has made payments in early Q3 to support withdrawal of Notices of Default, we will engage on a restrucutre of the Supplementary Service Fee to make the deal more financially sustainable to TAAX, whilst preserving healthy margins. Alternative scenario could be termination, which we are doing internal due diligence on. | Z218: -1 | AB218: Thai Airasia X Carried $25m debt with TAAX at interim, of which majority relates to Supplementary Service Fee (pre-pandemic Min U & LPI). Once TAAX has made payments in early Q3 to support withdrawal of Notices of Default, we will engage on a restrucutre of the Supplementary Service Fee to make the deal more financially sustainable to TAAX, whilst preserving healthy margins. Alternative scenario could be termination, which we are doing internal due diligence on. | AC218: -1
C219: Lufthansa Min term extension (life) - 4 a/c exit from 2028 | E219: 0 | F219: 0 | G219: =E219+F219 -> 0 | H219: {=INDEX('GLOBAL LOG'!#REF!,ROW()-169+15)} -> #REF! | I219: =_xlfn.XLOOKUP(H219,#REF!,#REF!,"",0,1) -> #REF! | J219: =IFERROR(I219*#REF!,"") | K219: {=INDEX('GLOBAL LOG'!#REF!,ROW()-169+15)} -> #REF! | L219: =_xlfn.XLOOKUP(K219,#REF!,#REF!,"",0,1) -> #REF! | M219: =IFERROR(L219*#REF!,"") | N219: =IFERROR(D219*J219*M219,-1) -> -1 | O219: =IFERROR(E219*J219*M219,-1) -> -1 | P219: =IFERROR(F219*J219*M219,-1) -> -1 | Q219: =IFERROR(G219*J219*M219,-1) -> -1 | S219: Lufthansa Min term extension (life) - 4 a/c exit from 2028 | T219: -1 | V219: Lufthansa Min term extension (life) - 4 a/c exit from 2028 | W219: -1 | Y219: Lufthansa Min term extension (life) - 4 a/c exit from 2028 | Z219: -1 | AB219: Lufthansa Min term extension (life) - 4 a/c exit from 2028 | AC219: -1
C220: Air Caraibes Min term extension (life) - 3 a/c exit from 2029 | E220: 0 | F220: 0 | G220: =E220+F220 -> 0 | H220: {=INDEX('GLOBAL LOG'!#REF!,ROW()-169+15)} -> #REF! | I220: =_xlfn.XLOOKUP(H220,#REF!,#REF!,"",0,1) -> #REF! | J220: =IFERROR(I220*#REF!,"") | K220: {=INDEX('GLOBAL LOG'!#REF!,ROW()-169+15)} -> #REF! | L220: =_xlfn.XLOOKUP(K220,#REF!,#REF!,"",0,1) -> #REF! | M220: =IFERROR(L220*#REF!,"") | N220: =IFERROR(D220*J220*M220,-1) -> -1 | O220: =IFERROR(E220*J220*M220,-1) -> -1 | P220: =IFERROR(F220*J220*M220,-1) -> -1 | Q220: =IFERROR(G220*J220*M220,-1) -> -1 | S220: Air Caraibes Min term extension (life) - 3 a/c exit from 2029 | T220: -1 | V220: Air Caraibes Min term extension (life) - 3 a/c exit from 2029 | W220: -1 | Y220: Air Caraibes Min term extension (life) - 3 a/c exit from 2029 | Z220: -1 | AB220: Air Caraibes Min term extension (life) - 3 a/c exit from 2029 | AC220: -1
C221: China Airlines 26 Feb 2026: The customer welcomes the proposed term extension approach on existing fleet. S&C will begin drafting the documents shortly. The contract is expected to be ready by March. Expected closure by Q2 2026. Assess other issues (Life to term conversation but that is early stages and capture in as a line item seperately) 7 Aug 2025: L2 strategy approved to persue launching detailed evaluation work and engagement with customer has commenced. Contract optimation is reliant on achieving contract amendment of the term extension rather than expected new contract. Confirmed new DEG approach can trigger start-stop commercial optimisation. Customer meeting (SVP) iniated the activity. VP visit in mid-Aug to follow up. | E221: 9 | F221: 4 | G221: =E221+F221 -> 13 | H221: {=INDEX('GLOBAL LOG'!#REF!,ROW()-169+15)} -> #REF! | I221: =_xlfn.XLOOKUP(H221,#REF!,#REF!,"",0,1) -> #REF! | J221: =IFERROR(I221*#REF!,"") | K221: {=INDEX('GLOBAL LOG'!#REF!,ROW()-169+15)} -> #REF! | L221: =_xlfn.XLOOKUP(K221,#REF!,#REF!,"",0,1) -> #REF! | M221: =IFERROR(L221*#REF!,"") | N221: =IFERROR(D221*J221*M221,-1) -> -1 | O221: =IFERROR(E221*J221*M221,-1) -> -1 | P221: =IFERROR(F221*J221*M221,-1) -> -1 | Q221: =IFERROR(G221*J221*M221,-1) -> -1 | S221: China Airlines 26 Feb 2026: The customer welcomes the proposed term extension approach on existing fleet. S&C will begin drafting the documents shortly. The contract is expected to be ready by March. Expected closure by Q2 2026. Assess other issues (Life to term conversation but that is early stages and capture in as a line item seperately) 7 Aug 2025: L2 strategy approved to persue launching detailed evaluation work and engagement with customer has commenced. Contract optimation is reliant on achieving contract amendment of the term extension rather than expected new contract. Confirmed new DEG approach can trigger start-stop commercial optimisation. Customer meeting (SVP) iniated the activity. VP visit in mid-Aug to follow up. | T221: -1 | V221: China Airlines 26 Feb 2026: The customer welcomes the proposed term extension approach on existing fleet. S&C will begin drafting the documents shortly. The contract is expected to be ready by March. Expected closure by Q2 2026. Assess other issues (Life to term conversation but that is early stages and capture in as a line item seperately) 7 Aug 2025: L2 strategy approved to persue launching detailed evaluation work and engagement with customer has commenced. Contract optimation is reliant on achieving contract amendment of the term extension rather than expected new contract. Confirmed new DEG approach can trigger start-stop commercial optimisation. Customer meeting (SVP) iniated the activity. VP visit in mid-Aug to follow up. | W221: -1 | Y221: China Airlines 26 Feb 2026: The customer welcomes the proposed term extension approach on existing fleet. S&C will begin drafting the documents shortly. The contract is expected to be ready by March. Expected closure by Q2 2026. Assess other issues (Life to term conversation but that is early stages and capture in as a line item seperately) 7 Aug 2025: L2 strategy approved to persue launching detailed evaluation work and engagement with customer has commenced. Contract optimation is reliant on achieving contract amendment of the term extension rather than expected new contract. Confirmed new DEG approach can trigger start-stop commercial optimisation. Customer meeting (SVP) iniated the activity. VP visit in mid-Aug to follow up. | Z221: -1 | AB221: China Airlines 26 Feb 2026: The customer welcomes the proposed term extension approach on existing fleet. S&C will begin drafting the documents shortly. The contract is expected to be ready by March. Expected closure by Q2 2026. Assess other issues (Life to term conversation but that is early stages and capture in as a line item seperately) 7 Aug 2025: L2 strategy approved to persue launching detailed evaluation work and engagement with customer has commenced. Contract optimation is reliant on achieving contract amendment of the term extension rather than expected new contract. Confirmed new DEG approach can trigger start-stop commercial optimisation. Customer meeting (SVP) iniated the activity. VP visit in mid-Aug to follow up. | AC221: -1
C222: Asiana Airlines Restructure/re-price backlog to compensate for erorsion of value relating backlog deferral. R-R position presented to Asiana during Customer visit to Seletar in May. Initial Customer feedback that they expect this activity to be rolled into conslidation of agreements with Korean Air, post the 2 year merger transition period. | E222: 0 | F222: 0 | G222: =E222+F222 -> 0 | H222: {=INDEX('GLOBAL LOG'!#REF!,ROW()-169+15)} -> #REF! | I222: =_xlfn.XLOOKUP(H222,#REF!,#REF!,"",0,1) -> #REF! | J222: =IFERROR(I222*#REF!,"") | K222: {=INDEX('GLOBAL LOG'!#REF!,ROW()-169+15)} -> #REF! | L222: =_xlfn.XLOOKUP(K222,#REF!,#REF!,"",0,1) -> #REF! | M222: =IFERROR(L222*#REF!,"") | N222: =IFERROR(D222*J222*M222,-1) -> -1 | O222: =IFERROR(E222*J222*M222,-1) -> -1 | P222: =IFERROR(F222*J222*M222,-1) -> -1 | Q222: =IFERROR(G222*J222*M222,-1) -> -1 | S222: Asiana Airlines Restructure/re-price backlog to compensate for erorsion of value relating backlog deferral. R-R position presented to Asiana during Customer visit to Seletar in May. Initial Customer feedback that they expect this activity to be rolled into conslidation of agreements with Korean Air, post the 2 year merger transition period. | T222: -1 | V222: Asiana Airlines Restructure/re-price backlog to compensate for erorsion of value relating backlog deferral. R-R position presented to Asiana during Customer visit to Seletar in May. Initial Customer feedback that they expect this activity to be rolled into conslidation of agreements with Korean Air, post the 2 year merger transition period. | W222: -1 | Y222: Asiana Airlines Restructure/re-price backlog to compensate for erorsion of value relating backlog deferral. R-R position presented to Asiana during Customer visit to Seletar in May. Initial Customer feedback that they expect this activity to be rolled into conslidation of agreements with Korean Air, post the 2 year merger transition period. | Z222: -1 | AB222: Asiana Airlines Restructure/re-price backlog to compensate for erorsion of value relating backlog deferral. R-R position presented to Asiana during Customer visit to Seletar in May. Initial Customer feedback that they expect this activity to be rolled into conslidation of agreements with Korean Air, post the 2 year merger transition period. | AC222: -1
C223: Cathay Pacific Airways 4 March 2026: Previous LLP cost of ownership initiative is parked. However following the lost longhaul campaign in 2025, various trades are being proposed to be repackaged: Law 1/2 (win-win), deletion of Benefit Sharing Mechanism (take), securing Climb Derate Algorithim (take), closure of Fire Claim without non-contractual give (mitigation), concession of Lease Engine Cyclic Charges rate (give), other minor settlements of CPA incremental costs incurred (give). L2 scheduled for 6 March to approve strategy. | E223: 12 | F223: 0 | G223: =E223+F223 -> 12 | H223: {=INDEX('GLOBAL LOG'!#REF!,ROW()-169+15)} -> #REF! | I223: =_xlfn.XLOOKUP(H223,#REF!,#REF!,"",0,1) -> #REF! | J223: =IFERROR(I223*#REF!,"") | K223: {=INDEX('GLOBAL LOG'!#REF!,ROW()-169+15)} -> #REF! | L223: =_xlfn.XLOOKUP(K223,#REF!,#REF!,"",0,1) -> #REF! | M223: =IFERROR(L223*#REF!,"") | N223: =IFERROR(D223*J223*M223,-1) -> -1 | O223: =IFERROR(E223*J223*M223,-1) -> -1 | P223: =IFERROR(F223*J223*M223,-1) -> -1 | Q223: =IFERROR(G223*J223*M223,-1) -> -1 | S223: Cathay Pacific Airways 4 March 2026: Previous LLP cost of ownership initiative is parked. However following the lost longhaul campaign in 2025, various trades are being proposed to be repackaged: Law 1/2 (win-win), deletion of Benefit Sharing Mechanism (take), securing Climb Derate Algorithim (take), closure of Fire Claim without non-contractual give (mitigation), concession of Lease Engine Cyclic Charges rate (give), other minor settlements of CPA incremental costs incurred (give). L2 scheduled for 6 March to approve strategy. | T223: -1 | V223: Cathay Pacific Airways 4 March 2026: Previous LLP cost of ownership initiative is parked. However following the lost longhaul campaign in 2025, various trades are being proposed to be repackaged: Law 1/2 (win-win), deletion of Benefit Sharing Mechanism (take), securing Climb Derate Algorithim (take), closure of Fire Claim without non-contractual give (mitigation), concession of Lease Engine Cyclic Charges rate (give), other minor settlements of CPA incremental costs incurred (give). L2 scheduled for 6 March to approve strategy. | W223: -1 | Y223: Cathay Pacific Airways 4 March 2026: Previous LLP cost of ownership initiative is parked. However following the lost longhaul campaign in 2025, various trades are being proposed to be repackaged: Law 1/2 (win-win), deletion of Benefit Sharing Mechanism (take), securing Climb Derate Algorithim (take), closure of Fire Claim without non-contractual give (mitigation), concession of Lease Engine Cyclic Charges rate (give), other minor settlements of CPA incremental costs incurred (give). L2 scheduled for 6 March to approve strategy. | Z223: -1 | AB223: Cathay Pacific Airways 4 March 2026: Previous LLP cost of ownership initiative is parked. However following the lost longhaul campaign in 2025, various trades are being proposed to be repackaged: Law 1/2 (win-win), deletion of Benefit Sharing Mechanism (take), securing Climb Derate Algorithim (take), closure of Fire Claim without non-contractual give (mitigation), concession of Lease Engine Cyclic Charges rate (give), other minor settlements of CPA incremental costs incurred (give). L2 scheduled for 6 March to approve strategy. | AC223: -1
C224: Air China | E224: 0 | F224: 30 | G224: =E224+F224 -> 30 | H224: {=INDEX('GLOBAL LOG'!#REF!,ROW()-169+15)} -> #REF! | I224: =_xlfn.XLOOKUP(H224,#REF!,#REF!,"",0,1) -> #REF! | J224: =IFERROR(I224*#REF!,"") | K224: {=INDEX('GLOBAL LOG'!#REF!,ROW()-169+15)} -> #REF! | L224: =_xlfn.XLOOKUP(K224,#REF!,#REF!,"",0,1) -> #REF! | M224: =IFERROR(L224*#REF!,"") | N224: =IFERROR(D224*J224*M224,-1) -> -1 | O224: =IFERROR(E224*J224*M224,-1) -> -1 | P224: =IFERROR(F224*J224*M224,-1) -> -1 | Q224: =IFERROR(G224*J224*M224,-1) -> -1 | S224: Air China | T224: -1 | V224: Air China | W224: -1 | Y224: Air China | Z224: -1 | AB224: Air China | AC224: -1
C225: Cebu Pacific Low margin contract and asked by value stream to brainstorm ideas to improve CRP | E225: 0 | F225: 0 | G225: =E225+F225 -> 0 | H225: {=INDEX('GLOBAL LOG'!#REF!,ROW()-169+15)} -> #REF! | I225: =_xlfn.XLOOKUP(H225,#REF!,#REF!,"",0,1) -> #REF! | J225: =IFERROR(I225*#REF!,"") | K225: {=INDEX('GLOBAL LOG'!#REF!,ROW()-169+15)} -> #REF! | L225: =_xlfn.XLOOKUP(K225,#REF!,#REF!,"",0,1) -> #REF! | M225: =IFERROR(L225*#REF!,"") | N225: =IFERROR(D225*J225*M225,-1) -> -1 | O225: =IFERROR(E225*J225*M225,-1) -> -1 | P225: =IFERROR(F225*J225*M225,-1) -> -1 | Q225: =IFERROR(G225*J225*M225,-1) -> -1 | S225: Cebu Pacific Low margin contract and asked by value stream to brainstorm ideas to improve CRP | T225: -1 | V225: Cebu Pacific Low margin contract and asked by value stream to brainstorm ideas to improve CRP | W225: -1 | Y225: Cebu Pacific Low margin contract and asked by value stream to brainstorm ideas to improve CRP | Z225: -1 | AB225: Cebu Pacific Low margin contract and asked by value stream to brainstorm ideas to improve CRP | AC225: -1
C226: Lion Air 2 Aircraft Cancellation settlement agreed in 2025Q4, expected to be contracted by 2026Q2. Min U uplift, 2y extension and escalation increased. Resultant is Utilisation uplifted to 2175, 2y extension for 6 ac and escalation set to 5.15%. | E226: 8.5 | F226: Confirm with Laura | G226: =E226+F226 -> #VALUE! | H226: {=INDEX('GLOBAL LOG'!#REF!,ROW()-169+15)} -> #REF! | I226: =_xlfn.XLOOKUP(H226,#REF!,#REF!,"",0,1) -> #REF! | J226: =IFERROR(I226*#REF!,"") | K226: {=INDEX('GLOBAL LOG'!#REF!,ROW()-169+15)} -> #REF! | L226: =_xlfn.XLOOKUP(K226,#REF!,#REF!,"",0,1) -> #REF! | M226: =IFERROR(L226*#REF!,"") | N226: =IFERROR(D226*J226*M226,-1) -> -1 | O226: =IFERROR(E226*J226*M226,-1) -> -1 | P226: =IFERROR(F226*J226*M226,-1) -> -1 | Q226: =IFERROR(G226*J226*M226,-1) -> -1 | S226: Lion Air 2 Aircraft Cancellation settlement agreed in 2025Q4, expected to be contracted by 2026Q2. Min U uplift, 2y extension and escalation increased. Resultant is Utilisation uplifted to 2175, 2y extension for 6 ac and escalation set to 5.15%. | T226: -1 | V226: Lion Air 2 Aircraft Cancellation settlement agreed in 2025Q4, expected to be contracted by 2026Q2. Min U uplift, 2y extension and escalation increased. Resultant is Utilisation uplifted to 2175, 2y extension for 6 ac and escalation set to 5.15%. | W226: -1 | Y226: Lion Air 2 Aircraft Cancellation settlement agreed in 2025Q4, expected to be contracted by 2026Q2. Min U uplift, 2y extension and escalation increased. Resultant is Utilisation uplifted to 2175, 2y extension for 6 ac and escalation set to 5.15%. | Z226: -1 | AB226: Lion Air 2 Aircraft Cancellation settlement agreed in 2025Q4, expected to be contracted by 2026Q2. Min U uplift, 2y extension and escalation increased. Resultant is Utilisation uplifted to 2175, 2y extension for 6 ac and escalation set to 5.15%. | AC226: -1
C227: Garuda Note: Notice of Breach Served on Garuda: Contract restructure, including possible PAYG->PASV flip, in the event of continuing payment disputes and as avenue to avoid termination of profitable CRPs - opportunity to sell new/used additional SPE's | E227: 0 | F227: 0 | G227: =E227+F227 -> 0 | H227: {=INDEX('GLOBAL LOG'!#REF!,ROW()-169+15)} -> #REF! | I227: =_xlfn.XLOOKUP(H227,#REF!,#REF!,"",0,1) -> #REF! | J227: =IFERROR(I227*#REF!,"") | K227: {=INDEX('GLOBAL LOG'!#REF!,ROW()-169+15)} -> #REF! | L227: =_xlfn.XLOOKUP(K227,#REF!,#REF!,"",0,1) -> #REF! | M227: =IFERROR(L227*#REF!,"") | N227: =IFERROR(D227*J227*M227,-1) -> -1 | O227: =IFERROR(E227*J227*M227,-1) -> -1 | P227: =IFERROR(F227*J227*M227,-1) -> -1 | Q227: =IFERROR(G227*J227*M227,-1) -> -1 | S227: Garuda Note: Notice of Breach Served on Garuda: Contract restructure, including possible PAYG->PASV flip, in the event of continuing payment disputes and as avenue to avoid termination of profitable CRPs - opportunity to sell new/used additional SPE's | T227: -1 | V227: Garuda Note: Notice of Breach Served on Garuda: Contract restructure, including possible PAYG->PASV flip, in the event of continuing payment disputes and as avenue to avoid termination of profitable CRPs - opportunity to sell new/used additional SPE's | W227: -1 | Y227: Garuda Note: Notice of Breach Served on Garuda: Contract restructure, including possible PAYG->PASV flip, in the event of continuing payment disputes and as avenue to avoid termination of profitable CRPs - opportunity to sell new/used additional SPE's | Z227: -1 | AB227: Garuda Note: Notice of Breach Served on Garuda: Contract restructure, including possible PAYG->PASV flip, in the event of continuing payment disputes and as avenue to avoid termination of profitable CRPs - opportunity to sell new/used additional SPE's | AC227: -1
C228: Delta Air Lines To be assessed in 2026 - Incremental SPE sale to further reduce NDSES costs | E228: 0 | F228: 0 | G228: =E228+F228 -> 0 | H228: {=INDEX('GLOBAL LOG'!#REF!,ROW()-169+15)} -> #REF! | I228: =_xlfn.XLOOKUP(H228,#REF!,#REF!,"",0,1) -> #REF! | J228: =IFERROR(I228*#REF!,"") | K228: {=INDEX('GLOBAL LOG'!#REF!,ROW()-169+15)} -> #REF! | L228: =_xlfn.XLOOKUP(K228,#REF!,#REF!,"",0,1) -> #REF! | M228: =IFERROR(L228*#REF!,"") | N228: =IFERROR(D228*J228*M228,-1) -> -1 | O228: =IFERROR(E228*J228*M228,-1) -> -1 | P228: =IFERROR(F228*J228*M228,-1) -> -1 | Q228: =IFERROR(G228*J228*M228,-1) -> -1 | S228: Delta Air Lines To be assessed in 2026 - Incremental SPE sale to further reduce NDSES costs | T228: -1 | V228: Delta Air Lines To be assessed in 2026 - Incremental SPE sale to further reduce NDSES costs | W228: -1 | Y228: Delta Air Lines To be assessed in 2026 - Incremental SPE sale to further reduce NDSES costs | Z228: -1 | AB228: Delta Air Lines To be assessed in 2026 - Incremental SPE sale to further reduce NDSES costs | AC228: -1
C229: Virgin Atlantic Restructure/buy-out of environmental partnership guarentee | E229: 0 | F229: 0 | G229: =E229+F229 -> 0 | H229: {=INDEX('GLOBAL LOG'!#REF!,ROW()-169+15)} -> #REF! | I229: =_xlfn.XLOOKUP(H229,#REF!,#REF!,"",0,1) -> #REF! | J229: =IFERROR(I229*#REF!,"") | K229: {=INDEX('GLOBAL LOG'!#REF!,ROW()-169+15)} -> #REF! | L229: =_xlfn.XLOOKUP(K229,#REF!,#REF!,"",0,1) -> #REF! | M229: =IFERROR(L229*#REF!,"") | N229: =IFERROR(D229*J229*M229,-1) -> -1 | O229: =IFERROR(E229*J229*M229,-1) -> -1 | P229: =IFERROR(F229*J229*M229,-1) -> -1 | Q229: =IFERROR(G229*J229*M229,-1) -> -1 | S229: Virgin Atlantic Restructure/buy-out of environmental partnership guarentee | T229: -1 | V229: Virgin Atlantic Restructure/buy-out of environmental partnership guarentee | W229: -1 | Y229: Virgin Atlantic Restructure/buy-out of environmental partnership guarentee | Z229: -1 | AB229: Virgin Atlantic Restructure/buy-out of environmental partnership guarentee | AC229: -1
C230: Latam Focus on fleet health at present, ICT generating ideas to improve onerous position (potential sale of used spare engine and term extension). | E230: 50 | F230: 0 | G230: =E230+F230 -> 50 | H230: {=INDEX('GLOBAL LOG'!#REF!,ROW()-169+15)} -> #REF! | I230: =_xlfn.XLOOKUP(H230,#REF!,#REF!,"",0,1) -> #REF! | J230: =IFERROR(I230*#REF!,"") | K230: {=INDEX('GLOBAL LOG'!#REF!,ROW()-169+15)} -> #REF! | L230: =_xlfn.XLOOKUP(K230,#REF!,#REF!,"",0,1) -> #REF! | M230: =IFERROR(L230*#REF!,"") | N230: =IFERROR(D230*J230*M230,-1) -> -1 | O230: =IFERROR(E230*J230*M230,-1) -> -1 | P230: =IFERROR(F230*J230*M230,-1) -> -1 | Q230: =IFERROR(G230*J230*M230,-1) -> -1 | S230: Latam Focus on fleet health at present, ICT generating ideas to improve onerous position (potential sale of used spare engine and term extension). | T230: -1 | V230: Latam Focus on fleet health at present, ICT generating ideas to improve onerous position (potential sale of used spare engine and term extension). | W230: -1 | Y230: Latam Focus on fleet health at present, ICT generating ideas to improve onerous position (potential sale of used spare engine and term extension). | Z230: -1 | AB230: Latam Focus on fleet health at present, ICT generating ideas to improve onerous position (potential sale of used spare engine and term extension). | AC230: -1
C231: Air Transat Consolidation of TotalCare structures | E231: 0 | F231: 0 | G231: =E231+F231 -> 0 | H231: {=INDEX('GLOBAL LOG'!#REF!,ROW()-169+15)} -> #REF! | I231: =_xlfn.XLOOKUP(H231,#REF!,#REF!,"",0,1) -> #REF! | J231: =IFERROR(I231*#REF!,"") | K231: {=INDEX('GLOBAL LOG'!#REF!,ROW()-169+15)} -> #REF! | L231: =_xlfn.XLOOKUP(K231,#REF!,#REF!,"",0,1) -> #REF! | M231: =IFERROR(L231*#REF!,"") | N231: =IFERROR(D231*J231*M231,-1) -> -1 | O231: =IFERROR(E231*J231*M231,-1) -> -1 | P231: =IFERROR(F231*J231*M231,-1) -> -1 | Q231: =IFERROR(G231*J231*M231,-1) -> -1 | S231: Air Transat Consolidation of TotalCare structures | T231: -1 | V231: Air Transat Consolidation of TotalCare structures | W231: -1 | Y231: Air Transat Consolidation of TotalCare structures | Z231: -1 | AB231: Air Transat Consolidation of TotalCare structures | AC231: -1
C232: Mas Air Adding aircraft to the TotalCare - either FSA currently or newly acquired AC | E232: 0 | F232: 0 | G232: =E232+F232 -> 0 | H232: {=INDEX('GLOBAL LOG'!#REF!,ROW()-169+15)} -> #REF! | I232: =_xlfn.XLOOKUP(H232,#REF!,#REF!,"",0,1) -> #REF! | J232: =IFERROR(I232*#REF!,"") | K232: {=INDEX('GLOBAL LOG'!#REF!,ROW()-169+15)} -> #REF! | L232: =_xlfn.XLOOKUP(K232,#REF!,#REF!,"",0,1) -> #REF! | M232: =IFERROR(L232*#REF!,"") | N232: =IFERROR(D232*J232*M232,-1) -> -1 | O232: =IFERROR(E232*J232*M232,-1) -> -1 | P232: =IFERROR(F232*J232*M232,-1) -> -1 | Q232: =IFERROR(G232*J232*M232,-1) -> -1 | S232: Mas Air Adding aircraft to the TotalCare - either FSA currently or newly acquired AC | T232: -1 | V232: Mas Air Adding aircraft to the TotalCare - either FSA currently or newly acquired AC | W232: -1 | Y232: Mas Air Adding aircraft to the TotalCare - either FSA currently or newly acquired AC | Z232: -1 | AB232: Mas Air Adding aircraft to the TotalCare - either FSA currently or newly acquired AC | AC232: -1
C233: Western Air Western Air Limited _ AE3007 _ Extension / Amendment for 2 AC | E233: 0 | F233: 0 | G233: =E233+F233 -> 0 | H233: {=INDEX('GLOBAL LOG'!#REF!,ROW()-169+15)} -> #REF! | I233: =_xlfn.XLOOKUP(H233,#REF!,#REF!,"",0,1) -> #REF! | J233: =IFERROR(I233*#REF!,"") | K233: {=INDEX('GLOBAL LOG'!#REF!,ROW()-169+15)} -> #REF! | L233: =_xlfn.XLOOKUP(K233,#REF!,#REF!,"",0,1) -> #REF! | M233: =IFERROR(L233*#REF!,"") | N233: =IFERROR(D233*J233*M233,-1) -> -1 | O233: =IFERROR(E233*J233*M233,-1) -> -1 | P233: =IFERROR(F233*J233*M233,-1) -> -1 | Q233: =IFERROR(G233*J233*M233,-1) -> -1 | S233: Western Air Western Air Limited _ AE3007 _ Extension / Amendment for 2 AC | T233: -1 | V233: Western Air Western Air Limited _ AE3007 _ Extension / Amendment for 2 AC | W233: -1 | Y233: Western Air Western Air Limited _ AE3007 _ Extension / Amendment for 2 AC | Z233: -1 | AB233: Western Air Western Air Limited _ AE3007 _ Extension / Amendment for 2 AC | AC233: -1
C234: Western Air Western Air Limited _ AE3007 _ Extension for full fleet of 9 | E234: 0 | F234: 0 | G234: =E234+F234 -> 0 | H234: {=INDEX('GLOBAL LOG'!#REF!,ROW()-169+15)} -> #REF! | I234: =_xlfn.XLOOKUP(H234,#REF!,#REF!,"",0,1) -> #REF! | J234: =IFERROR(I234*#REF!,"") | K234: {=INDEX('GLOBAL LOG'!#REF!,ROW()-169+15)} -> #REF! | L234: =_xlfn.XLOOKUP(K234,#REF!,#REF!,"",0,1) -> #REF! | M234: =IFERROR(L234*#REF!,"") | N234: =IFERROR(D234*J234*M234,-1) -> -1 | O234: =IFERROR(E234*J234*M234,-1) -> -1 | P234: =IFERROR(F234*J234*M234,-1) -> -1 | Q234: =IFERROR(G234*J234*M234,-1) -> -1 | S234: Western Air Western Air Limited _ AE3007 _ Extension for full fleet of 9 | T234: -1 | V234: Western Air Western Air Limited _ AE3007 _ Extension for full fleet of 9 | W234: -1 | Y234: Western Air Western Air Limited _ AE3007 _ Extension for full fleet of 9 | Z234: -1 | AB234: Western Air Western Air Limited _ AE3007 _ Extension for full fleet of 9 | AC234: -1
C235: IBC Airways IBC Airways _ AE3007 _ Extension for 1 AC | E235: 0 | F235: 0 | G235: =E235+F235 -> 0 | H235: {=INDEX('GLOBAL LOG'!#REF!,ROW()-169+15)} -> #REF! | I235: =_xlfn.XLOOKUP(H235,#REF!,#REF!,"",0,1) -> #REF! | J235: =IFERROR(I235*#REF!,"") | K235: {=INDEX('GLOBAL LOG'!#REF!,ROW()-169+15)} -> #REF! | L235: =_xlfn.XLOOKUP(K235,#REF!,#REF!,"",0,1) -> #REF! | M235: =IFERROR(L235*#REF!,"") | N235: =IFERROR(D235*J235*M235,-1) -> -1 | O235: =IFERROR(E235*J235*M235,-1) -> -1 | P235: =IFERROR(F235*J235*M235,-1) -> -1 | Q235: =IFERROR(G235*J235*M235,-1) -> -1 | S235: IBC Airways IBC Airways _ AE3007 _ Extension for 1 AC | T235: -1 | V235: IBC Airways IBC Airways _ AE3007 _ Extension for 1 AC | W235: -1 | Y235: IBC Airways IBC Airways _ AE3007 _ Extension for 1 AC | Z235: -1 | AB235: IBC Airways IBC Airways _ AE3007 _ Extension for 1 AC | AC235: -1
C236: Air China Opportunity to increase SPE level on Trent XWB x 2 SPE's at 40% | E236: 5.3 | F236: 3.6 | G236: =E236+F236 -> 8.9 | H236: {=INDEX('GLOBAL LOG'!#REF!,ROW()-169+15)} -> #REF! | I236: =_xlfn.XLOOKUP(H236,#REF!,#REF!,"",0,1) -> #REF! | J236: =IFERROR(I236*#REF!,"") | K236: {=INDEX('GLOBAL LOG'!#REF!,ROW()-169+15)} -> #REF! | L236: =_xlfn.XLOOKUP(K236,#REF!,#REF!,"",0,1) -> #REF! | M236: =IFERROR(L236*#REF!,"") | N236: =IFERROR(D236*J236*M236,-1) -> -1 | O236: =IFERROR(E236*J236*M236,-1) -> -1 | P236: =IFERROR(F236*J236*M236,-1) -> -1 | Q236: =IFERROR(G236*J236*M236,-1) -> -1 | S236: Air China Opportunity to increase SPE level on Trent XWB x 2 SPE's at 40% | T236: -1 | V236: Air China Opportunity to increase SPE level on Trent XWB x 2 SPE's at 40% | W236: -1 | Y236: Air China Opportunity to increase SPE level on Trent XWB x 2 SPE's at 40% | Z236: -1 | AB236: Air China Opportunity to increase SPE level on Trent XWB x 2 SPE's at 40% | AC236: -1
C237: Air France Opporunity to add a 1. XWB-84 Used SPE (Q1 2027) 2. Firm Up six (6) aircraft from existing Options. 3. PAS for A350F based on the volume change (4 to 3 FIRM) of A350F. | E237: 0 | F237: 0 | G237: =E237+F237 -> 0 | H237: {=INDEX('GLOBAL LOG'!#REF!,ROW()-169+15)} -> #REF! | I237: =_xlfn.XLOOKUP(H237,#REF!,#REF!,"",0,1) -> #REF! | J237: =IFERROR(I237*#REF!,"") | K237: {=INDEX('GLOBAL LOG'!#REF!,ROW()-169+15)} -> #REF! | L237: =_xlfn.XLOOKUP(K237,#REF!,#REF!,"",0,1) -> #REF! | M237: =IFERROR(L237*#REF!,"") | N237: =IFERROR(D237*J237*M237,-1) -> -1 | O237: =IFERROR(E237*J237*M237,-1) -> -1 | P237: =IFERROR(F237*J237*M237,-1) -> -1 | Q237: =IFERROR(G237*J237*M237,-1) -> -1 | S237: Air France Opporunity to add a 1. XWB-84 Used SPE (Q1 2027) 2. Firm Up six (6) aircraft from existing Options. 3. PAS for A350F based on the volume change (4 to 3 FIRM) of A350F. | T237: -1 | V237: Air France Opporunity to add a 1. XWB-84 Used SPE (Q1 2027) 2. Firm Up six (6) aircraft from existing Options. 3. PAS for A350F based on the volume change (4 to 3 FIRM) of A350F. | W237: -1 | Y237: Air France Opporunity to add a 1. XWB-84 Used SPE (Q1 2027) 2. Firm Up six (6) aircraft from existing Options. 3. PAS for A350F based on the volume change (4 to 3 FIRM) of A350F. | Z237: -1 | AB237: Air France Opporunity to add a 1. XWB-84 Used SPE (Q1 2027) 2. Firm Up six (6) aircraft from existing Options. 3. PAS for A350F based on the volume change (4 to 3 FIRM) of A350F. | AC237: -1
C238: Air France Opportunity to sell combined PAS to both KLM and Martinair for XWB-84 and XWB-97 due to A350F volume change | E238: 0 | F238: 0 | G238: =E238+F238 -> 0 | H238: {=INDEX('GLOBAL LOG'!#REF!,ROW()-169+15)} -> #REF! | I238: =_xlfn.XLOOKUP(H238,#REF!,#REF!,"",0,1) -> #REF! | J238: =IFERROR(I238*#REF!,"") | K238: {=INDEX('GLOBAL LOG'!#REF!,ROW()-169+15)} -> #REF! | L238: =_xlfn.XLOOKUP(K238,#REF!,#REF!,"",0,1) -> #REF! | M238: =IFERROR(L238*#REF!,"") | N238: =IFERROR(D238*J238*M238,-1) -> -1 | O238: =IFERROR(E238*J238*M238,-1) -> -1 | P238: =IFERROR(F238*J238*M238,-1) -> -1 | Q238: =IFERROR(G238*J238*M238,-1) -> -1 | S238: Air France Opportunity to sell combined PAS to both KLM and Martinair for XWB-84 and XWB-97 due to A350F volume change | T238: -1 | V238: Air France Opportunity to sell combined PAS to both KLM and Martinair for XWB-84 and XWB-97 due to A350F volume change | W238: -1 | Y238: Air France Opportunity to sell combined PAS to both KLM and Martinair for XWB-84 and XWB-97 due to A350F volume change | Z238: -1 | AB238: Air France Opportunity to sell combined PAS to both KLM and Martinair for XWB-84 and XWB-97 due to A350F volume change | AC238: -1
... C261: Japan Airlines SPE #2 - would be in trade for SL2 and net neutral benefit | E261: 0 | F261: 0 | G261: =E261+F261 -> 0 | H261: {=INDEX('GLOBAL LOG'!#REF!,ROW()-169+15)} -> #REF! | I261: =_xlfn.XLOOKUP(H261,#REF!,#REF!,"",0,1) -> #REF! | J261: =IFERROR(I261*#REF!,"") | K261: {=INDEX('GLOBAL LOG'!#REF!,ROW()-169+15)} -> #REF! | L261: =_xlfn.XLOOKUP(K261,#REF!,#REF!,"",0,1) -> #REF! | M261: =IFERROR(L261*#REF!,"") | N261: =IFERROR(D261*J261*M261,-1) -> -1 | O261: =IFERROR(E261*J261*M261,-1) -> -1 | P261: =IFERROR(F261*J261*M261,-1) -> -1 | Q261: =IFERROR(G261*J261*M261,-1) -> -1 | S261: Japan Airlines SPE #2 - would be in trade for SL2 and net neutral benefit | T261: -1 | V261: Japan Airlines SPE #2 - would be in trade for SL2 and net neutral benefit | W261: -1 | Y261: Japan Airlines SPE #2 - would be in trade for SL2 and net neutral benefit | Z261: -1 | AB261: Japan Airlines SPE #2 - would be in trade for SL2 and net neutral benefit | AC261: -1
C262: Japan Airlines 7 yr extension of existing contract (included as option in contract) - Looks like double count vs above row 59 | E262: 3.2 | F262: Harry to confirm | G262: =E262+F262 -> #VALUE! | H262: {=INDEX('GLOBAL LOG'!#REF!,ROW()-169+15)} -> #REF! | I262: =_xlfn.XLOOKUP(H262,#REF!,#REF!,"",0,1) -> #REF! | J262: =IFERROR(I262*#REF!,"") | K262: {=INDEX('GLOBAL LOG'!#REF!,ROW()-169+15)} -> #REF! | L262: =_xlfn.XLOOKUP(K262,#REF!,#REF!,"",0,1) -> #REF! | M262: =IFERROR(L262*#REF!,"") | N262: =IFERROR(D262*J262*M262,-1) -> -1 | O262: =IFERROR(E262*J262*M262,-1) -> -1 | P262: =IFERROR(F262*J262*M262,-1) -> -1 | Q262: =IFERROR(G262*J262*M262,-1) -> -1 | S262: Japan Airlines 7 yr extension of existing contract (included as option in contract) - Looks like double count vs above row 59 | T262: -1 | V262: Japan Airlines 7 yr extension of existing contract (included as option in contract) - Looks like double count vs above row 59 | W262: -1 | Y262: Japan Airlines 7 yr extension of existing contract (included as option in contract) - Looks like double count vs above row 59 | Z262: -1 | AB262: Japan Airlines 7 yr extension of existing contract (included as option in contract) - Looks like double count vs above row 59 | AC262: -1
C263: Air India Flexibility rights - value trade being considered as part of 2025 Campaign for 30+70 | E263: 0 | F263: 0 | G263: =E263+F263 -> 0 | H263: {=INDEX('GLOBAL LOG'!#REF!,ROW()-169+15)} -> #REF! | I263: =_xlfn.XLOOKUP(H263,#REF!,#REF!,"",0,1) -> #REF! | J263: =IFERROR(I263*#REF!,"") | K263: {=INDEX('GLOBAL LOG'!#REF!,ROW()-169+15)} -> #REF! | L263: =_xlfn.XLOOKUP(K263,#REF!,#REF!,"",0,1) -> #REF! | M263: =IFERROR(L263*#REF!,"") | N263: =IFERROR(D263*J263*M263,-1) -> -1 | O263: =IFERROR(E263*J263*M263,-1) -> -1 | P263: =IFERROR(F263*J263*M263,-1) -> -1 | Q263: =IFERROR(G263*J263*M263,-1) -> -1 | S263: Air India Flexibility rights - value trade being considered as part of 2025 Campaign for 30+70 | T263: -1 | V263: Air India Flexibility rights - value trade being considered as part of 2025 Campaign for 30+70 | W263: -1 | Y263: Air India Flexibility rights - value trade being considered as part of 2025 Campaign for 30+70 | Z263: -1 | AB263: Air India Flexibility rights - value trade being considered as part of 2025 Campaign for 30+70 | AC263: -1
C264: Air India £500m credit back held on CRP and is not "real" due to credit back clause. a min term extension or end at next SV would resolve this. | E264: 0 | F264: 0 | G264: =E264+F264 -> 0 | H264: {=INDEX('GLOBAL LOG'!#REF!,ROW()-169+15)} -> #REF! | I264: =_xlfn.XLOOKUP(H264,#REF!,#REF!,"",0,1) -> #REF! | J264: =IFERROR(I264*#REF!,"") | K264: {=INDEX('GLOBAL LOG'!#REF!,ROW()-169+15)} -> #REF! | L264: =_xlfn.XLOOKUP(K264,#REF!,#REF!,"",0,1) -> #REF! | M264: =IFERROR(L264*#REF!,"") | N264: =IFERROR(D264*J264*M264,-1) -> -1 | O264: =IFERROR(E264*J264*M264,-1) -> -1 | P264: =IFERROR(F264*J264*M264,-1) -> -1 | Q264: =IFERROR(G264*J264*M264,-1) -> -1 | S264: Air India £500m credit back held on CRP and is not "real" due to credit back clause. a min term extension or end at next SV would resolve this. | T264: -1 | V264: Air India £500m credit back held on CRP and is not "real" due to credit back clause. a min term extension or end at next SV would resolve this. | W264: -1 | Y264: Air India £500m credit back held on CRP and is not "real" due to credit back clause. a min term extension or end at next SV would resolve this. | Z264: -1 | AB264: Air India £500m credit back held on CRP and is not "real" due to credit back clause. a min term extension or end at next SV would resolve this. | AC264: -1
C265: SAS Group Potential Low probability opportunity to upsell LRU service as there has been some discussion with SAS on this. Lufthansa Technic incumbent LRU service supplier | E265: 0 | F265: 0 | G265: =E265+F265 -> 0 | H265: {=INDEX('GLOBAL LOG'!#REF!,ROW()-169+15)} -> #REF! | I265: =_xlfn.XLOOKUP(H265,#REF!,#REF!,"",0,1) -> #REF! | J265: =IFERROR(I265*#REF!,"") | K265: {=INDEX('GLOBAL LOG'!#REF!,ROW()-169+15)} -> #REF! | L265: =_xlfn.XLOOKUP(K265,#REF!,#REF!,"",0,1) -> #REF! | M265: =IFERROR(L265*#REF!,"") | N265: =IFERROR(D265*J265*M265,-1) -> -1 | O265: =IFERROR(E265*J265*M265,-1) -> -1 | P265: =IFERROR(F265*J265*M265,-1) -> -1 | Q265: =IFERROR(G265*J265*M265,-1) -> -1 | S265: SAS Group Potential Low probability opportunity to upsell LRU service as there has been some discussion with SAS on this. Lufthansa Technic incumbent LRU service supplier | T265: -1 | V265: SAS Group Potential Low probability opportunity to upsell LRU service as there has been some discussion with SAS on this. Lufthansa Technic incumbent LRU service supplier | W265: -1 | Y265: SAS Group Potential Low probability opportunity to upsell LRU service as there has been some discussion with SAS on this. Lufthansa Technic incumbent LRU service supplier | Z265: -1 | AB265: SAS Group Potential Low probability opportunity to upsell LRU service as there has been some discussion with SAS on this. Lufthansa Technic incumbent LRU service supplier | AC265: -1
