Workbook
Name Accounts: [1]INPUT!#REF!
Name Milestones: Table711[]
Name Milestones: #REF!
Name Project_Timeline: #REF!

Sheet L2
C3: OPP LOG SHEET | V3: Hopper | Z3: OPP LOG SHEET | BO3: RESOURCE PRIORITIZATION
V5: ICT Estimates
S6: 45861
V7: Contract
C8: AWAY DAY DATE | E8: 45768
BO9: High Priority | BP9: Med Priority | BQ9: Low Priority | BR9: Not Required
Q10: ICT Evaluations | BO10: 3 | BP10: 2 | BQ10: 1
Q12: SUMS: | S12: =SUM(S15:S99) -> 1834.032 | T12: =SUM(T15:T99) -> 151.85373 | U12: =SUM(U15:U99) -> 218.2044 | V12: =SUM(V15:V99) -> 370.05813 | Z12: Existing Deal | AM12: New Deal | AZ12: Supporting Financial Information | BI12: To Go | BO12: Priority
M13: =SUM($N$15:$N$513) -> 10.73 | N13: =SUM($O$15:$O$513) -> 0 | Z13: Cash Reciepts | AF13: In Year Profit | AM13: Cash Reciepts | AS13: In Year Profit
C14: # | D14: Project | E14: Programme | F14: Customer | G14: Region | H14: Asks | I14: Type of Opportunity | J14: Levers | K14: Priority | L14: SPE related | M14: No,of SPE | N14: CRP% | O14: External Probability | P14: Internal Complexity | Q14: Status | R14: Evaluation Level | S14: Term Benefit | T14: 2026 | U14: 2027 | V14: Sum of 26/27 | Z14: 2025 | AA14: 2026 | AB14: 2027 | AC14: 2028 | AD14: 2029 | AE14: 2030 | AF14: 2025 | AG14: 2026 | AH14: 2027 | AI14: 2028 | AJ14: 2029 | AK14: 2030 | AM14: 2025 | AN14: 2026 | AO14: 2027 | AP14: 2028 | AQ14: 2029 | AR14: 2030 | AS14: 2025 | AT14: 2026 | AU14: 2027 | AV14: 2028 | AW14: 2029 | AX14: 2030 | AZ14: Deal Benefits | BA14: Expected Deal Costs | BB14: In-year Profit Impact | BC14: 5YP Profit Improvement | BD14: Term Profit Imprvement | BE14: Total CRP Term Revnue | BF14: Total CRP Term Margin | BG14: CRP Margin % | BI14: Term Revenue | BJ14: Term Cost | BK14: Term Profit | BO14: Account Management | BP14: Contract Management | BQ14: Service Business | BR14: Business Evalautaion | BS14: Sales & Contracting | BT14: Customer Operations
C15: 1 | D15: {=IF('MEA LOG'!D15:Q100="","",'MEA LOG'!D15:Q100)} -> FiniQ II | E15: Trent XWB-84 | F15: Emirates | G15: MEA | H15: 3 year-extension + LRU Management + 23 a/c | I15: TCA Amendments | J15: XWB MRO - OWS Support - 97k & EP Pricing | K15: 1 | N15: 0 | O15: High | P15: Low | Q15: Completed | S15: =231*1.48 -> 341.88 | V15: =SUM(T15+U15) -> 0 | Y15: 0 | Z15: 0 | AA15: 0 | AB15: 0 | AC15: 0 | AD15: 0 | AE15: 0 | AF15: 0 | AG15: 0 | AH15: 0 | AI15: 0 | AJ15: 0 | AK15: 0 | AL15: 0 | AM15: 0 | AN15: 0 | AO15: 0 | AP15: 0 | AQ15: 0 | AR15: 0 | AS15: 0 | AT15: 0 | AU15: 0 | AV15: 0 | AW15: 0 | AX15: 0 | AZ15: 0 | BA15: 0 | BB15: 0 | BC15: 0 | BD15: 0 | BE15: 0 | BF15: 0 | BI15: 0 | BJ15: 0 | BK15: 0 | BO15: 1 | BP15: 1 | BQ15: 1 | BR15: 1 | BS15: 1 | BT15: 1 | BU15: 1 | BV15: 1 | BW15: 1 | BX15: 1 | BY15: 1 | BZ15: 1 | CA15: 1 | CB15: 1 | CC15: 1 | CD15: 1 | CE15: 1
C16: =C15+1 -> 2 | D16: FiniQ III | E16: Trent XWB-84 | F16: Emirates | G16: MEA | H16: OWS - eliminate $20k remedy | I16: Cost Reduction | J16: New Campaign | K16: 1 | N16: 0 | O16: High | P16: Low | Q16: Contracting | S16: 54 | T16: 0 | U16: 3 | V16: =SUM(T16+U16) -> 3 | Y16: 0 | Z16: 0 | AA16: 0 | AB16: 0 | AC16: 0 | AD16: 0 | AE16: 0 | AF16: 0 | AG16: 0 | AH16: 0 | AI16: 0 | AJ16: 0 | AK16: 0 | AL16: 0 | AM16: 0 | AN16: 0 | AO16: 0 | AP16: 0 | AQ16: 0 | AR16: 0 | AS16: 0 | AT16: 0 | AU16: 0 | AV16: 0 | AW16: 0 | AX16: 0 | AZ16: 0 | BA16: 0 | BB16: 0 | BC16: 0 | BD16: 0 | BE16: 0 | BF16: 0 | BI16: 0 | BJ16: 0 | BK16: 0 | BO16: 1 | BP16: 1 | BQ16: 1 | BR16: 1 | BS16: 1 | BT16: 1 | BU16: 1 | BV16: 1 | BW16: 1 | BX16: 1 | BY16: 1 | BZ16: 1 | CA16: 1 | CB16: 1 | CC16: 1 | CD16: 1 | CE16: 1
C17: =C16+1 -> 3 | D17: IDK | E17: Trent XWB-84 | F17: Emirates | G17: MEA | H17: Additional 3 x SPE (10 %to 12%) | I17: SPE increase | J17: New Campaign | K17: 2 | L17: yes | M17: 3 | N17: 0 | O17: Low | P17: Med | Q17: Hopper | S17: 50 | V17: =SUM(T17+U17) -> 0 | Y17: 0 | Z17: 0 | AA17: 0 | AB17: 0 | AC17: 0 | AD17: 0 | AE17: 0 | AF17: 0 | AG17: 0 | AH17: 0 | AI17: 0 | AJ17: 0 | AK17: 0 | AL17: 0 | AM17: 0 | AN17: 0 | AO17: 0 | AP17: 0 | AQ17: 0 | AR17: 0 | AS17: 0 | AT17: 0 | AU17: 0 | AV17: 0 | AW17: 0 | AX17: 0 | AZ17: 0 | BA17: 0 | BB17: 0 | BC17: 0 | BD17: 0 | BE17: 0 | BF17: 0 | BI17: 0 | BJ17: 0 | BK17: 0 | BO17: 1 | BP17: 1 | BQ17: 1 | BR17: 1 | BS17: 1 | BT17: 1 | BU17: 1 | BV17: 1 | BW17: 1 | BX17: 1 | BY17: 1 | BZ17: 1 | CA17: 1 | CB17: 1 | CC17: 1 | CD17: 1 | CE17: 1
C18: =C17+1 -> 4 | D18: IDK | E18: Trent XWB-84 | F18: Emirates | G18: MEA | H18: Eliminate NDSES Cost via DAT | I18: Cost Reduction | J18: New Campaign/Settlement | K18: 2 | N18: 0 | O18: Med | P18: Med | Q18: ICT | S18: 11.4 | V18: =SUM(T18+U18) -> 0 | Y18: 0 | Z18: 0 | AA18: 0 | AB18: 0 | AC18: 0 | AD18: 0 | AE18: 0 | AF18: 0 | AG18: 0 | AH18: 0 | AI18: 0 | AJ18: 0 | AK18: 0 | AL18: 0 | AM18: 0 | AN18: 0 | AO18: 0 | AP18: 0 | AQ18: 0 | AR18: 0 | AS18: 0 | AT18: 0 | AU18: 0 | AV18: 0 | AW18: 0 | AX18: 0 | AZ18: 0 | BA18: 0 | BB18: 0 | BC18: 0 | BD18: 0 | BE18: 0 | BF18: 0 | BI18: 0 | BJ18: 0 | BK18: 0 | BO18: 1 | BP18: 1 | BQ18: 1 | BR18: 1 | BS18: 1 | BT18: 1 | BU18: 1 | BV18: 1 | BW18: 1 | BX18: 1 | BY18: 1 | BZ18: 1 | CA18: 1 | CB18: 1 | CC18: 1 | CD18: 1 | CE18: 1
C19: =C18+1 -> 5 | D19: IDK | E19: Trent XWB-84 | F19: Emirates | G19: MEA | H19: Increase in escalation from 2% to 3% | I19: TCA Amendments | J19: XWB MRO - OWS Support - 97k & EP Pricing | K19: 2 | N19: 0 | O19: Low | P19: Low | Q19: Hopper | S19: 170 | V19: =SUM(T19+U19) -> 0 | Y19: 0 | Z19: 0 | AA19: 0 | AB19: 0 | AC19: 0 | AD19: 0 | AE19: 0 | AF19: 0 | AG19: 0 | AH19: 0 | AI19: 0 | AJ19: 0 | AK19: 0 | AL19: 0 | AM19: 0 | AN19: 0 | AO19: 0 | AP19: 0 | AQ19: 0 | AR19: 0 | AS19: 0 | AT19: 0 | AU19: 0 | AV19: 0 | AW19: 0 | AX19: 0 | AZ19: 0 | BA19: 0 | BB19: 0 | BC19: 0 | BD19: 0 | BE19: 0 | BF19: 0 | BI19: 0 | BJ19: 0 | BK19: 0 | BO19: 1 | BP19: 1 | BQ19: 1 | BR19: 1 | BS19: 1 | BT19: 1 | BU19: 1 | BV19: 1 | BW19: 1 | BX19: 1 | BY19: 1 | BZ19: 1 | CA19: 1 | CB19: 1 | CC19: 1 | CD19: 1 | CE19: 1
C20: =C19+1 -> 6 | D20: IDK | E20: Trent XWB-84 | F20: Emirates | G20: MEA | H20: Introduce Precedent Matrix | I20: TCA Amendments | J20: XWB MRO - OWS Support - 97k & EP Pricing | K20: 2 | N20: 0 | O20: Low | P20: Med | Q20: Hopper | S20: 50 | V20: =SUM(T20+U20) -> 0 | Y20: 0 | Z20: 0 | AA20: 0 | AB20: 0 | AC20: 0 | AD20: 0 | AE20: 0 | AF20: 0 | AG20: 0 | AH20: 0 | AI20: 0 | AJ20: 0 | AK20: 0 | AL20: 0 | AM20: 0 | AN20: 0 | AO20: 0 | AP20: 0 | AQ20: 0 | AR20: 0 | AS20: 0 | AT20: 0 | AU20: 0 | AV20: 0 | AW20: 0 | AX20: 0 | AZ20: 0 | BA20: 0 | BB20: 0 | BC20: 0 | BD20: 0 | BE20: 0 | BF20: 0 | BI20: 0 | BJ20: 0 | BK20: 0 | BO20: 1 | BP20: 1 | BQ20: 1 | BR20: 1 | BS20: 1 | BT20: 1 | BU20: 1 | BV20: 1 | BW20: 1 | BX20: 1 | BY20: 1 | BZ20: 1 | CA20: 1 | CB20: 1 | CC20: 1 | CD20: 1 | CE20: 1
C21: =C20+1 -> 7 | D21: Selassi | E21: Trent XWB-84 | F21: Ethiopia | G21: MEA | H21: SPE Pull forward | I21: TCA Amendments | J21: AOG Risk | K21: 1 | L21: yes | M21: 1 | N21: 0.49 | O21: Low | P21: Low | Q21: Completed | S21: 10 | T21: 1 | U21: 1 | V21: =SUM(T21+U21) -> 2 | Y21: 0 | Z21: 0 | AA21: 0 | AB21: 0 | AC21: 0 | AD21: 0 | AE21: 0 | AF21: 0 | AG21: 0 | AH21: 0 | AI21: 0 | AJ21: 0 | AK21: 0 | AL21: 0 | AM21: 0 | AN21: 0 | AO21: 0 | AP21: 0 | AQ21: 0 | AR21: 0 | AS21: 0 | AT21: 0 | AU21: 0 | AV21: 0 | AW21: 0 | AX21: 0 | AZ21: 0 | BA21: 0 | BB21: 0 | BC21: 0 | BD21: 0 | BE21: 0 | BF21: 0 | BI21: 0 | BJ21: 0 | BK21: 0
C22: =C21+1 -> 8 | D22: Selassi | E22: Trent XWB-84 | F22: Ethiopia | G22: MEA | H22: Incremental SPE | I22: SPE increase | J22: 2 Addition a/c | K22: 1 | L22: yes | M22: 1 | N22: 0 | O22: High | P22: Low | Q22: Negotiations | S22: 3 | T22: 0 | U22: 3 | V22: 3 | Y22: 0 | Z22: 0 | AA22: 0 | AB22: 0 | AC22: 0 | AD22: 0 | AE22: 0 | AF22: 0 | AG22: 0 | AH22: 0 | AI22: 0 | AJ22: 0 | AK22: 0 | AL22: 0 | AM22: 0 | AN22: 0 | AO22: 0 | AP22: 0 | AQ22: 0 | AR22: 0 | AS22: 0 | AT22: 0 | AU22: 0 | AV22: 0 | AW22: 0 | AX22: 0 | AZ22: 0 | BA22: 0 | BB22: 0 | BC22: 0 | BD22: 0 | BE22: 0 | BF22: 0 | BI22: 0 | BJ22: 0 | BK22: 0
C23: =C22+1 -> 9 | D23: Selassi | E23: Trent 1000 | F23: Ethiopia | G23: MEA | H23: Incremental SPE | I23: SPE increase | J23: Campaign | K23: 1 | L23: yes | N23: 0.54 | O23: Med | P23: Low | Q23: Hopper | S23: 33 | T23: =S23/12 -> 2.75 | U23: =S23/12 -> 2.75 | V23: 5.5 | Y23: 0 | Z23: 0 | AA23: 0 | AB23: 0 | AC23: 0 | AD23: 0 | AE23: 0 | AF23: 0 | AG23: 0 | AH23: 0 | AI23: 0 | AJ23: 0 | AK23: 0 | AL23: 0 | AM23: 0 | AN23: 0 | AO23: 0 | AP23: 0 | AQ23: 0 | AR23: 0 | AS23: 0 | AT23: 0 | AU23: 0 | AV23: 0 | AW23: 0 | AX23: 0 | AZ23: 0 | BA23: 0 | BB23: 0 | BC23: 0 | BD23: 0 | BE23: 0 | BF23: 0 | BI23: 0 | BJ23: 0 | BK23: 0
C24: =C23+1 -> 10 | D24: Selassi | E24: Trent 1000 | F24: Ethiopia | G24: MEA | H24: Min Term Extension (life) | I24: Term Extension | J24: Campaign | K24: 1 | N24: 0.54 | O24: Med | P24: Med | Q24: Hopper | S24: 43 | T24: 5.92 | U24: 0 | V24: =SUM(T24+U24) -> 5.92 | Y24: 0 | Z24: 0 | AA24: 0 | AB24: 0 | AC24: 0 | AD24: 0 | AE24: 0 | AF24: 0 | AG24: 0 | AH24: 0 | AI24: 0 | AJ24: 0 | AK24: 0 | AL24: 0 | AM24: 0 | AN24: 0 | AO24: 0 | AP24: 0 | AQ24: 0 | AR24: 0 | AS24: 0 | AT24: 0 | AU24: 0 | AV24: 0 | AW24: 0 | AX24: 0 | AZ24: 0 | BA24: 0 | BB24: 0 | BC24: 0 | BD24: 0 | BE24: 0 | BF24: 0 | BI24: 0 | BJ24: 0 | BK24: 0
C25: =C24+1 -> 11 | D25: Selassi II | E25: Trent XWB-84 | F25: Ethiopia | G25: MEA | H25: Min Term Extension | I25: Term Extension | J25: Campaign | K25: 1 | N25: 0.49 | O25: Med | P25: Med | Q25: Hopper | S25: 30 | T25: 0 | U25: 30 | V25: =SUM(T25+U25) -> 30 | Y25: 0 | Z25: 0 | AA25: 0 | AB25: 0 | AC25: 0 | AD25: 0 | AE25: 0 | AF25: 0 | AG25: 0 | AH25: 0 | AI25: 0 | AJ25: 0 | AK25: 0 | AL25: 0 | AM25: 0 | AN25: 0 | AO25: 0 | AP25: 0 | AQ25: 0 | AR25: 0 | AS25: 0 | AT25: 0 | AU25: 0 | AV25: 0 | AW25: 0 | AX25: 0 | AZ25: 0 | BA25: 0 | BB25: 0 | BC25: 0 | BD25: 0 | BE25: 0 | BF25: 0 | BI25: 0 | BJ25: 0 | BK25: 0
C26: =C25+1 -> 12 | D26: Selassi II | E26: Trent XWB-84 | F26: Ethiopia | G26: MEA | H26: Increase escalation | I26: TCA Amendments | J26: Campaign | K26: 1 | N26: 0.49 | O26: Low | P26: Low | Q26: Hopper | S26: 11.84 | T26: 0 | U26: 2.368 | V26: =SUM(T26+U26) -> 2.368 | Y26: 0 | Z26: 0 | AA26: 0 | AB26: 0 | AC26: 0 | AD26: 0 | AE26: 0 | AF26: 0 | AG26: 0 | AH26: 0 | AI26: 0 | AJ26: 0 | AK26: 0 | AL26: 0 | AM26: 0 | AN26: 0 | AO26: 0 | AP26: 0 | AQ26: 0 | AR26: 0 | AS26: 0 | AT26: 0 | AU26: 0 | AV26: 0 | AW26: 0 | AX26: 0 | AZ26: 0 | BA26: 0 | BB26: 0 | BC26: 0 | BD26: 0 | BE26: 0 | BF26: 0 | BI26: 0 | BJ26: 0 | BK26: 0
C27: =C26+1 -> 13 | D27: Selassi II | E27: Trent XWB-84 | F27: Ethiopia | G27: MEA | H27: Credit Back Removal | I27: TCA Amendments | J27: Campaign | K27: 1 | N27: 0.49 | O27: Med | P27: Med | Q27: Hopper | S27: 4.44 | T27: 0 | U27: 1.48 | V27: =SUM(T27+U27) -> 1.48 | Y27: 0 | Z27: 0 | AA27: 0 | AB27: 0 | AC27: 0 | AD27: 0 | AE27: 0 | AF27: 0 | AG27: 0 | AH27: 0 | AI27: 0 | AJ27: 0 | AK27: 0 | AL27: 0 | AM27: 0 | AN27: 0 | AO27: 0 | AP27: 0 | AQ27: 0 | AR27: 0 | AS27: 0 | AT27: 0 | AU27: 0 | AV27: 0 | AW27: 0 | AX27: 0 | AZ27: 0 | BA27: 0 | BB27: 0 | BC27: 0 | BD27: 0 | BE27: 0 | BF27: 0 | BI27: 0 | BJ27: 0 | BK27: 0
C28: =C27+1 -> 14 | D28: Burgundy | E28: Trent XWB-97 | F28: Qatar | G28: MEA | H28: SPE Pull-forward | I28: TCA Amendments | J28: Increased SPE Discount | K28: 1 | L28: yes | N28: 0.87 | O28: High | P28: Low | Q28: Completed | S28: 90 | T28: 0 | U28: 0 | V28: =SUM(T28+U28) -> 0 | Y28: 0 | Z28: 0 | AA28: 0 | AB28: 0 | AC28: 0 | AD28: 0 | AE28: 0 | AF28: 0 | AG28: 0 | AH28: 0 | AI28: 0 | AJ28: 0 | AK28: 0 | AL28: 0 | AM28: 0 | AN28: 0 | AO28: 0 | AP28: 0 | AQ28: 0 | AR28: 0 | AS28: 0 | AT28: 0 | AU28: 0 | AV28: 0 | AW28: 0 | AX28: 0 | AZ28: 0 | BA28: 0 | BB28: 0 | BC28: 0 | BD28: 0 | BE28: 0 | BF28: 0 | BI28: 0 | BJ28: 0 | BK28: 0
C29: =C28+1 -> 15 | D29: Burgundy II | E29: Trent XWB-84 | F29: Qatar | G29: MEA | H29: Exit for convenience removal -84 | I29: TCA Amendments | J29: Term Extension | K29: 1 | N29: 0.77 | O29: High | P29: High | Q29: Contracting | S29: 68.08 | T29: 68.08 | U29: 0 | V29: =SUM(T29+U29) -> 68.08 | Y29: 0 | Z29: 0 | AA29: 0 | AB29: 0 | AC29: 0 | AD29: 0 | AE29: 0 | AF29: 0 | AG29: 0 | AH29: 0 | AI29: 0 | AJ29: 0 | AK29: 0 | AL29: 0 | AM29: 0 | AN29: 0 | AO29: 0 | AP29: 0 | AQ29: 0 | AR29: 0 | AS29: 0 | AT29: 0 | AU29: 0 | AV29: 0 | AW29: 0 | AX29: 0 | AZ29: 0 | BA29: 0 | BB29: 0 | BC29: 0 | BD29: 0 | BE29: 0 | BF29: 0 | BI29: 0 | BJ29: 0 | BK29: 0 | BO29: 1 | BP29: 1 | BQ29: 1 | BR29: 1 | BS29: 1 | BT29: 1 | BU29: 1 | BV29: 1 | BW29: 1 | BX29: 1 | BY29: 1 | BZ29: 1 | CA29: 1 | CB29: 1 | CC29: 1 | CD29: 1 | CE29: 1
C30: =C29+1 -> 16 | D30: Burgundy III | E30: Trent XWB-97 | F30: Qatar | G30: MEA | H30: Exit for convenience removal -97 | I30: TCA Amendments | J30: Term Extension | K30: 2 | N30: 0.87 | O30: Low | P30: High | Q30: Hopper | S30: 45.88 | T30: 0 | U30: 45.88 | V30: =SUM(T30+U30) -> 45.88 | Y30: 0 | Z30: 0 | AA30: 0 | AB30: 0 | AC30: 0 | AD30: 0 | AE30: 0 | AF30: 0 | AG30: 0 | AH30: 0 | AI30: 0 | AJ30: 0 | AK30: 0 | AL30: 0 | AM30: 0 | AN30: 0 | AO30: 0 | AP30: 0 | AQ30: 0 | AR30: 0 | AS30: 0 | AT30: 0 | AU30: 0 | AV30: 0 | AW30: 0 | AX30: 0 | AZ30: 0 | BA30: 0 | BB30: 0 | BC30: 0 | BD30: 0 | BE30: 0 | BF30: 0 | BI30: 0 | BJ30: 0 | BK30: 0
C31: =C30+1 -> 17 | D31: QA | E31: Trent 500 | F31: Qatar Amiri | G31: MEA | H31: Sell 1 x SPE | I31: SPE increase | J31: Upsell | K31: 1 | L31: yes | M31: 1 | N31: 0 | O31: Med | P31: Med | Q31: Contracting | S31: 7.5 | T31: 5 | U31: 0 | V31: =SUM(T31+U31) -> 5 | Y31: 0 | Z31: 0 | AA31: 0 | AB31: 0 | AC31: 0 | AD31: 0 | AE31: 0 | AF31: 0 | AG31: 0 | AH31: 0 | AI31: 0 | AJ31: 0 | AK31: 0 | AL31: 0 | AM31: 0 | AN31: 0 | AO31: 0 | AP31: 0 | AQ31: 0 | AR31: 0 | AS31: 0 | AT31: 0 | AU31: 0 | AV31: 0 | AW31: 0 | AX31: 0 | AZ31: 0 | BA31: 0 | BB31: 0 | BC31: 0 | BD31: 0 | BE31: 0 | BF31: 0 | BI31: 0 | BJ31: 0 | BK31: 0
C32: =C31+1 -> 18 | D32: Horus | E32: Trent 1000 | F32: Egypt | G32: MEA | H32: Correct the CRP!! | I32: TCA Amendments | J32: Min Term extension | K32: 2 | N32: 0.18 | O32: Med | P32: Low | Q32: ICT | T32: 0 | U32: 0 | V32: =SUM(T32+U32) -> 0 | Y32: 0 | Z32: 0 | AA32: 0 | AB32: 0 | AC32: 0 | AD32: 0 | AE32: 0 | AF32: 0 | AG32: 0 | AH32: 0 | AI32: 0 | AJ32: 0 | AK32: 0 | AL32: 0 | AM32: 0 | AN32: 0 | AO32: 0 | AP32: 0 | AQ32: 0 | AR32: 0 | AS32: 0 | AT32: 0 | AU32: 0 | AV32: 0 | AW32: 0 | AX32: 0 | AZ32: 0 | BA32: 0 | BB32: 0 | BC32: 0 | BD32: 0 | BE32: 0 | BF32: 0 | BI32: 0 | BJ32: 0 | BK32: 0
C33: =C32+1 -> 19 | D33: Horus II | E33: Trent 700 | F33: Egypt | G33: MEA | H33: Term Extension | I33: Term Extension | J33: Existing Pricing | K33: 1 | N33: 0.11 | O33: High | P33: Med | Q33: ICT | S33: 120 | T33: 3 | U33: 14 | V33: =SUM(T33+U33) -> 17 | Y33: 0 | Z33: 0 | AA33: 0 | AB33: 0 | AC33: 0 | AD33: 0 | AE33: 0 | AF33: 0 | AG33: 0 | AH33: 0 | AI33: 0 | AJ33: 0 | AK33: 0 | AL33: 0 | AM33: 0 | AN33: 0 | AO33: 0 | AP33: 0 | AQ33: 0 | AR33: 0 | AS33: 0 | AT33: 0 | AU33: 0 | AV33: 0 | AW33: 0 | AX33: 0 | AZ33: 0 | BA33: 0 | BB33: 0 | BC33: 0 | BD33: 0 | BE33: 0 | BF33: 0 | BI33: 0 | BJ33: 0 | BK33: 0
C34: =C33+1 -> 20 | D34: Horus III | E34: Trent 1000 | F34: Egypt | G34: MEA | H34: Transportation Service Buy Out | I34: TCA Amendments | K34: 2 | N34: 0.18 | O34: Low | P34: Med | Q34: Cancelled | S34: 138.24 | T34: 0 | U34: 20 | V34: =SUM(T34+U34) -> 20 | Y34: 0 | Z34: 0 | AA34: 0 | AB34: 0 | AC34: 0 | AD34: 0 | AE34: 0 | AF34: 0 | AG34: 0 | AH34: 0 | AI34: 0 | AJ34: 0 | AK34: 0 | AL34: 0 | AM34: 0 | AN34: 0 | AO34: 0 | AP34: 0 | AQ34: 0 | AR34: 0 | AS34: 0 | AT34: 0 | AU34: 0 | AV34: 0 | AW34: 0 | AX34: 0 | AZ34: 0 | BA34: 0 | BB34: 0 | BC34: 0 | BD34: 0 | BE34: 0 | BF34: 0 | BI34: 0 | BJ34: 0 | BK34: 0
C35: =C34+1 -> 21 | D35: Horus IV | E35: Trent XWB-84 | F35: Egypt | G35: MEA | H35: PAS Upsell | I35: Service Upsells | K35: 1 | O35: Low | P35: Low | Q35: Cancelled | S35: 7.2 | T35: 0.6 | U35: 0.6 | V35: =SUM(T35+U35) -> 1.2 | Y35: 0 | Z35: 0 | AA35: 0 | AB35: 0 | AC35: 0 | AD35: 0 | AE35: 0 | AF35: 0 | AG35: 0 | AH35: 0 | AI35: 0 | AJ35: 0 | AK35: 0 | AL35: 0 | AM35: 0 | AN35: 0 | AO35: 0 | AP35: 0 | AQ35: 0 | AR35: 0 | AS35: 0 | AT35: 0 | AU35: 0 | AV35: 0 | AW35: 0 | AX35: 0 | AZ35: 0 | BA35: 0 | BB35: 0 | BC35: 0 | BD35: 0 | BE35: 0 | BF35: 0 | BI35: 0 | BJ35: 0 | BK35: 0
C36: =C35+1 -> 22 | D36: Turk | E36: Trent 700 | F36: Turkmenistan | G36: MEA | H36: SelectCare Upsell | I36: Service Upsells | K36: 2 | O36: Low | P36: Med | Q36: Cancelled | S36: 30 | T36: 0 | U36: 7.5 | V36: =SUM(T36+U36) -> 7.5 | Y36: 0 | Z36: 0 | AA36: 0 | AB36: 0 | AC36: 0 | AD36: 0 | AE36: 0 | AF36: 0 | AG36: 0 | AH36: 0 | AI36: 0 | AJ36: 0 | AK36: 0 | AL36: 0 | AM36: 0 | AN36: 0 | AO36: 0 | AP36: 0 | AQ36: 0 | AR36: 0 | AS36: 0 | AT36: 0 | AU36: 0 | AV36: 0 | AW36: 0 | AX36: 0 | AZ36: 0 | BA36: 0 | BB36: 0 | BC36: 0 | BD36: 0 | BE36: 0 | BF36: 0 | BI36: 0 | BJ36: 0 | BK36: 0
C37: =C36+1 -> 23 | D37: Qanot | E37: Trent 700 | F37: Qanot Sharq | G37: MEA | H37: TCA Life Upsell 2 x A330CEO | I37: New a/c | K37: 2 | O37: Low | P37: Med | Q37: Cancelled | S37: 36 | T37: 0 | U37: 0 | V37: =SUM(T37+U37) -> 0 | Y37: 0 | Z37: 0 | AA37: 0 | AB37: 0 | AC37: 0 | AD37: 0 | AE37: 0 | AF37: 0 | AG37: 0 | AH37: 0 | AI37: 0 | AJ37: 0 | AK37: 0 | AL37: 0 | AM37: 0 | AN37: 0 | AO37: 0 | AP37: 0 | AQ37: 0 | AR37: 0 | AS37: 0 | AT37: 0 | AU37: 0 | AV37: 0 | AW37: 0 | AX37: 0 | AZ37: 0 | BA37: 0 | BB37: 0 | BC37: 0 | BD37: 0 | BE37: 0 | BF37: 0 | BI37: 0 | BJ37: 0 | BK37: 0
C38: =C37+1 -> 24 | D38: SW | E38: RB211-524 | F38: Silkway | G38: MEA | H38: Increase in Green Time by 12k cycles | I38: TCA Amendments | K38: 1 | N38: 0 | O38: Low | P38: High | Q38: Cancelled | S38: 25.2 | T38: 12.6 | U38: 12.6 | V38: =SUM(T38+U38) -> 25.2 | Y38: 0 | Z38: 0 | AA38: 0 | AB38: 0 | AC38: 0 | AD38: 0 | AE38: 0 | AF38: 0 | AG38: 0 | AH38: 0 | AI38: 0 | AJ38: 0 | AK38: 0 | AL38: 0 | AM38: 0 | AN38: 0 | AO38: 0 | AP38: 0 | AQ38: 0 | AR38: 0 | AS38: 0 | AT38: 0 | AU38: 0 | AV38: 0 | AW38: 0 | AX38: 0 | AZ38: 0 | BA38: 0 | BB38: 0 | BC38: 0 | BD38: 0 | BE38: 0 | BF38: 0 | BI38: 0 | BJ38: 0 | BK38: 0 | BO38: 1 | BP38: 1 | BQ38: 1 | BR38: 1 | BS38: 1 | BT38: 1 | BU38: 1 | BV38: 1 | BW38: 1 | BX38: 1 | BY38: 1 | BZ38: 1 | CA38: 1 | CB38: 1 | CC38: 1 | CD38: 1 | CE38: 1
C39: =C38+1 -> 25 | D39: Sen | E39: Trent 7000 | F39: Senegal | G39: MEA | H39: Collect debt | I39: Other | K39: 2 | N39: 0.54 | O39: Low | P39: Med | Q39: Cancelled | S39: 10 | T39: 0 | U39: 10 | V39: =SUM(T39+U39) -> 10 | Y39: 0 | Z39: 0 | AA39: 0 | AB39: 0 | AC39: 0 | AD39: 0 | AE39: 0 | AF39: 0 | AG39: 0 | AH39: 0 | AI39: 0 | AJ39: 0 | AK39: 0 | AL39: 0 | AM39: 0 | AN39: 0 | AO39: 0 | AP39: 0 | AQ39: 0 | AR39: 0 | AS39: 0 | AT39: 0 | AU39: 0 | AV39: 0 | AW39: 0 | AX39: 0 | AZ39: 0 | BA39: 0 | BB39: 0 | BC39: 0 | BD39: 0 | BE39: 0 | BF39: 0 | BI39: 0 | BJ39: 0 | BK39: 0
C40: =C39+1 -> 26 | D40: Viva Algeria | E40: Trent 7000 | F40: Air Algerie | G40: MEA | H40: Additional SPE | I40: SPE increase | K40: 1 | L40: yes | O40: High | P40: Low | Q40: Completed | S40: 20 | T40: 0 | U40: 20 | V40: =SUM(T40+U40) -> 20 | Y40: 0 | Z40: 0 | AA40: 0 | AB40: 0 | AC40: 0 | AD40: 0 | AE40: 0 | AF40: 0 | AG40: 0 | AH40: 0 | AI40: 0 | AJ40: 0 | AK40: 0 | AL40: 0 | AM40: 0 | AN40: 0 | AO40: 0 | AP40: 0 | AQ40: 0 | AR40: 0 | AS40: 0 | AT40: 0 | AU40: 0 | AV40: 0 | AW40: 0 | AX40: 0 | AZ40: 0 | BA40: 0 | BB40: 0 | BC40: 0 | BD40: 0 | BE40: 0 | BF40: 0 | BI40: 0 | BJ40: 0 | BK40: 0
C41: =C40+1 -> 27 | D41: Dhabi I | E41: Trent XWB-97 | F41: Etihad | G41: MEA | H41: TCA Reconciliation (CRP Improvement) | I41: TCA Amendments | K41: 1 | N41: 0.09 | O41: High | P41: Med | Q41: Completed | S41: 60 | T41: 5 | U41: 1 | V41: =SUM(T41+U41) -> 6 | Y41: 0 | Z41: 0 | AA41: 0 | AB41: 0 | AC41: 0 | AD41: 0 | AE41: 0 | AF41: 0 | AG41: 0 | AH41: 0 | AI41: 0 | AJ41: 0 | AK41: 0 | AL41: 0 | AM41: 0 | AN41: 0 | AO41: 0 | AP41: 0 | AQ41: 0 | AR41: 0 | AS41: 0 | AT41: 0 | AU41: 0 | AV41: 0 | AW41: 0 | AX41: 0 | AZ41: 0 | BA41: 0 | BB41: 0 | BC41: 0 | BD41: 0 | BE41: 0 | BF41: 0 | BI41: 0 | BJ41: 0 | BK41: 0
C42: =C41+1 -> 28 | D42: Dhabi II | E42: Trent XWB-97 | F42: Etihad | G42: MEA | H42: Transportation Service Buy Out for first 12 | I42: TCA Amendments | K42: 3 | N42: 0.09 | O42: Low | P42: High | Q42: Hopper | S42: 17.76 | T42: 0 | U42: 1.48 | V42: =SUM(T42+U42) -> 1.48 | Y42: 0 | Z42: 0 | AA42: 0 | AB42: 0 | AC42: 0 | AD42: 0 | AE42: 0 | AF42: 0 | AG42: 0 | AH42: 0 | AI42: 0 | AJ42: 0 | AK42: 0 | AL42: 0 | AM42: 0 | AN42: 0 | AO42: 0 | AP42: 0 | AQ42: 0 | AR42: 0 | AS42: 0 | AT42: 0 | AU42: 0 | AV42: 0 | AW42: 0 | AX42: 0 | AZ42: 0 | BA42: 0 | BB42: 0 | BC42: 0 | BD42: 0 | BE42: 0 | BF42: 0 | BI42: 0 | BJ42: 0 | BK42: 0
C43: =C42+1 -> 29 | D43: Saud | E43: Trent 700 | F43: Saudia | G43: MEA | H43: Regional Fleet NDSES improvement | I43: Cost Reduction | K43: 1 | N43: 0.31 | O43: High | P43: Med | Q43: Completed | T43: 0 | U43: 0 | V43: =SUM(T43+U43) -> 0 | Y43: 0 | Z43: 0 | AA43: 0 | AB43: 0 | AC43: 0 | AD43: 0 | AE43: 0 | AF43: 0 | AG43: 0 | AH43: 0 | AI43: 0 | AJ43: 0 | AK43: 0 | AL43: 0 | AM43: 0 | AN43: 0 | AO43: 0 | AP43: 0 | AQ43: 0 | AR43: 0 | AS43: 0 | AT43: 0 | AU43: 0 | AV43: 0 | AW43: 0 | AX43: 0 | AZ43: 0 | BA43: 0 | BB43: 0 | BC43: 0 | BD43: 0 | BE43: 0 | BF43: 0 | BI43: 0 | BJ43: 0 | BK43: 0
C44: =C43+1 -> 30 | D44: Saud II | E44: Trent 700 | F44: Saudia | G44: MEA | H44: Extend Classic | I44: Term Extension | J44: Term Extension | K44: 2 | N44: 0.29 | O44: Low | P44: Med | Q44: Hopper | S44: 21.46 | T44: 0 | U44: 0 | V44: =SUM(T44+U44) -> 0 | Y44: 0 | Z44: 0 | AA44: 0 | AB44: 0 | AC44: 0 | AD44: 0 | AE44: 0 | AF44: 0 | AG44: 0 | AH44: 0 | AI44: 0 | AJ44: 0 | AK44: 0 | AL44: 0 | AM44: 0 | AN44: 0 | AO44: 0 | AP44: 0 | AQ44: 0 | AR44: 0 | AS44: 0 | AT44: 0 | AU44: 0 | AV44: 0 | AW44: 0 | AX44: 0 | AZ44: 0 | BA44: 0 | BB44: 0 | BC44: 0 | BD44: 0 | BE44: 0 | BF44: 0 | BI44: 0 | BJ44: 0 | BK44: 0
C45: =C44+1 -> 31 | D45: Tanz | E45: Trent 1000 | F45: Tanzania | G45: MEA | H45: Additional SPE | I45: SPE increase | K45: 1 | L45: yes | N45: 0.28 | O45: Med | P45: Low | Q45: Completed | S45: 25 | T45: 25 | V45: =SUM(T45+U45) -> 25 | Y45: 0 | Z45: 0 | AA45: 0 | AB45: 0 | AC45: 0 | AD45: 0 | AE45: 0 | AF45: 0 | AG45: 0 | AH45: 0 | AI45: 0 | AJ45: 0 | AK45: 0 | AL45: 0 | AM45: 0 | AN45: 0 | AO45: 0 | AP45: 0 | AQ45: 0 | AR45: 0 | AS45: 0 | AT45: 0 | AU45: 0 | AV45: 0 | AW45: 0 | AX45: 0 | AZ45: 0 | BA45: 0 | BB45: 0 | BC45: 0 | BD45: 0 | BE45: 0 | BF45: 0 | BI45: 0 | BJ45: 0 | BK45: 0
C46: =C45+1 -> 32 | D46: Tanz | E46: Trent 1000 | F46: Tanzania | G46: MEA | H46: NDSES CRP | I46: Cost Reduction | K46: 1 | N46: 0.28 | O46: Med | P46: Med | Q46: Completed | S46: 3.552 | T46: 0.7104 | U46: 0.7104 | V46: =SUM(T46+U46) -> 1.4208 | Y46: 0 | Z46: 0 | AA46: 0 | AB46: 0 | AC46: 0 | AD46: 0 | AE46: 0 | AF46: 0 | AG46: 0 | AH46: 0 | AI46: 0 | AJ46: 0 | AK46: 0 | AL46: 0 | AM46: 0 | AN46: 0 | AO46: 0 | AP46: 0 | AQ46: 0 | AR46: 0 | AS46: 0 | AT46: 0 | AU46: 0 | AV46: 0 | AW46: 0 | AX46: 0 | AZ46: 0 | BA46: 0 | BB46: 0 | BC46: 0 | BD46: 0 | BE46: 0 | BF46: 0 | BI46: 0 | BJ46: 0 | BK46: 0
C47: =C46+1 -> 33 | D47: Falcon | E47: Trent 1000 | F47: Gulf | G47: MEA | H47: NDSES improvement through SPE sales | I47: Cost Reduction | J47: Resolution of Claims | K47: 1 | N47: 0.38 | O47: Low | P47: Med | Q47: Negotiations | S47: 5.88 | T47: 0.84 | U47: 0.84 | V47: =SUM(T47+U47) -> 1.68 | Y47: 0 | Z47: 0 | AA47: 0 | AB47: 0 | AC47: 0 | AD47: 0 | AE47: 0 | AF47: 0 | AG47: 0 | AH47: 0 | AI47: 0 | AJ47: 0 | AK47: 0 | AL47: 0 | AM47: 0 | AN47: 0 | AO47: 0 | AP47: 0 | AQ47: 0 | AR47: 0 | AS47: 0 | AT47: 0 | AU47: 0 | AV47: 0 | AW47: 0 | AX47: 0 | AZ47: 0 | BA47: 0 | BB47: 0 | BC47: 0 | BD47: 0 | BE47: 0 | BF47: 0 | BI47: 0 | BJ47: 0 | BK47: 0
C48: =C47+1 -> 34 | D48: Falcon | E48: Trent 1000 | F48: Gulf | G48: MEA | H48: 3 Year Extension | I48: Term Extension | J48: Resolution of Claims | K48: 1 | N48: 0.38 | O48: Med | P48: Med | Q48: Negotiations | S48: 50 | T48: 0 | U48: 0 | V48: =SUM(T48+U48) -> 0 | Y48: 0 | Z48: 0 | AA48: 0 | AB48: 0 | AC48: 0 | AD48: 0 | AE48: 0 | AF48: 0 | AG48: 0 | AH48: 0 | AI48: 0 | AJ48: 0 | AK48: 0 | AL48: 0 | AM48: 0 | AN48: 0 | AO48: 0 | AP48: 0 | AQ48: 0 | AR48: 0 | AS48: 0 | AT48: 0 | AU48: 0 | AV48: 0 | AW48: 0 | AX48: 0 | AZ48: 0 | BA48: 0 | BB48: 0 | BC48: 0 | BD48: 0 | BE48: 0 | BF48: 0 | BI48: 0 | BJ48: 0 | BK48: 0
C49: =C48+1 -> 35 | D49: Falcon | E49: Trent 1000 | F49: Gulf | G49: MEA | H49: Additional 2 x A/C | I49: New a/c | J49: Resolution of Claims | K49: 2 | L49: yes | M49: 2 | N49: 0.38 | O49: Low | P49: Med | Q49: Cancelled | S49: 23.04 | T49: =S49/12 -> 1.92 | U49: =S49/12 -> 1.92 | V49: =SUM(T49+U49) -> 3.84 | Y49: 0 | Z49: 0 | AA49: 0 | AB49: 0 | AC49: 0 | AD49: 0 | AE49: 0 | AF49: 0 | AG49: 0 | AH49: 0 | AI49: 0 | AJ49: 0 | AK49: 0 | AL49: 0 | AM49: 0 | AN49: 0 | AO49: 0 | AP49: 0 | AQ49: 0 | AR49: 0 | AS49: 0 | AT49: 0 | AU49: 0 | AV49: 0 | AW49: 0 | AX49: 0 | AZ49: 0 | BA49: 0 | BB49: 0 | BC49: 0 | BD49: 0 | BE49: 0 | BF49: 0 | BI49: 0 | BJ49: 0 | BK49: 0
C50: =C49+1 -> 36 | D50: Star | E50: Trent 1000 | F50: Austral | G50: MEA | H50: TCA Extension/Exit credit trade | I50: Term Extension | J50: Blended TCA Rate | K50: 1 | N50: 0.61 | O50: Med | P50: Med | Q50: Hopper | S50: 10 | T50: 2 | U50: 6 | V50: =SUM(T50+U50) -> 8 | Y50: 0 | Z50: 0 | AA50: 0 | AB50: 0 | AC50: 0 | AD50: 0 | AE50: 0 | AF50: 0 | AG50: 0 | AH50: 0 | AI50: 0 | AJ50: 0 | AK50: 0 | AL50: 0 | AM50: 0 | AN50: 0 | AO50: 0 | AP50: 0 | AQ50: 0 | AR50: 0 | AS50: 0 | AT50: 0 | AU50: 0 | AV50: 0 | AW50: 0 | AX50: 0 | AZ50: 0 | BA50: 0 | BB50: 0 | BC50: 0 | BD50: 0 | BE50: 0 | BF50: 0 | BI50: 0 | BJ50: 0 | BK50: 0
C51: =C50+1 -> 37 | D51: Q8 | E51: Trent 7000 | F51: Kuwait | G51: MEA | H51: Maintain SPE % | I51: SPE increase | J51: Early Exit of a330-800 | K51: 3 | L51: yes | N51: 0.04 | O51: Low | P51: Med | Q51: Hopper | S51: 0 | T51: 0 | U51: 0 | V51: =SUM(T51+U51) -> 0 | Y51: 0 | Z51: 0 | AA51: 0 | AB51: 0 | AC51: 0 | AD51: 0 | AE51: 0 | AF51: 0 | AG51: 0 | AH51: 0 | AI51: 0 | AJ51: 0 | AK51: 0 | AL51: 0 | AM51: 0 | AN51: 0 | AO51: 0 | AP51: 0 | AQ51: 0 | AR51: 0 | AS51: 0 | AT51: 0 | AU51: 0 | AV51: 0 | AW51: 0 | AX51: 0 | AZ51: 0 | BA51: 0 | BB51: 0 | BC51: 0 | BD51: 0 | BE51: 0 | BF51: 0 | BI51: 0 | BJ51: 0 | BK51: 0
C52: =C51+1 -> 38 | D52: Mau | E52: Trent XWB-84 | F52: Mauritus | G52: MEA | H52: Escalation increase | I52: TCA Amendments | K52: 3 | N52: 0.31 | O52: High | P52: Low | Q52: Completed | S52: 1.3 | T52: =S52/3 -> 0.43333333 | U52: 0 | V52: =SUM(T52+U52) -> 0.43333333 | Y52: 0 | Z52: 0 | AA52: 0 | AB52: 0 | AC52: 0 | AD52: 0 | AE52: 0 | AF52: 0 | AG52: 0 | AH52: 0 | AI52: 0 | AJ52: 0 | AK52: 0 | AL52: 0 | AM52: 0 | AN52: 0 | AO52: 0 | AP52: 0 | AQ52: 0 | AR52: 0 | AS52: 0 | AT52: 0 | AU52: 0 | AV52: 0 | AW52: 0 | AX52: 0 | AZ52: 0 | BA52: 0 | BB52: 0 | BC52: 0 | BD52: 0 | BE52: 0 | BF52: 0 | BI52: 0 | BJ52: 0 | BK52: 0
C53: =C52+1 -> 39 | D53: Dodo | E53: Trent 7000 | F53: Mauritus | G53: MEA | H53: Reduce NDSES Cost | I53: Cost Reduction | J53: Termination | K53: 2 | N53: 0.54 | O53: Med | P53: Med | Q53: ICT | S53: 0.38 | T53: 0 | U53: =S53/5 -> 0.076 | V53: =SUM(T53+U53) -> 0.076 | Y53: 0 | Z53: 0 | AA53: 0 | AB53: 0 | AC53: 0 | AD53: 0 | AE53: 0 | AF53: 0 | AG53: 0 | AH53: 0 | AI53: 0 | AJ53: 0 | AK53: 0 | AL53: 0 | AM53: 0 | AN53: 0 | AO53: 0 | AP53: 0 | AQ53: 0 | AR53: 0 | AS53: 0 | AT53: 0 | AU53: 0 | AV53: 0 | AW53: 0 | AX53: 0 | AZ53: 0 | BA53: 0 | BB53: 0 | BC53: 0 | BD53: 0 | BE53: 0 | BF53: 0 | BI53: 0 | BJ53: 0 | BK53: 0
C54: =C53+1 -> 40 | D54: RW | E54: Trent 700 | F54: Rwanda | G54: MEA | H54: Min Term Extension | I54: Term Extension | K54: 3 | N54: 0.19 | O54: Low | P54: Med | Q54: Hopper | S54: 12 | T54: 0 | U54: 0 | V54: =SUM(T54+U54) -> 0 | Y54: 0 | Z54: 0 | AA54: 0 | AB54: 0 | AC54: 0 | AD54: 0 | AE54: 0 | AF54: 0 | AG54: 0 | AH54: 0 | AI54: 0 | AJ54: 0 | AK54: 0 | AL54: 0 | AM54: 0 | AN54: 0 | AO54: 0 | AP54: 0 | AQ54: 0 | AR54: 0 | AS54: 0 | AT54: 0 | AU54: 0 | AV54: 0 | AW54: 0 | AX54: 0 | AZ54: 0 | BA54: 0 | BB54: 0 | BC54: 0 | BD54: 0 | BE54: 0 | BF54: 0 | BI54: 0 | BJ54: 0 | BK54: 0
C55: =C54+1 -> 41 | D55: SAA | E55: Trent 700 | F55: SAA | G55: MEA | H55: Additional 7 X A/C | I55: New a/c | K55: 3 | O55: Med | P55: Med | Q55: Cancelled | S55: 54 | T55: 0 | U55: 0 | V55: =SUM(T55+U55) -> 0 | Y55: 0 | Z55: 0 | AA55: 0 | AB55: 0 | AC55: 0 | AD55: 0 | AE55: 0 | AF55: 0 | AG55: 0 | AH55: 0 | AI55: 0 | AJ55: 0 | AK55: 0 | AL55: 0 | AM55: 0 | AN55: 0 | AO55: 0 | AP55: 0 | AQ55: 0 | AR55: 0 | AS55: 0 | AT55: 0 | AU55: 0 | AV55: 0 | AW55: 0 | AX55: 0 | AZ55: 0 | BA55: 0 | BB55: 0 | BC55: 0 | BD55: 0 | BE55: 0 | BF55: 0 | BI55: 0 | BJ55: 0 | BK55: 0
C56: =C55+1 -> 42 | D56: Star | E56: Trent 1000 | F56: Austral | G56: MEA | H56: Used SPE | I56: SPE increase | J56: Min-term extension | K56: 1 | L56: Med | M56: Med | N56: ICT | O56: Low | P56: Low | Q56: Hopper | S56: 2 | T56: 0 | U56: 0 | V56: =SUM(T56+U56) -> 0 | Y56: 0 | Z56: 0 | AA56: 0 | AB56: 0 | AC56: 0 | AD56: 0 | AE56: 0 | AF56: 0 | AG56: 0 | AH56: 0 | AI56: 0 | AJ56: 0 | AK56: 0 | AL56: 0 | AM56: 0 | AN56: 0 | AO56: 0 | AP56: 0 | AQ56: 0 | AR56: 0 | AS56: 0 | AT56: 0 | AU56: 0 | AV56: 0 | AW56: 0 | AX56: 0 | AZ56: 0 | BA56: 0 | BB56: 0 | BC56: 0 | BD56: 0 | BE56: 0 | BF56: 0 | BI56: 0 | BJ56: 0 | BK56: 0
C57: =C56+1 -> 43 | D57: Horus V | E57: Trent XWB-84 | F57: Egypt | G57: MEA | H57: EP Upsell | I57: Last 6 aircraft | J57: Upsell | K57: 2 | O57: Med | P57: Med | Q57: Hopper | S57: 23 | V57: =SUM(T57+U57) -> 0 | Y57: 0 | Z57: 0 | AA57: 0 | AB57: 0 | AC57: 0 | AD57: 0 | AE57: 0 | AF57: 0 | AG57: 0 | AH57: 0 | AI57: 0 | AJ57: 0 | AK57: 0 | AL57: 0 | AM57: 0 | AN57: 0 | AO57: 0 | AP57: 0 | AQ57: 0 | AR57: 0 | AS57: 0 | AT57: 0 | AU57: 0 | AV57: 0 | AW57: 0 | AX57: 0 | AZ57: 0 | BA57: 0 | BB57: 0 | BC57: 0 | BD57: 0 | BE57: 0 | BF57: 0 | BI57: 0 | BJ57: 0 | BK57: 0
C58: =C57+1 -> 44 | D58: Pantheon | E58: Trent 900 | F58: Emirates | G58: MEA | H58: Retire SLA1 | I58: TCA Amendments | J58: MRO trade | K58: 1 | O58: Med | P58: High | Q58: Hopper | S58: 95 | T58: 0 | U58: 30 | V58: =SUM(T58+U58) -> 30 | Y58: 0 | Z58: 0 | AA58: 0 | AB58: 0 | AC58: 0 | AD58: 0 | AE58: 0 | AF58: 0 | AG58: 0 | AH58: 0 | AI58: 0 | AJ58: 0 | AK58: 0 | AL58: 0 | AM58: 0 | AN58: 0 | AO58: 0 | AP58: 0 | AQ58: 0 | AR58: 0 | AS58: 0 | AT58: 0 | AU58: 0 | AV58: 0 | AW58: 0 | AX58: 0 | AZ58: 0 | BA58: 0 | BB58: 0 | BC58: 0 | BD58: 0 | BE58: 0 | BF58: 0 | BI58: 0 | BJ58: 0 | BK58: 0
C59: =C58+1 -> 45 | D59: Cotton | E59: RB211-524 | F59: Silkway | G59: MEA | H59: Extend Greentime agreement by 12 months | I59: TCA Amendments | J59: Expiry | K59: 1 | O59: High | P59: Med | Q59: ICT | S59: 19 | T59: 17 | U59: 2 | V59: =SUM(T59+U59) -> 19 | Y59: 0 | Z59: 0 | AA59: 0 | AB59: 0 | AC59: 0 | AD59: 0 | AE59: 0 | AF59: 0 | AG59: 0 | AH59: 0 | AI59: 0 | AJ59: 0 | AK59: 0 | AL59: 0 | AM59: 0 | AN59: 0 | AO59: 0 | AP59: 0 | AQ59: 0 | AR59: 0 | AS59: 0 | AT59: 0 | AU59: 0 | AV59: 0 | AW59: 0 | AX59: 0 | AZ59: 0 | BA59: 0 | BB59: 0 | BC59: 0 | BD59: 0 | BE59: 0 | BF59: 0 | BI59: 0 | BJ59: 0 | BK59: 0
C60: =C59+1 -> 46 | V60: =SUM(T60+U60) -> 0 | Y60: 0 | Z60: 0 | AA60: 0 | AB60: 0 | AC60: 0 | AD60: 0 | AE60: 0 | AF60: 0 | AG60: 0 | AH60: 0 | AI60: 0 | AJ60: 0 | AK60: 0 | AL60: 0 | AM60: 0 | AN60: 0 | AO60: 0 | AP60: 0 | AQ60: 0 | AR60: 0 | AS60: 0 | AT60: 0 | AU60: 0 | AV60: 0 | AW60: 0 | AX60: 0 | AZ60: 0 | BA60: 0 | BB60: 0 | BC60: 0 | BD60: 0 | BE60: 0 | BF60: 0 | BI60: 0 | BJ60: 0 | BK60: 0
C61: =C60+1 -> 47 | V61: =SUM(T61+U61) -> 0 | Y61: 0 | Z61: 0 | AA61: 0 | AB61: 0 | AC61: 0 | AD61: 0 | AE61: 0 | AF61: 0 | AG61: 0 | AH61: 0 | AI61: 0 | AJ61: 0 | AK61: 0 | AL61: 0 | AM61: 0 | AN61: 0 | AO61: 0 | AP61: 0 | AQ61: 0 | AR61: 0 | AS61: 0 | AT61: 0 | AU61: 0 | AV61: 0 | AW61: 0 | AX61: 0 | AZ61: 0 | BA61: 0 | BB61: 0 | BC61: 0 | BD61: 0 | BE61: 0 | BF61: 0 | BI61: 0 | BJ61: 0 | BK61: 0
C62: =C61+1 -> 48 | V62: =SUM(T62+U62) -> 0 | Y62: 0 | Z62: 0 | AA62: 0 | AB62: 0 | AC62: 0 | AD62: 0 | AE62: 0 | AF62: 0 | AG62: 0 | AH62: 0 | AI62: 0 | AJ62: 0 | AK62: 0 | AL62: 0 | AM62: 0 | AN62: 0 | AO62: 0 | AP62: 0 | AQ62: 0 | AR62: 0 | AS62: 0 | AT62: 0 | AU62: 0 | AV62: 0 | AW62: 0 | AX62: 0 | AZ62: 0 | BA62: 0 | BB62: 0 | BC62: 0 | BD62: 0 | BE62: 0 | BF62: 0 | BI62: 0 | BJ62: 0 | BK62: 0
C63: =C62+1 -> 49 | V63: =SUM(T63+U63) -> 0 | Y63: 0 | Z63: 0 | AA63: 0 | AB63: 0 | AC63: 0 | AD63: 0 | AE63: 0 | AF63: 0 | AG63: 0 | AH63: 0 | AI63: 0 | AJ63: 0 | AK63: 0 | AL63: 0 | AM63: 0 | AN63: 0 | AO63: 0 | AP63: 0 | AQ63: 0 | AR63: 0 | AS63: 0 | AT63: 0 | AU63: 0 | AV63: 0 | AW63: 0 | AX63: 0 | AZ63: 0 | BA63: 0 | BB63: 0 | BC63: 0 | BD63: 0 | BE63: 0 | BF63: 0 | BI63: 0 | BJ63: 0 | BK63: 0
C64: =C63+1 -> 50 | V64: =SUM(T64+U64) -> 0 | Y64: 0 | Z64: 0 | AA64: 0 | AB64: 0 | AC64: 0 | AD64: 0 | AE64: 0 | AF64: 0 | AG64: 0 | AH64: 0 | AI64: 0 | AJ64: 0 | AK64: 0 | AL64: 0 | AM64: 0 | AN64: 0 | AO64: 0 | AP64: 0 | AQ64: 0 | AR64: 0 | AS64: 0 | AT64: 0 | AU64: 0 | AV64: 0 | AW64: 0 | AX64: 0 | AZ64: 0 | BA64: 0 | BB64: 0 | BC64: 0 | BD64: 0 | BE64: 0 | BF64: 0 | BI64: 0 | BJ64: 0 | BK64: 0
C65: =C64+1 -> 51 | V65: =SUM(T65+U65) -> 0 | Y65: 0 | Z65: 0 | AA65: 0 | AB65: 0 | AC65: 0 | AD65: 0 | AE65: 0 | AF65: 0 | AG65: 0 | AH65: 0 | AI65: 0 | AJ65: 0 | AK65: 0 | AL65: 0 | AM65: 0 | AN65: 0 | AO65: 0 | AP65: 0 | AQ65: 0 | AR65: 0 | AS65: 0 | AT65: 0 | AU65: 0 | AV65: 0 | AW65: 0 | AX65: 0 | AZ65: 0 | BA65: 0 | BB65: 0 | BC65: 0 | BD65: 0 | BE65: 0 | BF65: 0 | BI65: 0 | BJ65: 0 | BK65: 0
C66: =C65+1 -> 52 | V66: =SUM(T66+U66) -> 0 | Y66: 0 | Z66: 0 | AA66: 0 | AB66: 0 | AC66: 0 | AD66: 0 | AE66: 0 | AF66: 0 | AG66: 0 | AH66: 0 | AI66: 0 | AJ66: 0 | AK66: 0 | AL66: 0 | AM66: 0 | AN66: 0 | AO66: 0 | AP66: 0 | AQ66: 0 | AR66: 0 | AS66: 0 | AT66: 0 | AU66: 0 | AV66: 0 | AW66: 0 | AX66: 0 | AZ66: 0 | BA66: 0 | BB66: 0 | BC66: 0 | BD66: 0 | BE66: 0 | BF66: 0 | BI66: 0 | BJ66: 0 | BK66: 0
C67: =C66+1 -> 53 | V67: =SUM(T67+U67) -> 0 | Y67: 0 | Z67: 0 | AA67: 0 | AB67: 0 | AC67: 0 | AD67: 0 | AE67: 0 | AF67: 0 | AG67: 0 | AH67: 0 | AI67: 0 | AJ67: 0 | AK67: 0 | AL67: 0 | AM67: 0 | AN67: 0 | AO67: 0 | AP67: 0 | AQ67: 0 | AR67: 0 | AS67: 0 | AT67: 0 | AU67: 0 | AV67: 0 | AW67: 0 | AX67: 0 | AZ67: 0 | BA67: 0 | BB67: 0 | BC67: 0 | BD67: 0 | BE67: 0 | BF67: 0 | BI67: 0 | BJ67: 0 | BK67: 0
C68: =C67+1 -> 54 | V68: =SUM(T68+U68) -> 0 | Y68: 0 | Z68: 0 | AA68: 0 | AB68: 0 | AC68: 0 | AD68: 0 | AE68: 0 | AF68: 0 | AG68: 0 | AH68: 0 | AI68: 0 | AJ68: 0 | AK68: 0 | AL68: 0 | AM68: 0 | AN68: 0 | AO68: 0 | AP68: 0 | AQ68: 0 | AR68: 0 | AS68: 0 | AT68: 0 | AU68: 0 | AV68: 0 | AW68: 0 | AX68: 0 | AZ68: 0 | BA68: 0 | BB68: 0 | BC68: 0 | BD68: 0 | BE68: 0 | BF68: 0 | BI68: 0 | BJ68: 0 | BK68: 0
C69: =C68+1 -> 55 | V69: =SUM(T69+U69) -> 0 | Y69: 0 | Z69: 0 | AA69: 0 | AB69: 0 | AC69: 0 | AD69: 0 | AE69: 0 | AF69: 0 | AG69: 0 | AH69: 0 | AI69: 0 | AJ69: 0 | AK69: 0 | AL69: 0 | AM69: 0 | AN69: 0 | AO69: 0 | AP69: 0 | AQ69: 0 | AR69: 0 | AS69: 0 | AT69: 0 | AU69: 0 | AV69: 0 | AW69: 0 | AX69: 0 | AZ69: 0 | BA69: 0 | BB69: 0 | BC69: 0 | BD69: 0 | BE69: 0 | BF69: 0 | BI69: 0 | BJ69: 0 | BK69: 0
C70: =C69+1 -> 56 | V70: =SUM(T70+U70) -> 0 | Y70: 0 | Z70: 0 | AA70: 0 | AB70: 0 | AC70: 0 | AD70: 0 | AE70: 0 | AF70: 0 | AG70: 0 | AH70: 0 | AI70: 0 | AJ70: 0 | AK70: 0 | AL70: 0 | AM70: 0 | AN70: 0 | AO70: 0 | AP70: 0 | AQ70: 0 | AR70: 0 | AS70: 0 | AT70: 0 | AU70: 0 | AV70: 0 | AW70: 0 | AX70: 0 | AZ70: 0 | BA70: 0 | BB70: 0 | BC70: 0 | BD70: 0 | BE70: 0 | BF70: 0 | BI70: 0 | BJ70: 0 | BK70: 0
C71: =C70+1 -> 57 | V71: =SUM(T71+U71) -> 0 | Y71: 0 | Z71: 0 | AA71: 0 | AB71: 0 | AC71: 0 | AD71: 0 | AE71: 0 | AF71: 0 | AG71: 0 | AH71: 0 | AI71: 0 | AJ71: 0 | AK71: 0 | AL71: 0 | AM71: 0 | AN71: 0 | AO71: 0 | AP71: 0 | AQ71: 0 | AR71: 0 | AS71: 0 | AT71: 0 | AU71: 0 | AV71: 0 | AW71: 0 | AX71: 0 | AZ71: 0 | BA71: 0 | BB71: 0 | BC71: 0 | BD71: 0 | BE71: 0 | BF71: 0 | BI71: 0 | BJ71: 0 | BK71: 0
... C238: =C237+1 -> 224 | V238: =SUM(T238+U238) -> 0 | Y238: 0 | Z238: 0 | AA238: 0 | AB238: 0 | AC238: 0 | AD238: 0 | AE238: 0 | AF238: 0 | AG238: 0 | AH238: 0 | AI238: 0 | AJ238: 0 | AK238: 0 | AL238: 0 | AM238: 0 | AN238: 0 | AO238: 0 | AP238: 0 | AQ238: 0 | AR238: 0 | AS238: 0 | AT238: 0 | AU238: 0 | AV238: 0 | AW238: 0 | AX238: 0 | AZ238: 0 | BA238: 0 | BB238: 0 | BC238: 0 | BD238: 0 | BE238: 0 | BF238: 0 | BI238: 0 | BJ238: 0 | BK238: 0
C239: 226 | V239: =SUM(T239+U239) -> 0 | Y239: 0 | Z239: 0 | AA239: 0 | AB239: 0 | AC239: 0 | AD239: 0 | AE239: 0 | AF239: 0 | AG239: 0 | AH239: 0 | AI239: 0 | AJ239: 0 | AK239: 0 | AL239: 0 | AM239: 0 | AN239: 0 | AO239: 0 | AP239: 0 | AQ239: 0 | AR239: 0 | AS239: 0 | AT239: 0 | AU239: 0 | AV239: 0 | AW239: 0 | AX239: 0 | AZ239: 0 | BA239: 0 | BB239: 0 | BC239: 0 | BD239: 0 | BE239: 0 | BF239: 0 | BI239: 0 | BJ239: 0 | BK239: 0
C240: 227 | V240: =SUM(T240+U240) -> 0 | Y240: 0 | Z240: 0 | AA240: 0 | AB240: 0 | AC240: 0 | AD240: 0 | AE240: 0 | AF240: 0 | AG240: 0 | AH240: 0 | AI240: 0 | AJ240: 0 | AK240: 0 | AL240: 0 | AM240: 0 | AN240: 0 | AO240: 0 | AP240: 0 | AQ240: 0 | AR240: 0 | AS240: 0 | AT240: 0 | AU240: 0 | AV240: 0 | AW240: 0 | AX240: 0 | AZ240: 0 | BA240: 0 | BB240: 0 | BC240: 0 | BD240: 0 | BE240: 0 | BF240: 0 | BI240: 0 | BJ240: 0 | BK240: 0
C241: 228 | V241: =SUM(T241+U241) -> 0 | Y241: 0 | Z241: 0 | AA241: 0 | AB241: 0 | AC241: 0 | AD241: 0 | AE241: 0 | AF241: 0 | AG241: 0 | AH241: 0 | AI241: 0 | AJ241: 0 | AK241: 0 | AL241: 0 | AM241: 0 | AN241: 0 | AO241: 0 | AP241: 0 | AQ241: 0 | AR241: 0 | AS241: 0 | AT241: 0 | AU241: 0 | AV241: 0 | AW241: 0 | AX241: 0 | AZ241: 0 | BA241: 0 | BB241: 0 | BC241: 0 | BD241: 0 | BE241: 0 | BF241: 0 | BI241: 0 | BJ241: 0 | BK241: 0
C242: 229 | V242: =SUM(T242+U242) -> 0 | Y242: 0 | Z242: 0 | AA242: 0 | AB242: 0 | AC242: 0 | AD242: 0 | AE242: 0 | AF242: 0 | AG242: 0 | AH242: 0 | AI242: 0 | AJ242: 0 | AK242: 0 | AL242: 0 | AM242: 0 | AN242: 0 | AO242: 0 | AP242: 0 | AQ242: 0 | AR242: 0 | AS242: 0 | AT242: 0 | AU242: 0 | AV242: 0 | AW242: 0 | AX242: 0 | AZ242: 0 | BA242: 0 | BB242: 0 | BC242: 0 | BD242: 0 | BE242: 0 | BF242: 0 | BI242: 0 | BJ242: 0 | BK242: 0
C243: 230 | V243: =SUM(T243+U243) -> 0 | Y243: 0 | Z243: 0 | AA243: 0 | AB243: 0 | AC243: 0 | AD243: 0 | AE243: 0 | AF243: 0 | AG243: 0 | AH243: 0 | AI243: 0 | AJ243: 0 | AK243: 0 | AL243: 0 | AM243: 0 | AN243: 0 | AO243: 0 | AP243: 0 | AQ243: 0 | AR243: 0 | AS243: 0 | AT243: 0 | AU243: 0 | AV243: 0 | AW243: 0 | AX243: 0 | AZ243: 0 | BA243: 0 | BB243: 0 | BC243: 0 | BD243: 0 | BE243: 0 | BF243: 0 | BI243: 0 | BJ243: 0 | BK243: 0
C244: 231 | V244: =SUM(T244+U244) -> 0 | Y244: 0 | Z244: 0 | AA244: 0 | AB244: 0 | AC244: 0 | AD244: 0 | AE244: 0 | AF244: 0 | AG244: 0 | AH244: 0 | AI244: 0 | AJ244: 0 | AK244: 0 | AL244: 0 | AM244: 0 | AN244: 0 | AO244: 0 | AP244: 0 | AQ244: 0 | AR244: 0 | AS244: 0 | AT244: 0 | AU244: 0 | AV244: 0 | AW244: 0 | AX244: 0 | AZ244: 0 | BA244: 0 | BB244: 0 | BC244: 0 | BD244: 0 | BE244: 0 | BF244: 0 | BI244: 0 | BJ244: 0 | BK244: 0
C245: 232 | V245: =SUM(T245+U245) -> 0 | Y245: 0 | Z245: 0 | AA245: 0 | AB245: 0 | AC245: 0 | AD245: 0 | AE245: 0 | AF245: 0 | AG245: 0 | AH245: 0 | AI245: 0 | AJ245: 0 | AK245: 0 | AL245: 0 | AM245: 0 | AN245: 0 | AO245: 0 | AP245: 0 | AQ245: 0 | AR245: 0 | AS245: 0 | AT245: 0 | AU245: 0 | AV245: 0 | AW245: 0 | AX245: 0 | AZ245: 0 | BA245: 0 | BB245: 0 | BC245: 0 | BD245: 0 | BE245: 0 | BF245: 0 | BI245: 0 | BJ245: 0 | BK245: 0
C246: 233 | V246: =SUM(T246+U246) -> 0 | Y246: 0 | Z246: 0 | AA246: 0 | AB246: 0 | AC246: 0 | AD246: 0 | AE246: 0 | AF246: 0 | AG246: 0 | AH246: 0 | AI246: 0 | AJ246: 0 | AK246: 0 | AL246: 0 | AM246: 0 | AN246: 0 | AO246: 0 | AP246: 0 | AQ246: 0 | AR246: 0 | AS246: 0 | AT246: 0 | AU246: 0 | AV246: 0 | AW246: 0 | AX246: 0 | AZ246: 0 | BA246: 0 | BB246: 0 | BC246: 0 | BD246: 0 | BE246: 0 | BF246: 0 | BI246: 0 | BJ246: 0 | BK246: 0
C247: 234 | V247: =SUM(T247+U247) -> 0 | Y247: 0 | Z247: 0 | AA247: 0 | AB247: 0 | AC247: 0 | AD247: 0 | AE247: 0 | AF247: 0 | AG247: 0 | AH247: 0 | AI247: 0 | AJ247: 0 | AK247: 0 | AL247: 0 | AM247: 0 | AN247: 0 | AO247: 0 | AP247: 0 | AQ247: 0 | AR247: 0 | AS247: 0 | AT247: 0 | AU247: 0 | AV247: 0 | AW247: 0 | AX247: 0 | AZ247: 0 | BA247: 0 | BB247: 0 | BC247: 0 | BD247: 0 | BE247: 0 | BF247: 0 | BI247: 0 | BJ247: 0 | BK247: 0
C248: 235 | V248: =SUM(T248+U248) -> 0 | Y248: 0 | Z248: 0 | AA248: 0 | AB248: 0 | AC248: 0 | AD248: 0 | AE248: 0 | AF248: 0 | AG248: 0 | AH248: 0 | AI248: 0 | AJ248: 0 | AK248: 0 | AL248: 0 | AM248: 0 | AN248: 0 | AO248: 0 | AP248: 0 | AQ248: 0 | AR248: 0 | AS248: 0 | AT248: 0 | AU248: 0 | AV248: 0 | AW248: 0 | AX248: 0 | AZ248: 0 | BA248: 0 | BB248: 0 | BC248: 0 | BD248: 0 | BE248: 0 | BF248: 0 | BI248: 0 | BJ248: 0 | BK248: 0
C249: 236 | V249: =SUM(T249+U249) -> 0 | Y249: 0 | Z249: 0 | AA249: 0 | AB249: 0 | AC249: 0 | AD249: 0 | AE249: 0 | AF249: 0 | AG249: 0 | AH249: 0 | AI249: 0 | AJ249: 0 | AK249: 0 | AL249: 0 | AM249: 0 | AN249: 0 | AO249: 0 | AP249: 0 | AQ249: 0 | AR249: 0 | AS249: 0 | AT249: 0 | AU249: 0 | AV249: 0 | AW249: 0 | AX249: 0 | AZ249: 0 | BA249: 0 | BB249: 0 | BC249: 0 | BD249: 0 | BE249: 0 | BF249: 0 | BI249: 0 | BJ249: 0 | BK249: 0
C250: 237 | V250: =SUM(T250+U250) -> 0 | Y250: 0 | Z250: 0 | AA250: 0 | AB250: 0 | AC250: 0 | AD250: 0 | AE250: 0 | AF250: 0 | AG250: 0 | AH250: 0 | AI250: 0 | AJ250: 0 | AK250: 0 | AL250: 0 | AM250: 0 | AN250: 0 | AO250: 0 | AP250: 0 | AQ250: 0 | AR250: 0 | AS250: 0 | AT250: 0 | AU250: 0 | AV250: 0 | AW250: 0 | AX250: 0 | AZ250: 0 | BA250: 0 | BB250: 0 | BC250: 0 | BD250: 0 | BE250: 0 | BF250: 0 | BI250: 0 | BJ250: 0 | BK250: 0
... C513: 500 | V513: =SUM(T513+U513) -> 0 | Y513: 0 | Z513: 0 | AA513: 0 | AB513: 0 | AC513: 0 | AD513: 0 | AE513: 0 | AF513: 0 | AG513: 0 | AH513: 0 | AI513: 0 | AJ513: 0 | AK513: 0 | AL513: 0 | AM513: 0 | AN513: 0 | AO513: 0 | AP513: 0 | AQ513: 0 | AR513: 0 | AS513: 0 | AT513: 0 | AU513: 0 | AV513: 0 | AW513: 0 | AX513: 0 | AZ513: 0 | BA513: 0 | BB513: 0 | BC513: 0 | BD513: 0 | BE513: 0 | BF513: 0 | BI513: 0 | BJ513: 0 | BK513: 0

Sheet L3
C3: OPP LOG SHEET | V3: Hopper | Z3: FINANCIAL CRITERIA | BO3: RESOURCE PRIORITIZATION
V5: ICT Estimates
S6: 45861
V7: Contract
C8: AWAY DAY DATE | E8: 45768
BO9: High Priority | BP9: Med Priority | BQ9: Low Priority | BR9: Not Required
Q10: Contracting Actuals | BO10: 3 | BP10: 2 | BQ10: 1
Q12: SUMS: | S12: =SUM(S15:S99) -> 1536.232 | T12: =SUM(T15:T99) -> 159.04607 | U12: =SUM(U15:U99) -> 183.99273 | V12: =SUM(V15:V99) -> 343.0388 | Z12: Existing Deal | AM12: New Deal | AZ12: Supporting Financial Information | BI12: To Go | BO12: Priority
M13: =SUM($N$15:$N$513) -> 10.73 | N13: =SUM($O$15:$O$513) -> 0 | Z13: Cash Reciepts | AF13: In Year Profit | AM13: Cash Reciepts | AS13: In Year Profit
C14: # | D14: Project | E14: Programme | F14: Customer | G14: Region | H14: Asks | I14: Type of Opportunity | J14: Levers | K14: Priority | L14: SPE related | M14: No,of SPE | N14: CRP% | O14: External Probability | P14: Internal Complexity | Q14: Status | R14: Evaluation Level | S14: Term Benefit | T14: 2026 | U14: 2027 | V14: Sum of 26/27 | Z14: 2025 | AA14: 2026 | AB14: 2027 | AC14: 2028 | AD14: 2029 | AE14: 2030 | AF14: 2025 | AG14: 2026 | AH14: 2027 | AI14: 2028 | AJ14: 2029 | AK14: 2030 | AM14: 2025 | AN14: 2026 | AO14: 2027 | AP14: 2028 | AQ14: 2029 | AR14: 2030 | AS14: 2025 | AT14: 2026 | AU14: 2027 | AV14: 2028 | AW14: 2029 | AX14: 2030 | AZ14: Deal Benefits | BA14: Expected Deal Costs | BB14: In-year Profit Impact | BC14: 5YP Profit Improvement | BD14: Term Profit Imprvement | BE14: Total CRP Term Revnue | BF14: Total CRP Term Margin | BG14: CRP Margin % | BI14: Term Revenue | BJ14: Term Cost | BK14: Term Profit | BO14: Account Management | BP14: Contract Management | BQ14: Service Business | BR14: Business Evalautaion | BS14: Sales & Contracting | BT14: Customer Operations
C15: 1 | D15: {=IF('MEA LOG'!D15:Q100="","",'MEA LOG'!D15:Q100)} -> FiniQ II | E15: Trent XWB-84 | F15: Emirates | G15: MEA | H15: 3 year-extension + LRU Management + 23 a/c | I15: TCA Amendments | J15: XWB MRO - OWS Support - 97k & EP Pricing | K15: 1 | N15: 0 | O15: High | P15: Low | Q15: Completed | S15: =231*1.48 -> 341.88 | V15: =SUM(T15+U15) -> 0 | Y15: 0 | Z15: 0 | AA15: 0 | AB15: 0 | AC15: 0 | AD15: 0 | AE15: 0 | AF15: 0 | AG15: 0 | AH15: 0 | AI15: 0 | AJ15: 0 | AK15: 0 | AL15: 0 | AM15: 0 | AN15: 0 | AO15: 0 | AP15: 0 | AQ15: 0 | AR15: 0 | AS15: 0 | AT15: 0 | AU15: 0 | AV15: 0 | AW15: 0 | AX15: 0 | AZ15: 0 | BA15: 0 | BB15: 0 | BC15: 0 | BD15: 0 | BE15: 0 | BF15: 0 | BI15: 0 | BJ15: 0 | BK15: 0 | BO15: 1 | BP15: 1 | BQ15: 1 | BR15: 1 | BS15: 1 | BT15: 1 | BU15: 1 | BV15: 1 | BW15: 1 | BX15: 1 | BY15: 1 | BZ15: 1 | CA15: 1 | CB15: 1 | CC15: 1 | CD15: 1 | CE15: 1
C16: =C15+1 -> 2 | D16: FiniQ III | E16: Trent XWB-84 | F16: Emirates | G16: MEA | H16: OWS - eliminate $20k remedy | I16: Cost Reduction | J16: New Campaign | K16: 1 | N16: 0 | O16: High | P16: Low | Q16: Contracting | S16: 54 | T16: 20.8 | U16: 20.8 | V16: =SUM(T16+U16) -> 41.6 | Y16: 0 | Z16: 0 | AA16: 0 | AB16: 0 | AC16: 0 | AD16: 0 | AE16: 0 | AF16: 0 | AG16: 0 | AH16: 0 | AI16: 0 | AJ16: 0 | AK16: 0 | AL16: 0 | AM16: 0 | AN16: 0 | AO16: 0 | AP16: 0 | AQ16: 0 | AR16: 0 | AS16: 0 | AT16: 0 | AU16: 0 | AV16: 0 | AW16: 0 | AX16: 0 | AZ16: 0 | BA16: 0 | BB16: 0 | BC16: 0 | BD16: 0 | BE16: 0 | BF16: 0 | BI16: 0 | BJ16: 0 | BK16: 0 | BO16: 1 | BP16: 1 | BQ16: 1 | BR16: 1 | BS16: 1 | BT16: 1 | BU16: 1 | BV16: 1 | BW16: 1 | BX16: 1 | BY16: 1 | BZ16: 1 | CA16: 1 | CB16: 1 | CC16: 1 | CD16: 1 | CE16: 1
C17: =C16+1 -> 3 | D17: IDK | E17: Trent XWB-84 | F17: Emirates | G17: MEA | H17: Additional 3 x SPE (10 %to 12%) | I17: SPE increase | J17: New Campaign | K17: 2 | L17: yes | M17: 3 | N17: 0 | O17: Low | P17: Med | Q17: Hopper | S17: 50 | V17: =SUM(T17+U17) -> 0 | Y17: 0 | Z17: 0 | AA17: 0 | AB17: 0 | AC17: 0 | AD17: 0 | AE17: 0 | AF17: 0 | AG17: 0 | AH17: 0 | AI17: 0 | AJ17: 0 | AK17: 0 | AL17: 0 | AM17: 0 | AN17: 0 | AO17: 0 | AP17: 0 | AQ17: 0 | AR17: 0 | AS17: 0 | AT17: 0 | AU17: 0 | AV17: 0 | AW17: 0 | AX17: 0 | AZ17: 0 | BA17: 0 | BB17: 0 | BC17: 0 | BD17: 0 | BE17: 0 | BF17: 0 | BI17: 0 | BJ17: 0 | BK17: 0 | BO17: 1 | BP17: 1 | BQ17: 1 | BR17: 1 | BS17: 1 | BT17: 1 | BU17: 1 | BV17: 1 | BW17: 1 | BX17: 1 | BY17: 1 | BZ17: 1 | CA17: 1 | CB17: 1 | CC17: 1 | CD17: 1 | CE17: 1
C18: =C17+1 -> 4 | D18: IDK | E18: Trent XWB-84 | F18: Emirates | G18: MEA | H18: Eliminate NDSES Cost via DAT | I18: Cost Reduction | J18: New Campaign/Settlement | K18: 2 | N18: 0 | O18: Med | P18: Med | Q18: ICT | S18: 11.4 | V18: =SUM(T18+U18) -> 0 | Y18: 0 | Z18: 0 | AA18: 0 | AB18: 0 | AC18: 0 | AD18: 0 | AE18: 0 | AF18: 0 | AG18: 0 | AH18: 0 | AI18: 0 | AJ18: 0 | AK18: 0 | AL18: 0 | AM18: 0 | AN18: 0 | AO18: 0 | AP18: 0 | AQ18: 0 | AR18: 0 | AS18: 0 | AT18: 0 | AU18: 0 | AV18: 0 | AW18: 0 | AX18: 0 | AZ18: 0 | BA18: 0 | BB18: 0 | BC18: 0 | BD18: 0 | BE18: 0 | BF18: 0 | BI18: 0 | BJ18: 0 | BK18: 0 | BO18: 1 | BP18: 1 | BQ18: 1 | BR18: 1 | BS18: 1 | BT18: 1 | BU18: 1 | BV18: 1 | BW18: 1 | BX18: 1 | BY18: 1 | BZ18: 1 | CA18: 1 | CB18: 1 | CC18: 1 | CD18: 1 | CE18: 1
C19: =C18+1 -> 5 | D19: IDK | E19: Trent XWB-84 | F19: Emirates | G19: MEA | H19: Increase in escalation from 2% to 3% | I19: TCA Amendments | J19: XWB MRO - OWS Support - 97k & EP Pricing | K19: 2 | N19: 0 | O19: Low | P19: Low | Q19: Hopper | S19: 170 | V19: =SUM(T19+U19) -> 0 | Y19: 0 | Z19: 0 | AA19: 0 | AB19: 0 | AC19: 0 | AD19: 0 | AE19: 0 | AF19: 0 | AG19: 0 | AH19: 0 | AI19: 0 | AJ19: 0 | AK19: 0 | AL19: 0 | AM19: 0 | AN19: 0 | AO19: 0 | AP19: 0 | AQ19: 0 | AR19: 0 | AS19: 0 | AT19: 0 | AU19: 0 | AV19: 0 | AW19: 0 | AX19: 0 | AZ19: 0 | BA19: 0 | BB19: 0 | BC19: 0 | BD19: 0 | BE19: 0 | BF19: 0 | BI19: 0 | BJ19: 0 | BK19: 0 | BO19: 1 | BP19: 1 | BQ19: 1 | BR19: 1 | BS19: 1 | BT19: 1 | BU19: 1 | BV19: 1 | BW19: 1 | BX19: 1 | BY19: 1 | BZ19: 1 | CA19: 1 | CB19: 1 | CC19: 1 | CD19: 1 | CE19: 1
C20: =C19+1 -> 6 | D20: IDK | E20: Trent XWB-84 | F20: Emirates | G20: MEA | H20: Introduce Precedent Matrix | I20: TCA Amendments | J20: XWB MRO - OWS Support - 97k & EP Pricing | K20: 2 | N20: 0 | O20: Low | P20: Med | Q20: Hopper | S20: 50 | V20: =SUM(T20+U20) -> 0 | Y20: 0 | Z20: 0 | AA20: 0 | AB20: 0 | AC20: 0 | AD20: 0 | AE20: 0 | AF20: 0 | AG20: 0 | AH20: 0 | AI20: 0 | AJ20: 0 | AK20: 0 | AL20: 0 | AM20: 0 | AN20: 0 | AO20: 0 | AP20: 0 | AQ20: 0 | AR20: 0 | AS20: 0 | AT20: 0 | AU20: 0 | AV20: 0 | AW20: 0 | AX20: 0 | AZ20: 0 | BA20: 0 | BB20: 0 | BC20: 0 | BD20: 0 | BE20: 0 | BF20: 0 | BI20: 0 | BJ20: 0 | BK20: 0 | BO20: 1 | BP20: 1 | BQ20: 1 | BR20: 1 | BS20: 1 | BT20: 1 | BU20: 1 | BV20: 1 | BW20: 1 | BX20: 1 | BY20: 1 | BZ20: 1 | CA20: 1 | CB20: 1 | CC20: 1 | CD20: 1 | CE20: 1
C21: =C20+1 -> 7 | D21: Selassi | E21: Trent XWB-84 | F21: Ethiopia | G21: MEA | H21: SPE Pull forward | I21: TCA Amendments | J21: AOG Risk | K21: 1 | L21: yes | M21: 1 | N21: 0.49 | O21: Low | P21: Low | Q21: Completed | S21: 10 | T21: 1 | U21: 1 | V21: =SUM(T21+U21) -> 2 | Y21: 0 | Z21: 0 | AA21: 0 | AB21: 0 | AC21: 0 | AD21: 0 | AE21: 0 | AF21: 0 | AG21: 0 | AH21: 0 | AI21: 0 | AJ21: 0 | AK21: 0 | AL21: 0 | AM21: 0 | AN21: 0 | AO21: 0 | AP21: 0 | AQ21: 0 | AR21: 0 | AS21: 0 | AT21: 0 | AU21: 0 | AV21: 0 | AW21: 0 | AX21: 0 | AZ21: 0 | BA21: 0 | BB21: 0 | BC21: 0 | BD21: 0 | BE21: 0 | BF21: 0 | BI21: 0 | BJ21: 0 | BK21: 0
C22: =C21+1 -> 8 | D22: Selassi | E22: Trent XWB-84 | F22: Ethiopia | G22: MEA | H22: Incremental SPE | I22: SPE increase | J22: 2 Addition a/c | K22: 1 | L22: yes | M22: 1 | N22: 0 | O22: High | P22: Low | Q22: Negotiations | S22: 0 | T22: 0 | U22: 0 | V22: 0 | Y22: 0 | Z22: 0 | AA22: 0 | AB22: 0 | AC22: 0 | AD22: 0 | AE22: 0 | AF22: 0 | AG22: 0 | AH22: 0 | AI22: 0 | AJ22: 0 | AK22: 0 | AL22: 0 | AM22: 0 | AN22: 0 | AO22: 0 | AP22: 0 | AQ22: 0 | AR22: 0 | AS22: 0 | AT22: 0 | AU22: 0 | AV22: 0 | AW22: 0 | AX22: 0 | AZ22: 0 | BA22: 0 | BB22: 0 | BC22: 0 | BD22: 0 | BE22: 0 | BF22: 0 | BI22: 0 | BJ22: 0 | BK22: 0
C23: =C22+1 -> 9 | D23: Selassi | E23: Trent 1000 | F23: Ethiopia | G23: MEA | H23: Incremental SPE | I23: SPE increase | J23: Campaign | K23: 1 | L23: yes | N23: 0.54 | O23: Med | P23: Low | Q23: Hopper | S23: 33 | T23: =S23/12 -> 2.75 | U23: =S23/12 -> 2.75 | V23: 5.5 | Y23: 0 | Z23: 0 | AA23: 0 | AB23: 0 | AC23: 0 | AD23: 0 | AE23: 0 | AF23: 0 | AG23: 0 | AH23: 0 | AI23: 0 | AJ23: 0 | AK23: 0 | AL23: 0 | AM23: 0 | AN23: 0 | AO23: 0 | AP23: 0 | AQ23: 0 | AR23: 0 | AS23: 0 | AT23: 0 | AU23: 0 | AV23: 0 | AW23: 0 | AX23: 0 | AZ23: 0 | BA23: 0 | BB23: 0 | BC23: 0 | BD23: 0 | BE23: 0 | BF23: 0 | BI23: 0 | BJ23: 0 | BK23: 0
C24: =C23+1 -> 10 | D24: Selassi | E24: Trent 1000 | F24: Ethiopia | G24: MEA | H24: Min Term Extension (life) | I24: Term Extension | J24: Campaign | K24: 1 | N24: 0.54 | O24: Med | P24: Med | Q24: Hopper | S24: 43 | T24: 5.92 | U24: 0 | V24: =SUM(T24+U24) -> 5.92 | Y24: 0 | Z24: 0 | AA24: 0 | AB24: 0 | AC24: 0 | AD24: 0 | AE24: 0 | AF24: 0 | AG24: 0 | AH24: 0 | AI24: 0 | AJ24: 0 | AK24: 0 | AL24: 0 | AM24: 0 | AN24: 0 | AO24: 0 | AP24: 0 | AQ24: 0 | AR24: 0 | AS24: 0 | AT24: 0 | AU24: 0 | AV24: 0 | AW24: 0 | AX24: 0 | AZ24: 0 | BA24: 0 | BB24: 0 | BC24: 0 | BD24: 0 | BE24: 0 | BF24: 0 | BI24: 0 | BJ24: 0 | BK24: 0
C25: =C24+1 -> 11 | D25: Selassi II | E25: Trent XWB-84 | F25: Ethiopia | G25: MEA | H25: Min Term Extension | I25: Term Extension | J25: Campaign | K25: 1 | N25: 0.49 | O25: Med | P25: Med | Q25: Hopper | S25: 30 | T25: 0 | U25: 30 | V25: =SUM(T25+U25) -> 30 | Y25: 0 | Z25: 0 | AA25: 0 | AB25: 0 | AC25: 0 | AD25: 0 | AE25: 0 | AF25: 0 | AG25: 0 | AH25: 0 | AI25: 0 | AJ25: 0 | AK25: 0 | AL25: 0 | AM25: 0 | AN25: 0 | AO25: 0 | AP25: 0 | AQ25: 0 | AR25: 0 | AS25: 0 | AT25: 0 | AU25: 0 | AV25: 0 | AW25: 0 | AX25: 0 | AZ25: 0 | BA25: 0 | BB25: 0 | BC25: 0 | BD25: 0 | BE25: 0 | BF25: 0 | BI25: 0 | BJ25: 0 | BK25: 0
C26: =C25+1 -> 12 | D26: Selassi II | E26: Trent XWB-84 | F26: Ethiopia | G26: MEA | H26: Increase escalation | I26: TCA Amendments | J26: Campaign | K26: 1 | N26: 0.49 | O26: Low | P26: Low | Q26: Hopper | S26: 11.84 | T26: 2.368 | U26: 2.368 | V26: =SUM(T26+U26) -> 4.736 | Y26: 0 | Z26: 0 | AA26: 0 | AB26: 0 | AC26: 0 | AD26: 0 | AE26: 0 | AF26: 0 | AG26: 0 | AH26: 0 | AI26: 0 | AJ26: 0 | AK26: 0 | AL26: 0 | AM26: 0 | AN26: 0 | AO26: 0 | AP26: 0 | AQ26: 0 | AR26: 0 | AS26: 0 | AT26: 0 | AU26: 0 | AV26: 0 | AW26: 0 | AX26: 0 | AZ26: 0 | BA26: 0 | BB26: 0 | BC26: 0 | BD26: 0 | BE26: 0 | BF26: 0 | BI26: 0 | BJ26: 0 | BK26: 0
C27: =C26+1 -> 13 | D27: Selassi II | E27: Trent XWB-84 | F27: Ethiopia | G27: MEA | H27: Credit Back Removal | I27: TCA Amendments | J27: Campaign | K27: 1 | N27: 0.49 | O27: Med | P27: Med | Q27: Hopper | S27: 4.44 | T27: 1.48 | U27: 1.48 | V27: =SUM(T27+U27) -> 2.96 | Y27: 0 | Z27: 0 | AA27: 0 | AB27: 0 | AC27: 0 | AD27: 0 | AE27: 0 | AF27: 0 | AG27: 0 | AH27: 0 | AI27: 0 | AJ27: 0 | AK27: 0 | AL27: 0 | AM27: 0 | AN27: 0 | AO27: 0 | AP27: 0 | AQ27: 0 | AR27: 0 | AS27: 0 | AT27: 0 | AU27: 0 | AV27: 0 | AW27: 0 | AX27: 0 | AZ27: 0 | BA27: 0 | BB27: 0 | BC27: 0 | BD27: 0 | BE27: 0 | BF27: 0 | BI27: 0 | BJ27: 0 | BK27: 0
C28: =C27+1 -> 14 | D28: Burgundy | E28: Trent XWB-97 | F28: Qatar | G28: MEA | H28: SPE Pull-forward | I28: TCA Amendments | J28: Increased SPE Discount | K28: 1 | L28: yes | N28: 0.87 | O28: High | P28: Low | Q28: Completed | S28: 90 | T28: 0 | U28: 0 | V28: =SUM(T28+U28) -> 0 | Y28: 0 | Z28: 0 | AA28: 0 | AB28: 0 | AC28: 0 | AD28: 0 | AE28: 0 | AF28: 0 | AG28: 0 | AH28: 0 | AI28: 0 | AJ28: 0 | AK28: 0 | AL28: 0 | AM28: 0 | AN28: 0 | AO28: 0 | AP28: 0 | AQ28: 0 | AR28: 0 | AS28: 0 | AT28: 0 | AU28: 0 | AV28: 0 | AW28: 0 | AX28: 0 | AZ28: 0 | BA28: 0 | BB28: 0 | BC28: 0 | BD28: 0 | BE28: 0 | BF28: 0 | BI28: 0 | BJ28: 0 | BK28: 0
C29: =C28+1 -> 15 | D29: Burgundy II | E29: Trent XWB-84 | F29: Qatar | G29: MEA | H29: Exit for convenience removal -84 | I29: TCA Amendments | J29: Term Extension | K29: 1 | N29: 0.77 | O29: High | P29: High | Q29: Contracting | S29: 68.08 | T29: 68.08 | U29: 0 | V29: =SUM(T29+U29) -> 68.08 | Y29: 0 | Z29: 0 | AA29: 0 | AB29: 0 | AC29: 0 | AD29: 0 | AE29: 0 | AF29: 0 | AG29: 0 | AH29: 0 | AI29: 0 | AJ29: 0 | AK29: 0 | AL29: 0 | AM29: 0 | AN29: 0 | AO29: 0 | AP29: 0 | AQ29: 0 | AR29: 0 | AS29: 0 | AT29: 0 | AU29: 0 | AV29: 0 | AW29: 0 | AX29: 0 | AZ29: 0 | BA29: 0 | BB29: 0 | BC29: 0 | BD29: 0 | BE29: 0 | BF29: 0 | BI29: 0 | BJ29: 0 | BK29: 0 | BO29: 1 | BP29: 1 | BQ29: 1 | BR29: 1 | BS29: 1 | BT29: 1 | BU29: 1 | BV29: 1 | BW29: 1 | BX29: 1 | BY29: 1 | BZ29: 1 | CA29: 1 | CB29: 1 | CC29: 1 | CD29: 1 | CE29: 1
C30: =C29+1 -> 16 | D30: Burgundy III | E30: Trent XWB-97 | F30: Qatar | G30: MEA | H30: Exit for convenience removal -97 | I30: TCA Amendments | J30: Term Extension | K30: 2 | N30: 0.87 | O30: Low | P30: High | Q30: Hopper | S30: 45.88 | T30: 0 | U30: 45.88 | V30: =SUM(T30+U30) -> 45.88 | Y30: 0 | Z30: 0 | AA30: 0 | AB30: 0 | AC30: 0 | AD30: 0 | AE30: 0 | AF30: 0 | AG30: 0 | AH30: 0 | AI30: 0 | AJ30: 0 | AK30: 0 | AL30: 0 | AM30: 0 | AN30: 0 | AO30: 0 | AP30: 0 | AQ30: 0 | AR30: 0 | AS30: 0 | AT30: 0 | AU30: 0 | AV30: 0 | AW30: 0 | AX30: 0 | AZ30: 0 | BA30: 0 | BB30: 0 | BC30: 0 | BD30: 0 | BE30: 0 | BF30: 0 | BI30: 0 | BJ30: 0 | BK30: 0
C31: =C30+1 -> 17 | D31: QA | E31: Trent 500 | F31: Qatar Amiri | G31: MEA | H31: Sell 1 x SPE | I31: SPE increase | J31: Upsell | K31: 1 | L31: yes | M31: 1 | N31: 0 | O31: Med | P31: Med | Q31: Contracting | S31: 7.5 | T31: 5 | U31: 0 | V31: =SUM(T31+U31) -> 5 | Y31: 0 | Z31: 0 | AA31: 0 | AB31: 0 | AC31: 0 | AD31: 0 | AE31: 0 | AF31: 0 | AG31: 0 | AH31: 0 | AI31: 0 | AJ31: 0 | AK31: 0 | AL31: 0 | AM31: 0 | AN31: 0 | AO31: 0 | AP31: 0 | AQ31: 0 | AR31: 0 | AS31: 0 | AT31: 0 | AU31: 0 | AV31: 0 | AW31: 0 | AX31: 0 | AZ31: 0 | BA31: 0 | BB31: 0 | BC31: 0 | BD31: 0 | BE31: 0 | BF31: 0 | BI31: 0 | BJ31: 0 | BK31: 0
C32: =C31+1 -> 18 | D32: Horus | E32: Trent 1000 | F32: Egypt | G32: MEA | H32: Correct the CRP!! | I32: TCA Amendments | J32: Min Term extension | K32: 2 | N32: 0.18 | O32: Med | P32: Low | Q32: ICT | S32: 0 | T32: 0 | U32: 0 | V32: =SUM(T32+U32) -> 0 | Y32: 0 | Z32: 0 | AA32: 0 | AB32: 0 | AC32: 0 | AD32: 0 | AE32: 0 | AF32: 0 | AG32: 0 | AH32: 0 | AI32: 0 | AJ32: 0 | AK32: 0 | AL32: 0 | AM32: 0 | AN32: 0 | AO32: 0 | AP32: 0 | AQ32: 0 | AR32: 0 | AS32: 0 | AT32: 0 | AU32: 0 | AV32: 0 | AW32: 0 | AX32: 0 | AZ32: 0 | BA32: 0 | BB32: 0 | BC32: 0 | BD32: 0 | BE32: 0 | BF32: 0 | BI32: 0 | BJ32: 0 | BK32: 0
C33: =C32+1 -> 19 | D33: Horus II | E33: Trent 700 | F33: Egypt | G33: MEA | H33: Term Extension | I33: Term Extension | J33: Existing Pricing | K33: 1 | N33: 0.11 | O33: High | P33: Med | Q33: ICT | S33: 7.4 | T33: 0 | U33: 0 | V33: =SUM(T33+U33) -> 0 | Y33: 0 | Z33: 0 | AA33: 0 | AB33: 0 | AC33: 0 | AD33: 0 | AE33: 0 | AF33: 0 | AG33: 0 | AH33: 0 | AI33: 0 | AJ33: 0 | AK33: 0 | AL33: 0 | AM33: 0 | AN33: 0 | AO33: 0 | AP33: 0 | AQ33: 0 | AR33: 0 | AS33: 0 | AT33: 0 | AU33: 0 | AV33: 0 | AW33: 0 | AX33: 0 | AZ33: 0 | BA33: 0 | BB33: 0 | BC33: 0 | BD33: 0 | BE33: 0 | BF33: 0 | BI33: 0 | BJ33: 0 | BK33: 0
C34: =C33+1 -> 20 | D34: Horus III | E34: Trent 1000 | F34: Egypt | G34: MEA | H34: Transportation Service Buy Out | I34: TCA Amendments | K34: 2 | N34: 0.18 | O34: Low | P34: Med | Q34: Cancelled | S34: 138.24 | T34: 0 | U34: 20 | V34: =SUM(T34+U34) -> 20 | Y34: 0 | Z34: 0 | AA34: 0 | AB34: 0 | AC34: 0 | AD34: 0 | AE34: 0 | AF34: 0 | AG34: 0 | AH34: 0 | AI34: 0 | AJ34: 0 | AK34: 0 | AL34: 0 | AM34: 0 | AN34: 0 | AO34: 0 | AP34: 0 | AQ34: 0 | AR34: 0 | AS34: 0 | AT34: 0 | AU34: 0 | AV34: 0 | AW34: 0 | AX34: 0 | AZ34: 0 | BA34: 0 | BB34: 0 | BC34: 0 | BD34: 0 | BE34: 0 | BF34: 0 | BI34: 0 | BJ34: 0 | BK34: 0
C35: =C34+1 -> 21 | D35: Horus IV | E35: Trent XWB-84 | F35: Egypt | G35: MEA | H35: PAS Upsell | I35: Service Upsells | K35: 1 | O35: Low | P35: Low | Q35: Cancelled | S35: 7.2 | T35: 0.6 | U35: 0.6 | V35: =SUM(T35+U35) -> 1.2 | Y35: 0 | Z35: 0 | AA35: 0 | AB35: 0 | AC35: 0 | AD35: 0 | AE35: 0 | AF35: 0 | AG35: 0 | AH35: 0 | AI35: 0 | AJ35: 0 | AK35: 0 | AL35: 0 | AM35: 0 | AN35: 0 | AO35: 0 | AP35: 0 | AQ35: 0 | AR35: 0 | AS35: 0 | AT35: 0 | AU35: 0 | AV35: 0 | AW35: 0 | AX35: 0 | AZ35: 0 | BA35: 0 | BB35: 0 | BC35: 0 | BD35: 0 | BE35: 0 | BF35: 0 | BI35: 0 | BJ35: 0 | BK35: 0
C36: =C35+1 -> 22 | D36: Turk | E36: Trent 700 | F36: Turkmenistan | G36: MEA | H36: SelectCare Upsell | I36: Service Upsells | K36: 2 | O36: Low | P36: Med | Q36: Cancelled | S36: 30 | T36: 0 | U36: 7.5 | V36: =SUM(T36+U36) -> 7.5 | Y36: 0 | Z36: 0 | AA36: 0 | AB36: 0 | AC36: 0 | AD36: 0 | AE36: 0 | AF36: 0 | AG36: 0 | AH36: 0 | AI36: 0 | AJ36: 0 | AK36: 0 | AL36: 0 | AM36: 0 | AN36: 0 | AO36: 0 | AP36: 0 | AQ36: 0 | AR36: 0 | AS36: 0 | AT36: 0 | AU36: 0 | AV36: 0 | AW36: 0 | AX36: 0 | AZ36: 0 | BA36: 0 | BB36: 0 | BC36: 0 | BD36: 0 | BE36: 0 | BF36: 0 | BI36: 0 | BJ36: 0 | BK36: 0
C37: =C36+1 -> 23 | D37: Qanot | E37: Trent 700 | F37: Qanot Sharq | G37: MEA | H37: TCA Life Upsell 2 x A330CEO | I37: New a/c | K37: 2 | O37: Low | P37: Med | Q37: Cancelled | S37: 36 | T37: 0 | U37: 0 | V37: =SUM(T37+U37) -> 0 | Y37: 0 | Z37: 0 | AA37: 0 | AB37: 0 | AC37: 0 | AD37: 0 | AE37: 0 | AF37: 0 | AG37: 0 | AH37: 0 | AI37: 0 | AJ37: 0 | AK37: 0 | AL37: 0 | AM37: 0 | AN37: 0 | AO37: 0 | AP37: 0 | AQ37: 0 | AR37: 0 | AS37: 0 | AT37: 0 | AU37: 0 | AV37: 0 | AW37: 0 | AX37: 0 | AZ37: 0 | BA37: 0 | BB37: 0 | BC37: 0 | BD37: 0 | BE37: 0 | BF37: 0 | BI37: 0 | BJ37: 0 | BK37: 0
C38: =C37+1 -> 24 | D38: SW | E38: RB211-524 | F38: Silkway | G38: MEA | H38: Increase in Green Time by 12k cycles | I38: TCA Amendments | K38: 1 | N38: 0 | O38: Low | P38: High | Q38: Cancelled | S38: 25.2 | T38: 12.6 | U38: 12.6 | V38: =SUM(T38+U38) -> 25.2 | Y38: 0 | Z38: 0 | AA38: 0 | AB38: 0 | AC38: 0 | AD38: 0 | AE38: 0 | AF38: 0 | AG38: 0 | AH38: 0 | AI38: 0 | AJ38: 0 | AK38: 0 | AL38: 0 | AM38: 0 | AN38: 0 | AO38: 0 | AP38: 0 | AQ38: 0 | AR38: 0 | AS38: 0 | AT38: 0 | AU38: 0 | AV38: 0 | AW38: 0 | AX38: 0 | AZ38: 0 | BA38: 0 | BB38: 0 | BC38: 0 | BD38: 0 | BE38: 0 | BF38: 0 | BI38: 0 | BJ38: 0 | BK38: 0 | BO38: 1 | BP38: 1 | BQ38: 1 | BR38: 1 | BS38: 1 | BT38: 1 | BU38: 1 | BV38: 1 | BW38: 1 | BX38: 1 | BY38: 1 | BZ38: 1 | CA38: 1 | CB38: 1 | CC38: 1 | CD38: 1 | CE38: 1
C39: =C38+1 -> 25 | D39: Sen | E39: Trent 7000 | F39: Senegal | G39: MEA | H39: Collect debt | I39: Other | K39: 2 | N39: 0.54 | O39: Low | P39: Med | Q39: Cancelled | S39: 10 | T39: 0 | U39: 10 | V39: =SUM(T39+U39) -> 10 | Y39: 0 | Z39: 0 | AA39: 0 | AB39: 0 | AC39: 0 | AD39: 0 | AE39: 0 | AF39: 0 | AG39: 0 | AH39: 0 | AI39: 0 | AJ39: 0 | AK39: 0 | AL39: 0 | AM39: 0 | AN39: 0 | AO39: 0 | AP39: 0 | AQ39: 0 | AR39: 0 | AS39: 0 | AT39: 0 | AU39: 0 | AV39: 0 | AW39: 0 | AX39: 0 | AZ39: 0 | BA39: 0 | BB39: 0 | BC39: 0 | BD39: 0 | BE39: 0 | BF39: 0 | BI39: 0 | BJ39: 0 | BK39: 0
C40: =C39+1 -> 26 | D40: Viva Algeria | E40: Trent 7000 | F40: Air Algerie | G40: MEA | H40: Additional SPE | I40: SPE increase | K40: 1 | L40: yes | O40: High | P40: Low | Q40: Completed | S40: 20 | T40: 0 | U40: 20 | V40: =SUM(T40+U40) -> 20 | Y40: 0 | Z40: 0 | AA40: 0 | AB40: 0 | AC40: 0 | AD40: 0 | AE40: 0 | AF40: 0 | AG40: 0 | AH40: 0 | AI40: 0 | AJ40: 0 | AK40: 0 | AL40: 0 | AM40: 0 | AN40: 0 | AO40: 0 | AP40: 0 | AQ40: 0 | AR40: 0 | AS40: 0 | AT40: 0 | AU40: 0 | AV40: 0 | AW40: 0 | AX40: 0 | AZ40: 0 | BA40: 0 | BB40: 0 | BC40: 0 | BD40: 0 | BE40: 0 | BF40: 0 | BI40: 0 | BJ40: 0 | BK40: 0
C41: =C40+1 -> 27 | D41: Dhabi I | E41: Trent XWB-97 | F41: Etihad | G41: MEA | H41: TCA Reconciliation (CRP Improvement) | I41: TCA Amendments | K41: 1 | N41: 0.09 | O41: High | P41: Med | Q41: Completed | S41: 60 | T41: 5 | U41: 1 | V41: =SUM(T41+U41) -> 6 | Y41: 0 | Z41: 0 | AA41: 0 | AB41: 0 | AC41: 0 | AD41: 0 | AE41: 0 | AF41: 0 | AG41: 0 | AH41: 0 | AI41: 0 | AJ41: 0 | AK41: 0 | AL41: 0 | AM41: 0 | AN41: 0 | AO41: 0 | AP41: 0 | AQ41: 0 | AR41: 0 | AS41: 0 | AT41: 0 | AU41: 0 | AV41: 0 | AW41: 0 | AX41: 0 | AZ41: 0 | BA41: 0 | BB41: 0 | BC41: 0 | BD41: 0 | BE41: 0 | BF41: 0 | BI41: 0 | BJ41: 0 | BK41: 0
C42: =C41+1 -> 28 | D42: Dhabi II | E42: Trent XWB-97 | F42: Etihad | G42: MEA | H42: Transportation Service Buy Out for first 12 | I42: TCA Amendments | K42: 3 | N42: 0.09 | O42: Low | P42: High | Q42: Hopper | S42: 17.76 | T42: 1.48 | U42: 1.48 | V42: =SUM(T42+U42) -> 2.96 | Y42: 0 | Z42: 0 | AA42: 0 | AB42: 0 | AC42: 0 | AD42: 0 | AE42: 0 | AF42: 0 | AG42: 0 | AH42: 0 | AI42: 0 | AJ42: 0 | AK42: 0 | AL42: 0 | AM42: 0 | AN42: 0 | AO42: 0 | AP42: 0 | AQ42: 0 | AR42: 0 | AS42: 0 | AT42: 0 | AU42: 0 | AV42: 0 | AW42: 0 | AX42: 0 | AZ42: 0 | BA42: 0 | BB42: 0 | BC42: 0 | BD42: 0 | BE42: 0 | BF42: 0 | BI42: 0 | BJ42: 0 | BK42: 0
C43: =C42+1 -> 29 | D43: Saud | E43: Trent 700 | F43: Saudia | G43: MEA | H43: Regional Fleet NDSES improvement | I43: Cost Reduction | K43: 1 | N43: 0.31 | O43: High | P43: Med | Q43: Completed | T43: 0 | U43: 0 | V43: =SUM(T43+U43) -> 0 | Y43: 0 | Z43: 0 | AA43: 0 | AB43: 0 | AC43: 0 | AD43: 0 | AE43: 0 | AF43: 0 | AG43: 0 | AH43: 0 | AI43: 0 | AJ43: 0 | AK43: 0 | AL43: 0 | AM43: 0 | AN43: 0 | AO43: 0 | AP43: 0 | AQ43: 0 | AR43: 0 | AS43: 0 | AT43: 0 | AU43: 0 | AV43: 0 | AW43: 0 | AX43: 0 | AZ43: 0 | BA43: 0 | BB43: 0 | BC43: 0 | BD43: 0 | BE43: 0 | BF43: 0 | BI43: 0 | BJ43: 0 | BK43: 0
C44: =C43+1 -> 30 | D44: Saud II | E44: Trent 700 | F44: Saudia | G44: MEA | H44: Extend Classic | I44: Term Extension | J44: Term Extension | K44: 2 | N44: 0.29 | O44: Low | P44: Med | Q44: Hopper | S44: 21.46 | T44: 1.788333 | U44: 1.78833 | V44: =SUM(T44+U44) -> 3.576663 | Y44: 0 | Z44: 0 | AA44: 0 | AB44: 0 | AC44: 0 | AD44: 0 | AE44: 0 | AF44: 0 | AG44: 0 | AH44: 0 | AI44: 0 | AJ44: 0 | AK44: 0 | AL44: 0 | AM44: 0 | AN44: 0 | AO44: 0 | AP44: 0 | AQ44: 0 | AR44: 0 | AS44: 0 | AT44: 0 | AU44: 0 | AV44: 0 | AW44: 0 | AX44: 0 | AZ44: 0 | BA44: 0 | BB44: 0 | BC44: 0 | BD44: 0 | BE44: 0 | BF44: 0 | BI44: 0 | BJ44: 0 | BK44: 0
C45: =C44+1 -> 31 | D45: Tanz | E45: Trent 1000 | F45: Tanzania | G45: MEA | H45: Additional SPE | I45: SPE increase | K45: 1 | L45: yes | N45: 0.28 | O45: Med | P45: Low | Q45: Completed | S45: 25 | T45: 25 | V45: =SUM(T45+U45) -> 25 | Y45: 0 | Z45: 0 | AA45: 0 | AB45: 0 | AC45: 0 | AD45: 0 | AE45: 0 | AF45: 0 | AG45: 0 | AH45: 0 | AI45: 0 | AJ45: 0 | AK45: 0 | AL45: 0 | AM45: 0 | AN45: 0 | AO45: 0 | AP45: 0 | AQ45: 0 | AR45: 0 | AS45: 0 | AT45: 0 | AU45: 0 | AV45: 0 | AW45: 0 | AX45: 0 | AZ45: 0 | BA45: 0 | BB45: 0 | BC45: 0 | BD45: 0 | BE45: 0 | BF45: 0 | BI45: 0 | BJ45: 0 | BK45: 0
C46: =C45+1 -> 32 | D46: Tanz | E46: Trent 1000 | F46: Tanzania | G46: MEA | H46: NDSES CRP | I46: Cost Reduction | K46: 1 | N46: 0.28 | O46: Med | P46: Med | Q46: Completed | S46: 3.552 | T46: 0.7104 | U46: 0.7104 | V46: =SUM(T46+U46) -> 1.4208 | Y46: 0 | Z46: 0 | AA46: 0 | AB46: 0 | AC46: 0 | AD46: 0 | AE46: 0 | AF46: 0 | AG46: 0 | AH46: 0 | AI46: 0 | AJ46: 0 | AK46: 0 | AL46: 0 | AM46: 0 | AN46: 0 | AO46: 0 | AP46: 0 | AQ46: 0 | AR46: 0 | AS46: 0 | AT46: 0 | AU46: 0 | AV46: 0 | AW46: 0 | AX46: 0 | AZ46: 0 | BA46: 0 | BB46: 0 | BC46: 0 | BD46: 0 | BE46: 0 | BF46: 0 | BI46: 0 | BJ46: 0 | BK46: 0
C47: =C46+1 -> 33 | D47: Falcon | E47: Trent 1000 | F47: Gulf | G47: MEA | H47: NDSES improvement through SPE sales | I47: Cost Reduction | J47: Resolution of Claims | K47: 1 | N47: 0.38 | O47: Low | P47: Med | Q47: Negotiations | S47: 5.88 | T47: 0.84 | U47: 0.84 | V47: =SUM(T47+U47) -> 1.68 | Y47: 0 | Z47: 0 | AA47: 0 | AB47: 0 | AC47: 0 | AD47: 0 | AE47: 0 | AF47: 0 | AG47: 0 | AH47: 0 | AI47: 0 | AJ47: 0 | AK47: 0 | AL47: 0 | AM47: 0 | AN47: 0 | AO47: 0 | AP47: 0 | AQ47: 0 | AR47: 0 | AS47: 0 | AT47: 0 | AU47: 0 | AV47: 0 | AW47: 0 | AX47: 0 | AZ47: 0 | BA47: 0 | BB47: 0 | BC47: 0 | BD47: 0 | BE47: 0 | BF47: 0 | BI47: 0 | BJ47: 0 | BK47: 0
C48: =C47+1 -> 34 | D48: Falcon | E48: Trent 1000 | F48: Gulf | G48: MEA | H48: 3 Year Extension | I48: Term Extension | J48: Resolution of Claims | K48: 1 | N48: 0.38 | O48: Med | P48: Med | Q48: Negotiations | S48: 12 | T48: 1.2 | U48: 1.2 | V48: =SUM(T48+U48) -> 2.4 | Y48: 0 | Z48: 0 | AA48: 0 | AB48: 0 | AC48: 0 | AD48: 0 | AE48: 0 | AF48: 0 | AG48: 0 | AH48: 0 | AI48: 0 | AJ48: 0 | AK48: 0 | AL48: 0 | AM48: 0 | AN48: 0 | AO48: 0 | AP48: 0 | AQ48: 0 | AR48: 0 | AS48: 0 | AT48: 0 | AU48: 0 | AV48: 0 | AW48: 0 | AX48: 0 | AZ48: 0 | BA48: 0 | BB48: 0 | BC48: 0 | BD48: 0 | BE48: 0 | BF48: 0 | BI48: 0 | BJ48: 0 | BK48: 0
C49: =C48+1 -> 35 | D49: Falcon | E49: Trent 1000 | F49: Gulf | G49: MEA | H49: Additional 2 x A/C | I49: New a/c | J49: Resolution of Claims | K49: 2 | L49: yes | M49: 2 | N49: 0.38 | O49: Low | P49: Med | Q49: Cancelled | S49: 23.04 | T49: =S49/12 -> 1.92 | U49: =S49/12 -> 1.92 | V49: =SUM(T49+U49) -> 3.84 | Y49: 0 | Z49: 0 | AA49: 0 | AB49: 0 | AC49: 0 | AD49: 0 | AE49: 0 | AF49: 0 | AG49: 0 | AH49: 0 | AI49: 0 | AJ49: 0 | AK49: 0 | AL49: 0 | AM49: 0 | AN49: 0 | AO49: 0 | AP49: 0 | AQ49: 0 | AR49: 0 | AS49: 0 | AT49: 0 | AU49: 0 | AV49: 0 | AW49: 0 | AX49: 0 | AZ49: 0 | BA49: 0 | BB49: 0 | BC49: 0 | BD49: 0 | BE49: 0 | BF49: 0 | BI49: 0 | BJ49: 0 | BK49: 0
C50: =C49+1 -> 36 | D50: Star | E50: Trent 1000 | F50: Austral | G50: MEA | H50: TCA Extension/Exit credit trade | I50: Term Extension | J50: Blended TCA Rate | K50: 1 | N50: 0.61 | O50: Med | P50: Med | Q50: Hopper | S50: 4.8 | T50: 0 | U50: 0 | V50: =SUM(T50+U50) -> 0 | Y50: 0 | Z50: 0 | AA50: 0 | AB50: 0 | AC50: 0 | AD50: 0 | AE50: 0 | AF50: 0 | AG50: 0 | AH50: 0 | AI50: 0 | AJ50: 0 | AK50: 0 | AL50: 0 | AM50: 0 | AN50: 0 | AO50: 0 | AP50: 0 | AQ50: 0 | AR50: 0 | AS50: 0 | AT50: 0 | AU50: 0 | AV50: 0 | AW50: 0 | AX50: 0 | AZ50: 0 | BA50: 0 | BB50: 0 | BC50: 0 | BD50: 0 | BE50: 0 | BF50: 0 | BI50: 0 | BJ50: 0 | BK50: 0
C51: =C50+1 -> 37 | D51: Q8 | E51: Trent 7000 | F51: Kuwait | G51: MEA | H51: Maintain SPE % | I51: SPE increase | J51: Early Exit of a330-800 | K51: 3 | L51: yes | N51: 0.04 | O51: Low | P51: Med | Q51: Hopper | S51: 0 | T51: 0 | U51: 0 | V51: =SUM(T51+U51) -> 0 | Y51: 0 | Z51: 0 | AA51: 0 | AB51: 0 | AC51: 0 | AD51: 0 | AE51: 0 | AF51: 0 | AG51: 0 | AH51: 0 | AI51: 0 | AJ51: 0 | AK51: 0 | AL51: 0 | AM51: 0 | AN51: 0 | AO51: 0 | AP51: 0 | AQ51: 0 | AR51: 0 | AS51: 0 | AT51: 0 | AU51: 0 | AV51: 0 | AW51: 0 | AX51: 0 | AZ51: 0 | BA51: 0 | BB51: 0 | BC51: 0 | BD51: 0 | BE51: 0 | BF51: 0 | BI51: 0 | BJ51: 0 | BK51: 0
C52: =C51+1 -> 38 | D52: Mau | E52: Trent XWB-84 | F52: Mauritus | G52: MEA | H52: Escalation increase | I52: TCA Amendments | K52: 3 | N52: 0.31 | O52: High | P52: Low | Q52: Completed | S52: 1.3 | T52: =S52/3 -> 0.43333333 | U52: 0 | V52: =SUM(T52+U52) -> 0.43333333 | Y52: 0 | Z52: 0 | AA52: 0 | AB52: 0 | AC52: 0 | AD52: 0 | AE52: 0 | AF52: 0 | AG52: 0 | AH52: 0 | AI52: 0 | AJ52: 0 | AK52: 0 | AL52: 0 | AM52: 0 | AN52: 0 | AO52: 0 | AP52: 0 | AQ52: 0 | AR52: 0 | AS52: 0 | AT52: 0 | AU52: 0 | AV52: 0 | AW52: 0 | AX52: 0 | AZ52: 0 | BA52: 0 | BB52: 0 | BC52: 0 | BD52: 0 | BE52: 0 | BF52: 0 | BI52: 0 | BJ52: 0 | BK52: 0
C53: =C52+1 -> 39 | D53: Dodo | E53: Trent 7000 | F53: Mauritus | G53: MEA | H53: Reduce NDSES Cost | I53: Cost Reduction | J53: Termination | K53: 2 | N53: 0.54 | O53: Med | P53: Med | Q53: ICT | S53: 0.38 | T53: =S53/5 -> 0.076 | U53: =S53/5 -> 0.076 | V53: =SUM(T53+U53) -> 0.152 | Y53: 0 | Z53: 0 | AA53: 0 | AB53: 0 | AC53: 0 | AD53: 0 | AE53: 0 | AF53: 0 | AG53: 0 | AH53: 0 | AI53: 0 | AJ53: 0 | AK53: 0 | AL53: 0 | AM53: 0 | AN53: 0 | AO53: 0 | AP53: 0 | AQ53: 0 | AR53: 0 | AS53: 0 | AT53: 0 | AU53: 0 | AV53: 0 | AW53: 0 | AX53: 0 | AZ53: 0 | BA53: 0 | BB53: 0 | BC53: 0 | BD53: 0 | BE53: 0 | BF53: 0 | BI53: 0 | BJ53: 0 | BK53: 0
C54: =C53+1 -> 40 | D54: RW | E54: Trent 700 | F54: Rwanda | G54: MEA | H54: Min Term Extension | I54: Term Extension | K54: 3 | N54: 0.19 | O54: Low | P54: Med | Q54: Hopper | S54: 12 | T54: 0 | U54: 0 | V54: =SUM(T54+U54) -> 0 | Y54: 0 | Z54: 0 | AA54: 0 | AB54: 0 | AC54: 0 | AD54: 0 | AE54: 0 | AF54: 0 | AG54: 0 | AH54: 0 | AI54: 0 | AJ54: 0 | AK54: 0 | AL54: 0 | AM54: 0 | AN54: 0 | AO54: 0 | AP54: 0 | AQ54: 0 | AR54: 0 | AS54: 0 | AT54: 0 | AU54: 0 | AV54: 0 | AW54: 0 | AX54: 0 | AZ54: 0 | BA54: 0 | BB54: 0 | BC54: 0 | BD54: 0 | BE54: 0 | BF54: 0 | BI54: 0 | BJ54: 0 | BK54: 0
C55: =C54+1 -> 41 | D55: SAA | E55: Trent 700 | F55: SAA | G55: MEA | H55: Additional 7 X A/C | I55: New a/c | K55: 3 | O55: Med | P55: Med | Q55: Cancelled | S55: 54 | T55: 0 | U55: 0 | V55: =SUM(T55+U55) -> 0 | Y55: 0 | Z55: 0 | AA55: 0 | AB55: 0 | AC55: 0 | AD55: 0 | AE55: 0 | AF55: 0 | AG55: 0 | AH55: 0 | AI55: 0 | AJ55: 0 | AK55: 0 | AL55: 0 | AM55: 0 | AN55: 0 | AO55: 0 | AP55: 0 | AQ55: 0 | AR55: 0 | AS55: 0 | AT55: 0 | AU55: 0 | AV55: 0 | AW55: 0 | AX55: 0 | AZ55: 0 | BA55: 0 | BB55: 0 | BC55: 0 | BD55: 0 | BE55: 0 | BF55: 0 | BI55: 0 | BJ55: 0 | BK55: 0
C56: =C55+1 -> 42 | D56: Star | E56: Trent 1000 | F56: Austral | G56: MEA | H56: Used SPE | I56: SPE increase | J56: Min-term extension | K56: 1 | L56: Med | M56: Med | N56: ICT | O56: Low | P56: Low | Q56: Hopper | V56: =SUM(T56+U56) -> 0 | Y56: 0 | Z56: 0 | AA56: 0 | AB56: 0 | AC56: 0 | AD56: 0 | AE56: 0 | AF56: 0 | AG56: 0 | AH56: 0 | AI56: 0 | AJ56: 0 | AK56: 0 | AL56: 0 | AM56: 0 | AN56: 0 | AO56: 0 | AP56: 0 | AQ56: 0 | AR56: 0 | AS56: 0 | AT56: 0 | AU56: 0 | AV56: 0 | AW56: 0 | AX56: 0 | AZ56: 0 | BA56: 0 | BB56: 0 | BC56: 0 | BD56: 0 | BE56: 0 | BF56: 0 | BI56: 0 | BJ56: 0 | BK56: 0
C57: =C56+1 -> 43 | D57: Horus V | E57: Trent XWB-84 | F57: Egypt | G57: MEA | H57: EP Upsell | I57: Last 6 aircraft | J57: Upsell | K57: 2 | O57: Med | P57: Med | Q57: Hopper | V57: =SUM(T57+U57) -> 0 | Y57: 0 | Z57: 0 | AA57: 0 | AB57: 0 | AC57: 0 | AD57: 0 | AE57: 0 | AF57: 0 | AG57: 0 | AH57: 0 | AI57: 0 | AJ57: 0 | AK57: 0 | AL57: 0 | AM57: 0 | AN57: 0 | AO57: 0 | AP57: 0 | AQ57: 0 | AR57: 0 | AS57: 0 | AT57: 0 | AU57: 0 | AV57: 0 | AW57: 0 | AX57: 0 | AZ57: 0 | BA57: 0 | BB57: 0 | BC57: 0 | BD57: 0 | BE57: 0 | BF57: 0 | BI57: 0 | BJ57: 0 | BK57: 0
C58: =C57+1 -> 44 | D58: Pantheon | E58: Trent 900 | F58: Emirates | G58: MEA | H58: Retire SLA1 | I58: TCA Amendments | J58: MRO trade | K58: 1 | O58: Med | P58: High | Q58: Hopper | V58: =SUM(T58+U58) -> 0 | Y58: 0 | Z58: 0 | AA58: 0 | AB58: 0 | AC58: 0 | AD58: 0 | AE58: 0 | AF58: 0 | AG58: 0 | AH58: 0 | AI58: 0 | AJ58: 0 | AK58: 0 | AL58: 0 | AM58: 0 | AN58: 0 | AO58: 0 | AP58: 0 | AQ58: 0 | AR58: 0 | AS58: 0 | AT58: 0 | AU58: 0 | AV58: 0 | AW58: 0 | AX58: 0 | AZ58: 0 | BA58: 0 | BB58: 0 | BC58: 0 | BD58: 0 | BE58: 0 | BF58: 0 | BI58: 0 | BJ58: 0 | BK58: 0
C59: =C58+1 -> 45 | D59: Cotton | E59: RB211-524 | F59: Silkway | G59: MEA | H59: Extend Greentime agreement by 12 months | I59: TCA Amendments | J59: Expiry | K59: 1 | O59: High | P59: Med | Q59: ICT | V59: =SUM(T59+U59) -> 0 | Y59: 0 | Z59: 0 | AA59: 0 | AB59: 0 | AC59: 0 | AD59: 0 | AE59: 0 | AF59: 0 | AG59: 0 | AH59: 0 | AI59: 0 | AJ59: 0 | AK59: 0 | AL59: 0 | AM59: 0 | AN59: 0 | AO59: 0 | AP59: 0 | AQ59: 0 | AR59: 0 | AS59: 0 | AT59: 0 | AU59: 0 | AV59: 0 | AW59: 0 | AX59: 0 | AZ59: 0 | BA59: 0 | BB59: 0 | BC59: 0 | BD59: 0 | BE59: 0 | BF59: 0 | BI59: 0 | BJ59: 0 | BK59: 0
C60: =C59+1 -> 46 | V60: =SUM(T60+U60) -> 0 | Y60: 0 | Z60: 0 | AA60: 0 | AB60: 0 | AC60: 0 | AD60: 0 | AE60: 0 | AF60: 0 | AG60: 0 | AH60: 0 | AI60: 0 | AJ60: 0 | AK60: 0 | AL60: 0 | AM60: 0 | AN60: 0 | AO60: 0 | AP60: 0 | AQ60: 0 | AR60: 0 | AS60: 0 | AT60: 0 | AU60: 0 | AV60: 0 | AW60: 0 | AX60: 0 | AZ60: 0 | BA60: 0 | BB60: 0 | BC60: 0 | BD60: 0 | BE60: 0 | BF60: 0 | BI60: 0 | BJ60: 0 | BK60: 0
C61: =C60+1 -> 47 | V61: =SUM(T61+U61) -> 0 | Y61: 0 | Z61: 0 | AA61: 0 | AB61: 0 | AC61: 0 | AD61: 0 | AE61: 0 | AF61: 0 | AG61: 0 | AH61: 0 | AI61: 0 | AJ61: 0 | AK61: 0 | AL61: 0 | AM61: 0 | AN61: 0 | AO61: 0 | AP61: 0 | AQ61: 0 | AR61: 0 | AS61: 0 | AT61: 0 | AU61: 0 | AV61: 0 | AW61: 0 | AX61: 0 | AZ61: 0 | BA61: 0 | BB61: 0 | BC61: 0 | BD61: 0 | BE61: 0 | BF61: 0 | BI61: 0 | BJ61: 0 | BK61: 0
C62: =C61+1 -> 48 | V62: =SUM(T62+U62) -> 0 | Y62: 0 | Z62: 0 | AA62: 0 | AB62: 0 | AC62: 0 | AD62: 0 | AE62: 0 | AF62: 0 | AG62: 0 | AH62: 0 | AI62: 0 | AJ62: 0 | AK62: 0 | AL62: 0 | AM62: 0 | AN62: 0 | AO62: 0 | AP62: 0 | AQ62: 0 | AR62: 0 | AS62: 0 | AT62: 0 | AU62: 0 | AV62: 0 | AW62: 0 | AX62: 0 | AZ62: 0 | BA62: 0 | BB62: 0 | BC62: 0 | BD62: 0 | BE62: 0 | BF62: 0 | BI62: 0 | BJ62: 0 | BK62: 0
C63: =C62+1 -> 49 | V63: =SUM(T63+U63) -> 0 | Y63: 0 | Z63: 0 | AA63: 0 | AB63: 0 | AC63: 0 | AD63: 0 | AE63: 0 | AF63: 0 | AG63: 0 | AH63: 0 | AI63: 0 | AJ63: 0 | AK63: 0 | AL63: 0 | AM63: 0 | AN63: 0 | AO63: 0 | AP63: 0 | AQ63: 0 | AR63: 0 | AS63: 0 | AT63: 0 | AU63: 0 | AV63: 0 | AW63: 0 | AX63: 0 | AZ63: 0 | BA63: 0 | BB63: 0 | BC63: 0 | BD63: 0 | BE63: 0 | BF63: 0 | BI63: 0 | BJ63: 0 | BK63: 0
C64: =C63+1 -> 50 | V64: =SUM(T64+U64) -> 0 | Y64: 0 | Z64: 0 | AA64: 0 | AB64: 0 | AC64: 0 | AD64: 0 | AE64: 0 | AF64: 0 | AG64: 0 | AH64: 0 | AI64: 0 | AJ64: 0 | AK64: 0 | AL64: 0 | AM64: 0 | AN64: 0 | AO64: 0 | AP64: 0 | AQ64: 0 | AR64: 0 | AS64: 0 | AT64: 0 | AU64: 0 | AV64: 0 | AW64: 0 | AX64: 0 | AZ64: 0 | BA64: 0 | BB64: 0 | BC64: 0 | BD64: 0 | BE64: 0 | BF64: 0 | BI64: 0 | BJ64: 0 | BK64: 0
C65: =C64+1 -> 51 | V65: =SUM(T65+U65) -> 0 | Y65: 0 | Z65: 0 | AA65: 0 | AB65: 0 | AC65: 0 | AD65: 0 | AE65: 0 | AF65: 0 | AG65: 0 | AH65: 0 | AI65: 0 | AJ65: 0 | AK65: 0 | AL65: 0 | AM65: 0 | AN65: 0 | AO65: 0 | AP65: 0 | AQ65: 0 | AR65: 0 | AS65: 0 | AT65: 0 | AU65: 0 | AV65: 0 | AW65: 0 | AX65: 0 | AZ65: 0 | BA65: 0 | BB65: 0 | BC65: 0 | BD65: 0 | BE65: 0 | BF65: 0 | BI65: 0 | BJ65: 0 | BK65: 0
C66: =C65+1 -> 52 | V66: =SUM(T66+U66) -> 0 | Y66: 0 | Z66: 0 | AA66: 0 | AB66: 0 | AC66: 0 | AD66: 0 | AE66: 0 | AF66: 0 | AG66: 0 | AH66: 0 | AI66: 0 | AJ66: 0 | AK66: 0 | AL66: 0 | AM66: 0 | AN66: 0 | AO66: 0 | AP66: 0 | AQ66: 0 | AR66: 0 | AS66: 0 | AT66: 0 | AU66: 0 | AV66: 0 | AW66: 0 | AX66: 0 | AZ66: 0 | BA66: 0 | BB66: 0 | BC66: 0 | BD66: 0 | BE66: 0 | BF66: 0 | BI66: 0 | BJ66: 0 | BK66: 0
C67: =C66+1 -> 53 | V67: =SUM(T67+U67) -> 0 | Y67: 0 | Z67: 0 | AA67: 0 | AB67: 0 | AC67: 0 | AD67: 0 | AE67: 0 | AF67: 0 | AG67: 0 | AH67: 0 | AI67: 0 | AJ67: 0 | AK67: 0 | AL67: 0 | AM67: 0 | AN67: 0 | AO67: 0 | AP67: 0 | AQ67: 0 | AR67: 0 | AS67: 0 | AT67: 0 | AU67: 0 | AV67: 0 | AW67: 0 | AX67: 0 | AZ67: 0 | BA67: 0 | BB67: 0 | BC67: 0 | BD67: 0 | BE67: 0 | BF67: 0 | BI67: 0 | BJ67: 0 | BK67: 0
C68: =C67+1 -> 54 | V68: =SUM(T68+U68) -> 0 | Y68: 0 | Z68: 0 | AA68: 0 | AB68: 0 | AC68: 0 | AD68: 0 | AE68: 0 | AF68: 0 | AG68: 0 | AH68: 0 | AI68: 0 | AJ68: 0 | AK68: 0 | AL68: 0 | AM68: 0 | AN68: 0 | AO68: 0 | AP68: 0 | AQ68: 0 | AR68: 0 | AS68: 0 | AT68: 0 | AU68: 0 | AV68: 0 | AW68: 0 | AX68: 0 | AZ68: 0 | BA68: 0 | BB68: 0 | BC68: 0 | BD68: 0 | BE68: 0 | BF68: 0 | BI68: 0 | BJ68: 0 | BK68: 0
C69: =C68+1 -> 55 | V69: =SUM(T69+U69) -> 0 | Y69: 0 | Z69: 0 | AA69: 0 | AB69: 0 | AC69: 0 | AD69: 0 | AE69: 0 | AF69: 0 | AG69: 0 | AH69: 0 | AI69: 0 | AJ69: 0 | AK69: 0 | AL69: 0 | AM69: 0 | AN69: 0 | AO69: 0 | AP69: 0 | AQ69: 0 | AR69: 0 | AS69: 0 | AT69: 0 | AU69: 0 | AV69: 0 | AW69: 0 | AX69: 0 | AZ69: 0 | BA69: 0 | BB69: 0 | BC69: 0 | BD69: 0 | BE69: 0 | BF69: 0 | BI69: 0 | BJ69: 0 | BK69: 0
C70: =C69+1 -> 56 | V70: =SUM(T70+U70) -> 0 | Y70: 0 | Z70: 0 | AA70: 0 | AB70: 0 | AC70: 0 | AD70: 0 | AE70: 0 | AF70: 0 | AG70: 0 | AH70: 0 | AI70: 0 | AJ70: 0 | AK70: 0 | AL70: 0 | AM70: 0 | AN70: 0 | AO70: 0 | AP70: 0 | AQ70: 0 | AR70: 0 | AS70: 0 | AT70: 0 | AU70: 0 | AV70: 0 | AW70: 0 | AX70: 0 | AZ70: 0 | BA70: 0 | BB70: 0 | BC70: 0 | BD70: 0 | BE70: 0 | BF70: 0 | BI70: 0 | BJ70: 0 | BK70: 0
C71: =C70+1 -> 57 | V71: =SUM(T71+U71) -> 0 | Y71: 0 | Z71: 0 | AA71: 0 | AB71: 0 | AC71: 0 | AD71: 0 | AE71: 0 | AF71: 0 | AG71: 0 | AH71: 0 | AI71: 0 | AJ71: 0 | AK71: 0 | AL71: 0 | AM71: 0 | AN71: 0 | AO71: 0 | AP71: 0 | AQ71: 0 | AR71: 0 | AS71: 0 | AT71: 0 | AU71: 0 | AV71: 0 | AW71: 0 | AX71: 0 | AZ71: 0 | BA71: 0 | BB71: 0 | BC71: 0 | BD71: 0 | BE71: 0 | BF71: 0 | BI71: 0 | BJ71: 0 | BK71: 0
... C238: =C237+1 -> 224 | V238: =SUM(T238+U238) -> 0 | Y238: 0 | Z238: 0 | AA238: 0 | AB238: 0 | AC238: 0 | AD238: 0 | AE238: 0 | AF238: 0 | AG238: 0 | AH238: 0 | AI238: 0 | AJ238: 0 | AK238: 0 | AL238: 0 | AM238: 0 | AN238: 0 | AO238: 0 | AP238: 0 | AQ238: 0 | AR238: 0 | AS238: 0 | AT238: 0 | AU238: 0 | AV238: 0 | AW238: 0 | AX238: 0 | AZ238: 0 | BA238: 0 | BB238: 0 | BC238: 0 | BD238: 0 | BE238: 0 | BF238: 0 | BI238: 0 | BJ238: 0 | BK238: 0
C239: 226 | V239: =SUM(T239+U239) -> 0 | Y239: 0 | Z239: 0 | AA239: 0 | AB239: 0 | AC239: 0 | AD239: 0 | AE239: 0 | AF239: 0 | AG239: 0 | AH239: 0 | AI239: 0 | AJ239: 0 | AK239: 0 | AL239: 0 | AM239: 0 | AN239: 0 | AO239: 0 | AP239: 0 | AQ239: 0 | AR239: 0 | AS239: 0 | AT239: 0 | AU239: 0 | AV239: 0 | AW239: 0 | AX239: 0 | AZ239: 0 | BA239: 0 | BB239: 0 | BC239: 0 | BD239: 0 | BE239: 0 | BF239: 0 | BI239: 0 | BJ239: 0 | BK239: 0
C240: 227 | V240: =SUM(T240+U240) -> 0 | Y240: 0 | Z240: 0 | AA240: 0 | AB240: 0 | AC240: 0 | AD240: 0 | AE240: 0 | AF240: 0 | AG240: 0 | AH240: 0 | AI240: 0 | AJ240: 0 | AK240: 0 | AL240: 0 | AM240: 0 | AN240: 0 | AO240: 0 | AP240: 0 | AQ240: 0 | AR240: 0 | AS240: 0 | AT240: 0 | AU240: 0 | AV240: 0 | AW240: 0 | AX240: 0 | AZ240: 0 | BA240: 0 | BB240: 0 | BC240: 0 | BD240: 0 | BE240: 0 | BF240: 0 | BI240: 0 | BJ240: 0 | BK240: 0
C241: 228 | V241: =SUM(T241+U241) -> 0 | Y241: 0 | Z241: 0 | AA241: 0 | AB241: 0 | AC241: 0 | AD241: 0 | AE241: 0 | AF241: 0 | AG241: 0 | AH241: 0 | AI241: 0 | AJ241: 0 | AK241: 0 | AL241: 0 | AM241: 0 | AN241: 0 | AO241: 0 | AP241: 0 | AQ241: 0 | AR241: 0 | AS241: 0 | AT241: 0 | AU241: 0 | AV241: 0 | AW241: 0 | AX241: 0 | AZ241: 0 | BA241: 0 | BB241: 0 | BC241: 0 | BD241: 0 | BE241: 0 | BF241: 0 | BI241: 0 | BJ241: 0 | BK241: 0
C242: 229 | V242: =SUM(T242+U242) -> 0 | Y242: 0 | Z242: 0 | AA242: 0 | AB242: 0 | AC242: 0 | AD242: 0 | AE242: 0 | AF242: 0 | AG242: 0 | AH242: 0 | AI242: 0 | AJ242: 0 | AK242: 0 | AL242: 0 | AM242: 0 | AN242: 0 | AO242: 0 | AP242: 0 | AQ242: 0 | AR242: 0 | AS242: 0 | AT242: 0 | AU242: 0 | AV242: 0 | AW242: 0 | AX242: 0 | AZ242: 0 | BA242: 0 | BB242: 0 | BC242: 0 | BD242: 0 | BE242: 0 | BF242: 0 | BI242: 0 | BJ242: 0 | BK242: 0
C243: 230 | V243: =SUM(T243+U243) -> 0 | Y243: 0 | Z243: 0 | AA243: 0 | AB243: 0 | AC243: 0 | AD243: 0 | AE243: 0 | AF243: 0 | AG243: 0 | AH243: 0 | AI243: 0 | AJ243: 0 | AK243: 0 | AL243: 0 | AM243: 0 | AN243: 0 | AO243: 0 | AP243: 0 | AQ243: 0 | AR243: 0 | AS243: 0 | AT243: 0 | AU243: 0 | AV243: 0 | AW243: 0 | AX243: 0 | AZ243: 0 | BA243: 0 | BB243: 0 | BC243: 0 | BD243: 0 | BE243: 0 | BF243: 0 | BI243: 0 | BJ243: 0 | BK243: 0
C244: 231 | V244: =SUM(T244+U244) -> 0 | Y244: 0 | Z244: 0 | AA244: 0 | AB244: 0 | AC244: 0 | AD244: 0 | AE244: 0 | AF244: 0 | AG244: 0 | AH244: 0 | AI244: 0 | AJ244: 0 | AK244: 0 | AL244: 0 | AM244: 0 | AN244: 0 | AO244: 0 | AP244: 0 | AQ244: 0 | AR244: 0 | AS244: 0 | AT244: 0 | AU244: 0 | AV244: 0 | AW244: 0 | AX244: 0 | AZ244: 0 | BA244: 0 | BB244: 0 | BC244: 0 | BD244: 0 | BE244: 0 | BF244: 0 | BI244: 0 | BJ244: 0 | BK244: 0
C245: 232 | V245: =SUM(T245+U245) -> 0 | Y245: 0 | Z245: 0 | AA245: 0 | AB245: 0 | AC245: 0 | AD245: 0 | AE245: 0 | AF245: 0 | AG245: 0 | AH245: 0 | AI245: 0 | AJ245: 0 | AK245: 0 | AL245: 0 | AM245: 0 | AN245: 0 | AO245: 0 | AP245: 0 | AQ245: 0 | AR245: 0 | AS245: 0 | AT245: 0 | AU245: 0 | AV245: 0 | AW245: 0 | AX245: 0 | AZ245: 0 | BA245: 0 | BB245: 0 | BC245: 0 | BD245: 0 | BE245: 0 | BF245: 0 | BI245: 0 | BJ245: 0 | BK245: 0
C246: 233 | V246: =SUM(T246+U246) -> 0 | Y246: 0 | Z246: 0 | AA246: 0 | AB246: 0 | AC246: 0 | AD246: 0 | AE246: 0 | AF246: 0 | AG246: 0 | AH246: 0 | AI246: 0 | AJ246: 0 | AK246: 0 | AL246: 0 | AM246: 0 | AN246: 0 | AO246: 0 | AP246: 0 | AQ246: 0 | AR246: 0 | AS246: 0 | AT246: 0 | AU246: 0 | AV246: 0 | AW246: 0 | AX246: 0 | AZ246: 0 | BA246: 0 | BB246: 0 | BC246: 0 | BD246: 0 | BE246: 0 | BF246: 0 | BI246: 0 | BJ246: 0 | BK246: 0
C247: 234 | V247: =SUM(T247+U247) -> 0 | Y247: 0 | Z247: 0 | AA247: 0 | AB247: 0 | AC247: 0 | AD247: 0 | AE247: 0 | AF247: 0 | AG247: 0 | AH247: 0 | AI247: 0 | AJ247: 0 | AK247: 0 | AL247: 0 | AM247: 0 | AN247: 0 | AO247: 0 | AP247: 0 | AQ247: 0 | AR247: 0 | AS247: 0 | AT247: 0 | AU247: 0 | AV247: 0 | AW247: 0 | AX247: 0 | AZ247: 0 | BA247: 0 | BB247: 0 | BC247: 0 | BD247: 0 | BE247: 0 | BF247: 0 | BI247: 0 | BJ247: 0 | BK247: 0
C248: 235 | V248: =SUM(T248+U248) -> 0 | Y248: 0 | Z248: 0 | AA248: 0 | AB248: 0 | AC248: 0 | AD248: 0 | AE248: 0 | AF248: 0 | AG248: 0 | AH248: 0 | AI248: 0 | AJ248: 0 | AK248: 0 | AL248: 0 | AM248: 0 | AN248: 0 | AO248: 0 | AP248: 0 | AQ248: 0 | AR248: 0 | AS248: 0 | AT248: 0 | AU248: 0 | AV248: 0 | AW248: 0 | AX248: 0 | AZ248: 0 | BA248: 0 | BB248: 0 | BC248: 0 | BD248: 0 | BE248: 0 | BF248: 0 | BI248: 0 | BJ248: 0 | BK248: 0
C249: 236 | V249: =SUM(T249+U249) -> 0 | Y249: 0 | Z249: 0 | AA249: 0 | AB249: 0 | AC249: 0 | AD249: 0 | AE249: 0 | AF249: 0 | AG249: 0 | AH249: 0 | AI249: 0 | AJ249: 0 | AK249: 0 | AL249: 0 | AM249: 0 | AN249: 0 | AO249: 0 | AP249: 0 | AQ249: 0 | AR249: 0 | AS249: 0 | AT249: 0 | AU249: 0 | AV249: 0 | AW249: 0 | AX249: 0 | AZ249: 0 | BA249: 0 | BB249: 0 | BC249: 0 | BD249: 0 | BE249: 0 | BF249: 0 | BI249: 0 | BJ249: 0 | BK249: 0
C250: 237 | V250: =SUM(T250+U250) -> 0 | Y250: 0 | Z250: 0 | AA250: 0 | AB250: 0 | AC250: 0 | AD250: 0 | AE250: 0 | AF250: 0 | AG250: 0 | AH250: 0 | AI250: 0 | AJ250: 0 | AK250: 0 | AL250: 0 | AM250: 0 | AN250: 0 | AO250: 0 | AP250: 0 | AQ250: 0 | AR250: 0 | AS250: 0 | AT250: 0 | AU250: 0 | AV250: 0 | AW250: 0 | AX250: 0 | AZ250: 0 | BA250: 0 | BB250: 0 | BC250: 0 | BD250: 0 | BE250: 0 | BF250: 0 | BI250: 0 | BJ250: 0 | BK250: 0
... C513: 500 | V513: =SUM(T513+U513) -> 0 | Y513: 0 | Z513: 0 | AA513: 0 | AB513: 0 | AC513: 0 | AD513: 0 | AE513: 0 | AF513: 0 | AG513: 0 | AH513: 0 | AI513: 0 | AJ513: 0 | AK513: 0 | AL513: 0 | AM513: 0 | AN513: 0 | AO513: 0 | AP513: 0 | AQ513: 0 | AR513: 0 | AS513: 0 | AT513: 0 | AU513: 0 | AV513: 0 | AW513: 0 | AX513: 0 | AZ513: 0 | BA513: 0 | BB513: 0 | BC513: 0 | BD513: 0 | BE513: 0 | BF513: 0 | BI513: 0 | BJ513: 0 | BK513: 0

Sheet Summary
F2: Strategic | K2: Financials
C3: Project | D3: Customer | E3: Programme | F3: Kam Pack Complete | G3: CRP Deep Dive Complete | H3: Risk Review Complete | I3: Contract DCR Complete | J3: O&V Review Complete | K3: Current CRP Margin | L3: Onerous Provision | M3: Current CRP % | N3: 2024 onerous release | O3: 2025 onerous release | P3: 5YP improvement (cash or profit?) | U3: Overall Pack Improvement
P4: 2025 | Q4: 2026 | R4: 2027 | S4: 2028 | T4: 2029
B5: Launched | C5: Finiq | D5: Emirates | E5: Trent 900 | K5: -710.44 | L5: -437 | M5: -0.664 | N5: 0 | O5: -437
C6: Burgundy | D6: Qatar | E6: Trent XWB-84 | K6: -920.05 | M6: -0.46 | N6: -6 | U6: 75
E7: Trent XWB-97 | K7: -288.62 | M7: -1.426
C8: Falcon | D8: Gulf | E8: Trent 1000 | F8: 45352 | G8: 45352 | K8: -37 | L8: -25 | M8: -0.113
B9: Pending | C9: Horus | D9: Egypt | E9: Trent 1000 | F9: 45833 | G9: 45863 | K9: -55.05 | L9: -17 | M9: -0.257
D10: Etihad | E10: Trent XWB-97
C11: WAUH | D11: Ethiopia | E11: Trent 1000 | L11: 3.7
D12: Saudia | E12: Trent 700 | K12: 570.01 | M12: 0.531
D13: Mauritus | E13: Trent 7000 | K13: -3.2 | L13: 4 | M13: -0.054
D14: Austral | E14: Trent 1000 | L14: 3.9
D15: Senegal | E15: Trent 7000 | K15: -1.42 | L15: -4.7 | M15: -0.02

Sheet Opps and Threats
E1: Total: | F1: =SUBTOTAL(9,F4:F50) -> 104.62162 | G1: =SUBTOTAL(9,G4:G50) -> 834.72 | H1: =SUBTOTAL(9,H4:H50) -> 0.77027027 | I1: =SUBTOTAL(9,I4:I50) -> 0.82432432 | J1: =SUBTOTAL(9,J4:J50) -> 0.82644788 | K1: =SUBTOTAL(9,K4:K50) -> 0.89189189 | L1: =SUBTOTAL(9,L4:L50) -> 0.72200772 | M1: =SUBTOTAL(9,M4:M50) -> 1300.18
B2: Project | C2: Programme | D2: Customer | E2: Opportunity | F2: 2024 Profit Release | G2: 2025 Profit Release | H2: 2025 | I2: 2026 | J2: 2027 | K2: 2028 | L2: 2029 | M2: Overall Pack improvement (term) | N2: Window for forecast | O2: Due date | P2: Owner | Q2: Status | R2: Comments
H3: 5YP Improvement
B4: Falcon | C4: Trent 1000 | D4: Gulf | E4: Transport reduction from $437k to $300k | F4: =6.31/1.48 -> 4.2635135 | H4: =0.45/1.48 -> 0.30405405 | I4: =0.58/1.48 -> 0.39189189 | J4: =0.58/1.4 -> 0.41428571 | K4: =0.63/1.48 -> 0.42567568 | L4: =0.5/1.4 -> 0.35714286 | M4: =8*1.48 -> 11.84 | N4: W3 2023 | O4: 45627 | P4: Georgia Chapman | Q4: On-track | R4: Challenge transportation pack assumptions
B5: Falcon | C5: Trent 1000 | D5: Gulf | E5: NDSES improvement through SPE sales | F5: =10.15/1.48 -> 6.8581081 | H5: =0.69/1.48 -> 0.46621622 | I5: =0.64/1.48 -> 0.43243243 | J5: =0.61/1.48 -> 0.41216216 | K5: =0.69/1.48 -> 0.46621622 | L5: =0.54/1.48 -> 0.36486486 | M5: =1.5*1.48 -> 2.22 | N5: W3 2023 | O5: 45627 | P5: Georgia Chapman | Q5: On-track
B6: Burgundy | C6: Trent XWB-97 | D6: Qatar | E6: SPE Pull-forward | F6: =4.7 -> 4.7 | M6: =57*1.48 -> 84.36 | N6: W3 2023 | O6: 45596 | P6: Matthew Whatley | Q6: On-track
B7: Burgundy | C7: Multiple | D7: Qatar | E7: Transportation | M7: =25*1.48 -> 37 | N7: W3 2023 | O7: 45596 | P7: Matthew Whatley | Q7: On-track
B8: Burgundy | C8: Trent XWB-84 | D8: Qatar | E8: Exit for convenience removal | F8: =60*1.48 -> 88.8 | M8: =60*1.48 -> 88.8 | N8: W3 2023 | O8: 45565 | P8: Matthew Whatley | Q8: On-track
B9: Burgundy | C9: Trent XWB-97 | D9: Qatar | E9: Exit for convenience removal | G9: =1.48*127 -> 187.96 | M9: =127*1.48 -> 187.96 | N9: W3 2023 | O9: 45961 | P9: Matthew Whatley | Q9: On-track
B10: FiniQ | C10: Trent 900 | D10: Emirates | E10: Extension | G10: =1.48*437 -> 646.76 | M10: =600*1.48 -> 888 | N10: W3 2023 | O10: 45778 | P10: Matthew Whatley | Q10: On-track
B11: FiniQ | C11: Trent XWB-84 | D11: Emirates | E11: 3 year-extension + SPEs + LRU Management | N11: W3 2023 | O11: 45565 | P11: Matthew Whatley | Q11: On-track
B12: N/A | C12: Trent 900 | D12: Emirates | E12: LRU Management optimisation | O12: 45778 | P12: Darren O'Neill
B13: N/A | C13: Trent 1000 | D13: Egypt | E13: Time on wing improvements | P13: Tim Broadhead | R13: Challenge ToW pack assumptions
B14: N/A | C14: Trent XWB-97 | D14: Uganda | E14: Regional Engine washing
B15: N/A | C15: Trent 1000 | D15: Ethiopia | E15: Contract extension/NDSES reduction
B16: N/A | C16: Multiple | D16: Qatar | E16: 3 year extension

Sheet INPUT
C3: INPUT
C8: PROBABILITY | F8: COMPLEXITY | I8: WEIGHTS | L8: YEARS
C10: PROB | D10: SCORE | F10: COMPLEXITY | G10: SCORE | I10: FACTORS | J10: WEIGHT | L10: YEAR | M10: SCORE
C11: High | D11: 3 | F11: High | G11: 1 | I11: PROB | J11: 1 | L11: 2026
C12: Med | D12: 2 | F12: Med | G12: 1 | I12: COMPLEX | J12: 1 | L12: 2027
C13: Low | D13: 1 | F13: Low | G13: 1 | L13: 2028
C14: ="-" -> - | F14: ="-" -> - | L14: 2029
L15: 2030
L16: 2031
C17: STATUS | F17: PROJECT | I17: PROJECT
C19: STATUS | F19: CUSTOMER | G19: PROEJCT | I19: PROGRAMME
C20: Hopper | F20: {=IF(_xlfn.UNIQUE('MEA LOG'!$F$15:$F$100)<>0,_xlfn.UNIQUE('MEA LOG'!$F$15:$F$100),"")} -> Emirates | G20: {=IF(_xlfn.UNIQUE('MEA LOG'!$D$15:$D$100)<>0,_xlfn.UNIQUE('MEA LOG'!$D$15:$D$100),"")} -> FiniQ II | I20: Trent XWB-84
C21: ICT | F21: Ethiopia | G21: FiniQ III | I21: Trent XWB-97
C22: Negotiations | F22: Qatar | G22: IDK | I22: Trent 1000
C23: Contracting | F23: Qatar Amiri | G23: Selassi | I23: Trent 500
C24: Completed | F24: Egypt | G24: Selassi II | I24: Trent 700
C25: Cancelled | F25: Turkmenistan | G25: Burgundy | I25: RB211-524
F26: Qanot Sharq | G26: Burgundy II | I26: Trent 7000
C27: REGIONS | F27: Silkway | G27: Burgundy III
F28: Senegal | G28: QA | I28: NORMALIZE
C29: REGIONS | F29: Air Algerie | G29: Horus
C30: Americas | F30: Etihad | G30: Horus II | I30: TERM IMPACT | J30: VALUE | L30: 26/27 | M30: VALUE
C31: APAC | F31: Saudia | G31: Horus III | I31: MAX | J31: =MAX('MEA LOG'!S15:S99) -> 341.88 | L31: MAX | M31: =MAX('MEA LOG'!V15:V99) -> 68.08
C32: Europe | F32: Tanzania | G32: Horus IV | I32: MIN | J32: =MIN('MEA LOG'!S15:S99) -> 0 | L32: MIN | M32: =MIN('MEA LOG'!V15:V99) -> 0
C33: Greater China | F33: Gulf | G33: Turk | I33: MAX-MIN | J33: =J31-J32 -> 341.88 | L33: MAX-MIN | M33: =M31-M32 -> 68.08
C34: MEA | F34: Austral | G34: Qanot
F35: Kuwait | G35: SW | I35: 26 | J35: VALUE | L35: 27 | M35: VALUE
C36: Status | F36: Mauritus | G36: Sen | I36: MAX | J36: =MAX('MEA LOG'!T15:T99) -> 68.08 | L36: MAX | M36: =MAX('MEA LOG'!U15:U99) -> 45.88
F37: Rwanda | G37: Viva Algeria | I37: MIN | J37: =MIN('MEA LOG'!T15:T99) -> 0 | L37: MIN | M37: =MIN('MEA LOG'!U15:U99) -> 0
C38: Status | F38: SAA | G38: Dhabi I | I38: MAX-MIN | J38: =J36-J37 -> 68.08 | L38: MAX-MIN | M38: =M36-M37 -> 45.88
C39: Planned | G39: Dhabi II
C40: On-Going | G40: Saud
C41: Completed | G41: Saud II
C42: Cancelled | G42: Tanz
G43: Falcon
G44: Star
G45: Q8
C46: Type | G46: Mau
C47: Cost Reduction | G47: Dodo
C48: TCA Amendments | G48: RW
C49: Term Extension | G49: SAA
C50: Other | G50: Horus V
C51: Service Upsells | G51: Pantheon
C52: New a/c | G52: Cotton
C53: SPE increase

Sheet User Guide
A1: MEA Profit Opportunites Tracker
Q2: Version: V1.0
A3: Scope
B4: MEA LOG | C4: Log Sheet where the opportunity is identifies, priority, probability and current status are assigned and monitored along with initial AM estimates
B5: ICT Estimtes | C5: Profit Estimates evaluated by the ICT
B6: Contracting | C6: Profit Impact based on the contracted levles
B7: MEA Commercial Optimisation Report
A9: Instructions
A10: 1.1 | B10: Opportunity Identification
A11: Sheet: | B11: "MEA LOG"
A13: The MEA LOG sheet will include all non financial details of the Opportunity, along with initial AM estimates
A14: The Status column (Column Q) is to be updated as the opportuntiy progress through "ICT", "Negotiations", "Contracting" till "Completed"
A16: Note: Any changes to the Asks, levers, status, or any non-finanical details should be adjusted in the MEA LOG
A18: 1.2 | B18: ICT Estimates
A19: Sheet: | B19: "L2" sheet
A21: ICT estimates,which can be accessed by clicking ICT Estimates or L2 Sheet
A24: 1.3 | B24: Contracting
A25: Sheet: | B25: "L3" sheet
A27: Contracting level profit imprvoment, which can be accessed by clicking Contrcating or L3 Sheet
A29: 2 | B29: Timeline
A30: Sheet: | B30: Timeline
A32: The sheet is used to input the planned timeline against every commercial project following the Below structure
B34: Hopper | C34: Idea Generation
C35: Approval to Launch
B36: ICT | C36: Strategy Apporval
C37: BE Generated
C38: Apprvoal
B39: Negotiations | C39: Negotiations Strategy
C40: Proposal Submitted
C41: Proposal Signed
A43: Minor steps can be added in blank cells to be viewed then in the MEA Commercial Optimisation Report
A44: Note: Please ensure that the structure and the organisation of each milestone is maintained
A46: 3 | B46: MEA Commercial Optimisation Report
A47: File: | B47: MEA Commercial Optimisation Report
A49: The MEA Commercial Optimisation report is a Power BI dashboard that uses the data stored in this workbook to visualise all commercial opportunties

Sheet COVER
C3: COMMERCIAL OPTIMISATION OPPORTUNITY REPORT
C55: OPP COUNT
C57: =SUM(COUNT!D11:D29) -> 45
C59: PROB | D59: COUNIT OF OPP | E59: % OF ALL OPP | G59: COMPLEXITY | H59: COUNIT OF OPP | I59: % OF ALL OPP | K59: STATUS | L59: COUNIT OF OPP | M59: % OF ALL OPP | O59: YEARS | P59: COUNIT OF OPP | Q59: % OF ALL OPP
C60: {=_xlfn._xlws.FILTER(INPUT!C11:C13,TRUE)} -> High | D60: =COUNTIF('MEA LOG'!$O$15:$O$99,COVER!C60) -> 11 | E60: =D60/SUM($D$60:$D$62) -> 0.24444444 | G60: {=_xlfn._xlws.FILTER(INPUT!F11:F13,TRUE)} -> High | H60: =COUNTIF('MEA LOG'!$P$15:$P$99,COVER!C60) -> 5 | I60: =H60/SUM($H$60:$H$62) -> 0.11111111 | K60: {=_xlfn._xlws.FILTER(INPUT!$C$20:$C$24,TRUE)} -> Hopper | L60: =COUNTIF('MEA LOG'!$Q$15:$Q$99,K60) -> 17 | M60: =L60/SUM($L$60:$L$64) -> 0.45945946 | O60: {=_xlfn._xlws.FILTER(INPUT!L11:L16,TRUE)} -> 2026 | P60: =COUNTIF('MEA LOG'!$T$15:$T$99,"<>") -> 36 | Q60: =P60/SUM($P$60:$P$65) -> 0.8
C61: Med | D61: =COUNTIF('MEA LOG'!$O$15:$O$99,COVER!C61) -> 15 | E61: =D61/SUM($D$60:$D$62) -> 0.33333333 | G61: Med | H61: =COUNTIF('MEA LOG'!$P$15:$P$99,COVER!C61) -> 26 | I61: =H61/SUM($H$60:$H$62) -> 0.57777778 | K61: ICT | L61: =COUNTIF('MEA LOG'!$Q$15:$Q$99,K61) -> 5 | M61: =L61/SUM($L$60:$L$64) -> 0.13513514 | O61: 2027 | P61: =COUNTIF('MEA LOG'!$U$15:$U$99,"<>") -> 35 | Q61: =P61/SUM($P$60:$P$65) -> 0.77777778
C62: Low | D62: =COUNTIF('MEA LOG'!$O$15:$O$99,COVER!C62) -> 19 | E62: =D62/SUM($D$60:$D$62) -> 0.42222222 | G62: Low | H62: =COUNTIF('MEA LOG'!$P$15:$P$99,COVER!C62) -> 14 | I62: =H62/SUM($H$60:$H$62) -> 0.31111111 | K62: Negotiations | L62: =COUNTIF('MEA LOG'!$Q$15:$Q$99,K62) -> 3 | M62: =L62/SUM($L$60:$L$64) -> 0.081081081 | O62: 2028 | P62: =($C$57-SUM($P$60:$P$61))/4 -> -6.5 | Q62: =P62/SUM($P$60:$P$65) -> -0.14444444
K63: Contracting | L63: =COUNTIF('MEA LOG'!$Q$15:$Q$99,K63) -> 3 | M63: =L63/SUM($L$60:$L$64) -> 0.081081081 | O63: 2029 | P63: =($C$57-SUM($P$60:$P$61))/4 -> -6.5 | Q63: =P63/SUM($P$60:$P$65) -> -0.14444444
K64: Completed | L64: =COUNTIF('MEA LOG'!$Q$15:$Q$99,K64) -> 9 | M64: =L64/SUM($L$60:$L$64) -> 0.24324324 | O64: 2030 | P64: =($C$57-SUM($P$60:$P$61))/4 -> -6.5 | Q64: =P64/SUM($P$60:$P$65) -> -0.14444444
O65: 2031 | P65: =($C$57-SUM($P$60:$P$61))/4 -> -6.5 | Q65: =P65/SUM($P$60:$P$65) -> -0.14444444
C80: IMPACT DIST
C82: ='MEA LOG'!S12 -> 1531.432
C84: PROB | D84: SUM OF IMPACT | E84: % OF TOTAL IMPACT | G84: COMPLEXITY | H84: SUM OF IMPACT | I84: % OF TOTAL IMPACT | K84: STATUS | L84: SUM OF IMPACT | M84: % OF TOTAL IMPACT | O84: YEARS | P84: SUM OF IMPACT | Q84: % OF TOTAL IMPACT
C85: {=_xlfn._xlws.FILTER(INPUT!C11:C13,TRUE)} -> High | D85: =SUMIF('MEA LOG'!$O$15:$O$99,COVER!C85,'MEA LOG'!$S$15:$S$99) -> 782.36 | E85: =D85/'MEA LOG'!$S$12 -> 0.51086826 | G85: {=_xlfn._xlws.FILTER(INPUT!F11:F13,TRUE)} -> High | H85: =SUMIF('MEA LOG'!$P$15:$P$99,COVER!G85,'MEA LOG'!$S$15:$S$99) -> 156.92 | I85: =H85/'MEA LOG'!$S$12 -> 0.10246619 | K85: {=_xlfn._xlws.FILTER(INPUT!$C$20:$C$24,TRUE)} -> Hopper | L85: =SUMIF('MEA LOG'!$Q$15:$Q$99,COVER!K85,'MEA LOG'!$S$15:$S$99) -> 413.72 | M85: =L85/'MEA LOG'!$S$12 -> 0.27015238 | O85: {=_xlfn._xlws.FILTER(INPUT!L11:L16,TRUE)} -> 2026 | P85: =SUM('MEA LOG'!T$15:T$99) -> 156.74607 | Q85: =P85/$C$82 -> 0.10235261
C86: Med | D86: =SUMIF('MEA LOG'!$O$15:$O$99,COVER!C86,'MEA LOG'!$S$15:$S$99) -> 211.712 | E86: =D86/'MEA LOG'!$S$12 -> 0.13824447 | G86: Med | H86: =SUMIF('MEA LOG'!$P$15:$P$99,COVER!G86,'MEA LOG'!$S$15:$S$99) -> 622.892 | I86: =H86/'MEA LOG'!$S$12 -> 0.40673827 | K86: ICT | L86: =SUMIF('MEA LOG'!$Q$15:$Q$99,COVER!K86,'MEA LOG'!$S$15:$S$99) -> 188.62 | M86: =L86/'MEA LOG'!$S$12 -> 0.12316577 | O86: 2027 | P86: =SUM('MEA LOG'!U$15:U$99) -> 183.99273 | Q86: =P86/$C$82 -> 0.12014424
C87: Low | D87: =SUMIF('MEA LOG'!$O$15:$O$99,COVER!C87,'MEA LOG'!$S$15:$S$99) -> 537.36 | E87: =D87/'MEA LOG'!$S$12 -> 0.35088727 | G87: Low | H87: =SUMIF('MEA LOG'!$P$15:$P$99,COVER!G87,'MEA LOG'!$S$15:$S$99) -> 751.62 | I87: =H87/'MEA LOG'!$S$12 -> 0.49079554 | K87: Negotiations | L87: =SUMIF('MEA LOG'!$Q$15:$Q$99,COVER!K87,'MEA LOG'!$S$15:$S$99) -> 47.88 | M87: =L87/'MEA LOG'!$S$12 -> 0.031264855 | O87: 2028 | P87: =($C$82-SUM($P$85:$P$86))/4 -> 297.6733 | Q87: =P87/$C$82 -> 0.19437579
K88: Contracting | L88: =SUMIF('MEA LOG'!$Q$15:$Q$99,COVER!K88,'MEA LOG'!$S$15:$S$99) -> 82.18 | M88: =L88/'MEA LOG'!$S$12 -> 0.053662193 | O88: 2029 | P88: =($C$82-SUM($P$85:$P$86))/4 -> 297.6733 | Q88: =P88/$C$82 -> 0.19437579
K89: Completed | L89: =SUMIF('MEA LOG'!$Q$15:$Q$99,COVER!K89,'MEA LOG'!$S$15:$S$99) -> 606.192 | M89: =L89/'MEA LOG'!$S$12 -> 0.39583344 | O89: 2030 | P89: =($C$82-SUM($P$85:$P$86))/4 -> 297.6733 | Q89: =P89/$C$82 -> 0.19437579
O90: 2031 | P90: =($C$82-SUM($P$85:$P$86))/4 -> 297.6733 | Q90: =P90/$C$82 -> 0.19437579
C104: 2026
C106: =SUM('MEA LOG'!T15:T99) -> 156.74607
C108: PROB | D108: SUM OF IMPACT | E108: % OF TOTAL IMPACT | G108: COMPLEXITY | H108: SUM OF IMPACT | I108: % OF TOTAL IMPACT | K108: STATUS | L108: SUM OF IMPACT | M108: % OF TOTAL IMPACT
C109: {=_xlfn._xlws.FILTER(INPUT!C11:C13,TRUE)} -> High | D109: =SUMIF('MEA LOG'!$O$15:$O$99,COVER!C109,'MEA LOG'!$T$15:$T$99) -> 75.301666 | E109: =D109/$C$106 -> 0.48040546 | G109: {=_xlfn._xlws.FILTER(INPUT!F11:F13,TRUE)} -> High | H109: =SUMIF('MEA LOG'!$P$15:$P$99,G109,'MEA LOG'!$T$15:$T$99) -> 82.16 | I109: =H109/$C$106 -> 0.52415988 | K109: {=_xlfn._xlws.FILTER(INPUT!$C$20:$C$24,TRUE)} -> Hopper | L109: =SUMIF('MEA LOG'!$Q$15:$Q$99,COVER!K109,'MEA LOG'!$T$15:$T$99) -> 29.878 | M109: =L109/$C$106 -> 0.19061403
C110: Med | D110: =SUMIF('MEA LOG'!$O$15:$O$99,COVER!C110,'MEA LOG'!$T$15:$T$99) -> 37.2844 | E110: =D110/$C$106 -> 0.23786498 | G110: Med | H110: =SUMIF('MEA LOG'!$P$15:$P$99,G110,'MEA LOG'!$T$15:$T$99) -> 40.264733 | I110: =H110/$C$106 -> 0.25687875 | K110: ICT | L110: =SUMIF('MEA LOG'!$Q$15:$Q$99,COVER!K110,'MEA LOG'!$T$15:$T$99) -> 0.076 | M110: =L110/$C$106 -> 0.00048486065
C111: Low | D111: =SUMIF('MEA LOG'!$O$15:$O$99,COVER!C111,'MEA LOG'!$T$15:$T$99) -> 44.16 | E111: =D111/$C$106 -> 0.28172956 | G111: Low | H111: =SUMIF('MEA LOG'!$P$15:$P$99,G111,'MEA LOG'!$T$15:$T$99) -> 34.321333 | I111: =H111/$C$106 -> 0.21896137 | K111: Negotiations | L111: =SUMIF('MEA LOG'!$Q$15:$Q$99,COVER!K111,'MEA LOG'!$T$15:$T$99) -> 2.04 | M111: =L111/$C$106 -> 0.013014681
K112: Contracting | L112: =SUMIF('MEA LOG'!$Q$15:$Q$99,COVER!K112,'MEA LOG'!$T$15:$T$99) -> 70.78 | M112: =L112/$C$106 -> 0.45155838
K113: Completed | L113: =SUMIF('MEA LOG'!$Q$15:$Q$99,COVER!K113,'MEA LOG'!$T$15:$T$99) -> 38.852066 | M113: =L113/$C$106 -> 0.24786629
C128: 2027
C130: =SUM('MEA LOG'!U15:U99) -> 183.99273
C132: PROB | D132: SUM OF IMPACT | E132: % OF TOTAL IMPACT | G132: COMPLEXITY | H132: SUM OF IMPACT | I132: % OF TOTAL IMPACT | K132: STATUS | L132: SUM OF IMPACT | M132: % OF TOTAL IMPACT
C133: {=_xlfn._xlws.FILTER(INPUT!C11:C13,TRUE)} -> High | D133: =SUMIF('MEA LOG'!$O$15:$O$99,COVER!C133,'MEA LOG'!$U$15:$U$99) -> 72.78833 | E133: =D133/$C$130 -> 0.39560438 | G133: {=_xlfn._xlws.FILTER(INPUT!F11:F13,TRUE)} -> High | H133: =SUMIF('MEA LOG'!$P$15:$P$99,G133,'MEA LOG'!$U$15:$U$99) -> 59.96 | I133: =H133/$C$130 -> 0.32588244 | K133: {=_xlfn._xlws.FILTER(INPUT!$C$20:$C$24,TRUE)} -> Hopper | L133: =SUMIF('MEA LOG'!$Q$15:$Q$99,COVER!K133,'MEA LOG'!$U$15:$U$99) -> 75.758 | M133: =L133/$C$130 -> 0.41174453
C134: Med | D134: =SUMIF('MEA LOG'!$O$15:$O$99,COVER!C134,'MEA LOG'!$U$15:$U$99) -> 9.5844 | E134: =D134/$C$130 -> 0.052091189 | G134: Med | H134: =SUMIF('MEA LOG'!$P$15:$P$99,G134,'MEA LOG'!$U$15:$U$99) -> 71.06473 | I134: =H134/$C$130 -> 0.38623662 | K134: ICT | L134: =SUMIF('MEA LOG'!$Q$15:$Q$99,COVER!K134,'MEA LOG'!$U$15:$U$99) -> 20.076 | M134: =L134/$C$130 -> 0.10911301
C135: Low | D135: =SUMIF('MEA LOG'!$O$15:$O$99,COVER!C135,'MEA LOG'!$U$15:$U$99) -> 101.62 | E135: =D135/$C$130 -> 0.55230443 | G135: Low | H135: =SUMIF('MEA LOG'!$P$15:$P$99,G135,'MEA LOG'!$U$15:$U$99) -> 52.968 | I135: =H135/$C$130 -> 0.28788094 | K135: Negotiations | L135: =SUMIF('MEA LOG'!$Q$15:$Q$99,COVER!K135,'MEA LOG'!$U$15:$U$99) -> 32.04 | M135: =L135/$C$130 -> 0.17413732
K136: Contracting | L136: =SUMIF('MEA LOG'!$Q$15:$Q$99,COVER!K136,'MEA LOG'!$U$15:$U$99) -> 0 | M136: =L136/$C$130 -> 0
K137: Completed | L137: =SUMIF('MEA LOG'!$Q$15:$Q$99,COVER!K137,'MEA LOG'!$U$15:$U$99) -> 23.49873 | M137: =L137/$C$130 -> 0.12771554
C151: SPE
C153: =SUM('MEA LOG'!$M$15:$M$99) -> 8
C155: PROB | D155: SUM OF ENGINES | E155: % OF TOTAL IMPACT | G155: COMPLEXITY | H155: SUM OF ENGINES | I155: % OF TOTAL IMPACT | K155: STATUS | L155: SUM OF IMPACT | M155: % OF TOTAL IMPACT
C156: {=_xlfn._xlws.FILTER(INPUT!C11:C13,TRUE)} -> High | D156: =SUMIF('MEA LOG'!$O$15:$O$99,COVER!C156,'MEA LOG'!$M$15:$M$99) -> 1 | E156: =D156/$C$153 -> 0.125 | G156: {=_xlfn._xlws.FILTER(INPUT!F11:F13,TRUE)} -> High | H156: =SUMIF('MEA LOG'!$P$15:$P$99,COVER!G156,'MEA LOG'!$M$15:$M$99) -> 0 | I156: =H156/$C$153 -> 0 | K156: {=_xlfn._xlws.FILTER(INPUT!$C$20:$C$24,TRUE)} -> Hopper | L156: =SUMIF('MEA LOG'!$Q$15:$Q$99,K156,'MEA LOG'!$M$15:$M$99) -> 3 | M156: =L156/$C$153 -> 0.375
C157: Med | D157: =SUMIF('MEA LOG'!$O$15:$O$99,COVER!C157,'MEA LOG'!$M$15:$M$99) -> 1 | E157: =D157/$C$153 -> 0.125 | G157: Med | H157: =SUMIF('MEA LOG'!$P$15:$P$99,COVER!G157,'MEA LOG'!$M$15:$M$99) -> 6 | I157: =H157/$C$153 -> 0.75 | K157: ICT | L157: =SUMIF('MEA LOG'!$Q$15:$Q$99,K157,'MEA LOG'!$M$15:$M$99) -> 0 | M157: =L157/$C$153 -> 0
C158: Low | D158: =SUMIF('MEA LOG'!$O$15:$O$99,COVER!C158,'MEA LOG'!$M$15:$M$99) -> 6 | E158: =D158/$C$153 -> 0.75 | G158: Low | H158: =SUMIF('MEA LOG'!$P$15:$P$99,COVER!G158,'MEA LOG'!$M$15:$M$99) -> 2 | I158: =H158/$C$153 -> 0.25 | K158: Negotiations | L158: =SUMIF('MEA LOG'!$Q$15:$Q$99,K158,'MEA LOG'!$M$15:$M$99) -> 1 | M158: =L158/$C$153 -> 0.125
K159: Contracting | L159: =SUMIF('MEA LOG'!$Q$15:$Q$99,K159,'MEA LOG'!$M$15:$M$99) -> 1 | M159: =L159/$C$153 -> 0.125
K160: Completed | L160: =SUMIF('MEA LOG'!$Q$15:$Q$99,K160,'MEA LOG'!$M$15:$M$99) -> 1 | M160: =L160/$C$153 -> 0.125
C174: SPE IMPACT
C176: =SUMIF('MEA LOG'!$L$15:$L$99,"yes",'MEA LOG'!$S$15:$S$99) -> 299.58
C178: PROB | D178: SUM OF IMPACT | E178: % OF TOTAL IMPACT | G178: COMPLEXITY | H178: SUM OF IMPACT | I178: % OF TOTAL IMPACT | K178: STATUS | L178: SUM OF IMPACT | M178: % OF TOTAL IMPACT
C179: {=_xlfn._xlws.FILTER(INPUT!C11:C13,TRUE)} -> High | D179: =SUMIFS('MEA LOG'!$S$15:$S$99,'MEA LOG'!$O$15:$O$99,COVER!C179,'MEA LOG'!$L$15:$L$99,"yes") -> 140 | E179: =D179/$C$176 -> 0.46732092 | G179: {=_xlfn._xlws.FILTER(INPUT!F11:F13,TRUE)} -> High | H179: =SUMIFS('MEA LOG'!$S$15:$S$99,'MEA LOG'!$P$15:$P$99,COVER!C179,'MEA LOG'!$L$15:$L$99,"yes") -> 0 | I179: =H179/$C$176 -> 0 | K179: {=_xlfn._xlws.FILTER(INPUT!$C$20:$C$24,TRUE)} -> Hopper | L179: =SUMIFS('MEA LOG'!$S$15:$S$99,'MEA LOG'!$L$15:$L$99,"yes",'MEA LOG'!$Q$15:$Q$99,COVER!K179) -> 65.84 | M179: =L179/$C$176 -> 0.21977435
C180: Med | D180: =SUMIFS('MEA LOG'!$S$15:$S$99,'MEA LOG'!$O$15:$O$99,COVER!C180,'MEA LOG'!$L$15:$L$99,"yes") -> 39.54 | E180: =D180/$C$176 -> 0.13198478 | G180: Med | H180: =SUMIFS('MEA LOG'!$S$15:$S$99,'MEA LOG'!$P$15:$P$99,COVER!C180,'MEA LOG'!$L$15:$L$99,"yes") -> 79.74 | I180: =H180/$C$176 -> 0.26617264 | K180: ICT | L180: =SUMIFS('MEA LOG'!$S$15:$S$99,'MEA LOG'!$L$15:$L$99,"yes",'MEA LOG'!$Q$15:$Q$99,COVER!K180) -> 0 | M180: =L180/$C$176 -> 0
C181: Low | D181: =SUMIFS('MEA LOG'!$S$15:$S$99,'MEA LOG'!$O$15:$O$99,COVER!C181,'MEA LOG'!$L$15:$L$99,"yes") -> 120.04 | E181: =D181/$C$176 -> 0.40069431 | G181: Low | H181: =SUMIFS('MEA LOG'!$S$15:$S$99,'MEA LOG'!$P$15:$P$99,COVER!C181,'MEA LOG'!$L$15:$L$99,"yes") -> 219.84 | I181: =H181/$C$176 -> 0.73382736 | K181: Negotiations | L181: =SUMIFS('MEA LOG'!$S$15:$S$99,'MEA LOG'!$L$15:$L$99,"yes",'MEA LOG'!$Q$15:$Q$99,COVER!K181) -> 30 | M181: =L181/$C$176 -> 0.1001402
K182: Contracting | L182: =SUMIFS('MEA LOG'!$S$15:$S$99,'MEA LOG'!$L$15:$L$99,"yes",'MEA LOG'!$Q$15:$Q$99,COVER!K182) -> 2.7 | M182: =L182/$C$176 -> 0.0090126177
K183: Completed | L183: =SUMIFS('MEA LOG'!$S$15:$S$99,'MEA LOG'!$L$15:$L$99,"yes",'MEA LOG'!$Q$15:$Q$99,COVER!K183) -> 178 | M183: =L183/$C$176 -> 0.59416516
C199: ='MEA LOG'!V14 -> Sum of 26/27
C201: =SUM('MEA LOG'!V15:V513) -> 340.7388
C203: PROB | D203: SUM OF IMPACT | E203: % OF TOTAL IMPACT | G203: COMPLEXITY | H203: SUM OF IMPACT | I203: % OF TOTAL IMPACT | K203: STATUS | L203: SUM OF IMPACT | M203: % OF TOTAL IMPACT
C204: {=_xlfn._xlws.FILTER(INPUT!C11:C13,TRUE)} -> High | D204: =SUMIFS('MEA LOG'!$V$15:$V$99,'MEA LOG'!$O$15:$O$99,COVER!C204) -> 148.09 | E204: =D204/$C$201 -> 0.43461443 | G204: {=_xlfn._xlws.FILTER(INPUT!F11:F13,TRUE)} -> High | H204: =SUMIFS('MEA LOG'!$V$15:$V$99,'MEA LOG'!$P$15:$P$99,G204) -> 142.12 | I204: =H204/$C$201 -> 0.41709368 | K204: {=_xlfn._xlws.FILTER(INPUT!$C$20:$C$24,TRUE)} -> Hopper | L204: =SUMIFS('MEA LOG'!$V$15:$V$99,'MEA LOG'!$Q$15:$Q$99,K204) -> 105.636 | M204: =L204/$C$201 -> 0.31002046
C205: Med | D205: =SUMIFS('MEA LOG'!$V$15:$V$99,'MEA LOG'!$O$15:$O$99,COVER!C205) -> 46.8688 | E205: =D205/$C$201 -> 0.13755052 | G205: Med | H205: =SUMIFS('MEA LOG'!$V$15:$V$99,'MEA LOG'!$P$15:$P$99,G205) -> 111.32946 | I205: =H205/$C$201 -> 0.32672964 | K205: ICT | L205: =SUMIFS('MEA LOG'!$V$15:$V$99,'MEA LOG'!$Q$15:$Q$99,K205) -> 20.152 | M205: =L205/$C$201 -> 0.059142077
C206: Low | D206: =SUMIFS('MEA LOG'!$V$15:$V$99,'MEA LOG'!$O$15:$O$99,COVER!C206) -> 145.78 | E206: =D206/$C$201 -> 0.42783505 | G206: Low | H206: =SUMIFS('MEA LOG'!$V$15:$V$99,'MEA LOG'!$P$15:$P$99,G206) -> 87.289333 | I206: =H206/$C$201 -> 0.25617668 | K206: Negotiations | L206: =SUMIFS('MEA LOG'!$V$15:$V$99,'MEA LOG'!$Q$15:$Q$99,K206) -> 34.08 | M206: =L206/$C$201 -> 0.10001796
K207: Contracting | L207: =SUMIFS('MEA LOG'!$V$15:$V$99,'MEA LOG'!$Q$15:$Q$99,K207) -> 70.78 | M207: =L207/$C$201 -> 0.2077251
K208: Completed | L208: =SUMIFS('MEA LOG'!$V$15:$V$99,'MEA LOG'!$Q$15:$Q$99,K208) -> 62.350796 | M208: =L208/$C$201 -> 0.18298708

Sheet MEA LOG
C3: OPP LOG SHEET | V3: Hopper | Z3: FINANCIAL CRITERIA | BO3: RESOURCE PRIORITIZATION
V5: ICT Estimates
S6: =TODAY() -> 46069
V7: Contract
C8: AWAY DAY DATE | E8: 45768
BO9: High Priority | BP9: Med Priority | BQ9: Low Priority | BR9: Not Required
Q10: Account Management Evaluations for review | BO10: 1 | BP10: 2 | BQ10: 3
Q12: SUMS: | S12: =SUM(S15:S99) -> 1531.432 | T12: =SUM(T15:T99) -> 156.74607 | U12: =SUM(U15:U99) -> 183.99273 | V12: =SUM(V15:V99) -> 340.7388 | Z12: Existing Deal | AM12: New Deal | AZ12: Supporting Financial Information | BI12: To Go | BO12: Priority
M13: =SUM($N$15:$N$513) -> 10.73 | N13: =SUM($O$15:$O$513) -> 0 | Z13: Cash Reciepts | AF13: In Year Profit | AM13: Cash Reciepts | AS13: In Year Profit
C14: # | D14: Project | E14: Programme | F14: Customer | G14: Region | H14: Asks | I14: Type of Opportunity | J14: Levers | K14: Priority | L14: SPE related | M14: No,of SPE | N14: CRP% | O14: External Probability | P14: Internal Complexity | Q14: Status | R14: Evaluation Level | S14: Term Benefit | T14: 2026 | U14: 2027 | V14: Sum of 26/27 | Z14: 2025 | AA14: 2026 | AB14: 2027 | AC14: 2028 | AD14: 2029 | AE14: 2030 | AF14: 2025 | AG14: 2026 | AH14: 2027 | AI14: 2028 | AJ14: 2029 | AK14: 2030 | AM14: 2025 | AN14: 2026 | AO14: 2027 | AP14: 2028 | AQ14: 2029 | AR14: 2030 | AS14: 2025 | AT14: 2026 | AU14: 2027 | AV14: 2028 | AW14: 2029 | AX14: 2030 | AZ14: Deal Benefits | BA14: Expected Deal Costs | BB14: In-year Profit Impact | BC14: 5YP Profit Improvement | BD14: Term Profit Imprvement | BE14: Total CRP Term Revnue | BF14: Total CRP Term Margin | BG14: CRP Margin % | BI14: Term Revenue | BJ14: Term Cost | BK14: Term Profit | BO14: Account Management | BP14: Contract Management | BQ14: Service Business | BR14: Business Evalautaion | BS14: Sales & Contracting | BT14: Customer Operations
C15: 1 | D15: FiniQ II | E15: Trent XWB-84 | F15: Emirates | G15: MEA | H15: 3 year-extension + LRU Management + 23 a/c | I15: TCA Amendments | J15: XWB MRO - OWS Support - 97k & EP Pricing | K15: 1 | N15: 0 | O15: High | P15: Low | Q15: Completed | S15: =231*1.48 -> 341.88 | V15: =SUM(T15+U15) -> 0 | Y15: 0 | Z15: 0 | AA15: 0 | AB15: 0 | AC15: 0 | AD15: 0 | AE15: 0 | AF15: 0 | AG15: 0 | AH15: 0 | AI15: 0 | AJ15: 0 | AK15: 0 | AL15: 0 | AM15: 0 | AN15: 0 | AO15: 0 | AP15: 0 | AQ15: 0 | AR15: 0 | AS15: 0 | AT15: 0 | AU15: 0 | AV15: 0 | AW15: 0 | AX15: 0 | AZ15: 0 | BA15: 0 | BB15: 0 | BC15: 0 | BD15: 0 | BE15: 0 | BF15: 0 | BI15: 0 | BJ15: 0 | BK15: 0 | BO15: 1 | BP15: 1 | BQ15: 1 | BR15: 1 | BS15: 1 | BT15: 1 | BU15: 1 | BV15: 1 | BW15: 1 | BX15: 1 | BY15: 1 | BZ15: 1 | CA15: 1 | CB15: 1 | CC15: 1 | CD15: 1 | CE15: 1
C16: 2 | D16: FiniQ III | E16: Trent XWB-84 | F16: Emirates | G16: MEA | H16: OWS - eliminate $20k remedy | I16: Cost Reduction | J16: New Campaign | K16: 1 | N16: 0 | O16: High | P16: Low | Q16: Contracting | S16: 11.4 | V16: =SUM(T16+U16) -> 0 | Y16: 0 | Z16: 0 | AA16: 0 | AB16: 0 | AC16: 0 | AD16: 0 | AE16: 0 | AF16: 0 | AG16: 0 | AH16: 0 | AI16: 0 | AJ16: 0 | AK16: 0 | AL16: 0 | AM16: 0 | AN16: 0 | AO16: 0 | AP16: 0 | AQ16: 0 | AR16: 0 | AS16: 0 | AT16: 0 | AU16: 0 | AV16: 0 | AW16: 0 | AX16: 0 | AZ16: 0 | BA16: 0 | BB16: 0 | BC16: 0 | BD16: 0 | BE16: 0 | BF16: 0 | BI16: 0 | BJ16: 0 | BK16: 0 | BO16: 1 | BP16: 1 | BQ16: 1 | BR16: 1 | BS16: 1 | BT16: 1 | BU16: 1 | BV16: 1 | BW16: 1 | BX16: 1 | BY16: 1 | BZ16: 1 | CA16: 1 | CB16: 1 | CC16: 1 | CD16: 1 | CE16: 1
C17: 3 | D17: IDK | E17: Trent XWB-84 | F17: Emirates | G17: MEA | H17: Additional 3 x SPE (10 %to 12%) | I17: SPE increase | J17: New Campaign | K17: 2 | L17: yes | M17: 3 | N17: 0 | O17: Low | P17: Med | Q17: Hopper | S17: 54 | T17: 20.8 | U17: 20.8 | V17: =SUM(T17+U17) -> 41.6 | Y17: 0 | Z17: 0 | AA17: 0 | AB17: 0 | AC17: 0 | AD17: 0 | AE17: 0 | AF17: 0 | AG17: 0 | AH17: 0 | AI17: 0 | AJ17: 0 | AK17: 0 | AL17: 0 | AM17: 0 | AN17: 0 | AO17: 0 | AP17: 0 | AQ17: 0 | AR17: 0 | AS17: 0 | AT17: 0 | AU17: 0 | AV17: 0 | AW17: 0 | AX17: 0 | AZ17: 0 | BA17: 0 | BB17: 0 | BC17: 0 | BD17: 0 | BE17: 0 | BF17: 0 | BI17: 0 | BJ17: 0 | BK17: 0 | BO17: 1 | BP17: 1 | BQ17: 1 | BR17: 1 | BS17: 1 | BT17: 1 | BU17: 1 | BV17: 1 | BW17: 1 | BX17: 1 | BY17: 1 | BZ17: 1 | CA17: 1 | CB17: 1 | CC17: 1 | CD17: 1 | CE17: 1
C18: 4 | D18: IDK | E18: Trent XWB-84 | F18: Emirates | G18: MEA | H18: Eliminate NDSES Cost via DAT | I18: Cost Reduction | J18: New Campaign/Settlement | K18: 2 | N18: 0 | O18: Med | P18: Med | Q18: ICT | S18: 50 | V18: =SUM(T18+U18) -> 0 | Y18: 0 | Z18: 0 | AA18: 0 | AB18: 0 | AC18: 0 | AD18: 0 | AE18: 0 | AF18: 0 | AG18: 0 | AH18: 0 | AI18: 0 | AJ18: 0 | AK18: 0 | AL18: 0 | AM18: 0 | AN18: 0 | AO18: 0 | AP18: 0 | AQ18: 0 | AR18: 0 | AS18: 0 | AT18: 0 | AU18: 0 | AV18: 0 | AW18: 0 | AX18: 0 | AZ18: 0 | BA18: 0 | BB18: 0 | BC18: 0 | BD18: 0 | BE18: 0 | BF18: 0 | BI18: 0 | BJ18: 0 | BK18: 0 | BO18: 1 | BP18: 1 | BQ18: 1 | BR18: 1 | BS18: 1 | BT18: 1 | BU18: 1 | BV18: 1 | BW18: 1 | BX18: 1 | BY18: 1 | BZ18: 1 | CA18: 1 | CB18: 1 | CC18: 1 | CD18: 1 | CE18: 1
C19: 5 | D19: IDK | E19: Trent XWB-84 | F19: Emirates | G19: MEA | H19: Increase in escalation from 2% to 3% | I19: TCA Amendments | J19: XWB MRO - OWS Support - 97k & EP Pricing | K19: 2 | N19: 0 | O19: Low | P19: Low | Q19: Hopper | S19: 170 | V19: =SUM(T19+U19) -> 0 | Y19: 0 | Z19: 0 | AA19: 0 | AB19: 0 | AC19: 0 | AD19: 0 | AE19: 0 | AF19: 0 | AG19: 0 | AH19: 0 | AI19: 0 | AJ19: 0 | AK19: 0 | AL19: 0 | AM19: 0 | AN19: 0 | AO19: 0 | AP19: 0 | AQ19: 0 | AR19: 0 | AS19: 0 | AT19: 0 | AU19: 0 | AV19: 0 | AW19: 0 | AX19: 0 | AZ19: 0 | BA19: 0 | BB19: 0 | BC19: 0 | BD19: 0 | BE19: 0 | BF19: 0 | BI19: 0 | BJ19: 0 | BK19: 0 | BO19: 1 | BP19: 1 | BQ19: 1 | BR19: 1 | BS19: 1 | BT19: 1 | BU19: 1 | BV19: 1 | BW19: 1 | BX19: 1 | BY19: 1 | BZ19: 1 | CA19: 1 | CB19: 1 | CC19: 1 | CD19: 1 | CE19: 1
C20: 6 | D20: IDK | E20: Trent XWB-84 | F20: Emirates | G20: MEA | H20: Introduce Precedent Matrix | I20: TCA Amendments | J20: XWB MRO - OWS Support - 97k & EP Pricing | K20: 2 | N20: 0 | O20: Low | P20: Med | Q20: Hopper | S20: 50 | V20: =SUM(T20+U20) -> 0 | Y20: 0 | Z20: 0 | AA20: 0 | AB20: 0 | AC20: 0 | AD20: 0 | AE20: 0 | AF20: 0 | AG20: 0 | AH20: 0 | AI20: 0 | AJ20: 0 | AK20: 0 | AL20: 0 | AM20: 0 | AN20: 0 | AO20: 0 | AP20: 0 | AQ20: 0 | AR20: 0 | AS20: 0 | AT20: 0 | AU20: 0 | AV20: 0 | AW20: 0 | AX20: 0 | AZ20: 0 | BA20: 0 | BB20: 0 | BC20: 0 | BD20: 0 | BE20: 0 | BF20: 0 | BI20: 0 | BJ20: 0 | BK20: 0 | BO20: 1 | BP20: 1 | BQ20: 1 | BR20: 1 | BS20: 1 | BT20: 1 | BU20: 1 | BV20: 1 | BW20: 1 | BX20: 1 | BY20: 1 | BZ20: 1 | CA20: 1 | CB20: 1 | CC20: 1 | CD20: 1 | CE20: 1
C21: 7 | D21: Selassi | E21: Trent XWB-84 | F21: Ethiopia | G21: MEA | H21: SPE Pull forward | I21: TCA Amendments | J21: AOG Risk | K21: 1 | L21: yes | M21: 1 | N21: 0.49 | O21: Low | P21: Low | Q21: Completed | S21: 43 | T21: 5.92 | U21: 0 | V21: =SUM(T21+U21) -> 5.92 | Y21: 0 | Z21: 0 | AA21: 0 | AB21: 0 | AC21: 0 | AD21: 0 | AE21: 0 | AF21: 0 | AG21: 0 | AH21: 0 | AI21: 0 | AJ21: 0 | AK21: 0 | AL21: 0 | AM21: 0 | AN21: 0 | AO21: 0 | AP21: 0 | AQ21: 0 | AR21: 0 | AS21: 0 | AT21: 0 | AU21: 0 | AV21: 0 | AW21: 0 | AX21: 0 | AZ21: 0 | BA21: 0 | BB21: 0 | BC21: 0 | BD21: 0 | BE21: 0 | BF21: 0 | BI21: 0 | BJ21: 0 | BK21: 0
C22: 8 | D22: Selassi | E22: Trent XWB-84 | F22: Ethiopia | G22: MEA | H22: Incremental SPE | I22: SPE increase | J22: 2 Addition a/c | K22: 1 | L22: yes | M22: 1 | N22: 0 | O22: High | P22: Low | Q22: Negotiations | S22: 30 | T22: 0 | U22: 30 | V22: =SUM(T22+U22) -> 30 | Y22: 0 | Z22: 0 | AA22: 0 | AB22: 0 | AC22: 0 | AD22: 0 | AE22: 0 | AF22: 0 | AG22: 0 | AH22: 0 | AI22: 0 | AJ22: 0 | AK22: 0 | AL22: 0 | AM22: 0 | AN22: 0 | AO22: 0 | AP22: 0 | AQ22: 0 | AR22: 0 | AS22: 0 | AT22: 0 | AU22: 0 | AV22: 0 | AW22: 0 | AX22: 0 | AZ22: 0 | BA22: 0 | BB22: 0 | BC22: 0 | BD22: 0 | BE22: 0 | BF22: 0 | BI22: 0 | BJ22: 0 | BK22: 0
C23: 9 | D23: Selassi | E23: Trent 1000 | F23: Ethiopia | G23: MEA | H23: Incremental SPE | I23: SPE increase | J23: Campaign | K23: 1 | L23: yes | N23: 0.54 | O23: Med | P23: Low | Q23: Hopper | S23: 11.84 | T23: 2.368 | U23: 2.368 | V23: =SUM(T23+U23) -> 4.736 | Y23: 0 | Z23: 0 | AA23: 0 | AB23: 0 | AC23: 0 | AD23: 0 | AE23: 0 | AF23: 0 | AG23: 0 | AH23: 0 | AI23: 0 | AJ23: 0 | AK23: 0 | AL23: 0 | AM23: 0 | AN23: 0 | AO23: 0 | AP23: 0 | AQ23: 0 | AR23: 0 | AS23: 0 | AT23: 0 | AU23: 0 | AV23: 0 | AW23: 0 | AX23: 0 | AZ23: 0 | BA23: 0 | BB23: 0 | BC23: 0 | BD23: 0 | BE23: 0 | BF23: 0 | BI23: 0 | BJ23: 0 | BK23: 0
C24: 10 | D24: Selassi | E24: Trent 1000 | F24: Ethiopia | G24: MEA | H24: Min Term Extension (life) | I24: Term Extension | J24: Campaign | K24: 1 | N24: 0.54 | O24: Med | P24: Med | Q24: Hopper | S24: 4.44 | T24: 1.48 | U24: 1.48 | V24: =SUM(T24+U24) -> 2.96 | Y24: 0 | Z24: 0 | AA24: 0 | AB24: 0 | AC24: 0 | AD24: 0 | AE24: 0 | AF24: 0 | AG24: 0 | AH24: 0 | AI24: 0 | AJ24: 0 | AK24: 0 | AL24: 0 | AM24: 0 | AN24: 0 | AO24: 0 | AP24: 0 | AQ24: 0 | AR24: 0 | AS24: 0 | AT24: 0 | AU24: 0 | AV24: 0 | AW24: 0 | AX24: 0 | AZ24: 0 | BA24: 0 | BB24: 0 | BC24: 0 | BD24: 0 | BE24: 0 | BF24: 0 | BI24: 0 | BJ24: 0 | BK24: 0
C25: 11 | D25: Selassi II | E25: Trent XWB-84 | F25: Ethiopia | G25: MEA | H25: Min Term Extension | I25: Term Extension | J25: Campaign | K25: 1 | N25: 0.49 | O25: Med | P25: Med | Q25: Hopper | S25: 10 | T25: 1 | U25: 1 | V25: =SUM(T25+U25) -> 2 | Y25: 0 | Z25: 0 | AA25: 0 | AB25: 0 | AC25: 0 | AD25: 0 | AE25: 0 | AF25: 0 | AG25: 0 | AH25: 0 | AI25: 0 | AJ25: 0 | AK25: 0 | AL25: 0 | AM25: 0 | AN25: 0 | AO25: 0 | AP25: 0 | AQ25: 0 | AR25: 0 | AS25: 0 | AT25: 0 | AU25: 0 | AV25: 0 | AW25: 0 | AX25: 0 | AZ25: 0 | BA25: 0 | BB25: 0 | BC25: 0 | BD25: 0 | BE25: 0 | BF25: 0 | BI25: 0 | BJ25: 0 | BK25: 0
C26: 12 | D26: Selassi II | E26: Trent XWB-84 | F26: Ethiopia | G26: MEA | H26: Increase escalation | I26: TCA Amendments | J26: Campaign | K26: 1 | N26: 0.49 | O26: Low | P26: Low | Q26: Hopper | S26: 0 | T26: 0 | U26: 0 | V26: 0 | Y26: 0 | Z26: 0 | AA26: 0 | AB26: 0 | AC26: 0 | AD26: 0 | AE26: 0 | AF26: 0 | AG26: 0 | AH26: 0 | AI26: 0 | AJ26: 0 | AK26: 0 | AL26: 0 | AM26: 0 | AN26: 0 | AO26: 0 | AP26: 0 | AQ26: 0 | AR26: 0 | AS26: 0 | AT26: 0 | AU26: 0 | AV26: 0 | AW26: 0 | AX26: 0 | AZ26: 0 | BA26: 0 | BB26: 0 | BC26: 0 | BD26: 0 | BE26: 0 | BF26: 0 | BI26: 0 | BJ26: 0 | BK26: 0
C27: 13 | D27: Selassi II | E27: Trent XWB-84 | F27: Ethiopia | G27: MEA | H27: Credit Back Removal | I27: TCA Amendments | J27: Campaign | K27: 1 | N27: 0.49 | O27: Med | P27: Med | Q27: Hopper | S27: 33 | T27: =S27/12 -> 2.75 | U27: =S27/12 -> 2.75 | V27: 5.5 | Y27: 0 | Z27: 0 | AA27: 0 | AB27: 0 | AC27: 0 | AD27: 0 | AE27: 0 | AF27: 0 | AG27: 0 | AH27: 0 | AI27: 0 | AJ27: 0 | AK27: 0 | AL27: 0 | AM27: 0 | AN27: 0 | AO27: 0 | AP27: 0 | AQ27: 0 | AR27: 0 | AS27: 0 | AT27: 0 | AU27: 0 | AV27: 0 | AW27: 0 | AX27: 0 | AZ27: 0 | BA27: 0 | BB27: 0 | BC27: 0 | BD27: 0 | BE27: 0 | BF27: 0 | BI27: 0 | BJ27: 0 | BK27: 0
C28: 14 | D28: Burgundy | E28: Trent XWB-97 | F28: Qatar | G28: MEA | H28: SPE Pull-forward | I28: TCA Amendments | J28: Increased SPE Discount | K28: 1 | L28: yes | N28: 0.87 | O28: High | P28: Low | Q28: Completed | S28: 90 | T28: 0 | U28: 0 | V28: =SUM(T28+U28) -> 0 | Y28: 0 | Z28: 0 | AA28: 0 | AB28: 0 | AC28: 0 | AD28: 0 | AE28: 0 | AF28: 0 | AG28: 0 | AH28: 0 | AI28: 0 | AJ28: 0 | AK28: 0 | AL28: 0 | AM28: 0 | AN28: 0 | AO28: 0 | AP28: 0 | AQ28: 0 | AR28: 0 | AS28: 0 | AT28: 0 | AU28: 0 | AV28: 0 | AW28: 0 | AX28: 0 | AZ28: 0 | BA28: 0 | BB28: 0 | BC28: 0 | BD28: 0 | BE28: 0 | BF28: 0 | BI28: 0 | BJ28: 0 | BK28: 0
C29: 15 | D29: Burgundy II | E29: Trent XWB-84 | F29: Qatar | G29: MEA | H29: Exit for convenience removal -84 | I29: TCA Amendments | J29: Term Extension | K29: 1 | N29: 0.77 | O29: High | P29: High | Q29: Contracting | S29: 68.08 | T29: 68.08 | U29: 0 | V29: =SUM(T29+U29) -> 68.08 | Y29: 0 | Z29: 0 | AA29: 0 | AB29: 0 | AC29: 0 | AD29: 0 | AE29: 0 | AF29: 0 | AG29: 0 | AH29: 0 | AI29: 0 | AJ29: 0 | AK29: 0 | AL29: 0 | AM29: 0 | AN29: 0 | AO29: 0 | AP29: 0 | AQ29: 0 | AR29: 0 | AS29: 0 | AT29: 0 | AU29: 0 | AV29: 0 | AW29: 0 | AX29: 0 | AZ29: 0 | BA29: 0 | BB29: 0 | BC29: 0 | BD29: 0 | BE29: 0 | BF29: 0 | BI29: 0 | BJ29: 0 | BK29: 0 | BO29: 1 | BP29: 1 | BQ29: 1 | BR29: 1 | BS29: 1 | BT29: 1 | BU29: 1 | BV29: 1 | BW29: 1 | BX29: 1 | BY29: 1 | BZ29: 1 | CA29: 1 | CB29: 1 | CC29: 1 | CD29: 1 | CE29: 1
C30: 16 | D30: Burgundy III | E30: Trent XWB-97 | F30: Qatar | G30: MEA | H30: Exit for convenience removal -97 | I30: TCA Amendments | J30: Term Extension | K30: 2 | N30: 0.87 | O30: Low | P30: High | Q30: Hopper | S30: 45.88 | T30: 0 | U30: 45.88 | V30: =SUM(T30+U30) -> 45.88 | Y30: 0 | Z30: 0 | AA30: 0 | AB30: 0 | AC30: 0 | AD30: 0 | AE30: 0 | AF30: 0 | AG30: 0 | AH30: 0 | AI30: 0 | AJ30: 0 | AK30: 0 | AL30: 0 | AM30: 0 | AN30: 0 | AO30: 0 | AP30: 0 | AQ30: 0 | AR30: 0 | AS30: 0 | AT30: 0 | AU30: 0 | AV30: 0 | AW30: 0 | AX30: 0 | AZ30: 0 | BA30: 0 | BB30: 0 | BC30: 0 | BD30: 0 | BE30: 0 | BF30: 0 | BI30: 0 | BJ30: 0 | BK30: 0
C31: 17 | D31: QA | E31: Trent 500 | F31: Qatar Amiri | G31: MEA | H31: Sell 1 x SPE | I31: SPE increase | J31: Upsell | K31: 1 | L31: yes | M31: 1 | N31: 0 | O31: Med | P31: Med | Q31: Contracting | S31: 2.7 | T31: 2.7 | U31: 0 | V31: =SUM(T31+U31) -> 2.7 | Y31: 0 | Z31: 0 | AA31: 0 | AB31: 0 | AC31: 0 | AD31: 0 | AE31: 0 | AF31: 0 | AG31: 0 | AH31: 0 | AI31: 0 | AJ31: 0 | AK31: 0 | AL31: 0 | AM31: 0 | AN31: 0 | AO31: 0 | AP31: 0 | AQ31: 0 | AR31: 0 | AS31: 0 | AT31: 0 | AU31: 0 | AV31: 0 | AW31: 0 | AX31: 0 | AZ31: 0 | BA31: 0 | BB31: 0 | BC31: 0 | BD31: 0 | BE31: 0 | BF31: 0 | BI31: 0 | BJ31: 0 | BK31: 0
C32: 18 | D32: Horus | E32: Trent 1000 | F32: Egypt | G32: MEA | H32: Correct the CRP!! | I32: TCA Amendments | J32: Min Term extension | K32: 2 | N32: 0.18 | O32: Med | P32: Low | Q32: ICT | S32: 0 | T32: 0 | U32: 0 | V32: =SUM(T32+U32) -> 0 | Y32: 0 | Z32: 0 | AA32: 0 | AB32: 0 | AC32: 0 | AD32: 0 | AE32: 0 | AF32: 0 | AG32: 0 | AH32: 0 | AI32: 0 | AJ32: 0 | AK32: 0 | AL32: 0 | AM32: 0 | AN32: 0 | AO32: 0 | AP32: 0 | AQ32: 0 | AR32: 0 | AS32: 0 | AT32: 0 | AU32: 0 | AV32: 0 | AW32: 0 | AX32: 0 | AZ32: 0 | BA32: 0 | BB32: 0 | BC32: 0 | BD32: 0 | BE32: 0 | BF32: 0 | BI32: 0 | BJ32: 0 | BK32: 0
C33: 19 | D33: Horus II | E33: Trent 700 | F33: Egypt | G33: MEA | H33: Term Extension | I33: Term Extension | J33: Existing Pricing | K33: 1 | N33: 0.11 | O33: High | P33: Med | Q33: ICT | S33: 138.24 | T33: 0 | U33: 20 | V33: =SUM(T33+U33) -> 20 | Y33: 0 | Z33: 0 | AA33: 0 | AB33: 0 | AC33: 0 | AD33: 0 | AE33: 0 | AF33: 0 | AG33: 0 | AH33: 0 | AI33: 0 | AJ33: 0 | AK33: 0 | AL33: 0 | AM33: 0 | AN33: 0 | AO33: 0 | AP33: 0 | AQ33: 0 | AR33: 0 | AS33: 0 | AT33: 0 | AU33: 0 | AV33: 0 | AW33: 0 | AX33: 0 | AZ33: 0 | BA33: 0 | BB33: 0 | BC33: 0 | BD33: 0 | BE33: 0 | BF33: 0 | BI33: 0 | BJ33: 0 | BK33: 0
C34: 20 | D34: Horus III | E34: Trent 1000 | F34: Egypt | G34: MEA | H34: Transportation Service Buy Out | I34: TCA Amendments | K34: 2 | N34: 0.18 | O34: Low | P34: Med | Q34: Cancelled | S34: 7.4 | T34: 0 | U34: 0 | V34: =SUM(T34+U34) -> 0 | Y34: 0 | Z34: 0 | AA34: 0 | AB34: 0 | AC34: 0 | AD34: 0 | AE34: 0 | AF34: 0 | AG34: 0 | AH34: 0 | AI34: 0 | AJ34: 0 | AK34: 0 | AL34: 0 | AM34: 0 | AN34: 0 | AO34: 0 | AP34: 0 | AQ34: 0 | AR34: 0 | AS34: 0 | AT34: 0 | AU34: 0 | AV34: 0 | AW34: 0 | AX34: 0 | AZ34: 0 | BA34: 0 | BB34: 0 | BC34: 0 | BD34: 0 | BE34: 0 | BF34: 0 | BI34: 0 | BJ34: 0 | BK34: 0
C35: 21 | D35: Horus IV | E35: Trent XWB-84 | F35: Egypt | G35: MEA | H35: PAS Upsell | I35: Service Upsells | K35: 1 | O35: Low | P35: Low | Q35: Cancelled | S35: 7.2 | T35: 0.6 | U35: 0.6 | V35: =SUM(T35+U35) -> 1.2 | Y35: 0 | Z35: 0 | AA35: 0 | AB35: 0 | AC35: 0 | AD35: 0 | AE35: 0 | AF35: 0 | AG35: 0 | AH35: 0 | AI35: 0 | AJ35: 0 | AK35: 0 | AL35: 0 | AM35: 0 | AN35: 0 | AO35: 0 | AP35: 0 | AQ35: 0 | AR35: 0 | AS35: 0 | AT35: 0 | AU35: 0 | AV35: 0 | AW35: 0 | AX35: 0 | AZ35: 0 | BA35: 0 | BB35: 0 | BC35: 0 | BD35: 0 | BE35: 0 | BF35: 0 | BI35: 0 | BJ35: 0 | BK35: 0
C36: 22 | D36: Turk | E36: Trent 700 | F36: Turkmenistan | G36: MEA | H36: SelectCare Upsell | I36: Service Upsells | K36: 2 | O36: Low | P36: Med | Q36: Cancelled | S36: 30 | T36: 0 | U36: 7.5 | V36: =SUM(T36+U36) -> 7.5 | Y36: 0 | Z36: 0 | AA36: 0 | AB36: 0 | AC36: 0 | AD36: 0 | AE36: 0 | AF36: 0 | AG36: 0 | AH36: 0 | AI36: 0 | AJ36: 0 | AK36: 0 | AL36: 0 | AM36: 0 | AN36: 0 | AO36: 0 | AP36: 0 | AQ36: 0 | AR36: 0 | AS36: 0 | AT36: 0 | AU36: 0 | AV36: 0 | AW36: 0 | AX36: 0 | AZ36: 0 | BA36: 0 | BB36: 0 | BC36: 0 | BD36: 0 | BE36: 0 | BF36: 0 | BI36: 0 | BJ36: 0 | BK36: 0
C37: 23 | D37: Qanot | E37: Trent 700 | F37: Qanot Sharq | G37: MEA | H37: TCA Life Upsell 2 x A330CEO | I37: New a/c | K37: 2 | O37: Low | P37: Med | Q37: Cancelled | S37: 36 | T37: 0 | U37: 0 | V37: =SUM(T37+U37) -> 0 | Y37: 0 | Z37: 0 | AA37: 0 | AB37: 0 | AC37: 0 | AD37: 0 | AE37: 0 | AF37: 0 | AG37: 0 | AH37: 0 | AI37: 0 | AJ37: 0 | AK37: 0 | AL37: 0 | AM37: 0 | AN37: 0 | AO37: 0 | AP37: 0 | AQ37: 0 | AR37: 0 | AS37: 0 | AT37: 0 | AU37: 0 | AV37: 0 | AW37: 0 | AX37: 0 | AZ37: 0 | BA37: 0 | BB37: 0 | BC37: 0 | BD37: 0 | BE37: 0 | BF37: 0 | BI37: 0 | BJ37: 0 | BK37: 0
C38: 24 | D38: SW | E38: RB211-524 | F38: Silkway | G38: MEA | H38: Increase in Green Time by 12k cycles | I38: TCA Amendments | K38: 1 | N38: 0 | O38: Low | P38: High | Q38: Cancelled | S38: 25.2 | T38: 12.6 | U38: 12.6 | V38: =SUM(T38+U38) -> 25.2 | Y38: 0 | Z38: 0 | AA38: 0 | AB38: 0 | AC38: 0 | AD38: 0 | AE38: 0 | AF38: 0 | AG38: 0 | AH38: 0 | AI38: 0 | AJ38: 0 | AK38: 0 | AL38: 0 | AM38: 0 | AN38: 0 | AO38: 0 | AP38: 0 | AQ38: 0 | AR38: 0 | AS38: 0 | AT38: 0 | AU38: 0 | AV38: 0 | AW38: 0 | AX38: 0 | AZ38: 0 | BA38: 0 | BB38: 0 | BC38: 0 | BD38: 0 | BE38: 0 | BF38: 0 | BI38: 0 | BJ38: 0 | BK38: 0 | BO38: 1 | BP38: 1 | BQ38: 1 | BR38: 1 | BS38: 1 | BT38: 1 | BU38: 1 | BV38: 1 | BW38: 1 | BX38: 1 | BY38: 1 | BZ38: 1 | CA38: 1 | CB38: 1 | CC38: 1 | CD38: 1 | CE38: 1
C39: 25 | D39: Sen | E39: Trent 7000 | F39: Senegal | G39: MEA | H39: Collect debt | I39: Other | K39: 2 | N39: 0.54 | O39: Low | P39: Med | Q39: Cancelled | S39: 10 | T39: 0 | U39: 10 | V39: =SUM(T39+U39) -> 10 | Y39: 0 | Z39: 0 | AA39: 0 | AB39: 0 | AC39: 0 | AD39: 0 | AE39: 0 | AF39: 0 | AG39: 0 | AH39: 0 | AI39: 0 | AJ39: 0 | AK39: 0 | AL39: 0 | AM39: 0 | AN39: 0 | AO39: 0 | AP39: 0 | AQ39: 0 | AR39: 0 | AS39: 0 | AT39: 0 | AU39: 0 | AV39: 0 | AW39: 0 | AX39: 0 | AZ39: 0 | BA39: 0 | BB39: 0 | BC39: 0 | BD39: 0 | BE39: 0 | BF39: 0 | BI39: 0 | BJ39: 0 | BK39: 0
C40: 26 | D40: Viva Algeria | E40: Trent 7000 | F40: Air Algerie | G40: MEA | H40: Additional SPE | I40: SPE increase | K40: 1 | L40: yes | O40: High | P40: Low | Q40: Completed | S40: 20 | T40: 0 | U40: 20 | V40: =SUM(T40+U40) -> 20 | Y40: 0 | Z40: 0 | AA40: 0 | AB40: 0 | AC40: 0 | AD40: 0 | AE40: 0 | AF40: 0 | AG40: 0 | AH40: 0 | AI40: 0 | AJ40: 0 | AK40: 0 | AL40: 0 | AM40: 0 | AN40: 0 | AO40: 0 | AP40: 0 | AQ40: 0 | AR40: 0 | AS40: 0 | AT40: 0 | AU40: 0 | AV40: 0 | AW40: 0 | AX40: 0 | AZ40: 0 | BA40: 0 | BB40: 0 | BC40: 0 | BD40: 0 | BE40: 0 | BF40: 0 | BI40: 0 | BJ40: 0 | BK40: 0
C41: 27 | D41: Dhabi I | E41: Trent XWB-97 | F41: Etihad | G41: MEA | H41: TCA Reconciliation (CRP Improvement) | I41: TCA Amendments | K41: 1 | N41: 0.09 | O41: High | P41: Med | Q41: Completed | S41: 60 | T41: 5 | U41: 1 | V41: =SUM(T41+U41) -> 6 | Y41: 0 | Z41: 0 | AA41: 0 | AB41: 0 | AC41: 0 | AD41: 0 | AE41: 0 | AF41: 0 | AG41: 0 | AH41: 0 | AI41: 0 | AJ41: 0 | AK41: 0 | AL41: 0 | AM41: 0 | AN41: 0 | AO41: 0 | AP41: 0 | AQ41: 0 | AR41: 0 | AS41: 0 | AT41: 0 | AU41: 0 | AV41: 0 | AW41: 0 | AX41: 0 | AZ41: 0 | BA41: 0 | BB41: 0 | BC41: 0 | BD41: 0 | BE41: 0 | BF41: 0 | BI41: 0 | BJ41: 0 | BK41: 0
C42: 28 | D42: Dhabi II | E42: Trent XWB-97 | F42: Etihad | G42: MEA | H42: Transportation Service Buy Out for first 12 | I42: TCA Amendments | K42: 3 | N42: 0.09 | O42: Low | P42: High | Q42: Hopper | S42: 17.76 | T42: 1.48 | U42: 1.48 | V42: =SUM(T42+U42) -> 2.96 | Y42: 0 | Z42: 0 | AA42: 0 | AB42: 0 | AC42: 0 | AD42: 0 | AE42: 0 | AF42: 0 | AG42: 0 | AH42: 0 | AI42: 0 | AJ42: 0 | AK42: 0 | AL42: 0 | AM42: 0 | AN42: 0 | AO42: 0 | AP42: 0 | AQ42: 0 | AR42: 0 | AS42: 0 | AT42: 0 | AU42: 0 | AV42: 0 | AW42: 0 | AX42: 0 | AZ42: 0 | BA42: 0 | BB42: 0 | BC42: 0 | BD42: 0 | BE42: 0 | BF42: 0 | BI42: 0 | BJ42: 0 | BK42: 0
C43: 29 | D43: Saud | E43: Trent 700 | F43: Saudia | G43: MEA | H43: Regional Fleet NDSES improvement | I43: Cost Reduction | K43: 1 | N43: 0.31 | O43: High | P43: Med | Q43: Completed | S43: 21.46 | T43: 1.788333 | U43: 1.78833 | V43: =SUM(T43+U43) -> 3.576663 | Y43: 0 | Z43: 0 | AA43: 0 | AB43: 0 | AC43: 0 | AD43: 0 | AE43: 0 | AF43: 0 | AG43: 0 | AH43: 0 | AI43: 0 | AJ43: 0 | AK43: 0 | AL43: 0 | AM43: 0 | AN43: 0 | AO43: 0 | AP43: 0 | AQ43: 0 | AR43: 0 | AS43: 0 | AT43: 0 | AU43: 0 | AV43: 0 | AW43: 0 | AX43: 0 | AZ43: 0 | BA43: 0 | BB43: 0 | BC43: 0 | BD43: 0 | BE43: 0 | BF43: 0 | BI43: 0 | BJ43: 0 | BK43: 0
C44: 30 | D44: Saud II | E44: Trent 700 | F44: Saudia | G44: MEA | H44: Extend Classic | I44: Term Extension | J44: Term Extension | K44: 2 | N44: 0.29 | O44: Low | P44: Med | Q44: Hopper | T44: 0 | U44: 0 | V44: =SUM(T44+U44) -> 0 | Y44: 0 | Z44: 0 | AA44: 0 | AB44: 0 | AC44: 0 | AD44: 0 | AE44: 0 | AF44: 0 | AG44: 0 | AH44: 0 | AI44: 0 | AJ44: 0 | AK44: 0 | AL44: 0 | AM44: 0 | AN44: 0 | AO44: 0 | AP44: 0 | AQ44: 0 | AR44: 0 | AS44: 0 | AT44: 0 | AU44: 0 | AV44: 0 | AW44: 0 | AX44: 0 | AZ44: 0 | BA44: 0 | BB44: 0 | BC44: 0 | BD44: 0 | BE44: 0 | BF44: 0 | BI44: 0 | BJ44: 0 | BK44: 0
C45: 31 | D45: Tanz | E45: Trent 1000 | F45: Tanzania | G45: MEA | H45: Additional SPE | I45: SPE increase | K45: 1 | L45: yes | N45: 0.28 | O45: Med | P45: Low | Q45: Completed | S45: 25 | T45: 25 | V45: =SUM(T45+U45) -> 25 | Y45: 0 | Z45: 0 | AA45: 0 | AB45: 0 | AC45: 0 | AD45: 0 | AE45: 0 | AF45: 0 | AG45: 0 | AH45: 0 | AI45: 0 | AJ45: 0 | AK45: 0 | AL45: 0 | AM45: 0 | AN45: 0 | AO45: 0 | AP45: 0 | AQ45: 0 | AR45: 0 | AS45: 0 | AT45: 0 | AU45: 0 | AV45: 0 | AW45: 0 | AX45: 0 | AZ45: 0 | BA45: 0 | BB45: 0 | BC45: 0 | BD45: 0 | BE45: 0 | BF45: 0 | BI45: 0 | BJ45: 0 | BK45: 0
C46: 32 | D46: Tanz | E46: Trent 1000 | F46: Tanzania | G46: MEA | H46: NDSES CRP | I46: Cost Reduction | K46: 1 | N46: 0.28 | O46: Med | P46: Med | Q46: Completed | S46: 3.552 | T46: 0.7104 | U46: 0.7104 | V46: =SUM(T46+U46) -> 1.4208 | Y46: 0 | Z46: 0 | AA46: 0 | AB46: 0 | AC46: 0 | AD46: 0 | AE46: 0 | AF46: 0 | AG46: 0 | AH46: 0 | AI46: 0 | AJ46: 0 | AK46: 0 | AL46: 0 | AM46: 0 | AN46: 0 | AO46: 0 | AP46: 0 | AQ46: 0 | AR46: 0 | AS46: 0 | AT46: 0 | AU46: 0 | AV46: 0 | AW46: 0 | AX46: 0 | AZ46: 0 | BA46: 0 | BB46: 0 | BC46: 0 | BD46: 0 | BE46: 0 | BF46: 0 | BI46: 0 | BJ46: 0 | BK46: 0
C47: 33 | D47: Falcon | E47: Trent 1000 | F47: Gulf | G47: MEA | H47: NDSES improvement through SPE sales | I47: Cost Reduction | J47: Resolution of Claims | K47: 1 | N47: 0.38 | O47: Low | P47: Med | Q47: Negotiations | S47: 5.88 | T47: 0.84 | U47: 0.84 | V47: =SUM(T47+U47) -> 1.68 | Y47: 0 | Z47: 0 | AA47: 0 | AB47: 0 | AC47: 0 | AD47: 0 | AE47: 0 | AF47: 0 | AG47: 0 | AH47: 0 | AI47: 0 | AJ47: 0 | AK47: 0 | AL47: 0 | AM47: 0 | AN47: 0 | AO47: 0 | AP47: 0 | AQ47: 0 | AR47: 0 | AS47: 0 | AT47: 0 | AU47: 0 | AV47: 0 | AW47: 0 | AX47: 0 | AZ47: 0 | BA47: 0 | BB47: 0 | BC47: 0 | BD47: 0 | BE47: 0 | BF47: 0 | BI47: 0 | BJ47: 0 | BK47: 0
C48: 34 | D48: Falcon | E48: Trent 1000 | F48: Gulf | G48: MEA | H48: 3 Year Extension | I48: Term Extension | J48: Resolution of Claims | K48: 1 | N48: 0.38 | O48: Med | P48: Med | Q48: Negotiations | S48: 12 | T48: 1.2 | U48: 1.2 | V48: =SUM(T48+U48) -> 2.4 | Y48: 0 | Z48: 0 | AA48: 0 | AB48: 0 | AC48: 0 | AD48: 0 | AE48: 0 | AF48: 0 | AG48: 0 | AH48: 0 | AI48: 0 | AJ48: 0 | AK48: 0 | AL48: 0 | AM48: 0 | AN48: 0 | AO48: 0 | AP48: 0 | AQ48: 0 | AR48: 0 | AS48: 0 | AT48: 0 | AU48: 0 | AV48: 0 | AW48: 0 | AX48: 0 | AZ48: 0 | BA48: 0 | BB48: 0 | BC48: 0 | BD48: 0 | BE48: 0 | BF48: 0 | BI48: 0 | BJ48: 0 | BK48: 0
C49: 35 | D49: Falcon | E49: Trent 1000 | F49: Gulf | G49: MEA | H49: Additional 2 x A/C | I49: New a/c | J49: Resolution of Claims | K49: 2 | L49: yes | M49: 2 | N49: 0.38 | O49: Low | P49: Med | Q49: Cancelled | S49: 23.04 | T49: =S49/12 -> 1.92 | U49: =S49/12 -> 1.92 | V49: =SUM(T49+U49) -> 3.84 | Y49: 0 | Z49: 0 | AA49: 0 | AB49: 0 | AC49: 0 | AD49: 0 | AE49: 0 | AF49: 0 | AG49: 0 | AH49: 0 | AI49: 0 | AJ49: 0 | AK49: 0 | AL49: 0 | AM49: 0 | AN49: 0 | AO49: 0 | AP49: 0 | AQ49: 0 | AR49: 0 | AS49: 0 | AT49: 0 | AU49: 0 | AV49: 0 | AW49: 0 | AX49: 0 | AZ49: 0 | BA49: 0 | BB49: 0 | BC49: 0 | BD49: 0 | BE49: 0 | BF49: 0 | BI49: 0 | BJ49: 0 | BK49: 0
C50: 36 | D50: Star | E50: Trent 1000 | F50: Austral | G50: MEA | H50: TCA Extension/Exit credit trade | I50: Term Extension | J50: Blended TCA Rate | K50: 1 | N50: 0.61 | O50: Med | P50: Med | Q50: Hopper | S50: 4.8 | T50: 0 | U50: 0 | V50: =SUM(T50+U50) -> 0 | Y50: 0 | Z50: 0 | AA50: 0 | AB50: 0 | AC50: 0 | AD50: 0 | AE50: 0 | AF50: 0 | AG50: 0 | AH50: 0 | AI50: 0 | AJ50: 0 | AK50: 0 | AL50: 0 | AM50: 0 | AN50: 0 | AO50: 0 | AP50: 0 | AQ50: 0 | AR50: 0 | AS50: 0 | AT50: 0 | AU50: 0 | AV50: 0 | AW50: 0 | AX50: 0 | AZ50: 0 | BA50: 0 | BB50: 0 | BC50: 0 | BD50: 0 | BE50: 0 | BF50: 0 | BI50: 0 | BJ50: 0 | BK50: 0
C51: 37 | D51: Q8 | E51: Trent 7000 | F51: Kuwait | G51: MEA | H51: Maintain SPE % | I51: SPE increase | J51: Early Exit of a330-800 | K51: 3 | L51: yes | N51: 0.04 | O51: Low | P51: Med | Q51: Hopper | S51: 0 | T51: 0 | U51: 0 | V51: =SUM(T51+U51) -> 0 | Y51: 0 | Z51: 0 | AA51: 0 | AB51: 0 | AC51: 0 | AD51: 0 | AE51: 0 | AF51: 0 | AG51: 0 | AH51: 0 | AI51: 0 | AJ51: 0 | AK51: 0 | AL51: 0 | AM51: 0 | AN51: 0 | AO51: 0 | AP51: 0 | AQ51: 0 | AR51: 0 | AS51: 0 | AT51: 0 | AU51: 0 | AV51: 0 | AW51: 0 | AX51: 0 | AZ51: 0 | BA51: 0 | BB51: 0 | BC51: 0 | BD51: 0 | BE51: 0 | BF51: 0 | BI51: 0 | BJ51: 0 | BK51: 0
C52: 38 | D52: Mau | E52: Trent XWB-84 | F52: Mauritus | G52: MEA | H52: Escalation increase | I52: TCA Amendments | K52: 3 | N52: 0.31 | O52: High | P52: Low | Q52: Completed | S52: 1.3 | T52: =S52/3 -> 0.43333333 | U52: 0 | V52: =SUM(T52+U52) -> 0.43333333 | Y52: 0 | Z52: 0 | AA52: 0 | AB52: 0 | AC52: 0 | AD52: 0 | AE52: 0 | AF52: 0 | AG52: 0 | AH52: 0 | AI52: 0 | AJ52: 0 | AK52: 0 | AL52: 0 | AM52: 0 | AN52: 0 | AO52: 0 | AP52: 0 | AQ52: 0 | AR52: 0 | AS52: 0 | AT52: 0 | AU52: 0 | AV52: 0 | AW52: 0 | AX52: 0 | AZ52: 0 | BA52: 0 | BB52: 0 | BC52: 0 | BD52: 0 | BE52: 0 | BF52: 0 | BI52: 0 | BJ52: 0 | BK52: 0
C53: 39 | D53: Dodo | E53: Trent 7000 | F53: Mauritus | G53: MEA | H53: Reduce NDSES Cost | I53: Cost Reduction | J53: Termination | K53: 2 | N53: 0.54 | O53: Med | P53: Med | Q53: ICT | S53: 0.38 | T53: =S53/5 -> 0.076 | U53: =S53/5 -> 0.076 | V53: =SUM(T53+U53) -> 0.152 | Y53: 0 | Z53: 0 | AA53: 0 | AB53: 0 | AC53: 0 | AD53: 0 | AE53: 0 | AF53: 0 | AG53: 0 | AH53: 0 | AI53: 0 | AJ53: 0 | AK53: 0 | AL53: 0 | AM53: 0 | AN53: 0 | AO53: 0 | AP53: 0 | AQ53: 0 | AR53: 0 | AS53: 0 | AT53: 0 | AU53: 0 | AV53: 0 | AW53: 0 | AX53: 0 | AZ53: 0 | BA53: 0 | BB53: 0 | BC53: 0 | BD53: 0 | BE53: 0 | BF53: 0 | BI53: 0 | BJ53: 0 | BK53: 0
C54: 40 | D54: RW | E54: Trent 700 | F54: Rwanda | G54: MEA | H54: Min Term Extension | I54: Term Extension | K54: 3 | N54: 0.19 | O54: Low | P54: Med | Q54: Hopper | S54: 12 | T54: 0 | U54: 0 | V54: =SUM(T54+U54) -> 0 | Y54: 0 | Z54: 0 | AA54: 0 | AB54: 0 | AC54: 0 | AD54: 0 | AE54: 0 | AF54: 0 | AG54: 0 | AH54: 0 | AI54: 0 | AJ54: 0 | AK54: 0 | AL54: 0 | AM54: 0 | AN54: 0 | AO54: 0 | AP54: 0 | AQ54: 0 | AR54: 0 | AS54: 0 | AT54: 0 | AU54: 0 | AV54: 0 | AW54: 0 | AX54: 0 | AZ54: 0 | BA54: 0 | BB54: 0 | BC54: 0 | BD54: 0 | BE54: 0 | BF54: 0 | BI54: 0 | BJ54: 0 | BK54: 0
C55: 41 | D55: SAA | E55: Trent 700 | F55: SAA | G55: MEA | H55: Additional 7 X A/C | I55: New a/c | K55: 3 | O55: Med | P55: Med | Q55: Cancelled | S55: 54 | T55: 0 | U55: 0 | V55: =SUM(T55+U55) -> 0 | Y55: 0 | Z55: 0 | AA55: 0 | AB55: 0 | AC55: 0 | AD55: 0 | AE55: 0 | AF55: 0 | AG55: 0 | AH55: 0 | AI55: 0 | AJ55: 0 | AK55: 0 | AL55: 0 | AM55: 0 | AN55: 0 | AO55: 0 | AP55: 0 | AQ55: 0 | AR55: 0 | AS55: 0 | AT55: 0 | AU55: 0 | AV55: 0 | AW55: 0 | AX55: 0 | AZ55: 0 | BA55: 0 | BB55: 0 | BC55: 0 | BD55: 0 | BE55: 0 | BF55: 0 | BI55: 0 | BJ55: 0 | BK55: 0
C56: 42 | D56: Star | E56: Trent 1000 | F56: Austral | G56: MEA | H56: Used SPE | I56: SPE increase | J56: Min-term extension | K56: 1 | L56: Med | M56: Med | N56: ICT | O56: Low | P56: Low | Q56: Hopper | V56: =SUM(T56+U56) -> 0 | Y56: 0 | Z56: 0 | AA56: 0 | AB56: 0 | AC56: 0 | AD56: 0 | AE56: 0 | AF56: 0 | AG56: 0 | AH56: 0 | AI56: 0 | AJ56: 0 | AK56: 0 | AL56: 0 | AM56: 0 | AN56: 0 | AO56: 0 | AP56: 0 | AQ56: 0 | AR56: 0 | AS56: 0 | AT56: 0 | AU56: 0 | AV56: 0 | AW56: 0 | AX56: 0 | AZ56: 0 | BA56: 0 | BB56: 0 | BC56: 0 | BD56: 0 | BE56: 0 | BF56: 0 | BI56: 0 | BJ56: 0 | BK56: 0
C57: 43 | D57: Horus V | E57: Trent XWB-84 | F57: Egypt | G57: MEA | H57: EP Upsell | I57: Last 6 aircraft | J57: Upsell | K57: 2 | O57: Med | P57: Med | Q57: Hopper | V57: =SUM(T57+U57) -> 0 | Y57: 0 | Z57: 0 | AA57: 0 | AB57: 0 | AC57: 0 | AD57: 0 | AE57: 0 | AF57: 0 | AG57: 0 | AH57: 0 | AI57: 0 | AJ57: 0 | AK57: 0 | AL57: 0 | AM57: 0 | AN57: 0 | AO57: 0 | AP57: 0 | AQ57: 0 | AR57: 0 | AS57: 0 | AT57: 0 | AU57: 0 | AV57: 0 | AW57: 0 | AX57: 0 | AZ57: 0 | BA57: 0 | BB57: 0 | BC57: 0 | BD57: 0 | BE57: 0 | BF57: 0 | BI57: 0 | BJ57: 0 | BK57: 0
C58: 44 | D58: Pantheon | E58: Trent 900 | F58: Emirates | G58: MEA | H58: Retire SLA1 | I58: TCA Amendments | J58: MRO trade | K58: 1 | O58: Med | P58: High | Q58: Hopper | V58: =SUM(T58+U58) -> 0 | Y58: 0 | Z58: 0 | AA58: 0 | AB58: 0 | AC58: 0 | AD58: 0 | AE58: 0 | AF58: 0 | AG58: 0 | AH58: 0 | AI58: 0 | AJ58: 0 | AK58: 0 | AL58: 0 | AM58: 0 | AN58: 0 | AO58: 0 | AP58: 0 | AQ58: 0 | AR58: 0 | AS58: 0 | AT58: 0 | AU58: 0 | AV58: 0 | AW58: 0 | AX58: 0 | AZ58: 0 | BA58: 0 | BB58: 0 | BC58: 0 | BD58: 0 | BE58: 0 | BF58: 0 | BI58: 0 | BJ58: 0 | BK58: 0
C59: 45 | D59: Cotton | E59: RB211-524 | F59: Silkway | G59: MEA | H59: Extend Greentime agreement by 12 months | I59: TCA Amendments | J59: Expiry | K59: 1 | O59: High | P59: Med | Q59: ICT | V59: =SUM(T59+U59) -> 0 | Y59: 0 | Z59: 0 | AA59: 0 | AB59: 0 | AC59: 0 | AD59: 0 | AE59: 0 | AF59: 0 | AG59: 0 | AH59: 0 | AI59: 0 | AJ59: 0 | AK59: 0 | AL59: 0 | AM59: 0 | AN59: 0 | AO59: 0 | AP59: 0 | AQ59: 0 | AR59: 0 | AS59: 0 | AT59: 0 | AU59: 0 | AV59: 0 | AW59: 0 | AX59: 0 | AZ59: 0 | BA59: 0 | BB59: 0 | BC59: 0 | BD59: 0 | BE59: 0 | BF59: 0 | BI59: 0 | BJ59: 0 | BK59: 0
C60: 46 | V60: =SUM(T60+U60) -> 0 | Y60: 0 | Z60: 0 | AA60: 0 | AB60: 0 | AC60: 0 | AD60: 0 | AE60: 0 | AF60: 0 | AG60: 0 | AH60: 0 | AI60: 0 | AJ60: 0 | AK60: 0 | AL60: 0 | AM60: 0 | AN60: 0 | AO60: 0 | AP60: 0 | AQ60: 0 | AR60: 0 | AS60: 0 | AT60: 0 | AU60: 0 | AV60: 0 | AW60: 0 | AX60: 0 | AZ60: 0 | BA60: 0 | BB60: 0 | BC60: 0 | BD60: 0 | BE60: 0 | BF60: 0 | BI60: 0 | BJ60: 0 | BK60: 0
C61: 47 | V61: =SUM(T61+U61) -> 0 | Y61: 0 | Z61: 0 | AA61: 0 | AB61: 0 | AC61: 0 | AD61: 0 | AE61: 0 | AF61: 0 | AG61: 0 | AH61: 0 | AI61: 0 | AJ61: 0 | AK61: 0 | AL61: 0 | AM61: 0 | AN61: 0 | AO61: 0 | AP61: 0 | AQ61: 0 | AR61: 0 | AS61: 0 | AT61: 0 | AU61: 0 | AV61: 0 | AW61: 0 | AX61: 0 | AZ61: 0 | BA61: 0 | BB61: 0 | BC61: 0 | BD61: 0 | BE61: 0 | BF61: 0 | BI61: 0 | BJ61: 0 | BK61: 0
C62: 48 | V62: =SUM(T62+U62) -> 0 | Y62: 0 | Z62: 0 | AA62: 0 | AB62: 0 | AC62: 0 | AD62: 0 | AE62: 0 | AF62: 0 | AG62: 0 | AH62: 0 | AI62: 0 | AJ62: 0 | AK62: 0 | AL62: 0 | AM62: 0 | AN62: 0 | AO62: 0 | AP62: 0 | AQ62: 0 | AR62: 0 | AS62: 0 | AT62: 0 | AU62: 0 | AV62: 0 | AW62: 0 | AX62: 0 | AZ62: 0 | BA62: 0 | BB62: 0 | BC62: 0 | BD62: 0 | BE62: 0 | BF62: 0 | BI62: 0 | BJ62: 0 | BK62: 0
C63: 49 | V63: =SUM(T63+U63) -> 0 | Y63: 0 | Z63: 0 | AA63: 0 | AB63: 0 | AC63: 0 | AD63: 0 | AE63: 0 | AF63: 0 | AG63: 0 | AH63: 0 | AI63: 0 | AJ63: 0 | AK63: 0 | AL63: 0 | AM63: 0 | AN63: 0 | AO63: 0 | AP63: 0 | AQ63: 0 | AR63: 0 | AS63: 0 | AT63: 0 | AU63: 0 | AV63: 0 | AW63: 0 | AX63: 0 | AZ63: 0 | BA63: 0 | BB63: 0 | BC63: 0 | BD63: 0 | BE63: 0 | BF63: 0 | BI63: 0 | BJ63: 0 | BK63: 0
C64: 50 | V64: =SUM(T64+U64) -> 0 | Y64: 0 | Z64: 0 | AA64: 0 | AB64: 0 | AC64: 0 | AD64: 0 | AE64: 0 | AF64: 0 | AG64: 0 | AH64: 0 | AI64: 0 | AJ64: 0 | AK64: 0 | AL64: 0 | AM64: 0 | AN64: 0 | AO64: 0 | AP64: 0 | AQ64: 0 | AR64: 0 | AS64: 0 | AT64: 0 | AU64: 0 | AV64: 0 | AW64: 0 | AX64: 0 | AZ64: 0 | BA64: 0 | BB64: 0 | BC64: 0 | BD64: 0 | BE64: 0 | BF64: 0 | BI64: 0 | BJ64: 0 | BK64: 0
C65: 51 | V65: =SUM(T65+U65) -> 0 | Y65: 0 | Z65: 0 | AA65: 0 | AB65: 0 | AC65: 0 | AD65: 0 | AE65: 0 | AF65: 0 | AG65: 0 | AH65: 0 | AI65: 0 | AJ65: 0 | AK65: 0 | AL65: 0 | AM65: 0 | AN65: 0 | AO65: 0 | AP65: 0 | AQ65: 0 | AR65: 0 | AS65: 0 | AT65: 0 | AU65: 0 | AV65: 0 | AW65: 0 | AX65: 0 | AZ65: 0 | BA65: 0 | BB65: 0 | BC65: 0 | BD65: 0 | BE65: 0 | BF65: 0 | BI65: 0 | BJ65: 0 | BK65: 0
C66: 52 | V66: =SUM(T66+U66) -> 0 | Y66: 0 | Z66: 0 | AA66: 0 | AB66: 0 | AC66: 0 | AD66: 0 | AE66: 0 | AF66: 0 | AG66: 0 | AH66: 0 | AI66: 0 | AJ66: 0 | AK66: 0 | AL66: 0 | AM66: 0 | AN66: 0 | AO66: 0 | AP66: 0 | AQ66: 0 | AR66: 0 | AS66: 0 | AT66: 0 | AU66: 0 | AV66: 0 | AW66: 0 | AX66: 0 | AZ66: 0 | BA66: 0 | BB66: 0 | BC66: 0 | BD66: 0 | BE66: 0 | BF66: 0 | BI66: 0 | BJ66: 0 | BK66: 0
C67: 53 | V67: =SUM(T67+U67) -> 0 | Y67: 0 | Z67: 0 | AA67: 0 | AB67: 0 | AC67: 0 | AD67: 0 | AE67: 0 | AF67: 0 | AG67: 0 | AH67: 0 | AI67: 0 | AJ67: 0 | AK67: 0 | AL67: 0 | AM67: 0 | AN67: 0 | AO67: 0 | AP67: 0 | AQ67: 0 | AR67: 0 | AS67: 0 | AT67: 0 | AU67: 0 | AV67: 0 | AW67: 0 | AX67: 0 | AZ67: 0 | BA67: 0 | BB67: 0 | BC67: 0 | BD67: 0 | BE67: 0 | BF67: 0 | BI67: 0 | BJ67: 0 | BK67: 0
C68: 54 | V68: =SUM(T68+U68) -> 0 | Y68: 0 | Z68: 0 | AA68: 0 | AB68: 0 | AC68: 0 | AD68: 0 | AE68: 0 | AF68: 0 | AG68: 0 | AH68: 0 | AI68: 0 | AJ68: 0 | AK68: 0 | AL68: 0 | AM68: 0 | AN68: 0 | AO68: 0 | AP68: 0 | AQ68: 0 | AR68: 0 | AS68: 0 | AT68: 0 | AU68: 0 | AV68: 0 | AW68: 0 | AX68: 0 | AZ68: 0 | BA68: 0 | BB68: 0 | BC68: 0 | BD68: 0 | BE68: 0 | BF68: 0 | BI68: 0 | BJ68: 0 | BK68: 0
C69: 55 | V69: =SUM(T69+U69) -> 0 | Y69: 0 | Z69: 0 | AA69: 0 | AB69: 0 | AC69: 0 | AD69: 0 | AE69: 0 | AF69: 0 | AG69: 0 | AH69: 0 | AI69: 0 | AJ69: 0 | AK69: 0 | AL69: 0 | AM69: 0 | AN69: 0 | AO69: 0 | AP69: 0 | AQ69: 0 | AR69: 0 | AS69: 0 | AT69: 0 | AU69: 0 | AV69: 0 | AW69: 0 | AX69: 0 | AZ69: 0 | BA69: 0 | BB69: 0 | BC69: 0 | BD69: 0 | BE69: 0 | BF69: 0 | BI69: 0 | BJ69: 0 | BK69: 0
C70: 56 | V70: =SUM(T70+U70) -> 0 | Y70: 0 | Z70: 0 | AA70: 0 | AB70: 0 | AC70: 0 | AD70: 0 | AE70: 0 | AF70: 0 | AG70: 0 | AH70: 0 | AI70: 0 | AJ70: 0 | AK70: 0 | AL70: 0 | AM70: 0 | AN70: 0 | AO70: 0 | AP70: 0 | AQ70: 0 | AR70: 0 | AS70: 0 | AT70: 0 | AU70: 0 | AV70: 0 | AW70: 0 | AX70: 0 | AZ70: 0 | BA70: 0 | BB70: 0 | BC70: 0 | BD70: 0 | BE70: 0 | BF70: 0 | BI70: 0 | BJ70: 0 | BK70: 0
C71: 57 | V71: =SUM(T71+U71) -> 0 | Y71: 0 | Z71: 0 | AA71: 0 | AB71: 0 | AC71: 0 | AD71: 0 | AE71: 0 | AF71: 0 | AG71: 0 | AH71: 0 | AI71: 0 | AJ71: 0 | AK71: 0 | AL71: 0 | AM71: 0 | AN71: 0 | AO71: 0 | AP71: 0 | AQ71: 0 | AR71: 0 | AS71: 0 | AT71: 0 | AU71: 0 | AV71: 0 | AW71: 0 | AX71: 0 | AZ71: 0 | BA71: 0 | BB71: 0 | BC71: 0 | BD71: 0 | BE71: 0 | BF71: 0 | BI71: 0 | BJ71: 0 | BK71: 0
... C513: 499 | V513: =SUM(T513+U513) -> 0 | Y513: 0 | Z513: 0 | AA513: 0 | AB513: 0 | AC513: 0 | AD513: 0 | AE513: 0 | AF513: 0 | AG513: 0 | AH513: 0 | AI513: 0 | AJ513: 0 | AK513: 0 | AL513: 0 | AM513: 0 | AN513: 0 | AO513: 0 | AP513: 0 | AQ513: 0 | AR513: 0 | AS513: 0 | AT513: 0 | AU513: 0 | AV513: 0 | AW513: 0 | AX513: 0 | AZ513: 0 | BA513: 0 | BB513: 0 | BC513: 0 | BD513: 0 | BE513: 0 | BF513: 0 | BI513: 0 | BJ513: 0 | BK513: 0

Sheet Timeline
C3: 2025 Commecrial Optimisation Plan
C8: AWAY DAY DATE | E8: 45768
F11: =AND(COLUMN()>=MATCH("Idea Generation",$23:$23,0), COLUMN()<=MATCH("Approval to Launch",$23:$23,0)) -> FALSE | G11: =AND(COLUMN()>=MATCH("Idea Generation",$23:$23,0), COLUMN()<=MATCH("Approval to Launch",$23:$23,0)) -> FALSE | H11: =AND(COLUMN()>=MATCH("Idea Generation",$23:$23,0), COLUMN()<=MATCH("Approval to Launch",$23:$23,0)) -> FALSE | I11: =AND(COLUMN()>=MATCH("Idea Generation",$23:$23,0), COLUMN()<=MATCH("Approval to Launch",$23:$23,0)) -> FALSE
C13: =TODAY() -> 46069 | E13: Week 1 | F13: Week 2 | G13: Week 3 | H13: Week 4 | I13: Week 5 | J13: Week 6 | K13: Week 7 | L13: Week 8 | M13: Week 9 | N13: Week 10 | O13: Week 11 | P13: Week 12 | Q13: Week 13 | R13: Week 14 | S13: Week 15 | T13: Week 16 | U13: Week 17 | V13: Week 18 | W13: Week 19 | X13: Week 20 | Y13: Week 21 | Z13: Week 22 | AA13: Week 23 | AB13: Week 24 | AC13: Week 25 | AD13: Week 26 | AE13: Week 27 | AF13: Week 28 | AG13: Week 29 | AH13: Week 30 | AI13: Week 31 | AJ13: Week 32 | AK13: Week 33 | AL13: Week 34 | AM13: Week 35 | AN13: Week 36 | AO13: Week 37 | AP13: Week 38 | AQ13: Week 39 | AR13: Week 40 | AS13: Week 41 | AT13: Week 42 | AU13: Week 43 | AV13: Week 44 | AW13: Week 45 | AX13: Week 46 | AY13: Week 47 | AZ13: Week 48 | BA13: Week 49 | BB13: Week 50 | BC13: Week 51 | BD13: Week 52 | BE13: Week 1 | BF13: Week 2 | BG13: Week 3 | BH13: Week 4 | BI13: Week 5 | BJ13: Week 6 | BK13: Week 7 | BL13: Week 8 | BM13: Week 9 | BN13: Week 10 | BO13: Week 11 | BP13: Week 12 | BQ13: Week 13 | BR13: Week 14 | BS13: Week 15 | BT13: Week 16 | BU13: Week 17 | BV13: Week 18 | BW13: Week 19 | BX13: Week 20 | BY13: Week 21 | BZ13: Week 22 | CA13: Week 23 | CB13: Week 24 | CC13: Week 25 | CD13: Week 26 | CE13: Week 27 | CF13: Week 28 | CG13: Week 29 | CH13: Week 30 | CI13: Week 31 | CJ13: Week 32 | CK13: Week 33 | CL13: Week 34 | CM13: Week 35 | CN13: Week 36 | CO13: Week 37 | CP13: Week 38 | CQ13: Week 39 | CR13: Week 40 | CS13: Week 41 | CT13: Week 42 | CU13: Week 43 | CV13: Week 44 | CW13: Week 45 | CX13: Week 46 | CY13: Week 47 | CZ13: Week 48 | DA13: Week 49 | DB13: Week 50 | DC13: Week 51 | DD13: Week 52 | DE13: Week 1 | DF13: Week 2 | DG13: Week 3 | DH13: Week 4 | DI13: Week 5 | DJ13: Week 6 | DK13: Week 7 | DL13: Week 8 | DM13: Week 9 | DN13: Week 10 | DO13: Week 11 | DP13: Week 12 | DQ13: Week 13 | DR13: Week 14 | DS13: Week 15 | DT13: Week 16 | DU13: Week 17 | DV13: Week 18 | DW13: Week 19 | DX13: Week 20 | DY13: Week 21 | DZ13: Week 22 | EA13: Week 23 | EB13: Week 24 | EC13: Week 25 | ED13: Week 26 | EE13: Week 27 | EF13: Week 28 | EG13: Week 29 | EH13: Week 30 | EI13: Week 31 | EJ13: Week 32 | EK13: Week 33 | EL13: Week 34 | EM13: Week 35 | EN13: Week 36 | EO13: Week 37 | EP13: Week 38 | EQ13: Week 39 | ER13: Week 40 | ES13: Week 41 | ET13: Week 42 | EU13: Week 43 | EV13: Week 44 | EW13: Week 45 | EX13: Week 46 | EY13: Week 47 | EZ13: Week 48 | FA13: Week 49 | FB13: Week 50 | FC13: Week 51 | FD13: Week 52
C14: Project | D14: Customer | E14: 30/12/2024 | F14: 06/01/2025 | G14: 13/01/2025 | H14: 20/01/2025 | I14: 27/01/2025 | J14: 03/02/2025 | K14: 10/02/2025 | L14: 17/02/2025 | M14: 24/02/2025 | N14: 03/03/2025 | O14: 10/03/2025 | P14: 17/03/2025 | Q14: 24/03/2025 | R14: 31/03/2025 | S14: 07/04/2025 | T14: 14/04/2025 | U14: 21/04/2025 | V14: 28/04/2025 | W14: 05/05/2025 | X14: 12/05/2025 | Y14: 19/05/2025 | Z14: 26/05/2025 | AA14: 02/06/2025 | AB14: 09/06/2025 | AC14: 16/06/2025 | AD14: 23/06/2025 | AE14: 30/06/2025 | AF14: 07/07/2025 | AG14: 14/07/2025 | AH14: 21/07/2025 | AI14: 28/07/2025 | AJ14: 04/08/2025 | AK14: 11/08/2025 | AL14: 18/08/2025 | AM14: 25/08/2025 | AN14: 01/09/2025 | AO14: 08/09/2025 | AP14: 15/09/2025 | AQ14: 22/09/2025 | AR14: 29/09/2025 | AS14: 06/10/2025 | AT14: 13/10/2025 | AU14: 20/10/2025 | AV14: 27/10/2025 | AW14: 03/11/2025 | AX14: 10/11/2025 | AY14: 17/11/2025 | AZ14: 24/11/2025 | BA14: 01/12/2025 | BB14: 08/12/2025 | BC14: 15/12/2025 | BD14: 22/12/2025 | BE14: 29/12/2025 | BF14: 05/01/2026 | BG14: 12/01/2026 | BH14: 19/01/2026 | BI14: 26/01/2026 | BJ14: 02/02/2026 | BK14: 09/02/2026 | BL14: 16/02/2026 | BM14: 23/02/2026 | BN14: 02/03/2026 | BO14: 09/03/2026 | BP14: 16/03/2026 | BQ14: 23/03/2026 | BR14: 30/03/2026 | BS14: 06/04/2026 | BT14: 13/04/2026 | BU14: 20/04/2026 | BV14: 27/04/2026 | BW14: 04/05/2026 | BX14: 11/05/2026 | BY14: 18/05/2026 | BZ14: 25/05/2026 | CA14: 01/06/2026 | CB14: 08/06/2026 | CC14: 15/06/2026 | CD14: 22/06/2026 | CE14: 29/06/2026 | CF14: 06/07/2026 | CG14: 13/07/2026 | CH14: 20/07/2026 | CI14: 27/07/2026 | CJ14: 03/08/2026 | CK14: 10/08/2026 | CL14: 17/08/2026 | CM14: 24/08/2026 | CN14: 31/08/2026 | CO14: 07/09/2026 | CP14: 14/09/2026 | CQ14: 21/09/2026 | CR14: 28/09/2026 | CS14: 05/10/2026 | CT14: 12/10/2026 | CU14: 19/10/2026 | CV14: 26/10/2026 | CW14: 02/11/2026 | CX14: 09/11/2026 | CY14: 16/11/2026 | CZ14: 23/11/2026 | DA14: 30/11/2026 | DB14: 07/12/2026 | DC14: 14/12/2026 | DD14: 21/12/2026 | DE14: 28/12/2026 | DF14: 04/01/2027 | DG14: 11/01/2027 | DH14: 18/01/2027 | DI14: 25/01/2027 | DJ14: 01/02/2027 | DK14: 08/02/2027 | DL14: 15/02/2027 | DM14: 22/02/2027 | DN14: 01/03/2027 | DO14: 08/03/2027 | DP14: 15/03/2027 | DQ14: 22/03/2027 | DR14: 29/03/2027 | DS14: 05/04/2027 | DT14: 12/04/2027 | DU14: 19/04/2027 | DV14: 26/04/2027 | DW14: 03/05/2027 | DX14: 10/05/2027 | DY14: 17/05/2027 | DZ14: 24/05/2027 | EA14: 31/05/2027 | EB14: 07/06/2027 | EC14: 14/06/2027 | ED14: 21/06/2027 | EE14: 28/06/2027 | EF14: 05/07/2027 | EG14: 12/07/2027 | EH14: 19/07/2027 | EI14: 26/07/2027 | EJ14: 02/08/2027 | EK14: 09/08/2027 | EL14: 16/08/2027 | EM14: 23/08/2027 | EN14: 30/08/2027 | EO14: 06/09/2027 | EP14: 13/09/2027 | EQ14: 20/09/2027 | ER14: 27/09/2027 | ES14: 04/10/2027 | ET14: 11/10/2027 | EU14: 18/10/2027 | EV14: 25/10/2027 | EW14: 01/11/2027 | EX14: 08/11/2027 | EY14: 15/11/2027 | EZ14: 22/11/2027 | FA14: 29/11/2027 | FB14: 06/12/2027 | FC14: 13/12/2027 | FD14: 20/12/2027
C15: =INPUT!G20 -> FiniQ II | D15: =_xlfn.XLOOKUP(Table14[[#This Row],[Project]],'MEA LOG'!$D$15:$D$100,'MEA LOG'!$F$15:$F$100,"") -> Emirates | E15: {=IFERROR(_xlfn.LET( _xlpm.project, $C15, _xlpm.weekDate, E$14, _xlpm.headers, INDEX(Table2[#Headers], _xlfn.SEQUENCE(1, COLUMNS(Table2[])-2)+2), _xlpm.milestoneDates, INDEX(Table2[], MATCH(_xlpm.project, Table2[Project], 0), _xlfn.SEQUENCE(1, COLUMNS(Table2[])-2)+2), _xlpm.matchWeek, _xlfn.ISOWEEKNUM(_xlpm.milestoneDates) = _xlfn.ISOWEEKNUM(_xlpm.weekDate), _xlpm.matchYear, YEAR(_xlpm.milestoneDates) = YEAR(_xlpm.weekDate), _xlpm.matched, IF(_xlpm.matchWeek * _xlpm.matchYear, _xlpm.headers, ""), _xlpm.result, _xlfn.TEXTJOIN(", ", TRUE, _xlpm.matched), IF(_xlpm.result="", "", _xlpm.result) ),"")} | F15: {=IFERROR(_xlfn.LET( _xlpm.project, $C15, _xlpm.weekDate, F$14, _xlpm.headers, INDEX(Table2[#Headers], _xlfn.SEQUENCE(1, COLUMNS(Table2[])-2)+2), _xlpm.milestoneDates, INDEX(Table2[], MATCH(_xlpm.project, Table2[Project], 0), _xlfn.SEQUENCE(1, COLUMNS(Table2[])-2)+2), _xlpm.matchWeek, _xlfn.ISOWEEKNUM(_xlpm.milestoneDates) = _xlfn.ISOWEEKNUM(_xlpm.weekDate), _xlpm.matchYear, YEAR(_xlpm.milestoneDates) = YEAR(_xlpm.weekDate), _xlpm.matched, IF(_xlpm.matchWeek * _xlpm.matchYear, _xlpm.headers, ""), _xlpm.result, _xlfn.TEXTJOIN(", ", TRUE, _xlpm.matched), IF(_xlpm.result="", "", _xlpm.result) ),"")} -> Idea Generation | G15: {=IFERROR(_xlfn.LET( _xlpm.project, $C15, _xlpm.weekDate, G$14, _xlpm.headers, INDEX(Table2[#Headers], _xlfn.SEQUENCE(1, COLUMNS(Table2[])-2)+2), _xlpm.milestoneDates, INDEX(Table2[], MATCH(_xlpm.project, Table2[Project], 0), _xlfn.SEQUENCE(1, COLUMNS(Table2[])-2)+2), _xlpm.matchWeek, _xlfn.ISOWEEKNUM(_xlpm.milestoneDates) = _xlfn.ISOWEEKNUM(_xlpm.weekDate), _xlpm.matchYear, YEAR(_xlpm.milestoneDates) = YEAR(_xlpm.weekDate), _xlpm.matched, IF(_xlpm.matchWeek * _xlpm.matchYear, _xlpm.headers, ""), _xlpm.result, _xlfn.TEXTJOIN(", ", TRUE, _xlpm.matched), IF(_xlpm.result="", "", _xlpm.result) ),"")} | H15: {=IFERROR(_xlfn.LET( _xlpm.project, $C15, _xlpm.weekDate, H$14, _xlpm.headers, INDEX(Table2[#Headers], _xlfn.SEQUENCE(1, COLUMNS(Table2[])-2)+2), _xlpm.milestoneDates, INDEX(Table2[], MATCH(_xlpm.project, Table2[Project], 0), _xlfn.SEQUENCE(1, COLUMNS(Table2[])-2)+2), _xlpm.matchWeek, _xlfn.ISOWEEKNUM(_xlpm.milestoneDates) = _xlfn.ISOWEEKNUM(_xlpm.weekDate), _xlpm.matchYear, YEAR(_xlpm.milestoneDates) = YEAR(_xlpm.weekDate), _xlpm.matched, IF(_xlpm.matchWeek * _xlpm.matchYear, _xlpm.headers, ""), _xlpm.result, _xlfn.TEXTJOIN(", ", TRUE, _xlpm.matched), IF(_xlpm.result="", "", _xlpm.result) ),"")} | I15: {=IFERROR(_xlfn.LET( _xlpm.project, $C15, _xlpm.weekDate, I$14, _xlpm.headers, INDEX(Table2[#Headers], _xlfn.SEQUENCE(1, COLUMNS(Table2[])-2)+2), _xlpm.milestoneDates, INDEX(Table2[], MATCH(_xlpm.project, Table2[Project], 0), _xlfn.SEQUENCE(1, COLUMNS(Table2[])-2)+2), _xlpm.matchWeek, _xlfn.ISOWEEKNUM(_xlpm.milestoneDates) = _xlfn.ISOWEEKNUM(_xlpm.weekDate), _xlpm.matchYear, YEAR(_xlpm.milestoneDates) = YEAR(_xlpm.weekDate), _xlpm.matched, IF(_xlpm.matchWeek * _xlpm.matchYear, _xlpm.headers, ""), _xlpm.result, _xlfn.TEXTJOIN(", ", TRUE, _xlpm.matched), IF(_xlpm.result="", "", _xlpm.result) ),"")} | J15: {=IFERROR(_xlfn.LET( _xlpm.project, $C15, _xlpm.weekDate, J$14, _xlpm.headers, INDEX(Table2[#Headers], _xlfn.SEQUENCE(1, COLUMNS(Table2[])-2)+2), _xlpm.milestoneDates, INDEX(Table2[], MATCH(_xlpm.project, Table2[Project], 0), _xlfn.SEQUENCE(1, COLUMNS(Table2[])-2)+2), _xlpm.matchWeek, _xlfn.ISOWEEKNUM(_xlpm.milestoneDates) = _xlfn.ISOWEEKNUM(_xlpm.weekDate), _xlpm.matchYear, YEAR(_xlpm.milestoneDates) = YEAR(_xlpm.weekDate), _xlpm.matched, IF(_xlpm.matchWeek * _xlpm.matchYear, _xlpm.headers, ""), _xlpm.result, _xlfn.TEXTJOIN(", ", TRUE, _xlpm.matched), IF(_xlpm.result="", "", _xlpm.result) ),"")} | K15: {=IFERROR(_xlfn.LET( _xlpm.project, $C15, _xlpm.weekDate, K$14, _xlpm.headers, INDEX(Table2[#Headers], _xlfn.SEQUENCE(1, COLUMNS(Table2[])-2)+2), _xlpm.milestoneDates, INDEX(Table2[], MATCH(_xlpm.project, Table2[Project], 0), _xlfn.SEQUENCE(1, COLUMNS(Table2[])-2)+2), _xlpm.matchWeek, _xlfn.ISOWEEKNUM(_xlpm.milestoneDates) = _xlfn.ISOWEEKNUM(_xlpm.weekDate), _xlpm.matchYear, YEAR(_xlpm.milestoneDates) = YEAR(_xlpm.weekDate), _xlpm.matched, IF(_xlpm.matchWeek * _xlpm.matchYear, _xlpm.headers, ""), _xlpm.result, _xlfn.TEXTJOIN(", ", TRUE, _xlpm.matched), IF(_xlpm.result="", "", _xlpm.result) ),"")} | L15: {=IFERROR(_xlfn.LET( _xlpm.project, $C15, _xlpm.weekDate, L$14, _xlpm.headers, INDEX(Table2[#Headers], _xlfn.SEQUENCE(1, COLUMNS(Table2[])-2)+2), _xlpm.milestoneDates, INDEX(Table2[], MATCH(_xlpm.project, Table2[Project], 0), _xlfn.SEQUENCE(1, COLUMNS(Table2[])-2)+2), _xlpm.matchWeek, _xlfn.ISOWEEKNUM(_xlpm.milestoneDates) = _xlfn.ISOWEEKNUM(_xlpm.weekDate), _xlpm.matchYear, YEAR(_xlpm.milestoneDates) = YEAR(_xlpm.weekDate), _xlpm.matched, IF(_xlpm.matchWeek * _xlpm.matchYear, _xlpm.headers, ""), _xlpm.result, _xlfn.TEXTJOIN(", ", TRUE, _xlpm.matched), IF(_xlpm.result="", "", _xlpm.result) ),"")} | ... FD15: {=IFERROR(_xlfn.LET( _xlpm.project, $C15, _xlpm.weekDate, FD$14, _xlpm.headers, INDEX(Table2[#Headers], _xlfn.SEQUENCE(1, COLUMNS(Table2[])-2)+2), _xlpm.milestoneDates, INDEX(Table2[], MATCH(_xlpm.project, Table2[Project], 0), _xlfn.SEQUENCE(1, COLUMNS(Table2[])-2)+2), _xlpm.matchWeek, _xlfn.ISOWEEKNUM(_xlpm.milestoneDates) = _xlfn.ISOWEEKNUM(_xlpm.weekDate), _xlpm.matchYear, YEAR(_xlpm.milestoneDates) = YEAR(_xlpm.weekDate), _xlpm.matched, IF(_xlpm.matchWeek * _xlpm.matchYear, _xlpm.headers, ""), _xlpm.result, _xlfn.TEXTJOIN(", ", TRUE, _xlpm.matched), IF(_xlpm.result="", "", _xlpm.result) ),"")}
C16: =INPUT!G21 -> FiniQ III | D16: =_xlfn.XLOOKUP(Table14[[#This Row],[Project]],'MEA LOG'!$D$15:$D$100,'MEA LOG'!$F$15:$F$100,"") -> Emirates | E16: {=IFERROR(_xlfn.LET( _xlpm.project, $C16, _xlpm.weekDate, E$14, _xlpm.headers, INDEX(Table2[#Headers], _xlfn.SEQUENCE(1, COLUMNS(Table2[])-2)+2), _xlpm.milestoneDates, INDEX(Table2[], MATCH(_xlpm.project, Table2[Project], 0), _xlfn.SEQUENCE(1, COLUMNS(Table2[])-2)+2), _xlpm.matchWeek, _xlfn.ISOWEEKNUM(_xlpm.milestoneDates) = _xlfn.ISOWEEKNUM(_xlpm.weekDate), _xlpm.matchYear, YEAR(_xlpm.milestoneDates) = YEAR(_xlpm.weekDate), _xlpm.matched, IF(_xlpm.matchWeek * _xlpm.matchYear, _xlpm.headers, ""), _xlpm.result, _xlfn.TEXTJOIN(", ", TRUE, _xlpm.matched), IF(_xlpm.result="", "", _xlpm.result) ),"")} -> Idea Generation | F16: {=IFERROR(_xlfn.LET( _xlpm.project, $C16, _xlpm.weekDate, F$14, _xlpm.headers, INDEX(Table2[#Headers], _xlfn.SEQUENCE(1, COLUMNS(Table2[])-2)+2), _xlpm.milestoneDates, INDEX(Table2[], MATCH(_xlpm.project, Table2[Project], 0), _xlfn.SEQUENCE(1, COLUMNS(Table2[])-2)+2), _xlpm.matchWeek, _xlfn.ISOWEEKNUM(_xlpm.milestoneDates) = _xlfn.ISOWEEKNUM(_xlpm.weekDate), _xlpm.matchYear, YEAR(_xlpm.milestoneDates) = YEAR(_xlpm.weekDate), _xlpm.matched, IF(_xlpm.matchWeek * _xlpm.matchYear, _xlpm.headers, ""), _xlpm.result, _xlfn.TEXTJOIN(", ", TRUE, _xlpm.matched), IF(_xlpm.result="", "", _xlpm.result) ),"")} | G16: {=IFERROR(_xlfn.LET( _xlpm.project, $C16, _xlpm.weekDate, G$14, _xlpm.headers, INDEX(Table2[#Headers], _xlfn.SEQUENCE(1, COLUMNS(Table2[])-2)+2), _xlpm.milestoneDates, INDEX(Table2[], MATCH(_xlpm.project, Table2[Project], 0), _xlfn.SEQUENCE(1, COLUMNS(Table2[])-2)+2), _xlpm.matchWeek, _xlfn.ISOWEEKNUM(_xlpm.milestoneDates) = _xlfn.ISOWEEKNUM(_xlpm.weekDate), _xlpm.matchYear, YEAR(_xlpm.milestoneDates) = YEAR(_xlpm.weekDate), _xlpm.matched, IF(_xlpm.matchWeek * _xlpm.matchYear, _xlpm.headers, ""), _xlpm.result, _xlfn.TEXTJOIN(", ", TRUE, _xlpm.matched), IF(_xlpm.result="", "", _xlpm.result) ),"")} | H16: {=IFERROR(_xlfn.LET( _xlpm.project, $C16, _xlpm.weekDate, H$14, _xlpm.headers, INDEX(Table2[#Headers], _xlfn.SEQUENCE(1, COLUMNS(Table2[])-2)+2), _xlpm.milestoneDates, INDEX(Table2[], MATCH(_xlpm.project, Table2[Project], 0), _xlfn.SEQUENCE(1, COLUMNS(Table2[])-2)+2), _xlpm.matchWeek, _xlfn.ISOWEEKNUM(_xlpm.milestoneDates) = _xlfn.ISOWEEKNUM(_xlpm.weekDate), _xlpm.matchYear, YEAR(_xlpm.milestoneDates) = YEAR(_xlpm.weekDate), _xlpm.matched, IF(_xlpm.matchWeek * _xlpm.matchYear, _xlpm.headers, ""), _xlpm.result, _xlfn.TEXTJOIN(", ", TRUE, _xlpm.matched), IF(_xlpm.result="", "", _xlpm.result) ),"")} | I16: {=IFERROR(_xlfn.LET( _xlpm.project, $C16, _xlpm.weekDate, I$14, _xlpm.headers, INDEX(Table2[#Headers], _xlfn.SEQUENCE(1, COLUMNS(Table2[])-2)+2), _xlpm.milestoneDates, INDEX(Table2[], MATCH(_xlpm.project, Table2[Project], 0), _xlfn.SEQUENCE(1, COLUMNS(Table2[])-2)+2), _xlpm.matchWeek, _xlfn.ISOWEEKNUM(_xlpm.milestoneDates) = _xlfn.ISOWEEKNUM(_xlpm.weekDate), _xlpm.matchYear, YEAR(_xlpm.milestoneDates) = YEAR(_xlpm.weekDate), _xlpm.matched, IF(_xlpm.matchWeek * _xlpm.matchYear, _xlpm.headers, ""), _xlpm.result, _xlfn.TEXTJOIN(", ", TRUE, _xlpm.matched), IF(_xlpm.result="", "", _xlpm.result) ),"")} | J16: {=IFERROR(_xlfn.LET( _xlpm.project, $C16, _xlpm.weekDate, J$14, _xlpm.headers, INDEX(Table2[#Headers], _xlfn.SEQUENCE(1, COLUMNS(Table2[])-2)+2), _xlpm.milestoneDates, INDEX(Table2[], MATCH(_xlpm.project, Table2[Project], 0), _xlfn.SEQUENCE(1, COLUMNS(Table2[])-2)+2), _xlpm.matchWeek, _xlfn.ISOWEEKNUM(_xlpm.milestoneDates) = _xlfn.ISOWEEKNUM(_xlpm.weekDate), _xlpm.matchYear, YEAR(_xlpm.milestoneDates) = YEAR(_xlpm.weekDate), _xlpm.matched, IF(_xlpm.matchWeek * _xlpm.matchYear, _xlpm.headers, ""), _xlpm.result, _xlfn.TEXTJOIN(", ", TRUE, _xlpm.matched), IF(_xlpm.result="", "", _xlpm.result) ),"")} | K16: {=IFERROR(_xlfn.LET( _xlpm.project, $C16, _xlpm.weekDate, K$14, _xlpm.headers, INDEX(Table2[#Headers], _xlfn.SEQUENCE(1, COLUMNS(Table2[])-2)+2), _xlpm.milestoneDates, INDEX(Table2[], MATCH(_xlpm.project, Table2[Project], 0), _xlfn.SEQUENCE(1, COLUMNS(Table2[])-2)+2), _xlpm.matchWeek, _xlfn.ISOWEEKNUM(_xlpm.milestoneDates) = _xlfn.ISOWEEKNUM(_xlpm.weekDate), _xlpm.matchYear, YEAR(_xlpm.milestoneDates) = YEAR(_xlpm.weekDate), _xlpm.matched, IF(_xlpm.matchWeek * _xlpm.matchYear, _xlpm.headers, ""), _xlpm.result, _xlfn.TEXTJOIN(", ", TRUE, _xlpm.matched), IF(_xlpm.result="", "", _xlpm.result) ),"")} | L16: {=IFERROR(_xlfn.LET( _xlpm.project, $C16, _xlpm.weekDate, L$14, _xlpm.headers, INDEX(Table2[#Headers], _xlfn.SEQUENCE(1, COLUMNS(Table2[])-2)+2), _xlpm.milestoneDates, INDEX(Table2[], MATCH(_xlpm.project, Table2[Project], 0), _xlfn.SEQUENCE(1, COLUMNS(Table2[])-2)+2), _xlpm.matchWeek, _xlfn.ISOWEEKNUM(_xlpm.milestoneDates) = _xlfn.ISOWEEKNUM(_xlpm.weekDate), _xlpm.matchYear, YEAR(_xlpm.milestoneDates) = YEAR(_xlpm.weekDate), _xlpm.matched, IF(_xlpm.matchWeek * _xlpm.matchYear, _xlpm.headers, ""), _xlpm.result, _xlfn.TEXTJOIN(", ", TRUE, _xlpm.matched), IF(_xlpm.result="", "", _xlpm.result) ),"")} | ... FD16: {=IFERROR(_xlfn.LET( _xlpm.project, $C16, _xlpm.weekDate, FD$14, _xlpm.headers, INDEX(Table2[#Headers], _xlfn.SEQUENCE(1, COLUMNS(Table2[])-2)+2), _xlpm.milestoneDates, INDEX(Table2[], MATCH(_xlpm.project, Table2[Project], 0), _xlfn.SEQUENCE(1, COLUMNS(Table2[])-2)+2), _xlpm.matchWeek, _xlfn.ISOWEEKNUM(_xlpm.milestoneDates) = _xlfn.ISOWEEKNUM(_xlpm.weekDate), _xlpm.matchYear, YEAR(_xlpm.milestoneDates) = YEAR(_xlpm.weekDate), _xlpm.matched, IF(_xlpm.matchWeek * _xlpm.matchYear, _xlpm.headers, ""), _xlpm.result, _xlfn.TEXTJOIN(", ", TRUE, _xlpm.matched), IF(_xlpm.result="", "", _xlpm.result) ),"")}
C17: =INPUT!G22 -> IDK | D17: =_xlfn.XLOOKUP(Table14[[#This Row],[Project]],'MEA LOG'!$D$15:$D$100,'MEA LOG'!$F$15:$F$100,"") -> Emirates | E17: {=IFERROR(_xlfn.LET( _xlpm.project, $C17, _xlpm.weekDate, E$14, _xlpm.headers, INDEX(Table2[#Headers], _xlfn.SEQUENCE(1, COLUMNS(Table2[])-2)+2), _xlpm.milestoneDates, INDEX(Table2[], MATCH(_xlpm.project, Table2[Project], 0), _xlfn.SEQUENCE(1, COLUMNS(Table2[])-2)+2), _xlpm.matchWeek, _xlfn.ISOWEEKNUM(_xlpm.milestoneDates) = _xlfn.ISOWEEKNUM(_xlpm.weekDate), _xlpm.matchYear, YEAR(_xlpm.milestoneDates) = YEAR(_xlpm.weekDate), _xlpm.matched, IF(_xlpm.matchWeek * _xlpm.matchYear, _xlpm.headers, ""), _xlpm.result, _xlfn.TEXTJOIN(", ", TRUE, _xlpm.matched), IF(_xlpm.result="", "", _xlpm.result) ),"")} | F17: {=IFERROR(_xlfn.LET( _xlpm.project, $C17, _xlpm.weekDate, F$14, _xlpm.headers, INDEX(Table2[#Headers], _xlfn.SEQUENCE(1, COLUMNS(Table2[])-2)+2), _xlpm.milestoneDates, INDEX(Table2[], MATCH(_xlpm.project, Table2[Project], 0), _xlfn.SEQUENCE(1, COLUMNS(Table2[])-2)+2), _xlpm.matchWeek, _xlfn.ISOWEEKNUM(_xlpm.milestoneDates) = _xlfn.ISOWEEKNUM(_xlpm.weekDate), _xlpm.matchYear, YEAR(_xlpm.milestoneDates) = YEAR(_xlpm.weekDate), _xlpm.matched, IF(_xlpm.matchWeek * _xlpm.matchYear, _xlpm.headers, ""), _xlpm.result, _xlfn.TEXTJOIN(", ", TRUE, _xlpm.matched), IF(_xlpm.result="", "", _xlpm.result) ),"")} -> Idea Generation | G17: {=IFERROR(_xlfn.LET( _xlpm.project, $C17, _xlpm.weekDate, G$14, _xlpm.headers, INDEX(Table2[#Headers], _xlfn.SEQUENCE(1, COLUMNS(Table2[])-2)+2), _xlpm.milestoneDates, INDEX(Table2[], MATCH(_xlpm.project, Table2[Project], 0), _xlfn.SEQUENCE(1, COLUMNS(Table2[])-2)+2), _xlpm.matchWeek, _xlfn.ISOWEEKNUM(_xlpm.milestoneDates) = _xlfn.ISOWEEKNUM(_xlpm.weekDate), _xlpm.matchYear, YEAR(_xlpm.milestoneDates) = YEAR(_xlpm.weekDate), _xlpm.matched, IF(_xlpm.matchWeek * _xlpm.matchYear, _xlpm.headers, ""), _xlpm.result, _xlfn.TEXTJOIN(", ", TRUE, _xlpm.matched), IF(_xlpm.result="", "", _xlpm.result) ),"")} | H17: {=IFERROR(_xlfn.LET( _xlpm.project, $C17, _xlpm.weekDate, H$14, _xlpm.headers, INDEX(Table2[#Headers], _xlfn.SEQUENCE(1, COLUMNS(Table2[])-2)+2), _xlpm.milestoneDates, INDEX(Table2[], MATCH(_xlpm.project, Table2[Project], 0), _xlfn.SEQUENCE(1, COLUMNS(Table2[])-2)+2), _xlpm.matchWeek, _xlfn.ISOWEEKNUM(_xlpm.milestoneDates) = _xlfn.ISOWEEKNUM(_xlpm.weekDate), _xlpm.matchYear, YEAR(_xlpm.milestoneDates) = YEAR(_xlpm.weekDate), _xlpm.matched, IF(_xlpm.matchWeek * _xlpm.matchYear, _xlpm.headers, ""), _xlpm.result, _xlfn.TEXTJOIN(", ", TRUE, _xlpm.matched), IF(_xlpm.result="", "", _xlpm.result) ),"")} | I17: {=IFERROR(_xlfn.LET( _xlpm.project, $C17, _xlpm.weekDate, I$14, _xlpm.headers, INDEX(Table2[#Headers], _xlfn.SEQUENCE(1, COLUMNS(Table2[])-2)+2), _xlpm.milestoneDates, INDEX(Table2[], MATCH(_xlpm.project, Table2[Project], 0), _xlfn.SEQUENCE(1, COLUMNS(Table2[])-2)+2), _xlpm.matchWeek, _xlfn.ISOWEEKNUM(_xlpm.milestoneDates) = _xlfn.ISOWEEKNUM(_xlpm.weekDate), _xlpm.matchYear, YEAR(_xlpm.milestoneDates) = YEAR(_xlpm.weekDate), _xlpm.matched, IF(_xlpm.matchWeek * _xlpm.matchYear, _xlpm.headers, ""), _xlpm.result, _xlfn.TEXTJOIN(", ", TRUE, _xlpm.matched), IF(_xlpm.result="", "", _xlpm.result) ),"")} | J17: {=IFERROR(_xlfn.LET( _xlpm.project, $C17, _xlpm.weekDate, J$14, _xlpm.headers, INDEX(Table2[#Headers], _xlfn.SEQUENCE(1, COLUMNS(Table2[])-2)+2), _xlpm.milestoneDates, INDEX(Table2[], MATCH(_xlpm.project, Table2[Project], 0), _xlfn.SEQUENCE(1, COLUMNS(Table2[])-2)+2), _xlpm.matchWeek, _xlfn.ISOWEEKNUM(_xlpm.milestoneDates) = _xlfn.ISOWEEKNUM(_xlpm.weekDate), _xlpm.matchYear, YEAR(_xlpm.milestoneDates) = YEAR(_xlpm.weekDate), _xlpm.matched, IF(_xlpm.matchWeek * _xlpm.matchYear, _xlpm.headers, ""), _xlpm.result, _xlfn.TEXTJOIN(", ", TRUE, _xlpm.matched), IF(_xlpm.result="", "", _xlpm.result) ),"")} | K17: {=IFERROR(_xlfn.LET( _xlpm.project, $C17, _xlpm.weekDate, K$14, _xlpm.headers, INDEX(Table2[#Headers], _xlfn.SEQUENCE(1, COLUMNS(Table2[])-2)+2), _xlpm.milestoneDates, INDEX(Table2[], MATCH(_xlpm.project, Table2[Project], 0), _xlfn.SEQUENCE(1, COLUMNS(Table2[])-2)+2), _xlpm.matchWeek, _xlfn.ISOWEEKNUM(_xlpm.milestoneDates) = _xlfn.ISOWEEKNUM(_xlpm.weekDate), _xlpm.matchYear, YEAR(_xlpm.milestoneDates) = YEAR(_xlpm.weekDate), _xlpm.matched, IF(_xlpm.matchWeek * _xlpm.matchYear, _xlpm.headers, ""), _xlpm.result, _xlfn.TEXTJOIN(", ", TRUE, _xlpm.matched), IF(_xlpm.result="", "", _xlpm.result) ),"")} | L17: {=IFERROR(_xlfn.LET( _xlpm.project, $C17, _xlpm.weekDate, L$14, _xlpm.headers, INDEX(Table2[#Headers], _xlfn.SEQUENCE(1, COLUMNS(Table2[])-2)+2), _xlpm.milestoneDates, INDEX(Table2[], MATCH(_xlpm.project, Table2[Project], 0), _xlfn.SEQUENCE(1, COLUMNS(Table2[])-2)+2), _xlpm.matchWeek, _xlfn.ISOWEEKNUM(_xlpm.milestoneDates) = _xlfn.ISOWEEKNUM(_xlpm.weekDate), _xlpm.matchYear, YEAR(_xlpm.milestoneDates) = YEAR(_xlpm.weekDate), _xlpm.matched, IF(_xlpm.matchWeek * _xlpm.matchYear, _xlpm.headers, ""), _xlpm.result, _xlfn.TEXTJOIN(", ", TRUE, _xlpm.matched), IF(_xlpm.result="", "", _xlpm.result) ),"")} | ... FD17: {=IFERROR(_xlfn.LET( _xlpm.project, $C17, _xlpm.weekDate, FD$14, _xlpm.headers, INDEX(Table2[#Headers], _xlfn.SEQUENCE(1, COLUMNS(Table2[])-2)+2), _xlpm.milestoneDates, INDEX(Table2[], MATCH(_xlpm.project, Table2[Project], 0), _xlfn.SEQUENCE(1, COLUMNS(Table2[])-2)+2), _xlpm.matchWeek, _xlfn.ISOWEEKNUM(_xlpm.milestoneDates) = _xlfn.ISOWEEKNUM(_xlpm.weekDate), _xlpm.matchYear, YEAR(_xlpm.milestoneDates) = YEAR(_xlpm.weekDate), _xlpm.matched, IF(_xlpm.matchWeek * _xlpm.matchYear, _xlpm.headers, ""), _xlpm.result, _xlfn.TEXTJOIN(", ", TRUE, _xlpm.matched), IF(_xlpm.result="", "", _xlpm.result) ),"")}
C18: =INPUT!G23 -> Selassi | D18: =_xlfn.XLOOKUP(Table14[[#This Row],[Project]],'MEA LOG'!$D$15:$D$100,'MEA LOG'!$F$15:$F$100,"") -> Ethiopia | E18: {=IFERROR(_xlfn.LET( _xlpm.project, $C18, _xlpm.weekDate, E$14, _xlpm.headers, INDEX(Table2[#Headers], _xlfn.SEQUENCE(1, COLUMNS(Table2[])-2)+2), _xlpm.milestoneDates, INDEX(Table2[], MATCH(_xlpm.project, Table2[Project], 0), _xlfn.SEQUENCE(1, COLUMNS(Table2[])-2)+2), _xlpm.matchWeek, _xlfn.ISOWEEKNUM(_xlpm.milestoneDates) = _xlfn.ISOWEEKNUM(_xlpm.weekDate), _xlpm.matchYear, YEAR(_xlpm.milestoneDates) = YEAR(_xlpm.weekDate), _xlpm.matched, IF(_xlpm.matchWeek * _xlpm.matchYear, _xlpm.headers, ""), _xlpm.result, _xlfn.TEXTJOIN(", ", TRUE, _xlpm.matched), IF(_xlpm.result="", "", _xlpm.result) ),"")} | F18: {=IFERROR(_xlfn.LET( _xlpm.project, $C18, _xlpm.weekDate, F$14, _xlpm.headers, INDEX(Table2[#Headers], _xlfn.SEQUENCE(1, COLUMNS(Table2[])-2)+2), _xlpm.milestoneDates, INDEX(Table2[], MATCH(_xlpm.project, Table2[Project], 0), _xlfn.SEQUENCE(1, COLUMNS(Table2[])-2)+2), _xlpm.matchWeek, _xlfn.ISOWEEKNUM(_xlpm.milestoneDates) = _xlfn.ISOWEEKNUM(_xlpm.weekDate), _xlpm.matchYear, YEAR(_xlpm.milestoneDates) = YEAR(_xlpm.weekDate), _xlpm.matched, IF(_xlpm.matchWeek * _xlpm.matchYear, _xlpm.headers, ""), _xlpm.result, _xlfn.TEXTJOIN(", ", TRUE, _xlpm.matched), IF(_xlpm.result="", "", _xlpm.result) ),"")} | G18: {=IFERROR(_xlfn.LET( _xlpm.project, $C18, _xlpm.weekDate, G$14, _xlpm.headers, INDEX(Table2[#Headers], _xlfn.SEQUENCE(1, COLUMNS(Table2[])-2)+2), _xlpm.milestoneDates, INDEX(Table2[], MATCH(_xlpm.project, Table2[Project], 0), _xlfn.SEQUENCE(1, COLUMNS(Table2[])-2)+2), _xlpm.matchWeek, _xlfn.ISOWEEKNUM(_xlpm.milestoneDates) = _xlfn.ISOWEEKNUM(_xlpm.weekDate), _xlpm.matchYear, YEAR(_xlpm.milestoneDates) = YEAR(_xlpm.weekDate), _xlpm.matched, IF(_xlpm.matchWeek * _xlpm.matchYear, _xlpm.headers, ""), _xlpm.result, _xlfn.TEXTJOIN(", ", TRUE, _xlpm.matched), IF(_xlpm.result="", "", _xlpm.result) ),"")} | H18: {=IFERROR(_xlfn.LET( _xlpm.project, $C18, _xlpm.weekDate, H$14, _xlpm.headers, INDEX(Table2[#Headers], _xlfn.SEQUENCE(1, COLUMNS(Table2[])-2)+2), _xlpm.milestoneDates, INDEX(Table2[], MATCH(_xlpm.project, Table2[Project], 0), _xlfn.SEQUENCE(1, COLUMNS(Table2[])-2)+2), _xlpm.matchWeek, _xlfn.ISOWEEKNUM(_xlpm.milestoneDates) = _xlfn.ISOWEEKNUM(_xlpm.weekDate), _xlpm.matchYear, YEAR(_xlpm.milestoneDates) = YEAR(_xlpm.weekDate), _xlpm.matched, IF(_xlpm.matchWeek * _xlpm.matchYear, _xlpm.headers, ""), _xlpm.result, _xlfn.TEXTJOIN(", ", TRUE, _xlpm.matched), IF(_xlpm.result="", "", _xlpm.result) ),"")} | I18: {=IFERROR(_xlfn.LET( _xlpm.project, $C18, _xlpm.weekDate, I$14, _xlpm.headers, INDEX(Table2[#Headers], _xlfn.SEQUENCE(1, COLUMNS(Table2[])-2)+2), _xlpm.milestoneDates, INDEX(Table2[], MATCH(_xlpm.project, Table2[Project], 0), _xlfn.SEQUENCE(1, COLUMNS(Table2[])-2)+2), _xlpm.matchWeek, _xlfn.ISOWEEKNUM(_xlpm.milestoneDates) = _xlfn.ISOWEEKNUM(_xlpm.weekDate), _xlpm.matchYear, YEAR(_xlpm.milestoneDates) = YEAR(_xlpm.weekDate), _xlpm.matched, IF(_xlpm.matchWeek * _xlpm.matchYear, _xlpm.headers, ""), _xlpm.result, _xlfn.TEXTJOIN(", ", TRUE, _xlpm.matched), IF(_xlpm.result="", "", _xlpm.result) ),"")} | J18: {=IFERROR(_xlfn.LET( _xlpm.project, $C18, _xlpm.weekDate, J$14, _xlpm.headers, INDEX(Table2[#Headers], _xlfn.SEQUENCE(1, COLUMNS(Table2[])-2)+2), _xlpm.milestoneDates, INDEX(Table2[], MATCH(_xlpm.project, Table2[Project], 0), _xlfn.SEQUENCE(1, COLUMNS(Table2[])-2)+2), _xlpm.matchWeek, _xlfn.ISOWEEKNUM(_xlpm.milestoneDates) = _xlfn.ISOWEEKNUM(_xlpm.weekDate), _xlpm.matchYear, YEAR(_xlpm.milestoneDates) = YEAR(_xlpm.weekDate), _xlpm.matched, IF(_xlpm.matchWeek * _xlpm.matchYear, _xlpm.headers, ""), _xlpm.result, _xlfn.TEXTJOIN(", ", TRUE, _xlpm.matched), IF(_xlpm.result="", "", _xlpm.result) ),"")} | K18: {=IFERROR(_xlfn.LET( _xlpm.project, $C18, _xlpm.weekDate, K$14, _xlpm.headers, INDEX(Table2[#Headers], _xlfn.SEQUENCE(1, COLUMNS(Table2[])-2)+2), _xlpm.milestoneDates, INDEX(Table2[], MATCH(_xlpm.project, Table2[Project], 0), _xlfn.SEQUENCE(1, COLUMNS(Table2[])-2)+2), _xlpm.matchWeek, _xlfn.ISOWEEKNUM(_xlpm.milestoneDates) = _xlfn.ISOWEEKNUM(_xlpm.weekDate), _xlpm.matchYear, YEAR(_xlpm.milestoneDates) = YEAR(_xlpm.weekDate), _xlpm.matched, IF(_xlpm.matchWeek * _xlpm.matchYear, _xlpm.headers, ""), _xlpm.result, _xlfn.TEXTJOIN(", ", TRUE, _xlpm.matched), IF(_xlpm.result="", "", _xlpm.result) ),"")} | L18: {=IFERROR(_xlfn.LET( _xlpm.project, $C18, _xlpm.weekDate, L$14, _xlpm.headers, INDEX(Table2[#Headers], _xlfn.SEQUENCE(1, COLUMNS(Table2[])-2)+2), _xlpm.milestoneDates, INDEX(Table2[], MATCH(_xlpm.project, Table2[Project], 0), _xlfn.SEQUENCE(1, COLUMNS(Table2[])-2)+2), _xlpm.matchWeek, _xlfn.ISOWEEKNUM(_xlpm.milestoneDates) = _xlfn.ISOWEEKNUM(_xlpm.weekDate), _xlpm.matchYear, YEAR(_xlpm.milestoneDates) = YEAR(_xlpm.weekDate), _xlpm.matched, IF(_xlpm.matchWeek * _xlpm.matchYear, _xlpm.headers, ""), _xlpm.result, _xlfn.TEXTJOIN(", ", TRUE, _xlpm.matched), IF(_xlpm.result="", "", _xlpm.result) ),"")} | ... FD18: {=IFERROR(_xlfn.LET( _xlpm.project, $C18, _xlpm.weekDate, FD$14, _xlpm.headers, INDEX(Table2[#Headers], _xlfn.SEQUENCE(1, COLUMNS(Table2[])-2)+2), _xlpm.milestoneDates, INDEX(Table2[], MATCH(_xlpm.project, Table2[Project], 0), _xlfn.SEQUENCE(1, COLUMNS(Table2[])-2)+2), _xlpm.matchWeek, _xlfn.ISOWEEKNUM(_xlpm.milestoneDates) = _xlfn.ISOWEEKNUM(_xlpm.weekDate), _xlpm.matchYear, YEAR(_xlpm.milestoneDates) = YEAR(_xlpm.weekDate), _xlpm.matched, IF(_xlpm.matchWeek * _xlpm.matchYear, _xlpm.headers, ""), _xlpm.result, _xlfn.TEXTJOIN(", ", TRUE, _xlpm.matched), IF(_xlpm.result="", "", _xlpm.result) ),"")}
C19: =INPUT!G24 -> Selassi II | D19: =_xlfn.XLOOKUP(Table14[[#This Row],[Project]],'MEA LOG'!$D$15:$D$100,'MEA LOG'!$F$15:$F$100,"") -> Ethiopia | E19: {=IFERROR(_xlfn.LET( _xlpm.project, $C19, _xlpm.weekDate, E$14, _xlpm.headers, INDEX(Table2[#Headers], _xlfn.SEQUENCE(1, COLUMNS(Table2[])-2)+2), _xlpm.milestoneDates, INDEX(Table2[], MATCH(_xlpm.project, Table2[Project], 0), _xlfn.SEQUENCE(1, COLUMNS(Table2[])-2)+2), _xlpm.matchWeek, _xlfn.ISOWEEKNUM(_xlpm.milestoneDates) = _xlfn.ISOWEEKNUM(_xlpm.weekDate), _xlpm.matchYear, YEAR(_xlpm.milestoneDates) = YEAR(_xlpm.weekDate), _xlpm.matched, IF(_xlpm.matchWeek * _xlpm.matchYear, _xlpm.headers, ""), _xlpm.result, _xlfn.TEXTJOIN(", ", TRUE, _xlpm.matched), IF(_xlpm.result="", "", _xlpm.result) ),"")} -> Idea Generation | F19: {=IFERROR(_xlfn.LET( _xlpm.project, $C19, _xlpm.weekDate, F$14, _xlpm.headers, INDEX(Table2[#Headers], _xlfn.SEQUENCE(1, COLUMNS(Table2[])-2)+2), _xlpm.milestoneDates, INDEX(Table2[], MATCH(_xlpm.project, Table2[Project], 0), _xlfn.SEQUENCE(1, COLUMNS(Table2[])-2)+2), _xlpm.matchWeek, _xlfn.ISOWEEKNUM(_xlpm.milestoneDates) = _xlfn.ISOWEEKNUM(_xlpm.weekDate), _xlpm.matchYear, YEAR(_xlpm.milestoneDates) = YEAR(_xlpm.weekDate), _xlpm.matched, IF(_xlpm.matchWeek * _xlpm.matchYear, _xlpm.headers, ""), _xlpm.result, _xlfn.TEXTJOIN(", ", TRUE, _xlpm.matched), IF(_xlpm.result="", "", _xlpm.result) ),"")} | G19: {=IFERROR(_xlfn.LET( _xlpm.project, $C19, _xlpm.weekDate, G$14, _xlpm.headers, INDEX(Table2[#Headers], _xlfn.SEQUENCE(1, COLUMNS(Table2[])-2)+2), _xlpm.milestoneDates, INDEX(Table2[], MATCH(_xlpm.project, Table2[Project], 0), _xlfn.SEQUENCE(1, COLUMNS(Table2[])-2)+2), _xlpm.matchWeek, _xlfn.ISOWEEKNUM(_xlpm.milestoneDates) = _xlfn.ISOWEEKNUM(_xlpm.weekDate), _xlpm.matchYear, YEAR(_xlpm.milestoneDates) = YEAR(_xlpm.weekDate), _xlpm.matched, IF(_xlpm.matchWeek * _xlpm.matchYear, _xlpm.headers, ""), _xlpm.result, _xlfn.TEXTJOIN(", ", TRUE, _xlpm.matched), IF(_xlpm.result="", "", _xlpm.result) ),"")} | H19: {=IFERROR(_xlfn.LET( _xlpm.project, $C19, _xlpm.weekDate, H$14, _xlpm.headers, INDEX(Table2[#Headers], _xlfn.SEQUENCE(1, COLUMNS(Table2[])-2)+2), _xlpm.milestoneDates, INDEX(Table2[], MATCH(_xlpm.project, Table2[Project], 0), _xlfn.SEQUENCE(1, COLUMNS(Table2[])-2)+2), _xlpm.matchWeek, _xlfn.ISOWEEKNUM(_xlpm.milestoneDates) = _xlfn.ISOWEEKNUM(_xlpm.weekDate), _xlpm.matchYear, YEAR(_xlpm.milestoneDates) = YEAR(_xlpm.weekDate), _xlpm.matched, IF(_xlpm.matchWeek * _xlpm.matchYear, _xlpm.headers, ""), _xlpm.result, _xlfn.TEXTJOIN(", ", TRUE, _xlpm.matched), IF(_xlpm.result="", "", _xlpm.result) ),"")} | I19: {=IFERROR(_xlfn.LET( _xlpm.project, $C19, _xlpm.weekDate, I$14, _xlpm.headers, INDEX(Table2[#Headers], _xlfn.SEQUENCE(1, COLUMNS(Table2[])-2)+2), _xlpm.milestoneDates, INDEX(Table2[], MATCH(_xlpm.project, Table2[Project], 0), _xlfn.SEQUENCE(1, COLUMNS(Table2[])-2)+2), _xlpm.matchWeek, _xlfn.ISOWEEKNUM(_xlpm.milestoneDates) = _xlfn.ISOWEEKNUM(_xlpm.weekDate), _xlpm.matchYear, YEAR(_xlpm.milestoneDates) = YEAR(_xlpm.weekDate), _xlpm.matched, IF(_xlpm.matchWeek * _xlpm.matchYear, _xlpm.headers, ""), _xlpm.result, _xlfn.TEXTJOIN(", ", TRUE, _xlpm.matched), IF(_xlpm.result="", "", _xlpm.result) ),"")} | J19: {=IFERROR(_xlfn.LET( _xlpm.project, $C19, _xlpm.weekDate, J$14, _xlpm.headers, INDEX(Table2[#Headers], _xlfn.SEQUENCE(1, COLUMNS(Table2[])-2)+2), _xlpm.milestoneDates, INDEX(Table2[], MATCH(_xlpm.project, Table2[Project], 0), _xlfn.SEQUENCE(1, COLUMNS(Table2[])-2)+2), _xlpm.matchWeek, _xlfn.ISOWEEKNUM(_xlpm.milestoneDates) = _xlfn.ISOWEEKNUM(_xlpm.weekDate), _xlpm.matchYear, YEAR(_xlpm.milestoneDates) = YEAR(_xlpm.weekDate), _xlpm.matched, IF(_xlpm.matchWeek * _xlpm.matchYear, _xlpm.headers, ""), _xlpm.result, _xlfn.TEXTJOIN(", ", TRUE, _xlpm.matched), IF(_xlpm.result="", "", _xlpm.result) ),"")} | K19: {=IFERROR(_xlfn.LET( _xlpm.project, $C19, _xlpm.weekDate, K$14, _xlpm.headers, INDEX(Table2[#Headers], _xlfn.SEQUENCE(1, COLUMNS(Table2[])-2)+2), _xlpm.milestoneDates, INDEX(Table2[], MATCH(_xlpm.project, Table2[Project], 0), _xlfn.SEQUENCE(1, COLUMNS(Table2[])-2)+2), _xlpm.matchWeek, _xlfn.ISOWEEKNUM(_xlpm.milestoneDates) = _xlfn.ISOWEEKNUM(_xlpm.weekDate), _xlpm.matchYear, YEAR(_xlpm.milestoneDates) = YEAR(_xlpm.weekDate), _xlpm.matched, IF(_xlpm.matchWeek * _xlpm.matchYear, _xlpm.headers, ""), _xlpm.result, _xlfn.TEXTJOIN(", ", TRUE, _xlpm.matched), IF(_xlpm.result="", "", _xlpm.result) ),"")} | L19: {=IFERROR(_xlfn.LET( _xlpm.project, $C19, _xlpm.weekDate, L$14, _xlpm.headers, INDEX(Table2[#Headers], _xlfn.SEQUENCE(1, COLUMNS(Table2[])-2)+2), _xlpm.milestoneDates, INDEX(Table2[], MATCH(_xlpm.project, Table2[Project], 0), _xlfn.SEQUENCE(1, COLUMNS(Table2[])-2)+2), _xlpm.matchWeek, _xlfn.ISOWEEKNUM(_xlpm.milestoneDates) = _xlfn.ISOWEEKNUM(_xlpm.weekDate), _xlpm.matchYear, YEAR(_xlpm.milestoneDates) = YEAR(_xlpm.weekDate), _xlpm.matched, IF(_xlpm.matchWeek * _xlpm.matchYear, _xlpm.headers, ""), _xlpm.result, _xlfn.TEXTJOIN(", ", TRUE, _xlpm.matched), IF(_xlpm.result="", "", _xlpm.result) ),"")} | ... FD19: {=IFERROR(_xlfn.LET( _xlpm.project, $C19, _xlpm.weekDate, FD$14, _xlpm.headers, INDEX(Table2[#Headers], _xlfn.SEQUENCE(1, COLUMNS(Table2[])-2)+2), _xlpm.milestoneDates, INDEX(Table2[], MATCH(_xlpm.project, Table2[Project], 0), _xlfn.SEQUENCE(1, COLUMNS(Table2[])-2)+2), _xlpm.matchWeek, _xlfn.ISOWEEKNUM(_xlpm.milestoneDates) = _xlfn.ISOWEEKNUM(_xlpm.weekDate), _xlpm.matchYear, YEAR(_xlpm.milestoneDates) = YEAR(_xlpm.weekDate), _xlpm.matched, IF(_xlpm.matchWeek * _xlpm.matchYear, _xlpm.headers, ""), _xlpm.result, _xlfn.TEXTJOIN(", ", TRUE, _xlpm.matched), IF(_xlpm.result="", "", _xlpm.result) ),"")}
C20: =INPUT!G25 -> Burgundy | D20: =_xlfn.XLOOKUP(Table14[[#This Row],[Project]],'MEA LOG'!$D$15:$D$100,'MEA LOG'!$F$15:$F$100,"") -> Qatar | E20: {=IFERROR(_xlfn.LET( _xlpm.project, $C20, _xlpm.weekDate, E$14, _xlpm.headers, INDEX(Table2[#Headers], _xlfn.SEQUENCE(1, COLUMNS(Table2[])-2)+2), _xlpm.milestoneDates, INDEX(Table2[], MATCH(_xlpm.project, Table2[Project], 0), _xlfn.SEQUENCE(1, COLUMNS(Table2[])-2)+2), _xlpm.matchWeek, _xlfn.ISOWEEKNUM(_xlpm.milestoneDates) = _xlfn.ISOWEEKNUM(_xlpm.weekDate), _xlpm.matchYear, YEAR(_xlpm.milestoneDates) = YEAR(_xlpm.weekDate), _xlpm.matched, IF(_xlpm.matchWeek * _xlpm.matchYear, _xlpm.headers, ""), _xlpm.result, _xlfn.TEXTJOIN(", ", TRUE, _xlpm.matched), IF(_xlpm.result="", "", _xlpm.result) ),"")} | F20: {=IFERROR(_xlfn.LET( _xlpm.project, $C20, _xlpm.weekDate, F$14, _xlpm.headers, INDEX(Table2[#Headers], _xlfn.SEQUENCE(1, COLUMNS(Table2[])-2)+2), _xlpm.milestoneDates, INDEX(Table2[], MATCH(_xlpm.project, Table2[Project], 0), _xlfn.SEQUENCE(1, COLUMNS(Table2[])-2)+2), _xlpm.matchWeek, _xlfn.ISOWEEKNUM(_xlpm.milestoneDates) = _xlfn.ISOWEEKNUM(_xlpm.weekDate), _xlpm.matchYear, YEAR(_xlpm.milestoneDates) = YEAR(_xlpm.weekDate), _xlpm.matched, IF(_xlpm.matchWeek * _xlpm.matchYear, _xlpm.headers, ""), _xlpm.result, _xlfn.TEXTJOIN(", ", TRUE, _xlpm.matched), IF(_xlpm.result="", "", _xlpm.result) ),"")} | G20: {=IFERROR(_xlfn.LET( _xlpm.project, $C20, _xlpm.weekDate, G$14, _xlpm.headers, INDEX(Table2[#Headers], _xlfn.SEQUENCE(1, COLUMNS(Table2[])-2)+2), _xlpm.milestoneDates, INDEX(Table2[], MATCH(_xlpm.project, Table2[Project], 0), _xlfn.SEQUENCE(1, COLUMNS(Table2[])-2)+2), _xlpm.matchWeek, _xlfn.ISOWEEKNUM(_xlpm.milestoneDates) = _xlfn.ISOWEEKNUM(_xlpm.weekDate), _xlpm.matchYear, YEAR(_xlpm.milestoneDates) = YEAR(_xlpm.weekDate), _xlpm.matched, IF(_xlpm.matchWeek * _xlpm.matchYear, _xlpm.headers, ""), _xlpm.result, _xlfn.TEXTJOIN(", ", TRUE, _xlpm.matched), IF(_xlpm.result="", "", _xlpm.result) ),"")} | H20: {=IFERROR(_xlfn.LET( _xlpm.project, $C20, _xlpm.weekDate, H$14, _xlpm.headers, INDEX(Table2[#Headers], _xlfn.SEQUENCE(1, COLUMNS(Table2[])-2)+2), _xlpm.milestoneDates, INDEX(Table2[], MATCH(_xlpm.project, Table2[Project], 0), _xlfn.SEQUENCE(1, COLUMNS(Table2[])-2)+2), _xlpm.matchWeek, _xlfn.ISOWEEKNUM(_xlpm.milestoneDates) = _xlfn.ISOWEEKNUM(_xlpm.weekDate), _xlpm.matchYear, YEAR(_xlpm.milestoneDates) = YEAR(_xlpm.weekDate), _xlpm.matched, IF(_xlpm.matchWeek * _xlpm.matchYear, _xlpm.headers, ""), _xlpm.result, _xlfn.TEXTJOIN(", ", TRUE, _xlpm.matched), IF(_xlpm.result="", "", _xlpm.result) ),"")} | I20: {=IFERROR(_xlfn.LET( _xlpm.project, $C20, _xlpm.weekDate, I$14, _xlpm.headers, INDEX(Table2[#Headers], _xlfn.SEQUENCE(1, COLUMNS(Table2[])-2)+2), _xlpm.milestoneDates, INDEX(Table2[], MATCH(_xlpm.project, Table2[Project], 0), _xlfn.SEQUENCE(1, COLUMNS(Table2[])-2)+2), _xlpm.matchWeek, _xlfn.ISOWEEKNUM(_xlpm.milestoneDates) = _xlfn.ISOWEEKNUM(_xlpm.weekDate), _xlpm.matchYear, YEAR(_xlpm.milestoneDates) = YEAR(_xlpm.weekDate), _xlpm.matched, IF(_xlpm.matchWeek * _xlpm.matchYear, _xlpm.headers, ""), _xlpm.result, _xlfn.TEXTJOIN(", ", TRUE, _xlpm.matched), IF(_xlpm.result="", "", _xlpm.result) ),"")} | J20: {=IFERROR(_xlfn.LET( _xlpm.project, $C20, _xlpm.weekDate, J$14, _xlpm.headers, INDEX(Table2[#Headers], _xlfn.SEQUENCE(1, COLUMNS(Table2[])-2)+2), _xlpm.milestoneDates, INDEX(Table2[], MATCH(_xlpm.project, Table2[Project], 0), _xlfn.SEQUENCE(1, COLUMNS(Table2[])-2)+2), _xlpm.matchWeek, _xlfn.ISOWEEKNUM(_xlpm.milestoneDates) = _xlfn.ISOWEEKNUM(_xlpm.weekDate), _xlpm.matchYear, YEAR(_xlpm.milestoneDates) = YEAR(_xlpm.weekDate), _xlpm.matched, IF(_xlpm.matchWeek * _xlpm.matchYear, _xlpm.headers, ""), _xlpm.result, _xlfn.TEXTJOIN(", ", TRUE, _xlpm.matched), IF(_xlpm.result="", "", _xlpm.result) ),"")} | K20: {=IFERROR(_xlfn.LET( _xlpm.project, $C20, _xlpm.weekDate, K$14, _xlpm.headers, INDEX(Table2[#Headers], _xlfn.SEQUENCE(1, COLUMNS(Table2[])-2)+2), _xlpm.milestoneDates, INDEX(Table2[], MATCH(_xlpm.project, Table2[Project], 0), _xlfn.SEQUENCE(1, COLUMNS(Table2[])-2)+2), _xlpm.matchWeek, _xlfn.ISOWEEKNUM(_xlpm.milestoneDates) = _xlfn.ISOWEEKNUM(_xlpm.weekDate), _xlpm.matchYear, YEAR(_xlpm.milestoneDates) = YEAR(_xlpm.weekDate), _xlpm.matched, IF(_xlpm.matchWeek * _xlpm.matchYear, _xlpm.headers, ""), _xlpm.result, _xlfn.TEXTJOIN(", ", TRUE, _xlpm.matched), IF(_xlpm.result="", "", _xlpm.result) ),"")} | L20: {=IFERROR(_xlfn.LET( _xlpm.project, $C20, _xlpm.weekDate, L$14, _xlpm.headers, INDEX(Table2[#Headers], _xlfn.SEQUENCE(1, COLUMNS(Table2[])-2)+2), _xlpm.milestoneDates, INDEX(Table2[], MATCH(_xlpm.project, Table2[Project], 0), _xlfn.SEQUENCE(1, COLUMNS(Table2[])-2)+2), _xlpm.matchWeek, _xlfn.ISOWEEKNUM(_xlpm.milestoneDates) = _xlfn.ISOWEEKNUM(_xlpm.weekDate), _xlpm.matchYear, YEAR(_xlpm.milestoneDates) = YEAR(_xlpm.weekDate), _xlpm.matched, IF(_xlpm.matchWeek * _xlpm.matchYear, _xlpm.headers, ""), _xlpm.result, _xlfn.TEXTJOIN(", ", TRUE, _xlpm.matched), IF(_xlpm.result="", "", _xlpm.result) ),"")} | ... FD20: {=IFERROR(_xlfn.LET( _xlpm.project, $C20, _xlpm.weekDate, FD$14, _xlpm.headers, INDEX(Table2[#Headers], _xlfn.SEQUENCE(1, COLUMNS(Table2[])-2)+2), _xlpm.milestoneDates, INDEX(Table2[], MATCH(_xlpm.project, Table2[Project], 0), _xlfn.SEQUENCE(1, COLUMNS(Table2[])-2)+2), _xlpm.matchWeek, _xlfn.ISOWEEKNUM(_xlpm.milestoneDates) = _xlfn.ISOWEEKNUM(_xlpm.weekDate), _xlpm.matchYear, YEAR(_xlpm.milestoneDates) = YEAR(_xlpm.weekDate), _xlpm.matched, IF(_xlpm.matchWeek * _xlpm.matchYear, _xlpm.headers, ""), _xlpm.result, _xlfn.TEXTJOIN(", ", TRUE, _xlpm.matched), IF(_xlpm.result="", "", _xlpm.result) ),"")}
C21: =INPUT!G26 -> Burgundy II | D21: =_xlfn.XLOOKUP(Table14[[#This Row],[Project]],'MEA LOG'!$D$15:$D$100,'MEA LOG'!$F$15:$F$100,"") -> Qatar | E21: {=IFERROR(_xlfn.LET( _xlpm.project, $C21, _xlpm.weekDate, E$14, _xlpm.headers, INDEX(Table2[#Headers], _xlfn.SEQUENCE(1, COLUMNS(Table2[])-2)+2), _xlpm.milestoneDates, INDEX(Table2[], MATCH(_xlpm.project, Table2[Project], 0), _xlfn.SEQUENCE(1, COLUMNS(Table2[])-2)+2), _xlpm.matchWeek, _xlfn.ISOWEEKNUM(_xlpm.milestoneDates) = _xlfn.ISOWEEKNUM(_xlpm.weekDate), _xlpm.matchYear, YEAR(_xlpm.milestoneDates) = YEAR(_xlpm.weekDate), _xlpm.matched, IF(_xlpm.matchWeek * _xlpm.matchYear, _xlpm.headers, ""), _xlpm.result, _xlfn.TEXTJOIN(", ", TRUE, _xlpm.matched), IF(_xlpm.result="", "", _xlpm.result) ),"")} | F21: {=IFERROR(_xlfn.LET( _xlpm.project, $C21, _xlpm.weekDate, F$14, _xlpm.headers, INDEX(Table2[#Headers], _xlfn.SEQUENCE(1, COLUMNS(Table2[])-2)+2), _xlpm.milestoneDates, INDEX(Table2[], MATCH(_xlpm.project, Table2[Project], 0), _xlfn.SEQUENCE(1, COLUMNS(Table2[])-2)+2), _xlpm.matchWeek, _xlfn.ISOWEEKNUM(_xlpm.milestoneDates) = _xlfn.ISOWEEKNUM(_xlpm.weekDate), _xlpm.matchYear, YEAR(_xlpm.milestoneDates) = YEAR(_xlpm.weekDate), _xlpm.matched, IF(_xlpm.matchWeek * _xlpm.matchYear, _xlpm.headers, ""), _xlpm.result, _xlfn.TEXTJOIN(", ", TRUE, _xlpm.matched), IF(_xlpm.result="", "", _xlpm.result) ),"")} | G21: {=IFERROR(_xlfn.LET( _xlpm.project, $C21, _xlpm.weekDate, G$14, _xlpm.headers, INDEX(Table2[#Headers], _xlfn.SEQUENCE(1, COLUMNS(Table2[])-2)+2), _xlpm.milestoneDates, INDEX(Table2[], MATCH(_xlpm.project, Table2[Project], 0), _xlfn.SEQUENCE(1, COLUMNS(Table2[])-2)+2), _xlpm.matchWeek, _xlfn.ISOWEEKNUM(_xlpm.milestoneDates) = _xlfn.ISOWEEKNUM(_xlpm.weekDate), _xlpm.matchYear, YEAR(_xlpm.milestoneDates) = YEAR(_xlpm.weekDate), _xlpm.matched, IF(_xlpm.matchWeek * _xlpm.matchYear, _xlpm.headers, ""), _xlpm.result, _xlfn.TEXTJOIN(", ", TRUE, _xlpm.matched), IF(_xlpm.result="", "", _xlpm.result) ),"")} | H21: {=IFERROR(_xlfn.LET( _xlpm.project, $C21, _xlpm.weekDate, H$14, _xlpm.headers, INDEX(Table2[#Headers], _xlfn.SEQUENCE(1, COLUMNS(Table2[])-2)+2), _xlpm.milestoneDates, INDEX(Table2[], MATCH(_xlpm.project, Table2[Project], 0), _xlfn.SEQUENCE(1, COLUMNS(Table2[])-2)+2), _xlpm.matchWeek, _xlfn.ISOWEEKNUM(_xlpm.milestoneDates) = _xlfn.ISOWEEKNUM(_xlpm.weekDate), _xlpm.matchYear, YEAR(_xlpm.milestoneDates) = YEAR(_xlpm.weekDate), _xlpm.matched, IF(_xlpm.matchWeek * _xlpm.matchYear, _xlpm.headers, ""), _xlpm.result, _xlfn.TEXTJOIN(", ", TRUE, _xlpm.matched), IF(_xlpm.result="", "", _xlpm.result) ),"")} | I21: {=IFERROR(_xlfn.LET( _xlpm.project, $C21, _xlpm.weekDate, I$14, _xlpm.headers, INDEX(Table2[#Headers], _xlfn.SEQUENCE(1, COLUMNS(Table2[])-2)+2), _xlpm.milestoneDates, INDEX(Table2[], MATCH(_xlpm.project, Table2[Project], 0), _xlfn.SEQUENCE(1, COLUMNS(Table2[])-2)+2), _xlpm.matchWeek, _xlfn.ISOWEEKNUM(_xlpm.milestoneDates) = _xlfn.ISOWEEKNUM(_xlpm.weekDate), _xlpm.matchYear, YEAR(_xlpm.milestoneDates) = YEAR(_xlpm.weekDate), _xlpm.matched, IF(_xlpm.matchWeek * _xlpm.matchYear, _xlpm.headers, ""), _xlpm.result, _xlfn.TEXTJOIN(", ", TRUE, _xlpm.matched), IF(_xlpm.result="", "", _xlpm.result) ),"")} | J21: {=IFERROR(_xlfn.LET( _xlpm.project, $C21, _xlpm.weekDate, J$14, _xlpm.headers, INDEX(Table2[#Headers], _xlfn.SEQUENCE(1, COLUMNS(Table2[])-2)+2), _xlpm.milestoneDates, INDEX(Table2[], MATCH(_xlpm.project, Table2[Project], 0), _xlfn.SEQUENCE(1, COLUMNS(Table2[])-2)+2), _xlpm.matchWeek, _xlfn.ISOWEEKNUM(_xlpm.milestoneDates) = _xlfn.ISOWEEKNUM(_xlpm.weekDate), _xlpm.matchYear, YEAR(_xlpm.milestoneDates) = YEAR(_xlpm.weekDate), _xlpm.matched, IF(_xlpm.matchWeek * _xlpm.matchYear, _xlpm.headers, ""), _xlpm.result, _xlfn.TEXTJOIN(", ", TRUE, _xlpm.matched), IF(_xlpm.result="", "", _xlpm.result) ),"")} | K21: {=IFERROR(_xlfn.LET( _xlpm.project, $C21, _xlpm.weekDate, K$14, _xlpm.headers, INDEX(Table2[#Headers], _xlfn.SEQUENCE(1, COLUMNS(Table2[])-2)+2), _xlpm.milestoneDates, INDEX(Table2[], MATCH(_xlpm.project, Table2[Project], 0), _xlfn.SEQUENCE(1, COLUMNS(Table2[])-2)+2), _xlpm.matchWeek, _xlfn.ISOWEEKNUM(_xlpm.milestoneDates) = _xlfn.ISOWEEKNUM(_xlpm.weekDate), _xlpm.matchYear, YEAR(_xlpm.milestoneDates) = YEAR(_xlpm.weekDate), _xlpm.matched, IF(_xlpm.matchWeek * _xlpm.matchYear, _xlpm.headers, ""), _xlpm.result, _xlfn.TEXTJOIN(", ", TRUE, _xlpm.matched), IF(_xlpm.result="", "", _xlpm.result) ),"")} | L21: {=IFERROR(_xlfn.LET( _xlpm.project, $C21, _xlpm.weekDate, L$14, _xlpm.headers, INDEX(Table2[#Headers], _xlfn.SEQUENCE(1, COLUMNS(Table2[])-2)+2), _xlpm.milestoneDates, INDEX(Table2[], MATCH(_xlpm.project, Table2[Project], 0), _xlfn.SEQUENCE(1, COLUMNS(Table2[])-2)+2), _xlpm.matchWeek, _xlfn.ISOWEEKNUM(_xlpm.milestoneDates) = _xlfn.ISOWEEKNUM(_xlpm.weekDate), _xlpm.matchYear, YEAR(_xlpm.milestoneDates) = YEAR(_xlpm.weekDate), _xlpm.matched, IF(_xlpm.matchWeek * _xlpm.matchYear, _xlpm.headers, ""), _xlpm.result, _xlfn.TEXTJOIN(", ", TRUE, _xlpm.matched), IF(_xlpm.result="", "", _xlpm.result) ),"")} | ... FD21: {=IFERROR(_xlfn.LET( _xlpm.project, $C21, _xlpm.weekDate, FD$14, _xlpm.headers, INDEX(Table2[#Headers], _xlfn.SEQUENCE(1, COLUMNS(Table2[])-2)+2), _xlpm.milestoneDates, INDEX(Table2[], MATCH(_xlpm.project, Table2[Project], 0), _xlfn.SEQUENCE(1, COLUMNS(Table2[])-2)+2), _xlpm.matchWeek, _xlfn.ISOWEEKNUM(_xlpm.milestoneDates) = _xlfn.ISOWEEKNUM(_xlpm.weekDate), _xlpm.matchYear, YEAR(_xlpm.milestoneDates) = YEAR(_xlpm.weekDate), _xlpm.matched, IF(_xlpm.matchWeek * _xlpm.matchYear, _xlpm.headers, ""), _xlpm.result, _xlfn.TEXTJOIN(", ", TRUE, _xlpm.matched), IF(_xlpm.result="", "", _xlpm.result) ),"")}
C22: =INPUT!G27 -> Burgundy III | D22: =_xlfn.XLOOKUP(Table14[[#This Row],[Project]],'MEA LOG'!$D$15:$D$100,'MEA LOG'!$F$15:$F$100,"") -> Qatar | E22: {=IFERROR(_xlfn.LET( _xlpm.project, $C22, _xlpm.weekDate, E$14, _xlpm.headers, INDEX(Table2[#Headers], _xlfn.SEQUENCE(1, COLUMNS(Table2[])-2)+2), _xlpm.milestoneDates, INDEX(Table2[], MATCH(_xlpm.project, Table2[Project], 0), _xlfn.SEQUENCE(1, COLUMNS(Table2[])-2)+2), _xlpm.matchWeek, _xlfn.ISOWEEKNUM(_xlpm.milestoneDates) = _xlfn.ISOWEEKNUM(_xlpm.weekDate), _xlpm.matchYear, YEAR(_xlpm.milestoneDates) = YEAR(_xlpm.weekDate), _xlpm.matched, IF(_xlpm.matchWeek * _xlpm.matchYear, _xlpm.headers, ""), _xlpm.result, _xlfn.TEXTJOIN(", ", TRUE, _xlpm.matched), IF(_xlpm.result="", "", _xlpm.result) ),"")} | F22: {=IFERROR(_xlfn.LET( _xlpm.project, $C22, _xlpm.weekDate, F$14, _xlpm.headers, INDEX(Table2[#Headers], _xlfn.SEQUENCE(1, COLUMNS(Table2[])-2)+2), _xlpm.milestoneDates, INDEX(Table2[], MATCH(_xlpm.project, Table2[Project], 0), _xlfn.SEQUENCE(1, COLUMNS(Table2[])-2)+2), _xlpm.matchWeek, _xlfn.ISOWEEKNUM(_xlpm.milestoneDates) = _xlfn.ISOWEEKNUM(_xlpm.weekDate), _xlpm.matchYear, YEAR(_xlpm.milestoneDates) = YEAR(_xlpm.weekDate), _xlpm.matched, IF(_xlpm.matchWeek * _xlpm.matchYear, _xlpm.headers, ""), _xlpm.result, _xlfn.TEXTJOIN(", ", TRUE, _xlpm.matched), IF(_xlpm.result="", "", _xlpm.result) ),"")} | G22: {=IFERROR(_xlfn.LET( _xlpm.project, $C22, _xlpm.weekDate, G$14, _xlpm.headers, INDEX(Table2[#Headers], _xlfn.SEQUENCE(1, COLUMNS(Table2[])-2)+2), _xlpm.milestoneDates, INDEX(Table2[], MATCH(_xlpm.project, Table2[Project], 0), _xlfn.SEQUENCE(1, COLUMNS(Table2[])-2)+2), _xlpm.matchWeek, _xlfn.ISOWEEKNUM(_xlpm.milestoneDates) = _xlfn.ISOWEEKNUM(_xlpm.weekDate), _xlpm.matchYear, YEAR(_xlpm.milestoneDates) = YEAR(_xlpm.weekDate), _xlpm.matched, IF(_xlpm.matchWeek * _xlpm.matchYear, _xlpm.headers, ""), _xlpm.result, _xlfn.TEXTJOIN(", ", TRUE, _xlpm.matched), IF(_xlpm.result="", "", _xlpm.result) ),"")} | H22: {=IFERROR(_xlfn.LET( _xlpm.project, $C22, _xlpm.weekDate, H$14, _xlpm.headers, INDEX(Table2[#Headers], _xlfn.SEQUENCE(1, COLUMNS(Table2[])-2)+2), _xlpm.milestoneDates, INDEX(Table2[], MATCH(_xlpm.project, Table2[Project], 0), _xlfn.SEQUENCE(1, COLUMNS(Table2[])-2)+2), _xlpm.matchWeek, _xlfn.ISOWEEKNUM(_xlpm.milestoneDates) = _xlfn.ISOWEEKNUM(_xlpm.weekDate), _xlpm.matchYear, YEAR(_xlpm.milestoneDates) = YEAR(_xlpm.weekDate), _xlpm.matched, IF(_xlpm.matchWeek * _xlpm.matchYear, _xlpm.headers, ""), _xlpm.result, _xlfn.TEXTJOIN(", ", TRUE, _xlpm.matched), IF(_xlpm.result="", "", _xlpm.result) ),"")} | I22: {=IFERROR(_xlfn.LET( _xlpm.project, $C22, _xlpm.weekDate, I$14, _xlpm.headers, INDEX(Table2[#Headers], _xlfn.SEQUENCE(1, COLUMNS(Table2[])-2)+2), _xlpm.milestoneDates, INDEX(Table2[], MATCH(_xlpm.project, Table2[Project], 0), _xlfn.SEQUENCE(1, COLUMNS(Table2[])-2)+2), _xlpm.matchWeek, _xlfn.ISOWEEKNUM(_xlpm.milestoneDates) = _xlfn.ISOWEEKNUM(_xlpm.weekDate), _xlpm.matchYear, YEAR(_xlpm.milestoneDates) = YEAR(_xlpm.weekDate), _xlpm.matched, IF(_xlpm.matchWeek * _xlpm.matchYear, _xlpm.headers, ""), _xlpm.result, _xlfn.TEXTJOIN(", ", TRUE, _xlpm.matched), IF(_xlpm.result="", "", _xlpm.result) ),"")} | J22: {=IFERROR(_xlfn.LET( _xlpm.project, $C22, _xlpm.weekDate, J$14, _xlpm.headers, INDEX(Table2[#Headers], _xlfn.SEQUENCE(1, COLUMNS(Table2[])-2)+2), _xlpm.milestoneDates, INDEX(Table2[], MATCH(_xlpm.project, Table2[Project], 0), _xlfn.SEQUENCE(1, COLUMNS(Table2[])-2)+2), _xlpm.matchWeek, _xlfn.ISOWEEKNUM(_xlpm.milestoneDates) = _xlfn.ISOWEEKNUM(_xlpm.weekDate), _xlpm.matchYear, YEAR(_xlpm.milestoneDates) = YEAR(_xlpm.weekDate), _xlpm.matched, IF(_xlpm.matchWeek * _xlpm.matchYear, _xlpm.headers, ""), _xlpm.result, _xlfn.TEXTJOIN(", ", TRUE, _xlpm.matched), IF(_xlpm.result="", "", _xlpm.result) ),"")} | K22: {=IFERROR(_xlfn.LET( _xlpm.project, $C22, _xlpm.weekDate, K$14, _xlpm.headers, INDEX(Table2[#Headers], _xlfn.SEQUENCE(1, COLUMNS(Table2[])-2)+2), _xlpm.milestoneDates, INDEX(Table2[], MATCH(_xlpm.project, Table2[Project], 0), _xlfn.SEQUENCE(1, COLUMNS(Table2[])-2)+2), _xlpm.matchWeek, _xlfn.ISOWEEKNUM(_xlpm.milestoneDates) = _xlfn.ISOWEEKNUM(_xlpm.weekDate), _xlpm.matchYear, YEAR(_xlpm.milestoneDates) = YEAR(_xlpm.weekDate), _xlpm.matched, IF(_xlpm.matchWeek * _xlpm.matchYear, _xlpm.headers, ""), _xlpm.result, _xlfn.TEXTJOIN(", ", TRUE, _xlpm.matched), IF(_xlpm.result="", "", _xlpm.result) ),"")} | L22: {=IFERROR(_xlfn.LET( _xlpm.project, $C22, _xlpm.weekDate, L$14, _xlpm.headers, INDEX(Table2[#Headers], _xlfn.SEQUENCE(1, COLUMNS(Table2[])-2)+2), _xlpm.milestoneDates, INDEX(Table2[], MATCH(_xlpm.project, Table2[Project], 0), _xlfn.SEQUENCE(1, COLUMNS(Table2[])-2)+2), _xlpm.matchWeek, _xlfn.ISOWEEKNUM(_xlpm.milestoneDates) = _xlfn.ISOWEEKNUM(_xlpm.weekDate), _xlpm.matchYear, YEAR(_xlpm.milestoneDates) = YEAR(_xlpm.weekDate), _xlpm.matched, IF(_xlpm.matchWeek * _xlpm.matchYear, _xlpm.headers, ""), _xlpm.result, _xlfn.TEXTJOIN(", ", TRUE, _xlpm.matched), IF(_xlpm.result="", "", _xlpm.result) ),"")} | ... FD22: {=IFERROR(_xlfn.LET( _xlpm.project, $C22, _xlpm.weekDate, FD$14, _xlpm.headers, INDEX(Table2[#Headers], _xlfn.SEQUENCE(1, COLUMNS(Table2[])-2)+2), _xlpm.milestoneDates, INDEX(Table2[], MATCH(_xlpm.project, Table2[Project], 0), _xlfn.SEQUENCE(1, COLUMNS(Table2[])-2)+2), _xlpm.matchWeek, _xlfn.ISOWEEKNUM(_xlpm.milestoneDates) = _xlfn.ISOWEEKNUM(_xlpm.weekDate), _xlpm.matchYear, YEAR(_xlpm.milestoneDates) = YEAR(_xlpm.weekDate), _xlpm.matched, IF(_xlpm.matchWeek * _xlpm.matchYear, _xlpm.headers, ""), _xlpm.result, _xlfn.TEXTJOIN(", ", TRUE, _xlpm.matched), IF(_xlpm.result="", "", _xlpm.result) ),"")}
C23: =INPUT!G28 -> QA | D23: =_xlfn.XLOOKUP(Table14[[#This Row],[Project]],'MEA LOG'!$D$15:$D$100,'MEA LOG'!$F$15:$F$100,"") -> Qatar Amiri | E23: {=IFERROR(_xlfn.LET( _xlpm.project, $C23, _xlpm.weekDate, E$14, _xlpm.headers, INDEX(Table2[#Headers], _xlfn.SEQUENCE(1, COLUMNS(Table2[])-2)+2), _xlpm.milestoneDates, INDEX(Table2[], MATCH(_xlpm.project, Table2[Project], 0), _xlfn.SEQUENCE(1, COLUMNS(Table2[])-2)+2), _xlpm.matchWeek, _xlfn.ISOWEEKNUM(_xlpm.milestoneDates) = _xlfn.ISOWEEKNUM(_xlpm.weekDate), _xlpm.matchYear, YEAR(_xlpm.milestoneDates) = YEAR(_xlpm.weekDate), _xlpm.matched, IF(_xlpm.matchWeek * _xlpm.matchYear, _xlpm.headers, ""), _xlpm.result, _xlfn.TEXTJOIN(", ", TRUE, _xlpm.matched), IF(_xlpm.result="", "", _xlpm.result) ),"")} | F23: {=IFERROR(_xlfn.LET( _xlpm.project, $C23, _xlpm.weekDate, F$14, _xlpm.headers, INDEX(Table2[#Headers], _xlfn.SEQUENCE(1, COLUMNS(Table2[])-2)+2), _xlpm.milestoneDates, INDEX(Table2[], MATCH(_xlpm.project, Table2[Project], 0), _xlfn.SEQUENCE(1, COLUMNS(Table2[])-2)+2), _xlpm.matchWeek, _xlfn.ISOWEEKNUM(_xlpm.milestoneDates) = _xlfn.ISOWEEKNUM(_xlpm.weekDate), _xlpm.matchYear, YEAR(_xlpm.milestoneDates) = YEAR(_xlpm.weekDate), _xlpm.matched, IF(_xlpm.matchWeek * _xlpm.matchYear, _xlpm.headers, ""), _xlpm.result, _xlfn.TEXTJOIN(", ", TRUE, _xlpm.matched), IF(_xlpm.result="", "", _xlpm.result) ),"")} | G23: {=IFERROR(_xlfn.LET( _xlpm.project, $C23, _xlpm.weekDate, G$14, _xlpm.headers, INDEX(Table2[#Headers], _xlfn.SEQUENCE(1, COLUMNS(Table2[])-2)+2), _xlpm.milestoneDates, INDEX(Table2[], MATCH(_xlpm.project, Table2[Project], 0), _xlfn.SEQUENCE(1, COLUMNS(Table2[])-2)+2), _xlpm.matchWeek, _xlfn.ISOWEEKNUM(_xlpm.milestoneDates) = _xlfn.ISOWEEKNUM(_xlpm.weekDate), _xlpm.matchYear, YEAR(_xlpm.milestoneDates) = YEAR(_xlpm.weekDate), _xlpm.matched, IF(_xlpm.matchWeek * _xlpm.matchYear, _xlpm.headers, ""), _xlpm.result, _xlfn.TEXTJOIN(", ", TRUE, _xlpm.matched), IF(_xlpm.result="", "", _xlpm.result) ),"")} | H23: {=IFERROR(_xlfn.LET( _xlpm.project, $C23, _xlpm.weekDate, H$14, _xlpm.headers, INDEX(Table2[#Headers], _xlfn.SEQUENCE(1, COLUMNS(Table2[])-2)+2), _xlpm.milestoneDates, INDEX(Table2[], MATCH(_xlpm.project, Table2[Project], 0), _xlfn.SEQUENCE(1, COLUMNS(Table2[])-2)+2), _xlpm.matchWeek, _xlfn.ISOWEEKNUM(_xlpm.milestoneDates) = _xlfn.ISOWEEKNUM(_xlpm.weekDate), _xlpm.matchYear, YEAR(_xlpm.milestoneDates) = YEAR(_xlpm.weekDate), _xlpm.matched, IF(_xlpm.matchWeek * _xlpm.matchYear, _xlpm.headers, ""), _xlpm.result, _xlfn.TEXTJOIN(", ", TRUE, _xlpm.matched), IF(_xlpm.result="", "", _xlpm.result) ),"")} | I23: {=IFERROR(_xlfn.LET( _xlpm.project, $C23, _xlpm.weekDate, I$14, _xlpm.headers, INDEX(Table2[#Headers], _xlfn.SEQUENCE(1, COLUMNS(Table2[])-2)+2), _xlpm.milestoneDates, INDEX(Table2[], MATCH(_xlpm.project, Table2[Project], 0), _xlfn.SEQUENCE(1, COLUMNS(Table2[])-2)+2), _xlpm.matchWeek, _xlfn.ISOWEEKNUM(_xlpm.milestoneDates) = _xlfn.ISOWEEKNUM(_xlpm.weekDate), _xlpm.matchYear, YEAR(_xlpm.milestoneDates) = YEAR(_xlpm.weekDate), _xlpm.matched, IF(_xlpm.matchWeek * _xlpm.matchYear, _xlpm.headers, ""), _xlpm.result, _xlfn.TEXTJOIN(", ", TRUE, _xlpm.matched), IF(_xlpm.result="", "", _xlpm.result) ),"")} | J23: {=IFERROR(_xlfn.LET( _xlpm.project, $C23, _xlpm.weekDate, J$14, _xlpm.headers, INDEX(Table2[#Headers], _xlfn.SEQUENCE(1, COLUMNS(Table2[])-2)+2), _xlpm.milestoneDates, INDEX(Table2[], MATCH(_xlpm.project, Table2[Project], 0), _xlfn.SEQUENCE(1, COLUMNS(Table2[])-2)+2), _xlpm.matchWeek, _xlfn.ISOWEEKNUM(_xlpm.milestoneDates) = _xlfn.ISOWEEKNUM(_xlpm.weekDate), _xlpm.matchYear, YEAR(_xlpm.milestoneDates) = YEAR(_xlpm.weekDate), _xlpm.matched, IF(_xlpm.matchWeek * _xlpm.matchYear, _xlpm.headers, ""), _xlpm.result, _xlfn.TEXTJOIN(", ", TRUE, _xlpm.matched), IF(_xlpm.result="", "", _xlpm.result) ),"")} | K23: {=IFERROR(_xlfn.LET( _xlpm.project, $C23, _xlpm.weekDate, K$14, _xlpm.headers, INDEX(Table2[#Headers], _xlfn.SEQUENCE(1, COLUMNS(Table2[])-2)+2), _xlpm.milestoneDates, INDEX(Table2[], MATCH(_xlpm.project, Table2[Project], 0), _xlfn.SEQUENCE(1, COLUMNS(Table2[])-2)+2), _xlpm.matchWeek, _xlfn.ISOWEEKNUM(_xlpm.milestoneDates) = _xlfn.ISOWEEKNUM(_xlpm.weekDate), _xlpm.matchYear, YEAR(_xlpm.milestoneDates) = YEAR(_xlpm.weekDate), _xlpm.matched, IF(_xlpm.matchWeek * _xlpm.matchYear, _xlpm.headers, ""), _xlpm.result, _xlfn.TEXTJOIN(", ", TRUE, _xlpm.matched), IF(_xlpm.result="", "", _xlpm.result) ),"")} | L23: {=IFERROR(_xlfn.LET( _xlpm.project, $C23, _xlpm.weekDate, L$14, _xlpm.headers, INDEX(Table2[#Headers], _xlfn.SEQUENCE(1, COLUMNS(Table2[])-2)+2), _xlpm.milestoneDates, INDEX(Table2[], MATCH(_xlpm.project, Table2[Project], 0), _xlfn.SEQUENCE(1, COLUMNS(Table2[])-2)+2), _xlpm.matchWeek, _xlfn.ISOWEEKNUM(_xlpm.milestoneDates) = _xlfn.ISOWEEKNUM(_xlpm.weekDate), _xlpm.matchYear, YEAR(_xlpm.milestoneDates) = YEAR(_xlpm.weekDate), _xlpm.matched, IF(_xlpm.matchWeek * _xlpm.matchYear, _xlpm.headers, ""), _xlpm.result, _xlfn.TEXTJOIN(", ", TRUE, _xlpm.matched), IF(_xlpm.result="", "", _xlpm.result) ),"")} -> Idea Generation | ... FD23: {=IFERROR(_xlfn.LET( _xlpm.project, $C23, _xlpm.weekDate, FD$14, _xlpm.headers, INDEX(Table2[#Headers], _xlfn.SEQUENCE(1, COLUMNS(Table2[])-2)+2), _xlpm.milestoneDates, INDEX(Table2[], MATCH(_xlpm.project, Table2[Project], 0), _xlfn.SEQUENCE(1, COLUMNS(Table2[])-2)+2), _xlpm.matchWeek, _xlfn.ISOWEEKNUM(_xlpm.milestoneDates) = _xlfn.ISOWEEKNUM(_xlpm.weekDate), _xlpm.matchYear, YEAR(_xlpm.milestoneDates) = YEAR(_xlpm.weekDate), _xlpm.matched, IF(_xlpm.matchWeek * _xlpm.matchYear, _xlpm.headers, ""), _xlpm.result, _xlfn.TEXTJOIN(", ", TRUE, _xlpm.matched), IF(_xlpm.result="", "", _xlpm.result) ),"")}
